Workbook
Name A_anode: Chemistry!$D$130
Name A_anode_wet: Electrochemistry!$D$46
Name A_cath_wet: Electrochemistry!$D$47
Name A_DH: Chemistry!$D$186
Name a_int: 'Mass Transfer'!$D$49
Name a_surf: 'Mass Transfer'!$D$71
Name A_x: Geometry!$D$21
Name A_x: 'Mass Transfer'!$D$17
Name anode_dia: Electrochemistry!$D$42
Name anode_j_cont: Electrochemistry!$D$50
Name anode_j_max: Electrochemistry!$D$51
Name anode_material: Electrochemistry!$D$63
Name anode_shape: Electrochemistry!$D$41
Name b_anode: Electrochemistry!$D$107
Name b_cath: Electrochemistry!$D$109
Name bio_CO2: Biology!$D$12
Name bio_H2: Biology!$D$10
Name bio_O2: Biology!$D$11
Name bleach_flag: Chemistry!$D$109
Name bleach_rate: Chemistry!$D$107
Name bleach_t1ppm: Chemistry!$D$108
Name bubble_regime: 'Mass Transfer'!$D$64
Name buffer_flag: Chemistry!$D$219
Name C_air_CO2: 'Mass Transfer'!$D$146
Name C_cycle_peak: 'Mass Transfer'!$D$199
Name C_cycle_start: 'Mass Transfer'!$D$198
Name C_eff: Chemistry!$D$145
Name C_eff_Cl2: Chemistry!$D$226
Name C_eff_hi: Chemistry!$D$157
Name C_eff_lo: Chemistry!$D$156
Name C_H2_sat: Biology!$D$41
Name C_sat_CO2: 'Mass Transfer'!$D$145
Name Ca_CO2: 'Mass Transfer'!$D$157
Name cal_Dint: Calibrations!$D$75
Name cal_DO_impair: Calibrations!$D$105
Name cal_DO_min: Calibrations!$D$103
Name cal_DO_opt: Calibrations!$D$104
Name cal_DO_toxic: Calibrations!$D$106
Name cal_etaF: Calibrations!$D$31
Name cal_etaF_OER: Calibrations!$D$32
Name cal_flow: Calibrations!$D$60
Name cal_gerrit_int: Calibrations!$D$17
Name cal_gerrit_slope: Calibrations!$D$16
Name cal_j_ceiling: Calibrations!$D$137
Name cal_j_opt: Calibrations!$D$136
Name cal_kLa: Calibrations!$D$46
Name cal_knall_CO2: Calibrations!$D$122
Name cal_knall_H2: Calibrations!$D$120
Name cal_knall_O2: Calibrations!$D$121
Name cal_sinter: Calibrations!$D$89
Name cal_Vtot: Calibrations!$D$74
Name cal_warning: 'Mass Transfer'!$D$120
Name carbon_margin_min: 'Mass Transfer'!$D$85
Name carry_flag: 'Mass Transfer'!$D$59
Name cath_j_cont: Electrochemistry!$D$52
Name cath_j_max: Electrochemistry!$D$53
Name cathode_dia: Electrochemistry!$D$44
Name cathode_shape: Electrochemistry!$D$43
Name Cb_CO2: 'Mass Transfer'!$D$158
Name Cl_kill: Chemistry!$D$147

Sheet Summary
A1: Parameter | B1: Name | C1: Unit | D1: Value | E1: Source | F1: Comment
A2: Reactor | B2: Reactor_sel | D2: ed04 | E2: select | F2: Active build. Choose from the values below. Dropdown.
A3: Electrode | B3: electrode_sel | D3: Pt/Ti rod | E3: select | F3: CO₂ delivery route. Choose from the values below. Dropdown.
A4: HOB organism | B4: organism_sel | D4: UdG (mixed) | E4: select | F4: The HOB strain; sets the DO band the schedule targets.
A5: Media | B5: media_sel | D5: MC02 | E5: select | F5: Growth medium.
A6: Electrolysis power | B6: led_intensity | C6: % | D6: 3 | E6: input | F6: LED channel D %, the AEP-Plugin 'electrolysis_power' setting (runtime-clamped 0–10 %); drives the electrolysis current via Gerrit's Law.
A7: Stirrer rate | B7: stir_rpm_set | C7: rpm | D7: 1000 | E7: input | F7: Stir rate; sets tip speed and surface O2 transfer.
A8: Temperature setpoint | B8: temp_C | C8: °C | D8: 25 | E8: input | F8: Temperature setpoint; sets Henry solubilities and rates.
A9: Media volume | B9: media_volume | C9: mL | E9: input/blank | F9: Liquid charged; leave blank to use the reactor's recommended max working volume.
A10: Ambient pressure | B10: P_atm_set | C10: Pa | E10: input/blank | F10: blank = default 101325 Pa
A12: Results | B12: Name | C12: Unit | D12: Value | E12: Source | F12: Comment | G12: Override
A13: CO₂ sparge duration | C13: s | D13: =IFERROR('Mass Transfer'!$D$90,"calibrate this reactor first (see CO2 flows)") -> 0.78451305 | E13: =HYPERLINK("#'Mass Transfer'!D90","→ Mass") -> → Mass | F13: How long to open the CO2 solenoid each dose.
A14: CO₂ sparge duration (rounded) | C14: s | D14: =IF(AND(ISNUMBER($G$13),$G$13>0),$G$13,IF(NOT(ISNUMBER(D13)),D13,IF(D13>0.5,ROUND(D13,0),ROUND(D13,1-(1+INT(LOG10(ABS(D13)))))))) -> 1
A15: CO₂ sparge interval | C15: min | D15: =IFERROR('Mass Transfer'!$D$91,"calibrate this reactor first (see CO2 flows)") -> 13.911968 | E15: =HYPERLINK("#'Mass Transfer'!D91","→ Mass") -> → Mass | F15: Time between doses. Now credits surface O2 stripping (kL_surf proxy); when surface handles the O2 this is carbon-limited. Refine via the kL_surf measurement.
A16: CO₂ sparge interval (rounded) | C16: min | D16: =IF(AND(ISNUMBER($G$15),$G$15>0),$G$15,IF(NOT(ISNUMBER(D15)),D15,IF(D15>0.5,ROUND(D15,0),ROUND(D15,1-(1+INT(LOG10(ABS(D15)))))))) -> 14
A18: Checks | D18: Value | E18: Source | F18: Comment
A19: Vial geometry consistent? | D19: =Geometry!$D$90 -> VIAL GEOMETRY INCONSISTENT - measure true fill volume & bore depth | E19: =HYPERLINK("#Geometry!D90","→ Geometry") -> → Geometry | F19: Red until the vial headspace is measured (vial-geometry.md). While red, the pulse above is provisional (~4x uncertain).
A20: Reactor calibrated? | D20: ='Mass Transfer'!$D$120 -> calibrated: ed04 | E20: =HYPERLINK("#'Mass Transfer'!D120","→ Mass") -> → Mass | F20: Red = no CO2-flow calibration for this reactor; results read 'calibrate first' (flow-calibration.md).
A21: O₂ at/under organism optimum? | D21: ='Mass Transfer'!$D$109 -> organism optimum unknown | E21: =HYPERLINK("#'Mass Transfer'!D109","→ Mass") -> → Mass | F21: Green = dissolved O2 sits at/under the organism optimum; red = surface stripping insufficient, O2 may breach impairment.
A22: O₂ above organism minimum? | D22: ='Mass Transfer'!$D$110 -> minimum DO unknown - measure | E22: =HYPERLINK("#'Mass Transfer'!D110","→ Mass") -> → Mass | F22: Minimum DO is a data gap for most organisms (dissolved-oxygen.md).
A23: Interval can be relaxed (carbon-limited)? | D23: ='Mass Transfer'!$D$113 -> organism DO unknown | E23: =HYPERLINK("#'Mass Transfer'!D113","→ Mass") -> → Mass | F23: If surface stripping handles O2 you may dose far less often (the carbon-limited interval, in Supporting figures). The interval above is the safe fallback until kL_surf is measured.
A24: H₂ headspace safe? | D24: =Biology!$D$44 -> EXPLOSIVE | E24: =HYPERLINK("#Biology!D44","→ Biology") -> → Biology | F24: EXPLOSIVE = H2 evolves faster than it dissolves; ensure headspace venting and no ignition source.
A25: Bubble model valid? | D25: ='Mass Transfer'!$D$64 -> Static | E25: =HYPERLINK("#'Mass Transfer'!D64","→ Mass") -> → Mass | F25: 'Sinter OOR' = sinter pore size out of the validated bubble range; sparge mass-transfer is approximate (expected for the porosity-0 disc).
A26: CO₂ supply meets demand? | D26: =IFERROR("×"&TEXT('Mass Transfer'!$D$126,"0.0")&IF('Mass Transfer'!$D$126>=1," OK"," SHORTFALL (CO2 < demand)"),"calibrate this reactor first") -> ×26.6 OK | E26: =HYPERLINK("#'Mass Transfer'!D126","→ Mass") -> → Mass | F26: Ratio of CO2 supplied to carbon demand; should be >= 1.
A27: Pulse ≥ solenoid floor? | D27: =IFERROR('Mass Transfer'!$D$130,"calibrate this reactor first (see CO2 flows)") -> OK | E27: =HYPERLINK("#'Mass Transfer'!D130","→ Mass") -> → Mass | F27: The optimal pulse must exceed the shortest reliable sparge.
A28: Dosing window OK? | D28: =IFERROR('Mass Transfer'!$D$95,"calibrate this reactor first (see CO2 flows)") -> OK | E28: =HYPERLINK("#'Mass Transfer'!D95","→ Mass") -> → Mass | F28: Enough gap between doses to read OD without sparging.
A29: Carryover risk? | D29: ='Mass Transfer'!$D$59 -> OK | E29: =HYPERLINK("#'Mass Transfer'!D59","→ Mass") -> → Mass | F29: Gas velocity below the entrainment limit (no liquid carried out).
A30: Tip-speed shear OK? | D30: ='Mass Transfer'!$D$111 -> OK | E30: =HYPERLINK("#'Mass Transfer'!D111","→ Mass") -> → Mass | F30: Stirrer tip speed under the conservative 1.5 m/s shear limit.
A31: Media volume fits vial? | D31: =Geometry!$D$54 -> OK | E31: =HYPERLINK("#Geometry!D54","→ Geometry") -> → Geometry | F31: Media volume not exceeding the max working volume.
A32: Liquid level OK? | D32: =Geometry!$D$55 -> OK | E32: =HYPERLINK("#Geometry!D55","→ Geometry") -> → Geometry | F32: Liquid not above the usable vial depth.
A33: LED current-law in range? | D33: =Electrochemistry!$D$20 -> OK | E33: =HYPERLINK("#Electrochemistry!D20","→ Electrochemistry") -> → Electrochemistry | F33: LED intensity within Gerrit's-Law validated band 3-25% (gerrit-current.md).
A34: Organism DO data present? | D34: =IF(AND(ISNUMBER(Biology!$D$45),ISNUMBER(Biology!$D$46),ISNUMBER(Biology!$D$47),ISNUMBER(Biology!$D$48)),"inputs present","DATA GAP - organism DO thresholds unmeasured; results unreliable") -> DATA GAP - organism DO thresholds unmeasured; results unreliable | E34: =HYPERLINK("#Biology!D45","→ Biology") -> → Biology | F34: Red = the selected organism has no measured DO thresholds, so every DO/sparge verdict above is running on missing data.
A35: Endpoint pH (worst-case, full sparge) | D35: =Chemistry!$D$220 -> #DIV/0! | E35: =HYPERLINK("#Chemistry!D103","→ Chemistry") -> → Chemistry | F35: Operating pH at the CO₂ trough, on the activity scale a probe reads. Green 6.5–7.5; red outside 6–8.
A36: Effective biocidal chlorine | C36: mg/L | D36: =Chemistry!$D$226 -> #DIV/0! | E36: =HYPERLINK("#Chemistry!D226","→ Chemistry") -> → Chemistry | F36: Effective biocidal chlorine from the medium’s chloride, on the as-Cl₂ basis the literature thresholds use. Green <0.1, red >1 mg/L. Zero for chloride-free media.
A37: SUPPORTING FIGURES
A38: Steady-state DO (surface) | C38: mg/L | D38: ='Mass Transfer'!$D$108 -> 2.6390317 | E38: =HYPERLINK("#'Mass Transfer'!D108","→ Mass") -> → Mass | F38: Predicted dissolved O2 the surface stripping settles at; compare to the organism band.
A39: Sparge interval if O₂ handled | C39: min | D39: ='Mass Transfer'!$D$112 -> 185.24021 | E39: =HYPERLINK("#'Mass Transfer'!D112","→ Mass") -> → Mass | F39: The longer (carbon-limited) interval usable if the 'relaxed' check is green.
A40: Stir-bar tip speed | C40: m/s | D40: ='Mass Transfer'!$D$68 -> 0.62831853 | E40: =HYPERLINK("#'Mass Transfer'!D68","→ Mass") -> → Mass | F40: Checked against 1.5 m/s above.
A41: Carbon margin | C41: × | D41: =Biology!$D$35 -> 668.745 | E41: =HYPERLINK("#Biology!D35","→ Biology") -> → Biology | F41: Dissolved CO2 vs RuBisCO Km at in-sparge peak; large = ample carbon.
A42: ELECTROLYSIS & CURRENT DENSITY
A43: Electrolysis current | C43: mA | D43: =Electrochemistry!$D$19*1000 -> 5.69 | E43: =HYPERLINK("#Electrochemistry!D19","→ Electrochemistry") -> → Electrochemistry | F43: Cell current at the set Electrolysis power (Gerrit's Law).
A44: Anode current density | C44: mA/cm² | D44: =Electrochemistry!$D$48 -> 2.8260957 | E44: =HYPERLINK("#Electrochemistry!D48","→ Electrochemistry") -> → Electrochemistry | F44: Current per unit submerged anode area (shape-aware).
A45: Current density status (now) | D45: =Electrochemistry!$D$62 -> watch - above optimum current density | E45: =HYPERLINK("#Electrochemistry!D62","→ Electrochemistry") -> → Electrochemistry | F45: Green = at/below the strain optimum; amber = above optimum; red = over the strain ceiling or the electrode's rating.
A46: Max Electrolysis power | C46: % | D46: =Electrochemistry!$D$73 -> 10 | E46: =HYPERLINK("#Electrochemistry!D73","→ Electrochemistry") -> → Electrochemistry | F46: AEP-Plugin runtime clamp: electrolysis_power ≤ 10 %.
A47: Max electrolysis current | C47: mA | D47: =Electrochemistry!$D$74 -> 12.9 | E47: =HYPERLINK("#Electrochemistry!D74","→ Electrochemistry") -> → Electrochemistry | F47: Highest cell current you can set (at max power).
A48: Max anode current density | C48: mA/cm² | D48: =Electrochemistry!$D$75 -> 6.4071414 | E48: =HYPERLINK("#Electrochemistry!D75","→ Electrochemistry") -> → Electrochemistry | F48: Anode current density at max power.
A49: Current density status (at max power) | D49: =Electrochemistry!$D$76 -> EXCEED - max current over a limit | E49: =HYPERLINK("#Electrochemistry!D76","→ Electrochemistry") -> → Electrochemistry | F49: Whether the highest current you can set stays within the strain and electrode limits.
A51: Key
A52: Verified / handbook / defined / standard
A53: Literature-supported (~90%)
A54: Design assumption (~70%)
A55: Weak / coarse estimate (~50%)
A56: Guess - replace when known
A57: DATA GAP - measure, do not invent
A58: Value font: blue = input you set/measure
A59: black = formula / derived
A60: purple = fixed data / constant
A61: OK
A62: Caution
A63: Problem
A65: Improvements | B65: Impact | C65: Effort | D65: Protocol | F65: Why it matters
A66: Measure surface kLa (kL_surf) | B66: HIGH | C66: med | D66: =HYPERLINK("https://github.com/amy-bo/electroPioreactor/blob/CO2-modular/Media/protocols/surface-kla.md","surface-kla.md →") -> surface-kla.md → | F66: Sets how far dissolved O₂ must sit above the headspace to shed the surplus, and the feasibility margin behind the whole DO strategy (kLa in use ÷ kLa required). It no longer switches the sheet between two schedules — it moves the answer continuously.
A67: Measure / confirm vial total volume | B67: HIGH | C67: low | D67: =HYPERLINK("https://github.com/amy-bo/electroPioreactor/blob/CO2-modular/Media/protocols/vial-geometry.md","vial-geometry.md →") -> vial-geometry.md → | F67: ~106% on the schedule — sets the liquid charge, headspace and flush sizing; water-fill
A68: Measure cathodic Faradaic efficiency (etaF) | B68: HIGH | C68: med | D68: =HYPERLINK("https://github.com/amy-bo/electroPioreactor/blob/CO2-modular/Media/protocols/faradaic-efficiency.md","faradaic-efficiency.md →") -> faradaic-efficiency.md → | F68: Now calculated rather than assumed, from the cathodic O₂ flux — but the calculation rests on an estimated electrode mass-transfer coefficient. Measuring it settles the H₂/O₂ split and the peroxide source at once.
A69: Confirm knallgas uptake ratio (H2:O2:CO2) | B69: MED | C69: high | D69: =HYPERLINK("https://github.com/amy-bo/electroPioreactor/blob/CO2-modular/Media/protocols/knallgas-stoichiometry.md","knallgas-stoichiometry.md →") -> knallgas-stoichiometry.md → | F69: ~95% on the O2 surplus + carbon demand; needs a growing culture
A70: Measure anodic Faradaic efficiency (etaF_OER) | B70: MED | C70: med | D70: =HYPERLINK("https://github.com/amy-bo/electroPioreactor/blob/CO2-modular/Media/protocols/faradaic-efficiency.md","faradaic-efficiency.md →") -> faradaic-efficiency.md → | F70: Assumed to be 1 minus the chlorine share; any anodic metal dissolution comes straight off it, and the corrosion suspicion on Chemistry D163 needs exactly this number.
A71: Measure vial wall thickness | B71: MED | C71: low | D71: =HYPERLINK("https://github.com/amy-bo/electroPioreactor/blob/CO2-modular/Media/protocols/vial-geometry.md","vial-geometry.md →") -> vial-geometry.md → | F71: high-leverage caliper measurement — drives the headspace/displacement budget
A72: Bench-characterise the solenoid pulse floor | B72: LOW | C72: low | D72: =HYPERLINK("https://github.com/amy-bo/electroPioreactor/blob/CO2-modular/Media/protocols/flow-calibration.md","flow-calibration.md →") -> flow-calibration.md → | F72: ~27% — the recommended pulse IS pulse_floor; trivial to characterise on the bench
A73: Determine organism minimum DO | B73: MED | C73: low | D73: =HYPERLINK("https://github.com/amy-bo/electroPioreactor/blob/CO2-modular/Media/protocols/dissolved-oxygen.md","dissolved-oxygen.md →") -> dissolved-oxygen.md → | F73: lower DO guardrail; a gap for every organism
A74: Calibrate flow for each reactor | B74: MED | C74: low | D74: =HYPERLINK("https://github.com/amy-bo/electroPioreactor/blob/CO2-modular/Media/protocols/flow-calibration.md","flow-calibration.md →") -> flow-calibration.md → | F74: each experiment; only ed04 done
A75: Measure / confirm sinter porosity | B75: LOW | C75: low | D75: =HYPERLINK("https://github.com/amy-bo/electroPioreactor/blob/CO2-modular/Media/protocols/sinter-porosity.md","sinter-porosity.md →") -> sinter-porosity.md → | F75: bubble size; currently grade 0 from Gerrit's disc
A76: Record lab ambient pressure | B76: LOW | C76: low | D76: =HYPERLINK("https://github.com/amy-bo/electroPioreactor/blob/CO2-modular/Media/protocols/README.md","README.md →") -> README.md → | F76: ~33% via the O2 ceiling; also Henry solubilities + gas volumes
A77: Measure the electrode mass-transfer coefficient | B77: HIGH | C77: low | D77: =HYPERLINK("https://github.com/amy-bo/electroPioreactor/blob/CO2-modular/Media/protocols/current-density-screen.md","current-density-screen.md →") -> current-density-screen.md → | F77: One ferricyanide limiting-current run in the same vial at the same rpm replaces the assumed swirl velocity behind k_m — which sets the cathodic O₂ loss, the peroxide source, the chlorine cap and the electrode-surface pH verdict.
A78: Measure the electrode centre-to-centre gap | B78: MED | C78: low | D78: =HYPERLINK("https://github.com/amy-bo/electroPioreactor/blob/CO2-modular/Media/protocols/vial-geometry.md","vial-geometry.md →") -> vial-geometry.md → | F78: Calipers across the cap ports. Sets the ohmic term in the cell-voltage budget, which is the largest single term after the overpotentials.
A79: Measure the cell voltage at a known setpoint | B79: HIGH | C79: low | D79: =HYPERLINK("https://github.com/amy-bo/electroPioreactor/blob/CO2-modular/Media/protocols/gerrit-current.md","gerrit-current.md →") -> gerrit-current.md → | F79: The voltage budget is a testable prediction (3.3 V of a 5 V rail at 3 %). A multimeter reading across the electrodes either confirms the whole electrochemical picture or localises which term is wrong.
A80: Assay dissolved metals in spent medium | B80: HIGH | C80: med | D80: =HYPERLINK("https://github.com/amy-bo/electroPioreactor/blob/CO2-modular/Media/protocols/README.md","README.md →") -> README.md → | F80: Cu/Ni/Fe by ICP or a colorimetric kit. An O₂-evolving anode sits ~0.44 V above the Cu²⁺/Cu equilibrium, so dissolution is thermodynamically allowed; this is the unmodelled prime suspect for the Exp-2 death and it also closes the anodic charge budget.
A81: ELECTROCHEMISTRY — CALCULATED (wave-4; hand these to an electrochemist)
A82: Cathodic faradaic efficiency (calculated) | C82: - | D82: =Electrochemistry!$D$88 -> 0.9774753 | E82: =HYPERLINK("#Electrochemistry!D88","→ Electrochemistry") -> → Electrochemistry | F82: Fraction of cathode current making H₂ rather than reducing dissolved O₂. Was assumed to be 1.
A83: Estimated cell voltage | C83: V | D83: =Electrochemistry!$D$119 -> 3.219994 | E83: =HYPERLINK("#Electrochemistry!D119","→ Electrochemistry") -> → Electrochemistry | F83: Reversible voltage + both overpotentials + ohmic drop. Measure across the electrodes to test it.
A84: Cell-voltage verdict | C84: - | D84: =Electrochemistry!$D$122 -> OK — 3.22 V estimated against a 5 V rail | E84: =HYPERLINK("#Electrochemistry!D122","→ Electrochemistry") -> → Electrochemistry | F84: Whether the 5 V drive rail can deliver the set current.
A85: Peroxide verdict | C85: - | D85: =Electrochemistry!$D$99 -> watch — steady growth is clear (0.055 mg/L) but LAG PHASE is not: peroxide passes the threshold in 13 min before biomass can scavenge it | E85: =HYPERLINK("#Electrochemistry!D99","→ Electrochemistry") -> → Electrochemistry | F85: H₂O₂ from the 2-electron branch of cathodic O₂ reduction, against the growth-inhibition threshold, in both the growing and the lag phase.
A86: Electrode-surface pH verdict | C86: - | D86: =Chemistry!$D$219 -> #DIV/0! | E86: =HYPERLINK("#Chemistry!D219","→ Chemistry") -> → Chemistry | F86: Whether the phosphate buffer holds the electrode surfaces at the bulk pH at this current density.
A87: Chlorine headroom above O₂ evolution | C87: V | D87: =Chemistry!$D$209 -> #DIV/0! | E87: =HYPERLINK("#Chemistry!D209","→ Chemistry") -> → Chemistry | F87: How much extra anodic potential chlorine evolution would need. Large = disfavoured.
A88: Copper dissolution headroom at the anode | C88: V | D88: =Chemistry!$D$211 -> #DIV/0! | E88: =HYPERLINK("#Chemistry!D211","→ Chemistry") -> → Chemistry | F88: How far an O₂-evolving anode sits above the Cu²⁺/Cu equilibrium.
A89: Measured (activity-scale) pH | C89: - | D89: =Chemistry!$D$220 -> #DIV/0! | E89: =HYPERLINK("#Chemistry!D220","→ Chemistry") -> → Chemistry | F89: What a probe reads: the charge balance solves on concentrations, a glass electrode reads activity.
A90: Surface kLa required for the DO target | C90: 1/s | D90: ='Mass Transfer'!$D$186 -> 0.0036147484 | E90: =HYPERLINK("#'Mass Transfer'!D186","→ Mass Transfer") -> → Mass Transfer | F90: Below this, no sparge interval holds the target dissolved O₂. Compare with the estimate in use.

Sheet Geometry
A1: GEOMETRY
A2: Parameter | B2: Name | C2: Unit | D2: Value | E2: Source / assumption
A4: IMPORTS (from other tabs)
A5: (import) Reactor selection | B5: reactor_sel | C5: - | D5: =Summary!$D$2 -> ed04 | E5: =HYPERLINK("#Summary!D2","→ Summary") -> → Summary
A6: (import) Media volume (set) | B6: media_volume | C6: mL | D6: =Summary!$D$9 -> 0 | E6: =HYPERLINK("#Summary!D9","→ Summary") -> → Summary
A8: valid version 1 | B8: ver_name_1 | C8: - | D8: AEP0.1.1 | E8: Superseded by the reactor-type lookup below; not read by any formula
A9: valid version 2 | B9: ver_name_2 | C9: - | D9: AEP0.2 | E9: Superseded by the reactor-type lookup below; not read by any formula
A10: Vial outer diameter - AEP0.1.1 | B10: vial_OD_1 | C10: mm | D10: 27.48 | E10: Superseded by the reactor-type lookup below; not read by any formula
A11: Vial outer diameter - AEP0.2 | B11: vial_OD_2 | C11: mm | D11: 27.48 | E11: Superseded by the reactor-type lookup below; not read by any formula
A12: Internal usable depth - AEP0.1.1 | B12: D_int_1 | C12: mm | D12: 55 | E12: Superseded by the reactor-type lookup below; not read by any formula
A13: Internal usable depth - AEP0.2 | B13: D_int_2 | C13: mm | D13: 95 | E13: Superseded by the reactor-type lookup below; not read by any formula
A14: Recommended max working volume - AEP0.1.1 | B14: Vmax_1 | C14: mL | D14: 16 | E14: Superseded by the reactor-type lookup below; not read by any formula
A15: Recommended max working volume - AEP0.2 | B15: Vmax_2 | C15: mL | D15: 30 | E15: Superseded by the reactor-type lookup below; not read by any formula
A16: Total internal vial volume - AEP0.1.1 | B16: Vtot_1 | C16: mL | D16: 20 | E16: Superseded by the reactor-type lookup below; not read by any formula
A17: Total internal vial volume - AEP0.2 | B17: Vtot_2 | C17: mL | D17: 42 | E17: Superseded by the reactor-type lookup below; not read by any formula
A18: Vial outer diameter | B18: vial_OD | C18: mm | D18: =VLOOKUP(rx_ver,$A$84:$I$87,7,FALSE) -> 27.48 | E18: Selected by rx_ver; invalid version returns an error.
A19: Vial wall thickness | B19: vial_wall | C19: mm | D19: 1.1 | E19: Borosilicate vial; Pioreactor publish neither wall nor internal diameter, so wall estimated ~1.1 mm (typical for this glass-vial class).
A20: Vial internal diameter | B20: vial_ID | C20: mm | D20: =vial_OD-2*vial_wall -> 25.28 | E20: OD minus two wall thicknesses.
A21: Internal cross-sectional area | B21: A_x | C21: mm² | D21: =PI()/4*vial_ID^2 -> 501.931 | E21: Uniform-cylinder body approximation (neck excluded - see headspace).
A22: Internal usable depth | B22: D_int | C22: mm | D22: =IF(ISNUMBER(cal_Dint),cal_Dint,VLOOKUP(rx_ver,$A$84:$I$87,4,FALSE)) -> 55 | E22: Selected by rx_ver.
A23: Recommended max working volume (datum) | B23: V_max | C23: mL | D23: =VLOOKUP(rx_ver,$A$84:$I$87,5,FALSE) -> 16 | E23: Selected by rx_ver.
A24: Total internal vial volume | B24: V_vial_total | C24: mL | D24: =IF(ISNUMBER(cal_Vtot),cal_Vtot,VLOOKUP(rx_ver,$A$84:$I$87,6,FALSE)) -> 20 | E24: Selected by rx_ver.
A25: Bare liquid level (datum height) | B25: h_datum | C25: mm | D25: =V_max*1000/A_x -> 31.876891 | E25: Height the bare max volume reaches with no inserts.
A26: Electrode rod diameter | B26: rod_d | C26: mm | D26: 6 | E26: 6 mm rod electrodes.
A27: Number of electrodes | B27: rod_n | C27: - | D27: 2 | E27: Anode + cathode.
A28: Electrode tip clearance above base | B28: elec_clear | C28: mm | D28: 22 | E28: Held constant across builds (OD clear zone). 22 mm ↔ 33 mm insertion in AEP0.1.1. Input.
A29: Electrode insertion depth (derived) | B29: elec_ins | C29: mm | D29: =D_int-elec_clear -> 33 | E29: Cap underside -> tip. Increases for the taller AEP0.2 to keep clearance constant.
A30: Sparge tube OD | B30: spg_OD | C30: mm | D30: 3.175 | E30: 1/8" OD Flexelene 135C.
A31: Sparge tube ID | B31: spg_ID | C31: mm | D31: 1.5875 | E31: 1/16" ID.
A32: Sparge release height (= anode tip) | B32: spg_tip_h | C32: mm | D32: =elec_clear -> 22 | E32: CO₂ released near anode tip.
A33: Efflux tube OD | B33: eff_OD | C33: mm | D33: 3.175 | E33: 1/8" OD Flexelene 135C.
A34: Efflux tube ID | B34: eff_ID | C34: mm | D34: 1.5875 | E34: 1/16" ID.
A35: Electrode submerged length (@datum) | B35: elec_sub_L | C35: mm | D35: =MAX(0,h_datum-elec_clear) -> 9.8768913 | E35: For displacement bookkeeping.
A36: Electrode displaced volume | B36: elec_disp | C36: mL | D36: =rod_n*(PI()/4*rod_d^2)*elec_sub_L/1000 -> 0.55852505 | E36: Submerged rod volume.
A37: Sparge tube displaced volume | B37: spg_disp | C37: mL | D37: =(PI()/4*spg_OD^2)*MAX(0,h_datum-spg_tip_h)/1000 -> 0.078198355 | E37: Submerged sparge-tube volume.
A38: Efflux tube submerged length | B38: eff_sub_L | C38: mm | D38: =(eff_OD+eff_ID)/2 -> 2.38125 | E38: 45 deg cut; level held at top of the ID opening, so wall is wetted from tip up to (OD+ID)/2.
A39: Efflux tube displaced volume | B39: eff_disp | C39: mL | D39: =(PI()/4*(eff_OD^2-eff_ID^2))*eff_sub_L/1000 -> 0.014139811 | E39: Annular wall only (bore is open to withdrawal). 45 deg approximation.
A40: Total displaced volume | B40: disp_tot | C40: mL | D40: =elec_disp+spg_disp+eff_disp -> 0.65086321 | E40: Sum of submerged inserts.
A41: LIQUID VOLUME TO CHARGE | B41: V_charge | C41: mL | D41: =IF(media_volume>0,media_volume,ROUND(V_max-disp_tot,0)) -> 15 | E41: Integer mL to charge so the level matches the bare datum despite inserts.
A42: Resulting liquid level | B42: h_actual | C42: mm | D42: =(V_charge+disp_tot)*1000/A_x -> 31.181304 | E42: Level achieved by the integer charge (displacement taken at datum; sub-mm error).
A43: Sparge depth / bubble path length | B43: sparge_depth | C43: mm | D43: =MAX(0,h_actual-spg_tip_h) -> 9.1813041 | E43: Release point to surface.
A44: Gas-liquid interfacial area | B44: interface_A | C44: mm² | D44: =A_x-(rod_n*(PI()/4*rod_d^2)+(PI()/4*spg_OD^2)+(PI()/4*eff_OD^2)) -> 429.54773 | E44: Free surface = cross-section minus inserts piercing it.
A45: Extra headspace tube OD | B45: xtube_OD | C45: mm | D45: =eff_OD -> 3.175 | E45: 3 further 1/8" tubes (gas-out, etc.) through the cap.
A46: Number of extra headspace tubes | B46: xtube_n | C46: - | D46: 3 | E46: Protrude through the cap into headspace. 1x media in, 2x gas out
A47: Extra tube protrusion | B47: xtube_pro | C47: mm | D47: 5 | E47: Each protrudes ~5 mm below cap (45 deg cut). Input.
A48: Total in-vial insert volume | B48: V_inserts | C48: mL | D48: =(rod_n*(PI()/4*rod_d^2)*elec_ins+(PI()/4*spg_OD^2)*spg_len+(PI()/4*(eff_OD^2-eff_ID^2))*(D_int-h_actual)+xtube_n*(PI()/4*xtube_OD^2)*xtube_pro)/1000 -> 2.3875715 | E48: In-vial inserts: electrodes & sparge solid; efflux annular (open bore); extra tubes solid.
A49: Headspace gas volume | B49: headspace_V | C49: mL | D49: =V_vial_total-V_charge-V_inserts -> 2.6124285 | E49: Total vial volume - liquid charged - inserts (captures neck narrowing).
A50: Sparge tube in-vial length | B50: spg_len | C50: mm | D50: =D_int-spg_tip_h -> 33 | E50: Cap underside to release point; tracks spg_tip_h.
A51: Reactor type (resolved from reactor) | B51: rx_ver | D51: =VLOOKUP(reactor_sel,$A$59:$B$80,2,FALSE) -> MEP0.3
A52: Stir-bar length (from reactor type) | B52: stir_bar_L | D52: =VLOOKUP(rx_ver,$A$84:$I$87,8,FALSE) -> 12
A53: 40 mL OD = 20 mL diameter (Pioreactor source); depths/volumes confirm by measurement.
A54: Media vs max working volume | B54: media_vol_warn | D54: =IF(V_charge>V_max,"MEDIA > MAX WORKING VOLUME","OK") -> OK
A55: Liquid level vs usable depth | B55: depth_warn | D55: =IF(h_actual>D_int,"LIQUID OVER USABLE DEPTH","OK") -> OK
A57: REACTOR LOOKUP (reactor ID → type)
A58: Reactor | B58: Type
A59: imp01 | B59: AEP0.1.1
A60: imp02 | B60: AEP0.1.1
A61: imp03 | B61: AEP0.1.1
A62: imp04 | B62: AEP0.1.1
A63: imp05 | B63: AEP0.1.1
A64: imp06 | B64: AEP0.1.1
A65: ed01 | B65: AEP0.1.1
A66: ed02 | B66: AEP0.1.1
A67: ed03 | B67: AEP0.1.1
A68: ed04 | B68: MEP0.3
A69: ed05 | B69: MEP0.3
... A80: nm02 | B80: AEP0.2
A82: REACTOR-TYPE LOOKUP (geometry & stir bar; pulled by type)
A83: Type | B83: Pioreactor | C83: vial (mL) | D83: usable depth (mm) | E83: max working (mL) | F83: total vial (mL) | G83: vial OD (mm) | H83: stir bar L (mm) | I83: stir bar dia (mm)
A84: AEP0.1.1 | B84: 1.1 | C84: 20 | D84: 55 | E84: 16 | F84: 20 | G84: 27.48 | H84: 12 | I84: 3
A85: MEP0.3 | B85: 1.1 | C85: 20 | D85: 55 | E85: 16 | F85: 20 | G85: 27.48 | H85: 12 | I85: 3
A86: AEP0.2 | B86: 1.5 | C86: 40 | D86: 95 | E86: 30 | F86: 42 | G86: 27.48 | H86: 15 | I86: 6
A87: AEP0.2a | B87: 1.5 | C87: 40 | D87: 95 | E87: 30 | F87: 42 | G87: 27.48 | H87: 15 | I87: 6
A89: VIAL GEOMETRY CONSISTENCY CHECK
A90: Vial geometry consistency check | B90: geom_check | D90: =IF(ABS(A_x*D_int/1000-V_vial_total)>3,"VIAL GEOMETRY INCONSISTENT - measure true fill volume & bore depth","OK") -> VIAL GEOMETRY INCONSISTENT - measure true fill volume & bore depth | F90: Fires INCONSISTENT for the 20 mL vial because the bare cylinder (A_x x usable depth ~28 mL) overestimates the true 20 mL vial (it tapers/necks, not a full cylinder to 55 mm). Expected tolerance artifact, not a data error - resolved by measuring true bore depth (protocols/vial-geometry.md).
A91: ELECTRODE GEOMETRY FOR THE OHMIC DROP (wave-4)
A92: Electrode centre-to-centre gap | B92: elec_gap | C92: mm | D92: 14 | E92: DATA GAP — measure across the cap ports with calipers. 14 mm is the mid-range for two 6 mm rods in a 25.3 mm bore. The solution resistance goes as acosh(gap/rod_d), so this sets the ohmic term in the cell-voltage budget (Electrochemistry).
A93: Electrode submerged length (at the achieved level) | B93: elec_sub_L_act | C93: mm | D93: =MAX(0,h_actual-elec_clear) -> 9.1813041 | E93: Submerged length at the ACHIEVED liquid level (D42), not the bare datum (D35, which exists for displacement bookkeeping). This is what sets the wetted area and hence current density.

Sheet Electrochemistry
A1: ELECTROCHEMISTRY
A2: Parameter | B2: Name | C2: Unit | D2: Value | E2: Source / assumption
A4: IMPORTS (from other tabs)
A5: (import) Temperature (absolute) | B5: T_K | C5: K | D5: =Biology!$D$18 -> 298.15 | E5: =HYPERLINK("#Biology!D18","→ Biology") -> → Biology
A6: (import) Surface pressure | B6: P_atm | C6: Pa | D6: =Biology!$D$19 -> 101325 | E6: =HYPERLINK("#Biology!D19","→ Biology") -> → Biology
A7: (import) Ideal gas constant | B7: R_gas | C7: J/mol/K | D7: ='Mass Transfer'!$D$101 -> 8.3144626 | E7: =HYPERLINK("#'Mass Transfer'!D101","→ Mass Transfer") -> → Mass Transfer
A8: (import) Electrode selection | B8: electrode_sel | D8: =Summary!$D$3 -> Pt/Ti rod | E8: =HYPERLINK("#Summary!D3","→ Summary") -> → Summary
A10: LED intensity setpoint (Pioreactor LED_D) | B10: intensity | C10: % | D10: =Summary!$D$6 -> 3 | E10: Electrode drive via LED_D channel. Input.
A11: Gerrit's Law - slope | B11: gerrit_slope | C11: mA/% | D11: =IF(ISNUMBER(cal_gerrit_slope),cal_gerrit_slope,1.03) -> 1.03 | E11: Gerrit's Law fit (slope) - from LED-current calibration; see protocol gerrit-current.md
A12: Gerrit's Law - intercept | B12: gerrit_int | C12: mA | D12: =IF(ISNUMBER(cal_gerrit_int),cal_gerrit_int,2.6) -> 2.6 | E12: Gerrit's Law fit (intercept); calibration-derived constant
A13: Gerrit's Law - min valid intensity | B13: gerrit_min | C13: % | D13: 3 | E13: Fit validated from 3%.
A14: Gerrit's Law - max valid intensity | B14: gerrit_max | C14: % | D14: 25 | E14: Fit validated to 25%; above this constant-current may fail as cell V nears the 5 V rail.
A15: Faraday constant | B15: F_const | C15: C/mol | D15: 96485.332 | E15: NIST CODATA (exact, SI 2019).
A16: Electrons per H₂ | B16: z_e_H2 | C16: - | D16: 2 | E16: 2H⁺ + 2e⁻ -> H₂.
A17: Electrons per O₂ | B17: z_e_O2 | C17: - | D17: 4 | E17: 2H₂O -> O₂ + 4H⁺ + 4e⁻.
A18: Faradaic efficiency – H₂ at cathode (HER share) | B18: etaF | C18: - | D18: =IF(ISNUMBER(cal_etaF),cal_etaF,etaF_calc) -> 0.9774753 | E18: Cathodic H₂ faradaic efficiency: a measured value from the Calibrations tab if there is one, otherwise CALCULATED (D89) from the cathodic O₂ reduction competing for the current — it is no longer assumed to be 1. Neutral-pH HER on stainless peaks near 97% before that competition is counted, so the calculated value remains an upper bound.
A19: Electrolysis current (Gerrit's Law) | B19: I_app | C19: A | D19: =(gerrit_slope*intensity+gerrit_int)/1000 -> 0.00569 | E19: I(mA) = slope x intensity + intercept; /1000 -> A.
A20: Gerrit's Law validity flag | B20: I_valid | C20: - | D20: =IF(AND(intensity>=gerrit_min,intensity<=gerrit_max),"OK","OUT") -> OK | E20: Linear fit only validated over the stated range.
A21: H₂ generation rate | B21: rH2_gen | C21: mol/h | D21: =I_app*etaF/(z_e_H2*F_const)*3600 -> 0.00010375983 | E21: Faraday: I x etaF /(z F).
A22: O₂ generation rate (anodic, gross) | B22: rO2_gen | C22: mol/h | D22: =I_app*etaF_OER/(z_e_O2*F_const)*3600 -> 5.3075425e-05 | E22: Anodic OER, gross. Uses etaF_OER (anodic), not the cathodic etaF. H₂:O₂(anodic) = 2:1.
A23: H₂ generation rate (volumetric) | B23: V_H2_gen | C23: mL/min | D23: =rH2_gen/60*R_gas*T_K/P_atm*1000000 -> 0.04230877 | E23: Ideal gas at surface T,P. Collect gas over water to check against this.
A24: O₂ generation rate (volumetric) | B24: V_O2_gen | C24: mL/min | D24: =rO2_gen/60*R_gas*T_K/P_atm*1000000 -> 0.021641862 | E24: Anodic gross O₂.
A25: Total gas generation rate | B25: V_gas_total | C25: mL/min | D25: =V_H2_gen+V_O2_gen -> 0.063950632 | E25: Total electrolytic gas (H₂+O₂) — abiotic check: collect over water, no cells, to verify Gerrit/etaF. Less if etaF<1.
A26: Anodic O₂ faradaic efficiency | B26: etaF_OER | C26: - | D26: =IF(ISNUMBER(cal_etaF_OER),cal_etaF_OER,etaF_OER_calc) -> 1 | E26: Anodic O₂ faradaic efficiency: measured if available, otherwise CALCULATED (etaF_OER_calc) as 1 − the chlorine share − the metal-dissolution share. The old note asserted a chloride-free medium; UdG contains chloride and the sheet now models the chlorine current explicitly.
A27: Electrons per O₂ reduced (cathode) | B27: z_e_ORR | C27: - | D27: =VLOOKUP(electrode_sel,$A$35:$I$38,9,FALSE) -> 2 | E27: Electrode lookup fixes ORR at 2 e- (peroxide pathway, SS cathode, neutral pH) for every current electrode; a 4 e- (to-water) electrode would need its own table row.
A28: O₂ consumed at cathode (ORR) | B28: O2_cathode_ORR | C28: mol/h | D28: =I_app*(1-etaF)/(z_e_ORR*F_const)*3600 -> 2.3910162e-06 | E28: Cathodic current not making H₂ (1−etaF) reduces dissolved O₂. 0 at etaF=1.
A29: Net O₂ to dissolved pool | B29: O2_net_gen | C29: mol/h | D29: =rO2_gen-O2_cathode_ORR -> 5.0684409e-05 | E29: Anodic O₂ minus cathodic consumption — the O₂ the dissolved pool receives.
A30: z_e_ORR=2 assumed (peroxide, non-Pt SS cathode, neutral pH); etaF unmeasured - both live here per electrode.
A31: Sparger (from electrode) | B31: sparger_e | D31: =VLOOKUP(electrode_sel,$A$35:$I$38,4,FALSE) -> Tube
A32: Sinter porosity grade (from electrode) | B32: por_grade_e | D32: =IF(ISNUMBER(cal_sinter),cal_sinter,IF(ISNUMBER(VLOOKUP(electrode_sel,$A$35:$I$38,5,FALSE)),VLOOKUP(electrode_sel,$A$35:$I$38,5,FALSE),0)) -> 0 | E32: Porosity 0 = Gerrit's sourced sintered disc (SD8/0/P 8mm, fallback SD10/0/P 10mm; Scientific Glass Labs, 2026-05)
A33: ELECTRODE LOOKUP (selecting the electrode sets sparger, porosity, cathode)
A34: Electrode | B34: anode material | C34: anode dia (mm) | D34: sparger | E34: sinter porosity | F34: cathode | G34: cathode dia (mm) | H34: etaF | I34: z_e_ORR | J34: anode shape | K34: anode j cont (mA/cm²) | L34: anode j max (mA/cm²) | M34: cathode shape | N34: material note
A35: Pt/Ti rod | B35: Pt/Ti | C35: 6 | D35: Tube | E35: n/a | F35: SS rod | G35: 6 | H35: ? | I35: 2 | J35: rod | K35: 100 | L35: 500 | M35: rod | N35: Pt/Ti O₂-evolution; cells bind before the coating.
A36: MMO rod | B36: MMO | C36: 6 | D36: Tube | E36: n/a | F36: SS rod | G36: 6 | H36: ? | I36: 2 | J36: rod | K36: 50 | L36: 500 | M36: rod | N36: IrO₂-Ta₂O₅ O₂-selective; derates vs chloride.
A37: MMO tube | B37: MMO | C37: 6 | D37: Sintered | E37: 0 | F37: SS rod | G37: 6 | H37: ? | I37: 2 | J37: tube | K37: 10 | L37: 60 | M37: rod | N37: Tubular MMO CP rating ~100 A/m²; binds near the cell limit.
A38: Graphite rod | B38: Graphite | C38: 6 | D38: Tube | E38: n/a | F38: SS rod | G38: 6 | H38: ? | I38: 2 | J38: rod | K38: 35 | L38: 50 | M38: rod | N38: Consumable; ~35 mA/cm² erosion, unsuitable for sustained neutral O₂; testing only.
A40: CURRENT DENSITY, WETTED AREA & LIMITS
A41: Anode shape (from electrode) | B41: anode_shape | C41: - | D41: =VLOOKUP(electrode_sel,$A$35:$N$38,10,FALSE) -> rod | E41: Rod counts its end face; a tube does not.
A42: Anode diameter (from electrode) | B42: anode_dia | C42: mm | D42: =VLOOKUP(electrode_sel,$A$35:$N$38,3,FALSE) -> 6 | E42: Electrode table.
A43: Cathode shape (from electrode) | B43: cathode_shape | C43: - | D43: =VLOOKUP(electrode_sel,$A$35:$N$38,13,FALSE) -> rod | E43: Rod/tube; sets the end-face term.
A44: Cathode diameter (from electrode) | B44: cathode_dia | C44: mm | D44: =VLOOKUP(electrode_sel,$A$35:$N$38,7,FALSE) -> 6 | E44: Electrode table.
A45: (import) Submerged electrode length | B45: L_sub | C45: mm | D45: =Geometry!$D$93 -> 9.1813041 | E45: Submerged length at the achieved liquid level (Geometry D93). Was taken from the bare datum (Geometry D35), which overstated the wetted area by 6.5% and understated every current density by the same factor.
A46: Anode wetted area | B46: A_anode_wet | C46: cm² | D46: =(PI()*anode_dia*L_sub+IF(anode_shape="rod",PI()/4*anode_dia^2,0))/100 -> 2.0133784 | E46: Lateral π·d·L (+ end face for a rod). mm²→cm².
A47: Cathode wetted area | B47: A_cath_wet | C47: cm² | D47: =(PI()*cathode_dia*L_sub+IF(cathode_shape="rod",PI()/4*cathode_dia^2,0))/100 -> 2.0133784 | E47: Same, cathode.
A48: Anode current density | B48: j_anode | C48: mA/cm² | D48: =I_app*1000/A_anode_wet -> 2.8260957 | E48: I / anode wetted area.
A49: Cathode current density | B49: j_cathode | C49: mA/cm² | D49: =I_app*1000/A_cath_wet -> 2.8260957 | E49: I / cathode wetted area.
A50: Anode plating limit — continuous | B50: anode_j_cont | C50: mA/cm² | D50: =VLOOKUP(electrode_sel,$A$35:$N$38,11,FALSE) -> 100 | E50: Coating continuous rating (electrode table).
A51: Anode plating limit — maximum | B51: anode_j_max | C51: mA/cm² | D51: =VLOOKUP(electrode_sel,$A$35:$N$38,12,FALSE) -> 500 | E51: Coating maximum (electrode table).
A52: Cathode (SS) HER limit — continuous | B52: cath_j_cont | C52: mA/cm² | D52: 80 | E52: Stainless-steel HER ~25–80 mA/cm² continuous.
A53: Cathode (SS) HER limit — maximum | B53: cath_j_max | C53: mA/cm² | D53: 250 | E53: Stainless-steel HER ~250 mA/cm² lab max.
A54: Fallback optimum j (unlisted strain) | B54: j_opt_default | C54: mA/cm² | D54: 1 | E54: Conservative fallback for an unlisted organism.
A55: Fallback ceiling j (unlisted strain) | B55: j_ceiling_default | C55: mA/cm² | D55: 2 | E55: Conservative fallback ceiling.
A56: Strain optimum current density | B56: j_opt_strain | C56: mA/cm² | D56: =IF(ISNUMBER(cal_j_opt),cal_j_opt,IFERROR(VLOOKUP(Summary!$D$4,$A$66:$E$71,2,FALSE),j_opt_default)) -> 2.14 | E56: Strain table below; fallback if unlisted.
A57: Strain tolerated ceiling | B57: j_ceiling_strain | C57: mA/cm² | D57: =IF(ISNUMBER(cal_j_ceiling),cal_j_ceiling,IFERROR(VLOOKUP(Summary!$D$4,$A$66:$E$71,3,FALSE),j_ceiling_default)) -> 4.29 | E57: Inhibition above this.
A58: Strain data confidence | B58: j_strain_conf | C58: - | D58: =IFERROR(VLOOKUP(Summary!$D$4,$A$66:$E$71,4,FALSE),"unknown") -> med | E58: low/unknown → provisional; run the screen.
A59: Current density vs strain | B59: j_bio_flag | C59: - | D59: =IF(j_anode<=j_opt_strain,"OK - at/below optimum",IF(j_anode<=j_ceiling_strain,"watch - above optimum","EXCEED - over strain ceiling")) -> watch - above optimum | E59: Green ≤ optimum, amber ≤ ceiling, red above.
A60: Current density vs anode plating | B60: j_mat_flag | C60: - | D60: =IF(j_anode>anode_j_max,"EXCEED - over plating maximum",IF(OR(j_anode>anode_j_cont,anode_material="Graphite"),IF(anode_material="Graphite","watch - graphite consumable in neutral O₂ (testing only)","watch - above continuous plating rating"),"OK - within plating rating")) -> OK - within plating rating | E60: Anode coating limit; graphite always ≥ amber.
A61: Cathode current density vs SS norm | B61: j_cath_flag | C61: - | D61: =IF(j_cathode<=cath_j_cont,"OK - cathode within HER norm",IF(j_cathode<=cath_j_max,"watch - high cathodic j","EXCEED - over SS HER norm")) -> OK - cathode within HER norm | E61: SS cathode HER check.
A62: CURRENT DENSITY STATUS (worst of above) | B62: j_flag | C62: - | D62: =IF(OR(ISNUMBER(SEARCH("EXCEED",j_bio_flag)),ISNUMBER(SEARCH("EXCEED",j_mat_flag)),ISNUMBER(SEARCH("EXCEED",j_cath_flag))),"EXCEED - current density over a limit",IF(OR(ISNUMBER(SEARCH("watch",j_bio_flag)),ISNUMBER(SEARCH("watch",j_mat_flag)),ISNUMBER(SEARCH("watch",j_cath_flag))),"watch - above optimum current density","OK - current density in range")) -> watch - above optimum current density | E62: Worst of strain, plating and cathode.
A63: Anode material (from electrode) | B63: anode_material | C63: - | D63: =VLOOKUP(electrode_sel,$A$35:$N$38,2,FALSE) -> Pt/Ti | E63: Electrode table; drives the graphite warning.
A64: STRAIN CURRENT-DENSITY TOLERANCE (mA/cm²) — keyed on organism; see current-density-screen.md
A65: Strain / organism | B65: j_opt | C65: j_ceiling | D65: confidence | E65: source
A66: Cupriavidus necator | B66: 2 | C66: 4 | D66: low | E66: Inferred analogue (Zhang 2020; Bause 2018 biofilm 0.5). Run screen.
A67: Xanthobacter autotrophicus | B67: 2 | C67: 4 | D67: low | E67: No strain-specific j; mixed-HOB analogue. Run screen.
A68: Xanthobacter flavus | B68: 2 | C68: 4 | D68: low | E68: No strain-specific j; mixed-HOB analogue. Run screen.
A69: Xanthobacter tagetidis | B69: 2 | C69: 4 | D69: low | E69: No strain-specific j; mixed-HOB analogue. Run screen.
A70: Cupriavidus metallidurans | B70: 2 | C70: 4 | D70: low | E70: No strain-specific j; genus-mate of necator. Run screen.
A71: UdG (mixed) | B71: 2.14 | C71: 4.29 | D71: med | E71: Zhang 2020 (JCP 263:121596) + Pous 2022 (BiTE 18:101010); undivided cell.
A72: MAXIMUM-POWER CURRENT (AEP-Plugin clamp)
A73: Max electrolysis power | B73: power_max | C73: % | D73: 10 | E73: AEP-Plugin runtime clamp: electrolysis_power ≤ 10 % (MAX_ELECTROLYSIS_POWER).
A74: Max electrolysis current | B74: I_max | C74: mA | D74: =gerrit_slope*power_max+gerrit_int -> 12.9 | E74: Gerrit's Law at the power clamp.
A75: Max anode current density | B75: j_anode_max | C75: mA/cm² | D75: =I_max/A_anode_wet -> 6.4071414 | E75: Anode current density at max power.
A76: Status at max power | B76: j_flag_max | C76: - | D76: =IF(OR(j_anode_max>j_ceiling_strain,j_anode_max>anode_j_max),"EXCEED - max current over a limit",IF(OR(j_anode_max>j_opt_strain,j_anode_max>anode_j_cont),"watch - max current above optimum","OK - max current in range")) -> EXCEED - max current over a limit | E76: Worst of strain ceiling and plating at max power.
A78: CALCULATED FARADAIC SPLIT — the cathode competes with dissolved O₂ (wave-4)
A79: (import) target DO fraction | B79: ec_DO_frac | C79: - | D79: =Biology!$D$60 -> 0.22608696 | E79: → Biology (DO_frac_target)
A80: (import) dissolved-O₂ ceiling | B80: ec_O2_ceil | C80: mol/m³ | D80: =Biology!$D$27 -> 0.36477 | E80: → Biology (O2_ceil_C)
A81: (import) O₂ diffusivity at reactor T | B81: ec_D_O2 | C81: m²/s | D81: ='Mass Transfer'!$D$32 -> 1.9976723e-09 | E81: → Mass Transfer (D_O2)
A82: (import) reactor liquid volume | B82: ec_V_L | C82: L | D82: =Biology!$D$6/1000 -> 0.015 | E82: → Biology (V_charge / 1000)
A83: Electrode mass-transfer coefficient — O₂ | B83: km_O2 | C83: cm/s | D83: 0.004 | E83: Eisenberg, Tobias & Wilke 1954 (JES 101:306): Sh = 0.0791·Re^0.7·Sc^0.356 for a cylinder in axial swirl. At an assumed 20 cm/s swirl past a 6 mm rod this gives 3.7e-3 cm/s; bracket 2–6e-3 for 10–40 cm/s. The swirl velocity past a STATIONARY rod is the weak link — Sh goes as u^0.7, so a 4× velocity error is a 2.6× error here. One ferricyanide limiting-current run in the same vial at the same rpm would replace this estimate outright.
A84: Diffusivity exponent for k_m scaling | B84: km_exp | C84: - | D84: 0.644 | E84: k_m ∝ D^(1−0.356) from the Eisenberg correlation. (A rotating disc would give D^(2/3); a stagnant film D^1.)
A85: Design DO for the cathodic O₂ flux | B85: ec_DO_design | C85: mol/m³ | D85: =ec_DO_frac*ec_O2_ceil -> 0.082469739 | E85: The dissolved O₂ the schedule is designed to hold. The cathodic O₂ reduction below is evaluated here rather than at the modelled steady DO, which would make the sheet circular (DO depends on the net O₂, which depends on this loss).
A86: Cathodic O₂ current at the design DO | B86: i_ORR_design | C86: A | D86: =z_e_ORR*F_const*(km_O2/100)*ec_DO_design*(A_cath_wet/10000) -> 0.00012816555 | E86: i = n·F·k_m·C·A, the O₂ mass-transport limit at the cathode. This is current that does NOT make hydrogen, and it consumes dissolved O₂. Le Bozec 2001 (Corros Sci 43:765) show ORR on 316L in neutral solution running mixed 2e⁻/4e⁻ and limited by the passive film as much as by transport, so this is an upper bound on the loss.
A87: Cathodic O₂ current at the ceiling DO | B87: i_ORR_ceiling | C87: A | D87: =z_e_ORR*F_const*(km_O2/100)*ec_O2_ceil*(A_cath_wet/10000) -> 0.00056688609 | E87: The same flux if dissolved O₂ ever reached the inhibition ceiling — the worst case for the faradaic split.
A88: Cathodic faradaic efficiency (calculated) | B88: etaF_calc | C88: - | D88: =MAX(0,1-i_ORR_design/I_app) -> 0.9774753 | E88: 1 − (cathodic O₂ current)/(applied current). Replaces the previous assumption that every cathode electron makes H₂. Neutral-pH HER on stainless also has its own kinetic losses; this accounts only for the O₂ that competes for the current.
A89: same, at the ceiling DO (worst case) | B89: etaF_calc_min | C89: - | D89: =MAX(0,1-i_ORR_ceiling/I_app) -> 0.90037151 | E89: Lower bound on the cathodic efficiency if DO ran up to the inhibition ceiling.
A90: HYDROGEN PEROXIDE — the 2-electron branch of that O₂ reduction
A91: Peroxide selectivity of the O₂ reduction | B91: f_HOOH | C91: - | D91: 0.15 | E91: 10–20% of the O₂ reduced on stainless in neutral solution leaves as H₂O₂ rather than water (Le Bozec et al. 2001, RRDE on 316L/904L; prereduced surfaces favour the 4e⁻ route, polished ones run mixed). 0.15 is the midpoint. Nobody has published a defensible j₀/Tafel pair for ORR on steel — the surface is a potential-history-dependent Cr/Fe oxide — so this is bounded by transport above and by selectivity here.
A92: Peroxide molar mass | B92: M_H2O2 | C92: g/mol | D92: 34.0147 | E92: H₂O₂, IUPAC atomic weights.
A93: Peroxide production rate | B93: r_H2O2 | C93: mg/L/h | D93: =f_HOOH*i_ORR_design/(2*F_const)*M_H2O2*1000*3600/ec_V_L -> 0.81329698 | E93: 2 electrons per H₂O₂. This is a source term the model previously did not have at all, and it runs whenever there is current and dissolved O₂.
A94: Catalase clearance rate (growing culture) | B94: k_cat_cells | C94: 1/s | D94: 0.0041 | E94: First-order whole-culture peroxide clearance at ~1e8 cells/mL, from the measured half-lives (21 s at OD 1.0, 3.5 min at OD 0.1; Uhl & Dukan 2016, PLoS ONE 11:e0159706) — t½ ≈ 3 min here. Catalase is far below saturation at µM peroxide (Km is tens of mM), so first order is the right form. Scales with cell density: at inoculation it is effectively zero.
A95: Steady peroxide, growing culture | B95: H2O2_ss | C95: mg/L | D95: =r_H2O2/(k_cat_cells*3600) -> 0.055101422 | E95: Production ÷ catalase clearance. The bulk Fenton route is not modelled: the medium's 0.18 mM Fe(II) would consume peroxide within a second, but it is a one-shot 6 mg/L capacity that is itself oxidised away in 5–20 min, and bulk hydroxyl radicals are scavenged by bicarbonate within ~0.2 µm, far short of a cell. The damage route that matters is intracellular.
A96: Peroxide after 1 h with no biomass (lag) | B96: H2O2_lag_1h | C96: mg/L | D96: =r_H2O2 -> 0.81329698 | E96: At inoculation there is no catalase pool, so peroxide simply accumulates. This is the exposed window.
A97: Peroxide growth-inhibition threshold | B97: H2O2_thresh | C97: mg/L | D97: 0.17 | E97: 5 µM sustained extracellular H₂O₂ measurably slows growth (doubling time 63 → 94 min); E. coli K-12 in glucose minimal medium, chemostatted rather than bolus exposure — the same shape as an electrode source. Li & Imlay 2018, Free Radic Biol Med 120:217. Killing is a different regime entirely, 1–2 mM. No H₂O₂ dose-response exists for C. necator, Hydrogenophaga or Xanthobacter; this is the E. coli number, used as the closest available.
A98: Time to that threshold during lag | B98: t_H2O2_thresh | C98: min | D98: =IF(r_H2O2>0,H2O2_thresh/r_H2O2*60,NA()) -> 12.541544 | E98: How long an un-inoculated or just-inoculated vessel takes to pass the growth-inhibition threshold at the current electrolysis rate.
A99: Peroxide verdict | B99: H2O2_flag | C99: - | D99: =IF(H2O2_ss>H2O2_thresh,"PEROXIDE ABOVE THE GROWTH-INHIBITION THRESHOLD even with a full catalase pool ("&TEXT(H2O2_ss,"0.00")&" mg/L)",IF(H2O2_lag_1h>H2O2_thresh,"watch — steady growth is clear ("&TEXT(H2O2_ss,"0.000")&" mg/L) but LAG PHASE is not: peroxide passes the threshold in "&TEXT(t_H2O2_thresh,"0")&" min before biomass can scavenge it","OK — peroxide stays below the growth-inhibition threshold in both phases")) -> watch — steady growth is clear (0.055 mg/L) but LAG PHASE is not: peroxide passes the threshold in 13 min before biomass can scavenge it | E99: Two regimes: a growing culture clears peroxide in minutes, an inoculating one does not. Precedent for the failure mode: Torella 2015 (PNAS 112:2337) and Liu 2016 (Science 352:1210) ran this exact architecture and had to change cathode material because reactive oxygen and metal leaching poisoned the culture.
A100: ANODIC CHARGE BUDGET
A101: (import) chlorine current | B101: ec_I_Cl | C101: A | D101: =Chemistry!$D$133 -> 0 | E101: → Chemistry (I_Cl, chloride-mass-transport limited)
A102: (import) metal-dissolution charge fraction | B102: ec_corr_I | C102: - | D102: =Chemistry!$D$158 -> 0 | E102: → Chemistry (corr_I_frac; a DATA GAP until measured)
A103: Chlorine share of the anodic current | B103: f_Cl_anode | C103: - | D103: =ec_I_Cl/I_app -> 0 | E103: Chlorine evolution as a fraction of the applied current, at the chloride mass-transport limit. Small at trace chloride, and thermodynamically disfavoured besides — see the chlorine headroom on the Chemistry sheet.
A104: Anodic faradaic efficiency (calculated) | B104: etaF_OER_calc | C104: - | D104: =MAX(0,1-f_Cl_anode-IF(ISNUMBER(ec_corr_I),ec_corr_I,0)) -> 1 | E104: 1 − chlorine share − metal-dissolution share. Replaces the previous assertion of 1 with its unsupported "chloride-free medium" note. It remains an UPPER BOUND while the metal-dissolution charge is unmeasured: a corroding anode takes current that this cell still credits to oxygen.
...

Sheet Chemistry
A1: CHEMISTRY — buffered pH & anodic bleaching (open-system carbonate+phosphate charge balance, van't Hoff to reactor T)
A2: Parameter | B2: Name | C2: Unit | D2: Value | E2: Source / assumption
A3: IMPORTS (from other tabs)
A4: (import) Reactor temperature | B4: TKc | C4: K | D4: =Biology!$D$18 -> 298.15 | E4: → Biology
A5: (import) Dissolved CO₂ (worst case, full sparge) | B5: CO2aqc | C5: mol/L | D5: ='Mass Transfer'!$D$162 -> 0.0097159948 | E5: Schedule-dependent steady-state dissolved CO₂ (sawtooth limit cycle, bounded air-eq..saturation) - was the fixed full-sparge worst case
A6: (import) Electrolysis current (Gerrit's Law) | B6: Iappc | C6: A | D6: =Electrochemistry!$D$19 -> 0.00569 | E6: → Electrochemistry (I_app)
A7: (import) Faraday constant | B7: Fcc | C7: C/mol | D7: =Electrochemistry!$D$15 -> 96485.332 | E7: → Electrochemistry (F_const)
A8: (import) Reactor liquid volume | B8: VLc | C8: L | D8: =Biology!$D$6/1000 -> 0.015 | E8: → Biology (V_charge / 1000)
A9: Molar gas constant | B9: R_gas | C9: J/mol/K | D9: ='Mass Transfer'!$D$101 -> 8.3144626 | E9: → Mass Transfer (R_gas). Was a second, separately typed 8.314 that disagreed with the workbook's own constant in the fifth digit.
A11: EQUILIBRIUM CONSTANTS (van't Hoff to reactor T) | F11: K(T)=K₂₅·exp(−ΔH/R·(1/T−1/298.15)). ΔH = standard enthalpy of dissociation; well documented. Same van't Hoff treatment your sheet already uses for the Henry constants.
A12: constant | B12: K₂₅ | C12: ΔH kJ/mol | D12: K at reactor T | E12: source
A13: Carbonate Ka1 (pKa 6.35) | B13: 4.45e-07 | C13: 9.15 | D13: =B13*EXP(-C13*1000/R_gas*(1/TKc-1/298.15)) -> 4.45e-07 | E13: Handbook: K₂₅ (CRC/IUPAC); ΔH dissociation (CRC)
A14: Carbonate Ka2 (pKa 10.33) | B14: 4.69e-11 | C14: 14.9 | D14: =B14*EXP(-C14*1000/R_gas*(1/TKc-1/298.15)) -> 4.69e-11 | E14: Handbook: K₂₅ (CRC/IUPAC); ΔH dissociation (CRC)
A15: Phosphate Ka1 (pKa 2.15) | B15: 0.0071 | C15: -8 | D15: =B15*EXP(-C15*1000/R_gas*(1/TKc-1/298.15)) -> 0.0071 | E15: Handbook: K₂₅ (CRC/IUPAC); ΔH dissociation (CRC)
A16: Phosphate Ka2 (pKa 7.20) | B16: 6.31e-08 | C16: 3.6 | D16: =B16*EXP(-C16*1000/R_gas*(1/TKc-1/298.15)) -> 6.31e-08 | E16: Handbook: K₂₅ (CRC/IUPAC); ΔH dissociation (CRC)
A17: Phosphate Ka3 (pKa 12.38) | B17: 4.2e-13 | C17: 16 | D17: =B17*EXP(-C17*1000/R_gas*(1/TKc-1/298.15)) -> 4.2e-13 | E17: Handbook: K₂₅ (CRC/IUPAC); ΔH dissociation (CRC)
A18: Ammonium Ka (pKa 9.25) | B18: 5.6e-10 | C18: 52.2 | D18: =B18*EXP(-C18*1000/R_gas*(1/TKc-1/298.15)) -> 5.6e-10 | E18: Handbook: K₂₅ (CRC/IUPAC); ΔH dissociation (CRC)
A19: Water Kw | B19: 1e-14 | C19: 55.8 | D19: =B19*EXP(-C19*1000/R_gas*(1/TKc-1/298.15)) -> 1e-14 | E19: Handbook: K₂₅ (CRC/IUPAC); ΔH dissociation (CRC)
A20: Hypochlorous Ka (pKa 7.54) | B20: 2.8840315e-08 | C20: 13.8 | D20: =B20*EXP(-C20*1000/R_gas*(1/TKc-1/298.15)) -> 2.8840315e-08 | E20: Handbook: K₂₅ (CRC/IUPAC); ΔH dissociation (CRC)
A21: HOCl pKa at reactor T | B21: pKa_HOCl | C21: - | D21: =-LOG10(Ka_HOCl) -> 7.54 | E21: = −log₁₀(Ka_HOCl at T)
A23: MEDIA IONIC COMPOSITION (per litre, as published; Excel derives the charge balance) | F23: Trace-metal salts omitted from SID (<0.2 mM charge, negligible vs ~50–60 mM); their chloride is carried in the chloride row.
A24: salt | B24: MW g/mol | C24: MC02 g/L | D24: UdG g/L | E24: source
A25: KH₂PO₄ | B25: 136.086 | C25: 0 | D25: 2.3 | E25: Pous 2022 (BiTE 101010) / Pous 2023 (JECE 111550), UdG recipe
A26: Na₂HPO₄ | B26: 141.96 | C26: 2.895 | D26: 2.9 | E26: Media/README.md (MC02); per Sydow 2017 SI Table S1
A27: NaH₂PO₄·2H₂O | B27: 156.01 | C27: 3.06 | D27: 0 | E27: Media/README.md (MC02); per Sydow 2017 SI Table S1
A28: NaHCO₃ | B28: 84.007 | C28: 0 | D28: 1.05 | E28: Pous 2022 (BiTE 101010) / Pous 2023 (JECE 111550), UdG recipe
A29: K₂SO₄ | B29: 174.26 | C29: 0.17 | D29: 0 | E29: Media/README.md (MC02); per Sydow 2017 SI Table S1
A30: CaSO₄·2H₂O | B30: 172.17 | C30: 0.097 | D30: 0 | E30: Media/README.md (MC02); per Sydow 2017 SI Table S1
A31: MgSO₄·7H₂O | B31: 246.48 | C31: 0.8 | D31: 0.5 | E31: Media/README.md (MC02); per Sydow 2017 SI Table S1
A32: (NH₄)₂SO₄ | B32: 132.14 | C32: 0.943 | D32: 0.47 | E32: Media/README.md (MC02); per Sydow 2017 SI Table S1
A33: CaCl₂ | B33: 110.98 | C33: 0 | D33: 0.01 | E33: Pous 2022 (BiTE 101010) / Pous 2023 (JECE 111550), UdG recipe = 0.01 g/L.
A35: MC02 — total phosphate | B35: PT_mc02 | C35: mol/L | D35: =mc_Na2HPO4/MW_Na2HPO4+mc_NaH2PO4_2H2O/MW_NaH2PO4_2H2O -> 0.040007196 | E35: Σ phosphate salts
A36: MC02 — strong-ion difference | B36: SID_mc02 | C36: mol/L | D36: =(2*mc_Na2HPO4/MW_Na2HPO4+mc_NaH2PO4_2H2O/MW_NaH2PO4_2H2O+2*mc_K2SO4/MW_K2SO4+2*mc_MgSO4_7H2O/MW_MgSO4_7H2O+2*mc_CaSO4_2H2O/MW_CaSO4_2H2O)-2*(mc_NH42SO4/MW_NH42SO4+mc_MgSO4_7H2O/MW_MgSO4_7H2O+mc_K2SO4/MW_K2SO4+mc_CaSO4_2H2O/MW_CaSO4_2H2O) -> 0.046127523 | E36: Σ strong cations − strong anions
A37: MC02 — total ammonium | B37: NT_mc02 | C37: mol/L | D37: =2*mc_NH42SO4/MW_NH42SO4 -> 0.014272741
A38: MC02 — chloride | B38: Cl_mc02 | C38: mol/L | D38: =0 -> 0 | E38: no chloride salts
A39: UdG — total phosphate | B39: PT_udg | C39: mol/L | D39: =udg_KH2PO4/MW_KH2PO4+udg_Na2HPO4/MW_Na2HPO4 -> 0.037329367 | E39: Σ phosphate salts
A40: UdG — strong-ion difference | B40: SID_udg | C40: mol/L | D40: =(udg_NaHCO3/MW_NaHCO3+2*udg_Na2HPO4/MW_Na2HPO4+udg_KH2PO4/MW_KH2PO4+2*udg_MgSO4_7H2O/MW_MgSO4_7H2O+2*udg_CaCl2/MW_CaCl2)-(2*(udg_NH42SO4/MW_NH42SO4+udg_MgSO4_7H2O/MW_MgSO4_7H2O)+2*udg_CaCl2/MW_CaCl2) -> 0.063142948 | E40: Σ strong cations − strong anions
A41: UdG — total ammonium | B41: NT_udg | C41: mol/L | D41: =2*udg_NH42SO4/MW_NH42SO4 -> 0.0071136673
A42: UdG — chloride | B42: Cl_udg | C42: mol/L | D42: =2*udg_CaCl2/MW_CaCl2 -> 0.00018021265 | E42: trace-metal Cl excluded (negligible)
A44: (sel) strong-ion difference | B44: pH_SID | C44: mol/L | D44: =IF(Summary!$D$5="MC02",SID_mc02,IF(Summary!$D$5="UdG phosphate",SID_udg,NA())) -> 0.046127523 | E44: by media_sel
A45: (sel) total phosphate | B45: pH_PT | C45: mol/L | D45: =IF(Summary!$D$5="MC02",PT_mc02,IF(Summary!$D$5="UdG phosphate",PT_udg,NA())) -> 0.040007196 | E45: by media_sel
A46: (sel) total ammonium | B46: pH_NT | C46: mol/L | D46: =IF(Summary!$D$5="MC02",NT_mc02,IF(Summary!$D$5="UdG phosphate",NT_udg,NA())) -> 0.014272741 | E46: by media_sel
A47: (sel) chloride | B47: pH_Cl | C47: mol/L | D47: =IF(Summary!$D$5="MC02",Cl_mc02,IF(Summary!$D$5="UdG phosphate",Cl_udg,NA())) -> 0 | E47: by media_sel
A49: pH SOLVE GRID (charge residual vs trial pH; root = operating pH). Constants are on the CONCENTRATION scale (activity-corrected, rows 186-194) because the balance is written in concentrations. | B49: residual mol/L | C49: interp pH at root
A50: 4 | B50: =pH_SID + pH_NT*(10^-A50)/((10^-A50)+KaN_c) + (10^-A50) - (pH_PT*Ka1p_c*(10^-A50)^2 + 2*pH_PT*Ka1p_c*Ka2p_c*(10^-A50) + 3*pH_PT*Ka1p_c*Ka2p_c*Ka3p_c)/((10^-A50)^3 + Ka1p_c*(10^-A50)^2 + Ka1p_c*Ka2p_c*(10^-A50) + Ka1p_c*Ka2p_c*Ka3p_c) - Ka1c_c*CO2aqc/(10^-A50) - 2*Ka1c_c*Ka2c_c*CO2aqc/(10^-A50)^2 - Kw_c/(10^-A50) -> #DIV/0! | C50: =IF(AND(B50>=0,B51<0),A50+0.1*B50/(B50-B51),0) -> #DIV/0!
A51: 4.1 | B51: =pH_SID + pH_NT*(10^-A51)/((10^-A51)+KaN_c) + (10^-A51) - (pH_PT*Ka1p_c*(10^-A51)^2 + 2*pH_PT*Ka1p_c*Ka2p_c*(10^-A51) + 3*pH_PT*Ka1p_c*Ka2p_c*Ka3p_c)/((10^-A51)^3 + Ka1p_c*(10^-A51)^2 + Ka1p_c*Ka2p_c*(10^-A51) + Ka1p_c*Ka2p_c*Ka3p_c) - Ka1c_c*CO2aqc/(10^-A51) - 2*Ka1c_c*Ka2c_c*CO2aqc/(10^-A51)^2 - Kw_c/(10^-A51) -> #DIV/0! | C51: =IF(AND(B51>=0,B52<0),A51+0.1*B51/(B51-B52),0) -> #DIV/0!
A52: 4.2 | B52: =pH_SID + pH_NT*(10^-A52)/((10^-A52)+KaN_c) + (10^-A52) - (pH_PT*Ka1p_c*(10^-A52)^2 + 2*pH_PT*Ka1p_c*Ka2p_c*(10^-A52) + 3*pH_PT*Ka1p_c*Ka2p_c*Ka3p_c)/((10^-A52)^3 + Ka1p_c*(10^-A52)^2 + Ka1p_c*Ka2p_c*(10^-A52) + Ka1p_c*Ka2p_c*Ka3p_c) - Ka1c_c*CO2aqc/(10^-A52) - 2*Ka1c_c*Ka2c_c*CO2aqc/(10^-A52)^2 - Kw_c/(10^-A52) -> #DIV/0! | C52: =IF(AND(B52>=0,B53<0),A52+0.1*B52/(B52-B53),0) -> #DIV/0!
A53: 4.3 | B53: =pH_SID + pH_NT*(10^-A53)/((10^-A53)+KaN_c) + (10^-A53) - (pH_PT*Ka1p_c*(10^-A53)^2 + 2*pH_PT*Ka1p_c*Ka2p_c*(10^-A53) + 3*pH_PT*Ka1p_c*Ka2p_c*Ka3p_c)/((10^-A53)^3 + Ka1p_c*(10^-A53)^2 + Ka1p_c*Ka2p_c*(10^-A53) + Ka1p_c*Ka2p_c*Ka3p_c) - Ka1c_c*CO2aqc/(10^-A53) - 2*Ka1c_c*Ka2c_c*CO2aqc/(10^-A53)^2 - Kw_c/(10^-A53) -> #DIV/0! | C53: =IF(AND(B53>=0,B54<0),A53+0.1*B53/(B53-B54),0) -> #DIV/0!
A54: 4.4 | B54: =pH_SID + pH_NT*(10^-A54)/((10^-A54)+KaN_c) + (10^-A54) - (pH_PT*Ka1p_c*(10^-A54)^2 + 2*pH_PT*Ka1p_c*Ka2p_c*(10^-A54) + 3*pH_PT*Ka1p_c*Ka2p_c*Ka3p_c)/((10^-A54)^3 + Ka1p_c*(10^-A54)^2 + Ka1p_c*Ka2p_c*(10^-A54) + Ka1p_c*Ka2p_c*Ka3p_c) - Ka1c_c*CO2aqc/(10^-A54) - 2*Ka1c_c*Ka2c_c*CO2aqc/(10^-A54)^2 - Kw_c/(10^-A54) -> #DIV/0! | C54: =IF(AND(B54>=0,B55<0),A54+0.1*B54/(B54-B55),0) -> #DIV/0!
A55: 4.5 | B55: =pH_SID + pH_NT*(10^-A55)/((10^-A55)+KaN_c) + (10^-A55) - (pH_PT*Ka1p_c*(10^-A55)^2 + 2*pH_PT*Ka1p_c*Ka2p_c*(10^-A55) + 3*pH_PT*Ka1p_c*Ka2p_c*Ka3p_c)/((10^-A55)^3 + Ka1p_c*(10^-A55)^2 + Ka1p_c*Ka2p_c*(10^-A55) + Ka1p_c*Ka2p_c*Ka3p_c) - Ka1c_c*CO2aqc/(10^-A55) - 2*Ka1c_c*Ka2c_c*CO2aqc/(10^-A55)^2 - Kw_c/(10^-A55) -> #DIV/0! | C55: =IF(AND(B55>=0,B56<0),A55+0.1*B55/(B55-B56),0) -> #DIV/0!
A56: 4.6 | B56: =pH_SID + pH_NT*(10^-A56)/((10^-A56)+KaN_c) + (10^-A56) - (pH_PT*Ka1p_c*(10^-A56)^2 + 2*pH_PT*Ka1p_c*Ka2p_c*(10^-A56) + 3*pH_PT*Ka1p_c*Ka2p_c*Ka3p_c)/((10^-A56)^3 + Ka1p_c*(10^-A56)^2 + Ka1p_c*Ka2p_c*(10^-A56) + Ka1p_c*Ka2p_c*Ka3p_c) - Ka1c_c*CO2aqc/(10^-A56) - 2*Ka1c_c*Ka2c_c*CO2aqc/(10^-A56)^2 - Kw_c/(10^-A56) -> #DIV/0! | C56: =IF(AND(B56>=0,B57<0),A56+0.1*B56/(B56-B57),0) -> #DIV/0!
A57: 4.7 | B57: =pH_SID + pH_NT*(10^-A57)/((10^-A57)+KaN_c) + (10^-A57) - (pH_PT*Ka1p_c*(10^-A57)^2 + 2*pH_PT*Ka1p_c*Ka2p_c*(10^-A57) + 3*pH_PT*Ka1p_c*Ka2p_c*Ka3p_c)/((10^-A57)^3 + Ka1p_c*(10^-A57)^2 + Ka1p_c*Ka2p_c*(10^-A57) + Ka1p_c*Ka2p_c*Ka3p_c) - Ka1c_c*CO2aqc/(10^-A57) - 2*Ka1c_c*Ka2c_c*CO2aqc/(10^-A57)^2 - Kw_c/(10^-A57) -> #DIV/0! | C57: =IF(AND(B57>=0,B58<0),A57+0.1*B57/(B57-B58),0) -> #DIV/0!
A58: 4.8 | B58: =pH_SID + pH_NT*(10^-A58)/((10^-A58)+KaN_c) + (10^-A58) - (pH_PT*Ka1p_c*(10^-A58)^2 + 2*pH_PT*Ka1p_c*Ka2p_c*(10^-A58) + 3*pH_PT*Ka1p_c*Ka2p_c*Ka3p_c)/((10^-A58)^3 + Ka1p_c*(10^-A58)^2 + Ka1p_c*Ka2p_c*(10^-A58) + Ka1p_c*Ka2p_c*Ka3p_c) - Ka1c_c*CO2aqc/(10^-A58) - 2*Ka1c_c*Ka2c_c*CO2aqc/(10^-A58)^2 - Kw_c/(10^-A58) -> #DIV/0! | C58: =IF(AND(B58>=0,B59<0),A58+0.1*B58/(B58-B59),0) -> #DIV/0!
A59: 4.9 | B59: =pH_SID + pH_NT*(10^-A59)/((10^-A59)+KaN_c) + (10^-A59) - (pH_PT*Ka1p_c*(10^-A59)^2 + 2*pH_PT*Ka1p_c*Ka2p_c*(10^-A59) + 3*pH_PT*Ka1p_c*Ka2p_c*Ka3p_c)/((10^-A59)^3 + Ka1p_c*(10^-A59)^2 + Ka1p_c*Ka2p_c*(10^-A59) + Ka1p_c*Ka2p_c*Ka3p_c) - Ka1c_c*CO2aqc/(10^-A59) - 2*Ka1c_c*Ka2c_c*CO2aqc/(10^-A59)^2 - Kw_c/(10^-A59) -> #DIV/0! | C59: =IF(AND(B59>=0,B60<0),A59+0.1*B59/(B59-B60),0) -> #DIV/0!
A60: 5 | B60: =pH_SID + pH_NT*(10^-A60)/((10^-A60)+KaN_c) + (10^-A60) - (pH_PT*Ka1p_c*(10^-A60)^2 + 2*pH_PT*Ka1p_c*Ka2p_c*(10^-A60) + 3*pH_PT*Ka1p_c*Ka2p_c*Ka3p_c)/((10^-A60)^3 + Ka1p_c*(10^-A60)^2 + Ka1p_c*Ka2p_c*(10^-A60) + Ka1p_c*Ka2p_c*Ka3p_c) - Ka1c_c*CO2aqc/(10^-A60) - 2*Ka1c_c*Ka2c_c*CO2aqc/(10^-A60)^2 - Kw_c/(10^-A60) -> #DIV/0! | C60: =IF(AND(B60>=0,B61<0),A60+0.1*B60/(B60-B61),0) -> #DIV/0!
A61: 5.1 | B61: =pH_SID + pH_NT*(10^-A61)/((10^-A61)+KaN_c) + (10^-A61) - (pH_PT*Ka1p_c*(10^-A61)^2 + 2*pH_PT*Ka1p_c*Ka2p_c*(10^-A61) + 3*pH_PT*Ka1p_c*Ka2p_c*Ka3p_c)/((10^-A61)^3 + Ka1p_c*(10^-A61)^2 + Ka1p_c*Ka2p_c*(10^-A61) + Ka1p_c*Ka2p_c*Ka3p_c) - Ka1c_c*CO2aqc/(10^-A61) - 2*Ka1c_c*Ka2c_c*CO2aqc/(10^-A61)^2 - Kw_c/(10^-A61) -> #DIV/0! | C61: =IF(AND(B61>=0,B62<0),A61+0.1*B61/(B61-B62),0) -> #DIV/0!
... A99: 8.9 | B99: =pH_SID + pH_NT*(10^-A99)/((10^-A99)+KaN_c) + (10^-A99) - (pH_PT*Ka1p_c*(10^-A99)^2 + 2*pH_PT*Ka1p_c*Ka2p_c*(10^-A99) + 3*pH_PT*Ka1p_c*Ka2p_c*Ka3p_c)/((10^-A99)^3 + Ka1p_c*(10^-A99)^2 + Ka1p_c*Ka2p_c*(10^-A99) + Ka1p_c*Ka2p_c*Ka3p_c) - Ka1c_c*CO2aqc/(10^-A99) - 2*Ka1c_c*Ka2c_c*CO2aqc/(10^-A99)^2 - Kw_c/(10^-A99) -> #DIV/0! | C99: =IF(AND(B99>=0,B100<0),A99+0.1*B99/(B99-B100),0) -> #DIV/0!
A100: 9 | B100: =pH_SID + pH_NT*(10^-A100)/((10^-A100)+KaN_c) + (10^-A100) - (pH_PT*Ka1p_c*(10^-A100)^2 + 2*pH_PT*Ka1p_c*Ka2p_c*(10^-A100) + 3*pH_PT*Ka1p_c*Ka2p_c*Ka3p_c)/((10^-A100)^3 + Ka1p_c*(10^-A100)^2 + Ka1p_c*Ka2p_c*(10^-A100) + Ka1p_c*Ka2p_c*Ka3p_c) - Ka1c_c*CO2aqc/(10^-A100) - 2*Ka1c_c*Ka2c_c*CO2aqc/(10^-A100)^2 - Kw_c/(10^-A100) -> #DIV/0! | C100: =0 -> 0
A102: Parameter | B102: Name | C102: Unit | D102: Value | E102: Source / assumption
A103: OPERATING pH (buffered, worst case) | B103: pH_op | C103: - | D103: =IF(n_cross=1,SUM(C50:C100),NA()) -> #DIV/0! | E103: Root of the charge-balance grid, on the concentration scale. A pH probe reads hydrogen-ion ACTIVITY, so the comparable number is pH_meas (D220) — about 0.11 higher at this ionic strength. Every downstream pH comparison uses pH_meas. | F103: WORST CASE: pH at full-sparge dissolved CO₂ (the trough during/after a CO₂ pulse). A real probe with response lag may read higher between pulses — a measurement that misses this trough is not the model being wrong.
A104: HOCl fraction at operating pH | B104: pH_fHOCl | C104: - | D104: =1/(1+10^(pH_meas-pKa_HOCl)) -> #DIV/0! | E104: Henderson–Hasselbalch on the activity scale: the tabulated pKa is a thermodynamic constant, so it pairs with the activity-scale pH, not the concentration-scale root.
A105: pH-grid crossings (must be exactly 1) | B105: n_cross | C105: - | D105: =SUMPRODUCT((B50:B99>=0)*(B51:B100<0)) -> #DIV/0! | E105: Count of +→− sign crossings of the charge residual on the pH grid. Exactly 1 = a single bracketed root inside [4,9]. 0 (root outside the grid) or >1 (non-monotone) must NOT be read as pH 0.
A106: ANODIC BLEACHING (free-chlorine evolution; conservative FE=1) | G106: HOCl-tolerance evidence (Comments)
A107: Naïve FE=1 production ceiling (NOT operative) | B107: bleach_rate | C107: mg/L/h | D107: =Iappc/(2*Fcc)*M_HOCl*3600/VLc -> 371.24491 | E107: Naïve FE=1 upper bound (all anode current → Cl₂). Superseded by the mass-transport-limited chlorine current I_Cl (D133) and the production rate P_HOCl (D134). Kept only to show the overstatement (~50× as the model now stands). | G107: Threshold seed 0.2 mg/L free chlorine = conservative FIRST-IMPAIRMENT floor for suspended gram-negative environmental bacteria; deliberately below water-industry disinfection doses. Tiers: 0.02-0.1 no inhibition; 0.2 first-impairment (pick); 0.3-0.6 measurable die-off; 0.75-1.75 complete regrowth inhibition.
A108: Time to ~1 ppm HOCl (FE=1) | B108: bleach_t1ppm | C108: min | D108: =1/(bleach_rate)*60 -> 0.16161838 | E108: ~1 mg/L HOCl ≈ bactericidal threshold | G108: C. necator: no direct HOCl MIC; genus-mate C. metallidurans is documented chlorine/chloramine-TOLERANT (Gomez-Alvarez/Wang 2018, STOTEN). 0.2 mg/L is a safety UNDERestimate, not its breaking point — do not assume necator is chlorine-fragile.
A109: Bleaching / hypochlorite flag | B109: bleach_flag | C109: - | D109: =IF(C_eff<Cl_onset,"negligible free chlorine ("&TEXT(C_eff,"0.00")&" mg/L < onset); does NOT account for the Exp-2 death - see metal_flag",IF(C_eff<Cl_kill,"sub-lethal "&TEXT(C_eff,"0.00")&" mg/L (band "&TEXT(C_eff_lo,"0.00")&"-"&TEXT(C_eff_hi,"0.00")&"); chloride-pool-bounded, cannot reach the kill threshold in this medium; does NOT explain the death - see metal_flag","SEVERE free chlorine: "&TEXT(C_eff,"0.0")&" mg/L biofilm/electrode damage (Baek 2021)")) -> #DIV/0! | E109: Operative flag: effective biocidal chlorine (C_eff, D145) vs the sub-lethal onset (D146) and kill (D147). Graded — MILD for trace-chloride UdG, SEVERE only at high chloride/current. | G109: Hydrogenophaga: dominant chlorine/chloramine-RESISTANT genus in chloraminated distribution systems; survives >0.5 mg/L. Treat as resistant; 0.2 mg/L is a floor, not an observed inhibition point.
A110: pH band flag (HOB optimum 6.5–7.5) | B110: pH_band_flag | C110: - | D110: =IF(pH_meas<6.5,"pH BELOW HOB optimum (<6.5) — reduce the CO₂ dose or lengthen the interval",IF(pH_meas>7.5,"pH above optimum (>7.5)","pH in HOB band 6.5–7.5")) -> #DIV/0! | E110: HOB optimum 6.5–7.5 (Pous / Rovira-Alsina), compared against the activity-scale pH a probe would read. A short oxygen-driven sparge interval delivers far more CO₂ than the carbon demand, so this flag is the counterweight to the DO-limited interval on Mass Transfer. | G110: Xanthobacter: no species value found in literature (genuine gap — not invented); use the 0.2 mg/L gram-negative fallback. CONSERVATIVE-FLOOR CAVEAT: the 0.2 seed is a safety floor; real impairment for these resistant genera is likely higher (mid-tenths to >1 mg/L). necator/Xanthobacter rows are inferred, not measured.
A112: MEDIA LOOKUP (selector source)
A113: Media | B113: buffer | C113: buffer conc mM | D113: notes | E113: source
A114: MC02 | B114: phosphate | C114: =PT_mc02*1000 -> 40.007196 | D114: low-chloride, organic-free | E114: Media/README.md (MC02); per Sydow 2017 SI
A115: UdG phosphate | B115: phosphate | C115: =PT_udg*1000 -> 37.329367 | D115: low-chloride (trace Cl⁻); N varies urea/(NH₄)₂SO₄/NH₄Cl | E115: Pous 2022 & 2023; Rovira-Alsina 2025
A125: Naïve FE=1 ceiling: all chloride → free chlorine (NOT operative) | B125: HOCl_max | C125: mg/L | D125: =pH_Cl*pH_fHOCl*M_HOCl -> #DIV/0! | E125: Naïve FE=1 ceiling: the whole chloride inventory converted to free chlorine, times the HOCl fraction at the operating pH. Superseded by the steady free chlorine HOCl_ss (D139); it ignores both the chloride mass-transport cap and the ammonium demand.
A127: FREE-CHLORINE PENALTY MODEL (graded, kinetic — operative; supersedes the naïve FE=1 ceiling above)
A128: Max active-Cl evolution efficiency (high-Cl plateau) | B128: FE_CER | C128: - | D128: 0.5 | E128: Active-chlorine current efficiency on the high-chloride plateau (approaches ~1 above ~50 mM Cl⁻; Vos & Koper, JACS 140:10270 / JEAC 819:260). 0.5 is a mid-plateau value and is NOT the operative limit here — at trace Cl⁻ the chloride mass-transport limit (D132) binds.
A129: Cl⁻ mass-transfer coefficient | B129: km_Cl | C129: cm/s | D129: 0.00405 | E129: Same Eisenberg–Tobias–Wilke basis as the O₂ coefficient on the Electrochemistry sheet, scaled by D^0.644: k_m(Cl⁻) = k_m(O₂)·(D_Cl/D_O2)^0.644 = 4.0e-3 × 1.01. Bracket 2–6e-3 cm/s, dominated by the unmeasured swirl velocity past the rod.
A130: Anode wetted area | B130: A_anode | C130: cm² | D130: =Electrochemistry!$D$46 -> 2.0133784 | E130: Computed from the shape-aware wetted area (Electrochemistry A_anode_wet); tracks reactor & electrode.
A131: Cl₂ current — efficiency-limited | B131: I_Cl_FE | C131: A | D131: =Iappc*FE_CER -> 0.002845 | E131: Applied anode current × plateau efficiency.
A132: Cl₂ current — chloride mass-transport limit | B132: I_Cl_mt | C132: A | D132: =Fcc*km_Cl*(pH_Cl/1000)*A_anode -> 0 | E132: i_lim = n·F·k_m·[Cl⁻]·A, n = 1 per ARRIVING chloride; [Cl⁻] in mol/cm³ = pH_Cl/1000. Caps chlorine at the chloride flux — binds at trace Cl⁻ (0.112 mA for UdG at the current anode wetted area), so production scales with chloride.
A133: Realistic chlorine current (binding limit) | B133: I_Cl | C133: A | D133: =MIN(I_Cl_FE,I_Cl_mt) -> 0 | E133: Smaller of efficiency- and mass-transport-limited.
A134: Volumetric free-chlorine production | B134: P_HOCl | C134: mol/L/s | D134: =I_Cl/(n_e_Cl*Fcc*VLc) -> 0 | E134: P_HOCl = I_Cl/(n_e_Cl·F·V), n_e_Cl = 2 on every route (D148).
A135: Medium ammonium (as N) | B135: NH3_N | C135: mg/L | D135: =pH_NT*MW_N -> 199.91828 | E135: Active-medium total ammonium × 14.007 g/mol N.
A136: Monochloramine formation rate constant | B136: k1_NH2Cl | C136: M⁻¹s⁻¹ | D136: 4200000 | E136: HOCl + NH₃ → NH₂Cl, k₁ = 4.2e6 M⁻¹s⁻¹ (Morris & Isaac 1983; Jafvert & Valentine 1992, ES&T 26:577, DOI 10.1021/es00027a022). Fast but NOT instantaneous.
A137: Ammonium pKa (NH₄⁺/NH₃) | B137: pKa_NH4 | C137: - | D137: =-LOG10(Ka_NH4) -> 9.251812 | E137: From the van ʼt Hoff-corrected Ka_NH4 (D18) so the sheet cannot hold two different ammonium pKa values at once. Only free NH₃ reacts with HOCl; at pH 7 about 0.6% of the ammonium pool is free NH₃, so the sink is finite and a steady residual coexists.
A138: Free ammonia | B138: NH3_free | C138: mol/L | D138: =pH_NT/(1+10^(pKa_NH4-pH_meas)) -> #DIV/0! | E138: NH₃ = NH₄_tot/(1+10^(pKa_NH4−pH)). The reactive fraction that scavenges HOCl.
A139: Steady bulk free HOCl | B139: HOCl_ss | C139: mol/L | D139: =P_HOCl/(k1_NH2Cl*NH3_free) -> #DIV/0! | E139: [HOCl]_ss = production/(k₁·NH₃_free). Non-zero by construction; rises with current, falls with ammonium/pH.
A140: Steady bulk free HOCl (mass) | B140: HOCl_ss_mgL | C140: mg/L | D140: =HOCl_ss*M_HOCl -> #DIV/0! | E140: Bulk free chlorine, mg/L. Small for UdG — below the impairment onset, so no bulk sterilisation (UdG runs for days).
A141: Anode boundary-layer enrichment | B141: f_local | C141: - | D141: 10 | E141: Local HOCl at the anode is higher than bulk before it diffuses out and meets ammonia (boundary-layer time ~0.1–10 s ≫ ms bulk scavenging). f_local ≥ 1; sub-mM value unmeasured — SENSITIVITY parameter.
A142: Monochloramine effective residence | B142: tau_NH2Cl | C142: h | D142: 1 | E142: Time combined chlorine persists before consumption (growth N-uptake, cathodic reduction, dilution). Lit: minutes–hours; system-specific value unknown — SENSITIVITY parameter.
A143: Steady combined chlorine (monochloramine) | B143: NH2Cl_mgL | C143: mg/L | D143: =MIN(P_HOCl*tau_NH2Cl*3600*M_HOCl,cl_per_N*NH3_N,Cl_pool_mgL) -> 0 | E143: Production held as monochloramine over its residence, capped at the ammonium capacity (5.06 mg Cl₂/mg N). Longer-lived and still biocidal — not harmless.
A144: Monochloramine potency divisor | B144: R_chloramine | C144: - | D144: 25 | E144: Monochloramine is ~18–70× less biocidal than free chlorine (EPA SWTR ~18×, Giardia; IWA 2008 ~70×, E. coli). 25 = conservative (kinder-to-chloramine).
A145: EFFECTIVE biocidal chlorine load | B145: C_eff | C145: mg/L | D145: =f_local*HOCl_ss_mgL+NH2Cl_mgL/R_chloramine -> #DIV/0! | E145: OPERATIVE bleaching value: local-weighted free HOCl + combined chlorine ÷ potency. At trace chloride it is bounded by the chloride pool (D149) rather than by current, so it scales with the medium's chloride; it only becomes current-sensitive once the pool cap stops binding.
A146: Free-chlorine impairment onset (sub-lethal) | B146: Cl_onset | C146: mg/L | D146: 0.1 | E146: Growth measurably slowed above ~0.1 mg/L free-Cl-equiv (graded, gram-negative proxy; Murray 2017 Ecotox 26:1115; HOCl oxidative-stress onset). Distinct from kill.
A147: Free-chlorine kill threshold | B147: Cl_kill | C147: mg/L | D147: 2 | E147: ~1–5 mg/L for tolerant gram-negatives; 2 used. Above C_eff this → biofilm/electrode damage (Baek 2021, CEJ 405:126742).
A148: electrons per produced HOCl | B148: n_e_Cl | C148: e-/HOCl | D148: =2 -> 2 | E148: Electrons per HOCl formed — 2 on every route. 2Cl⁻ → Cl₂ + 2e⁻ then Cl₂ + H₂O → HOCl + H⁺ + Cl⁻ is 2 e⁻ per HOCl (and 1 net chloride consumed); the direct route Cl⁻ + H₂O → HOCl + H⁺ + 2e⁻ is also 2. Distinct from the n = 1 per ARRIVING chloride in the mass-transport limit (D132) — that is a flux count, not a stoichiometry.
A149: chloride-pool ceiling on chlorine | B149: Cl_pool_mgL | C149: mg/L | D149: =pH_Cl*M_HOCl -> 0 | E149: Total chloride pool as HOCl-equivalent; chlorine (free+combined) cannot exceed this. UdG CaCl2-derived (closed batch also depletes it)
A150: monochloramine residence (low) | B150: tau_NH2Cl_lo | C150: h | D150: 0.016666667 | E150: Low bound of monochloramine residence (~1 min); weak estimate, swept for the C_eff band
A151: monochloramine residence (high) | B151: tau_NH2Cl_hi | C151: h | D151: 5 | E151: High bound of monochloramine residence (5 h); weak estimate, swept for the C_eff band
A152: chloramine potency divisor (low) | B152: R_chloramine_lo | C152: x | D152: 18 | E152: Most-potent end of the monochloramine potency-divisor band (defensible)
A153: chloramine potency divisor (high) | B153: R_chloramine_hi | C153: x | D153: 70 | E153: Least-potent end of the monochloramine potency-divisor band
A154: combined chlorine (low-tau) | B154: NH2Cl_lo | C154: mg/L | D154: =MIN(P_HOCl*tau_NH2Cl_lo*3600*M_HOCl,cl_per_N*NH3_N,Cl_pool_mgL) -> 0 | E154: Combined chlorine at the low-tau bound, chloride-pool-capped
...

Sheet Biology
A1: BIOLOGY
A2: Parameter | B2: Name | C2: Unit | D2: Value | E2: Source / assumption
A3: IMPORTS (from other tabs)
A4: (import) H₂ generation rate | B4: rH2_gen | C4: mol/h | D4: =Electrochemistry!$D$21 -> 0.00010375983 | E4: =HYPERLINK("#Electrochemistry!D21","→ Electrochemistry") -> → Electrochemistry
A5: (import) Net O₂ to dissolved pool | B5: O2_net_gen | C5: mol/h | D5: =Electrochemistry!$D$29 -> 5.0684409e-05 | E5: =HYPERLINK("#Electrochemistry!D29","→ Electrochemistry") -> → Electrochemistry
A6: (import) LIQUID VOLUME TO CHARGE | B6: V_charge | C6: mL | D6: =Geometry!$D$41 -> 15 | E6: =HYPERLINK("#Geometry!D41","→ Geometry") -> → Geometry
A7: (import) HOB organism | B7: organism_sel | D7: =Summary!$D$4 -> UdG (mixed) | E7: =HYPERLINK("#Summary!D4","→ Summary") -> → Summary
A8: (import) HOB organism | B8: organism_sel | D8: =Summary!$D$4 -> UdG (mixed) | E8: =HYPERLINK("#Summary!D4","→ Summary") -> → Summary
A10: Gas requirement ratio - H₂ | B10: bio_H2 | C10: - | D10: =IF(ISNUMBER(cal_knall_H2),cal_knall_H2,6) -> 6 | E10: H₂:O₂:CO₂ UPTAKE ratio (not feed; phase-dependent, Lu & Yu 2019). Knallgas caps O₂:H₂≤0.5; growth gives O₂:H₂≈0.29–0.35, CO₂:H₂≈0.15–0.19. 6:2:1 = mid-range central. Feed optimum 7:2:1 (Ishizaki 2001). Can't measure pre-growth.
A11: Gas requirement ratio - O₂ | B11: bio_O2 | C11: - | D11: =IF(ISNUMBER(cal_knall_O2),cal_knall_O2,2) -> 2 | E11: O₂:H₂ uptake, range 0.29–0.35 (×6 → 1.75–2.1). 2 = central; 1.8 (lean) is growth-protective.
A12: Gas requirement ratio - CO₂ | B12: bio_CO2 | C12: - | D12: =IF(ISNUMBER(cal_knall_CO2),cal_knall_CO2,1) -> 1 | E12: CO₂:H₂ uptake, range 0.15–0.19 (×6 → 0.9–1.15). 1 = central. Supply ≫ demand → non-limiting.
A13: H₂ consumed | B13: H2_cons | C13: mol/h | D13: =rH2_gen -> 0.00010375983 | E13: Assumes 100% of evolved H₂ consumed — steady growth only; ~0 during lag (see §13).
A14: O₂ consumed | B14: O2_cons | C14: mol/h | D14: =H2_cons*bio_O2/bio_H2 -> 3.4586611e-05 | E14: Assumes 100% H₂ uptake (upper bound); true limit is gas-liquid H₂ transfer — see H2_turnover
A15: CO₂ consumed (carbon fixation) | B15: CO2_cons | C15: mol/h | D15: =H2_cons*bio_CO2/bio_H2 -> 1.7293306e-05 | E15: H₂ consumed x (CO₂/H₂ ratio).
A16: EXCESS O₂ to remove | B16: O2_excess | C16: mol/h | D16: =MAX(0,O2_net_gen-O2_cons) -> 1.6097798e-05 | E16: Net electrolytic O₂ minus biological uptake, floored at zero. The floor matters: at the knallgas cap (O₂:H₂ = 0.5, i.e. bio_O2 = 3) uptake exactly consumes the electrolytic surplus and everything downstream that divides by this would blow up. Upper bound in any case, because it rests on the full-H₂-uptake assumption above.
A17: Temperature | B17: T_C | C17: °C | D17: =Summary!$D$8 -> 25 | E17: C. necator optimum ~30 °C. Input.
A18: Temperature (absolute) | B18: T_K | C18: K | D18: =T_C+273.15 -> 298.15 | E18: °C + 273.15.
A19: Surface pressure | B19: P_atm | C19: Pa | D19: =IF(Summary!$D$10>0,Summary!$D$10,101325) -> 101325 | E19: Atmospheric at the liquid surface (assumed).
A20: Standard atmosphere (atm->Pa) | B20: Pa_per_atm | C20: Pa/atm | D20: 101325 | E20: Defined: 1 atm = 101 325 Pa exactly.
A21: Henry solubility O₂ (ref, 298.15 K) | B21: H_O2ref | C21: mol/m³/Pa | D21: 1.2e-05 | E21: Sander (2023) recommended H^cp O2; reproduces ~7.5 mg/L air-saturation at 30 degC
A22: Henry T-dependence O₂ | B22: H_O2T | C22: K | D22: 1500 | E22: Sander (2023): d ln(Hcp)/d(1/T).
A23: Reference temperature | B23: T_ref | C23: K | D23: 298.15 | E23: Standard reference for Henry constants.
A24: Henry solubility O₂ at T | B24: H_O2_T | C24: mol/m³/Pa | D24: =H_O2ref*EXP(H_O2T*(1/T_K-1/T_ref)) -> 1.2e-05 | E24: van 't Hoff correction to reactor T.
A25: O₂ growth-inhibition ceiling (gas) | B25: O2_ceil_atm | C25: atm | D25: 0.3 | E25: Whole-cell growth inhibited above ~0.30 atm O₂ (Amer & Kim 2023); the [NiFe] hydrogenase itself is O₂-tolerant.
A26: O₂ ceiling (partial pressure) | B26: O2_ceil_Pa | C26: Pa | D26: =O2_ceil_atm*Pa_per_atm -> 30397.5 | E26: Ceiling in Pa.
A27: Dissolved-O₂ ceiling | B27: O2_ceil_C | C27: mol/m³ | D27: =H_O2_T*O2_ceil_Pa -> 0.36477 | E27: Henry's law at the gas ceiling.
A28: Dissolved-O₂ ceiling | B28: O2_ceil_uM | C28: µM | D28: =O2_ceil_C*1000 -> 364.77 | E28: mol/m³ = mM; ×1000 = µM. Aim: minimise dissolved O₂; floor set by O₂-removal capacity (§11).
A29: Henry solubility CO₂ (ref, 298.15 K) | B29: H_CO2ref | C29: mol/m³/Pa | D29: 0.00033 | E29: Sander (2023) compilation; CO₂ ~28× more soluble than O₂ (vs the 1.2e-5 O₂ Hcp).
A30: Henry T-dependence CO₂ | B30: H_CO2T | C30: K | D30: 2400 | E30: Sander (2023): d ln(Hcp)/d(1/T) for CO₂.
A31: Henry solubility CO₂ at T | B31: H_CO2_T | C31: mol/m³/Pa | D31: =H_CO2ref*EXP(H_CO2T*(1/T_K-1/T_ref)) -> 0.00033 | E31: van 't Hoff to reactor T.
A32: CO₂ partial pressure at sparge | B32: p_CO2_sparge | C32: Pa | D32: =P_atm -> 101325 | E32: Pure-CO₂ sparge: p_CO₂ ≈ surface pressure during a pulse. Assumption.
A33: Dissolved CO₂ (during sparge) | B33: CO2_diss | C33: mol/m³ | D33: =H_CO2_T*p_CO2_sparge -> 33.43725 | E33: Equilibrium dissolved CO₂ while sparging (mol/m³ = mM).
A34: RuBisCO Km for CO₂ | B34: Km_CO2 | C34: µM | D34: 50 | E34: RuBisCO Km(CO₂) ~ order 50 µM. Coarse — confirm.
A35: Carbon margin (dissolved CO₂ : Km) | B35: CO2_carbon_margin | C35: × | D35: =CO2_diss*1000/Km_CO2 -> 668.745 | E35: Dissolved CO₂ : RuBisCO Km. ≫1 = saturating (duty-averaged lower).
A36: Carbonic-acid Ka1 (apparent) | B36: Ka1_carb | C36: mol/L | D36: 4.45e-07 | E36: CO₂(aq)+H₂O ⇌ H⁺+HCO₃⁻, pKa1 6.35 (25 °C).
A37: pH — UNBUFFERED worst case | B37: pH_CO2_unbuf | C37: - | D37: =-LOG10(SQRT(Ka1_carb*(CO2_diss/1000))) -> 3.9137047 | E37: Unbuffered worst case (pure water + CO₂) — lower bound only; the Sydow phosphate medium holds pH near setpoint.
A38: Henry solubility H₂ (ref, 298.15 K) | B38: H_H2ref | C38: mol/m³/Pa | D38: 7.8e-06 | E38: Sander (2023). H₂ ~1.5× less soluble than O₂ (vs the 1.2e-5 O₂ Hcp).
A39: Henry T-dependence H₂ | B39: H_H2T | C39: K | D39: 500 | E39: Sander (2023): d ln(Hcp)/d(1/T) for H₂ (weak T-dependence).
A40: Henry solubility H₂ at T | B40: H_H2_T | C40: mol/m³/Pa | D40: =H_H2ref*EXP(H_H2T*(1/T_K-1/T_ref)) -> 7.8e-06 | E40: van 't Hoff to reactor T.
A41: Dissolved-H₂ saturation (1 atm) | B41: C_H2_sat | C41: mol/m³ | D41: =H_H2_T*P_atm -> 0.790335 | E41: Max dissolved H₂ at 1 atm — the cells' H₂ ceiling.
A42: Time to saturate dissolved H₂ (LAG) | B42: t_H2_sat | C42: min | D42: =C_H2_sat*(V_charge/1000000)/rH2_gen*60 -> 6.8552683 | E42: Lag: dissolved H₂ saturates this fast unconsumed, then bubbles off (lost + explosive headspace). Mirrors the O₂ lag timescale.
A43: H₂ pool turnovers per hour | B43: H2_turnover | C43: 1/h | D43: =rH2_gen/(V_charge/1000000)/C_H2_sat -> 8.7523926 | E43: H₂ evolved ÷ saturable pool. ≫1 → cells must consume in near-real-time or it escapes.
A44: H₂ headspace safety flag | B44: H2_safety | C44: - | D44: =IF(H2_turnover>1,"EXPLOSIVE","watch") -> EXPLOSIVE | E44: On when H₂ escapes faster than it dissolves (H2_turnover>1) → explosive H₂+O₂ headspace (4–94% in O₂). On at any useful current — headspace venting is mandatory. | F44: Pink no longer used here - red fill = hazard (H2 evolving faster than it dissolves), not a data gap.
A45: Minimum DO (organism) | B45: DO_min | C45: mg/L | D45: =IF(ISNUMBER(cal_DO_min),cal_DO_min,IF(ISNUMBER(VLOOKUP(organism_sel,$A$52:$F$57,2,FALSE)),VLOOKUP(organism_sel,$A$52:$F$57,2,FALSE),NA())) -> #N/A
A46: Optimum DO (organism) | B46: DO_opt | C46: mg/L | D46: =IF(ISNUMBER(cal_DO_opt),cal_DO_opt,IF(ISNUMBER(VLOOKUP(organism_sel,$A$52:$F$57,3,FALSE)),VLOOKUP(organism_sel,$A$52:$F$57,3,FALSE),NA())) -> #N/A
A47: Impairment DO (organism) | B47: DO_impair | C47: mg/L | D47: =IF(ISNUMBER(cal_DO_impair),cal_DO_impair,IF(ISNUMBER(VLOOKUP(organism_sel,$A$52:$F$57,4,FALSE)),VLOOKUP(organism_sel,$A$52:$F$57,4,FALSE),NA())) -> #N/A
A48: Toxic/inhibition DO (organism) | B48: DO_toxic | C48: mg/L | D48: =IF(ISNUMBER(cal_DO_toxic),cal_DO_toxic,IF(ISNUMBER(VLOOKUP(organism_sel,$A$52:$F$57,5,FALSE)),VLOOKUP(organism_sel,$A$52:$F$57,5,FALSE),NA())) -> #N/A
A50: HOB LOOKUP (dissolved O₂ thresholds, mg/L)
A51: Organism | B51: minimum DO | C51: optimum DO | D51: impairment DO | E51: toxic DO | F51: source
A52: Cupriavidus necator | B52: ? | C52: 2.6 | D52: 3 | E52: 11.5 | F52: 11.5 = Wilde & Schlegel 1982 literature datum; model's operative O2 ceiling is computed via Henry (~10.7 mg/L at 30C) - the two differ slightly
A53: Xanthobacter autotrophicus | B53: ? | C53: ? | D53: ? | E53: 11.5 | F53: Wilde & Schlegel 1982 (~0.30 atm)
A54: Xanthobacter flavus | B54: ? | C54: ? | D54: ? | E54: ? | F54: no species data — assume genus ~11.5
A55: Xanthobacter tagetidis | B55: ? | C55: ? | D55: ? | E55: ? | F55: no species data — assume genus ~11.5
A56: Cupriavidus metallidurans | B56: ? | C56: ? | D56: ? | E56: ? | F56: no species data — assume genus ~11.5
A57: UdG (mixed) | B57: ? | C57: ? | D57: ? | E57: ? | F57: Rovira-Alsina 2025; Pous 2022/23
A59: TARGET DISSOLVED-OXYGEN FRACTION (wave-4: one definition, used by every guard)
A60: Target DO fraction (optimum ÷ inhibition ceiling) | B60: DO_frac_target | C60: - | D60: =IF(AND(ISNUMBER(DO_opt),ISNUMBER(DO_toxic)),DO_opt/DO_toxic,DO_frac_fallback) -> 0.22608696 | E60: Hold dissolved O₂ at or below this fraction of the inhibition ceiling. Taken from the selected organism's own measured band when there is one; otherwise the fallback below.
A61: fallback when the organism band is unmeasured | B61: DO_frac_fallback | C61: - | D61: 0.22608696 | E61: C. necator DO_opt 2.6 ÷ DO_toxic 11.5 mg/L (row 52) — the only organism in the table with a measured band, used as the stand-in for the rest. Same optimum ÷ ceiling ratio the row above computes, so the fallback is consistent with the definition. Replaces an unsourced 0.5, which was 2.2× less protective.

Sheet Mass Transfer
A1: MASS TRANSFER
A2: Parameter | B2: Name | C2: Unit | D2: Value | E2: Source / assumption
A4: IMPORTS (from other tabs)
A5: (import) Stir-bar length (from reactor type) | B5: stir_len | C5: mm | D5: =Geometry!$D$52 -> 12 | E5: =HYPERLINK("#Geometry!D52","→ Geometry") -> → Geometry | F5: Magnetic stir bar. Pioreactor max 20 mm; confirm the supplied bar's length. Input.
A6: (import) Dissolved-O₂ ceiling | B6: O2_ceil_C | C6: mol/m³ | D6: =Biology!$D$27 -> 0.36477 | E6: =HYPERLINK("#Biology!D27","→ Biology") -> → Biology
A7: (import) O₂ ceiling (partial pressure) | B7: O2_ceil_Pa | C7: Pa | D7: =Biology!$D$26 -> 30397.5 | E7: =HYPERLINK("#Biology!D26","→ Biology") -> → Biology
A8: (import) Temperature (absolute) | B8: T_K | C8: K | D8: =Biology!$D$18 -> 298.15 | E8: =HYPERLINK("#Biology!D18","→ Biology") -> → Biology
A9: (import) Surface pressure | B9: P_atm | C9: Pa | D9: =Biology!$D$19 -> 101325 | E9: =HYPERLINK("#Biology!D19","→ Biology") -> → Biology
A10: (import) CO₂ consumed (carbon fixation) | B10: CO2_cons | C10: mol/h | D10: =Biology!$D$15 -> 1.7293306e-05 | E10: =HYPERLINK("#Biology!D15","→ Biology") -> → Biology
A11: (import) EXCESS O₂ to remove | B11: O2_excess | C11: mol/h | D11: =Biology!$D$16 -> 1.6097798e-05 | E11: =HYPERLINK("#Biology!D16","→ Biology") -> → Biology
A12: (import) Henry solubility O₂ at T | B12: H_O2_T | C12: mol/m³/Pa | D12: =Biology!$D$24 -> 1.2e-05 | E12: =HYPERLINK("#Biology!D24","→ Biology") -> → Biology
A13: (import) Net O₂ to dissolved pool | B13: O2_net_gen | C13: mol/h | D13: =Electrochemistry!$D$29 -> 5.0684409e-05 | E13: =HYPERLINK("#Electrochemistry!D29","→ Electrochemistry") -> → Electrochemistry
A14: (import) Gas-liquid interfacial area | B14: interface_A | C14: mm² | D14: =Geometry!$D$44 -> 429.54773 | E14: =HYPERLINK("#Geometry!D44","→ Geometry") -> → Geometry
A15: (import) Vial internal diameter | B15: vial_ID | C15: mm | D15: =Geometry!$D$20 -> 25.28 | E15: =HYPERLINK("#Geometry!D20","→ Geometry") -> → Geometry
A16: (import) LIQUID VOLUME TO CHARGE | B16: V_charge | C16: mL | D16: =Geometry!$D$41 -> 15 | E16: =HYPERLINK("#Geometry!D41","→ Geometry") -> → Geometry
A17: (import) Internal cross-sectional area | B17: A_x | C17: mm² | D17: =Geometry!$D$21 -> 501.931 | E17: =HYPERLINK("#Geometry!D21","→ Geometry") -> → Geometry
A18: (import) Sparge tube ID | B18: spg_ID | C18: mm | D18: =Geometry!$D$31 -> 1.5875 | E18: =HYPERLINK("#Geometry!D31","→ Geometry") -> → Geometry
A19: (import) Headspace gas volume | B19: headspace_V | C19: mL | D19: =Geometry!$D$49 -> 2.6124285 | E19: =HYPERLINK("#Geometry!D49","→ Geometry") -> → Geometry
A20: (import) Sinter porosity grade (from electrode) | B20: por_grade | C20: 0-5 | D20: =Electrochemistry!$D$32 -> 0 | E20: =HYPERLINK("#Electrochemistry!D32","→ Electrochemistry") -> → Electrochemistry
A21: (import) Sparger type (from electrode) | B21: sparger | C21: - | D21: =Electrochemistry!$D$31 -> Tube | E21: =HYPERLINK("#Electrochemistry!D31","→ Electrochemistry") -> → Electrochemistry
A22: (import) Optimum DO (organism) | B22: DO_opt | D22: =Biology!$D$46 -> #N/A | E22: =HYPERLINK("#Biology!D46","→ Biology") -> → Biology
A23: (import) Impairment DO (organism) | B23: DO_impair | D23: =Biology!$D$47 -> #N/A | E23: =HYPERLINK("#Biology!D47","→ Biology") -> → Biology
A24: (import) Toxic/inhibition DO (organism) | B24: DO_toxic | D24: =Biology!$D$48 -> #N/A | E24: =HYPERLINK("#Biology!D48","→ Biology") -> → Biology
A25: (import) Minimum DO (organism) | B25: DO_min | D25: =Biology!$D$45 -> #N/A | E25: =HYPERLINK("#Biology!D45","→ Biology") -> → Biology
A27: valid sparger 1 | B27: spg_name_1 | C27: - | D27: Tube | E27: Bare 1/8" OD x 1/16" ID Flexelene 135C tube orifice.
A28: valid sparger 2 | B28: spg_name_2 | C28: - | D28: Sintered | E28: 10 mm sintered-glass disc annulus on a tubular anode.
A29: Surface tension (water, T) | B29: sigma | C29: N/m | D29: =sigma_0+sigma_k*(T_K-273.15) -> 0.071965 | E29: IAPWS R1-76(2014), evaluated at the reactor temperature (T_C) rather than frozen at 30 °C. Feeds the bubble-detachment diameter.
A30: Liquid density (water, T) | B30: rho_L | C30: kg/m³ | D30: =rho_0+rho_k*(T_K-273.15) -> 996.94 | E30: IAPWS-95, evaluated at the reactor temperature.
A31: Gravitational acceleration | B31: g_const | C31: m/s² | D31: 9.80665 | E31: Standard gravity (defined).
A32: O₂ diffusivity in water (T) | B32: D_O2 | C32: m²/s | D32: =10^(HB_a+HB_b/T_K-(HB_c/T_K)^2)/10000 -> 1.9976723e-09 | E32: Han & Bartels (1996) evaluated at the reactor temperature. At 25 °C this is 2.00e-9 m²/s; the sheet previously carried the 30 °C value 2.249e-9 as a constant, which overstated the surface transfer coefficient by 6%.
A33: Pore size - grade 0 | B33: por0_um | C33: µm | D33: 205 | E33: DURAN P0 160-250 µm, midpoint. ISO 4793 (paywalled) underlies; DURAN table is free.
A34: Pore size - grade 1 | B34: por1_um | C34: µm | D34: 130 | E34: DURAN P1 100-160 µm, midpoint.
A35: Pore size - grade 2 | B35: por2_um | C35: µm | D35: 70 | E35: DURAN P2 40-100 µm, midpoint.
A36: Pore size - grade 3 | B36: por3_um | C36: µm | D36: 28 | E36: DURAN P3 16-40 µm, midpoint.
A37: Pore size - grade 4 | B37: por4_um | C37: µm | D37: 13 | E37: DURAN P4 10-16 µm, midpoint.
A38: Pore size - grade 5 | B38: por5_um | C38: µm | D38: 1.3 | E38: DURAN P5 1.0-1.6 µm, midpoint.
A39: Selected sinter pore diameter | B39: por_pore | C39: m | D39: =CHOOSE(por_grade+1,por0_um,por1_um,por2_um,por3_um,por4_um,por5_um)/1000000 -> 0.000205 | E39: Picked by por_grade.
A40: Tube orifice diameter | B40: tube_d_m | C40: m | D40: =spg_ID/1000 -> 0.0015875 | E40: Tube ID in metres.
A41: Effective orifice/pore diameter | B41: d_orifice | C41: m | D41: =IF(sparger=spg_name_1,tube_d_m,IF(sparger=spg_name_2,por_pore,NA())) -> 0.0015875 | E41: Tube ID or sinter pore; invalid sparger returns an error.
A42: Bubble detachment diameter | B42: d_bubble | C42: m | D42: =(6*d_orifice*sigma/(rho_L*g_const))^(1/3) -> 0.0041234956 | E42: Static low-flow force balance (buoyancy vs surface tension); valid in the quasi-static regime — see bubble_regime (§10).
A43: Bubble diameter (display) | B43: d_bubble_mm | C43: mm | D43: =d_bubble*1000 -> 4.1234956
A44: Mendelson coefficient a | B44: mend_a | C44: - | D44: 2.14 | E44: Mendelson (1967) wave-theory bubble rise correlation (AIChE J, paywalled).
A45: Mendelson coefficient b | B45: mend_b | C45: - | D45: 0.505 | E45: Mendelson (1967), as above.
A46: Bubble rise velocity | B46: u_rise | C46: m/s | D46: =SQRT(mend_a*sigma/(rho_L*d_bubble)+mend_b*g_const*d_bubble) -> 0.24059064 | E46: Mendelson rise velocity, valid ~1–10 mm. Sub-mm bubbles (fine sinters) are out of range → bubble strip excluded and flagged (bubble_regime); §11 surface path and §14 optimiser unaffected. Tube = 4.1 mm.
A47: Superficial gas velocity (sparge on) | B47: u_sg | C47: m/s | D47: =(Q_CO2/1000000/60)/(A_x/1000000) -> 0.006634378 | E47: Gas flow / liquid cross-section.
A48: Gas holdup (sparge on) | B48: holdup | C48: - | D48: =u_sg/u_rise -> 0.027575379 | E48: ε ≈ superficial gas velocity / rise velocity.
A49: Interfacial area for transfer | B49: a_int | C49: 1/m | D49: =6*holdup/d_bubble -> 40.124275 | E49: a = 6ε/d_b (spheres).
A50: Bubble-liquid contact time | B50: t_contact | C50: s | D50: =d_bubble/u_rise -> 0.017139053 | E50: d_b / rise velocity.
A51: Liquid-film coefficient kL | B51: kL | C51: m/s | D51: =2*SQRT(D_O2/(PI()*t_contact)) -> 0.00038523326 | E51: Higbie penetration theory.
A52: kLa during sparge | B52: kLa_sparge | C52: 1/s | D52: =kL*a_int -> 0.015457205 | E52: kL x a.
A53: kLa time-averaged | B53: kLa_avg | C53: 1/s | D53: =kLa_sparge*duty -> 1.4527515e-05 | E53: Sparge-on regime only; not meaningful in the surface-strip-dominated default
A54: O₂ strip rate at ceiling (sparge on) | B54: strip_sparge | C54: mol/h | D54: =IF(d_bubble<0.001,0,kLa_sparge*(V_charge/1000000)*O2_ceil_C*3600) -> 0.00030446954 | E54: Bubble O₂ strip at the ceiling driving force (best case). 0 for sub-mm bubbles (fine sinter, bubble model out of range — see bubble_regime).
A55: O₂ strip rate time-averaged | B55: strip_avg | C55: mol/h | D55: =strip_sparge*duty -> 2.8615689e-07 | E55: x duty cycle.
A56: Strip capacity : excess-O₂ | B56: strip_ratio | C56: × | D56: =IF(O2_excess>0,strip_avg/O2_excess,NA()) -> 0.017776152 | E56: Bubble strip : surplus. ≪1 — the §11 surface path is the real route.
A57: Required time-avg kLa | B57: kLa_req | C57: 1/s | D57: =IF(O2_excess>0,O2_excess/3600/((V_charge/1000000)*O2_ceil_C),NA()) -> 0.00081724747 | E57: kLa that would exactly strip the excess at the ceiling.
A58: Entrainment velocity ceiling (rule of thumb) | B58: u_g_max | C58: m/s | D58: 0.05 | E58: Provisional superficial-velocity ceiling above which droplet carryover to the hydrophilic vent filters becomes likely. Replace with measured value.
A59: Carryover flag | B59: carry_flag | C59: - | D59: =IF(u_sg>u_g_max,"RISK","OK") -> OK | E59: Operating gas velocity vs ceiling.
A60: CO₂ gas density (T,P) | B60: rho_CO2 | C60: kg/m³ | D60: =P_atm*(M_CO2/1000)/(R_gas*T_K) -> 1.7988463 | E60: Ideal gas at surface conditions; for the orifice Weber number.
A61: Active sparge orifices | B61: n_pores_active | C61: - | D61: 1 | E61: Tube = 1. Sinter pore count unknown; 1 = worst case. DATA GAP.
A62: Gas velocity at orifice | B62: v_orifice | C62: m/s | D62: =(Q_CO2/1000000/60)/(n_pores_active*(PI()/4*d_orifice^2)) -> 1.6823908 | E62: Sparge-on regime only; not meaningful in the surface-strip-dominated default
A63: Orifice Weber number | B63: We_orifice | C63: - | D63: =rho_CO2*v_orifice^2*d_orifice/sigma -> 0.11231564 | E63: Sparge-on regime only; not meaningful in the surface-strip-dominated default
A64: Bubble-formation regime | B64: bubble_regime | C64: - | D64: =IF(d_bubble<0.001,"Sinter OOR – add fine-bubble model",IF(We_orifice<2,"Static","Dynamic")) -> Static | E64: Tate's law assumes quasi-static detachment (We<~2). 'Sinter OOR' = sub-mm bubble; the fine-sinter model isn't built yet.
A65: O₂ time-to-ceiling (no removal) | B65: t_O2_ceiling | C65: min | D65: =O2_ceil_C*(V_charge/1000000)/O2_excess*60 -> 20.393659 | E65: Minutes to reach the O₂ ceiling from ~0 with no removal (steady, etaF=1) — the O₂ timescale.
A66: O₂ time-to-ceiling (with time-avg strip) | B66: t_O2_ceiling_strip | C66: min | D66: =IF(O2_excess-strip_avg>0,O2_ceil_C*(V_charge/1000000)/(O2_excess-strip_avg)*60,9999) -> 20.762741 | E66: As above, crediting time-averaged bubble strip (≈unchanged → bubbles aren't the mechanism). 9999 = cleared.
A67: Stir-bar speed | B67: stir_rpm | C67: 1/min | D67: =Summary!$D$7 -> 1000 | E67: Pioreactor stir setpoint. RPM floor ~125 (stalls below). Input/confirm.
A68: Stir-bar tip speed | B68: tip_speed | C68: m/s | D68: =PI()*(stir_len/1000)*stir_rpm/60 -> 0.62831853 | E68: π·d·rpm/60.
A69: Surface renewal frequency | B69: s_renew | C69: 1/s | D69: =tip_speed/(vial_ID/1000) -> 24.854372 | E69: Surface renewal ≈ tip speed / vial ID. Coarse proxy.
A70: Surface liquid-film coeff kL | B70: kL_surf | C70: m/s | D70: =2*SQRT(D_O2*s_renew/PI()) -> 0.00025143086 | E70: Penetration-theory / surface-renewal proxy (Higbie form, t=1/s_renew) — coarse; measure by gassing-out (§15).
A71: Surface area per volume | B71: a_surf | C71: 1/m | D71: =interface_A/V_charge -> 28.636515 | E71: Free-surface area / liquid volume (mm²/mL = 1/m); uses interface_A (§1B).
A72: Surface O₂ transfer kLa | B72: kLa_surf | C72: 1/s | D72: =kL_surf*a_surf -> 0.0072001037 | E72: kL_surf × a_surf.
A73: O₂ strip via surface (ceiling) | B73: surf_strip | C73: mol/h | D73: =kLa_surf_used*(V_charge/1000000)*O2_ceil_C*3600 -> 0.00014182462 | E73: O₂ removable across the stirred surface at ceiling driving force — a FEASIBILITY CEILING for surf_ratio / O2_removal_ratio only. NEVER subtracted inside a safety guard (kL_surf is a ~375%-uncertain best-case proxy); the guards size on O2_src_guard (D132) with this credit withheld.
A74: Surface strip : excess-O₂ | B74: surf_ratio | C74: × | D74: =IF(O2_excess>0,surf_strip/O2_excess,NA()) -> 8.8101877 | E74: Surface strip : surplus. Coarse (kL_surf). ≫ bubble path — the dominant O₂ route.
A75: Headspace O₂ frac. to vent excess | B75: y_O2_vent | C75: - | D75: =IF(CO2_supply>0,O2_excess/(O2_excess+CO2_supply),NA()) -> 0.033774599 | E75: Headspace O₂ fraction at which the vented CO₂ carries the surplus out. kL-independent.
A76: DO in equilib. with that headspace | B76: DO_vent_eq | C76: µM | D76: =H_O2_T*y_O2_vent*P_atm*1000 -> 41.066535 | E76: Dissolved O₂ in equilibrium with that vent headspace fraction. At the current operating point it is ~405 µM against the ~365 µM inhibition ceiling (Biology D28) — the kL-independent vent leg does NOT on its own hold DO under the ceiling. Diagnostic, not a backstop.
A77: Headspace flush time | B77: hs_flush_time | C77: min | D77: =headspace_V/(Q_CO2*duty) -> 13.911968 | E77: Avg CO₂ flow to displace one headspace volume.
A78: Combined O₂ removal : excess | B78: O2_removal_ratio | C78: × | D78: =IF(O2_excess>0,(strip_avg+surf_strip)/O2_excess,NA()) -> 8.8279639 | E78: Upper bound: surface + sparge O2 sinks are in series (liquid->headspace->vent), not strictly additive
A79: O₂ time-to-ceiling (LAG, no uptake) | B79: t_O2_ceiling_lag | C79: min | D79: =O2_ceil_C*(V_charge/1000000)/O2_net_gen*60 -> 6.477199 | E79: Lag/establishment: no biological O₂ uptake yet, so the full net O₂ accumulates. Worst case.
A80: O₂ time-to-ceiling (with all removal) | B80: t_O2_ceiling_rem | C80: min | D80: =IF(O2_net_gen-strip_avg-surf_strip>0,O2_ceil_C*(V_charge/1000000)/(O2_net_gen-strip_avg-surf_strip)*60,9999) -> 9999 | E80: Companion to t_O2_ceiling_lag crediting BOTH removal paths at their best-case ceiling driving force. Best-case diagnostic only: surf_strip is the ~375%-uncertain surface proxy, so this cell must never gate a schedule or a guard. 9999 = removal exceeds the source at that best case.
A81: Schedule mode | B81: sched_mode | C81: - | D81: Optimal | E81: Set by the Summary 'Your setting' override (G13/G15) when filled; otherwise this Manual/Optimal selector + the manual cells below apply. Optimal = recommended schedule.
A82: Manual pulse duration | B82: spg_dur_man | C82: s | D82: 1 | E82: Your pulse length when sched_mode=Manual. Easiest: type into the Summary 'Your setting' column (G13) instead — it overrides everything.
A83: Manual sparge interval | B83: spg_int_man | C83: min | D83: 1 | E83: Your interval when sched_mode=Manual. Easiest: type into the Summary 'Your setting' column (G15) instead — it overrides everything.
A84: Target DO fraction (organism optimum / inhibition) | B84: target_DO_frac | C84: - | D84: =Biology!$D$60 -> 0.22608696 | E84: Imported from Biology D60 — one definition of the target DO fraction, computed from the selected organism's measured band where there is one and from C. necator's 3/11.5 otherwise. Sizes the O₂ guards below.
A85: Min carbon supply margin | B85: carbon_margin_min | C85: - | D85: 2 | E85: Required CO₂ supply : fixation demand. Input.
A86: Duty floor — carbon | B86: duty_carbon | C86: - | D86: =carbon_margin_min*CO2_cons/(nCO2_rate*3600) -> 7.0585202e-05 | E86: Duty needed so CO₂ supply ≥ margin × fixation demand.
A87: Duty floor — O₂ venting (lag) | B87: duty_O2vent | C87: - | D87: =O2_src_guard/(target_DO_frac*(O2_ceil_Pa/P_atm))/(nCO2_rate*3600) -> 0.0015250472 | E87: Conservative O₂-vent duty: net O₂ with the surface-strip credit withheld (O2_src_guard). Sizes the O₂-limited fallback; the recommended schedule credits the surface estimate when DO is held.
A88: Optimal duty cycle | B88: duty_opt | C88: - | D88: =MAX(duty_carbon,duty_O2vent) -> 0.0015250472 | E88: Least feasible CO₂ duty (binding of the two floors). The recommended schedule follows this duty only in the SPARGE-NEEDED regime; under SURFACE-HELD, D91 follows the carbon-limited interval and the achieved duty (D93) is correspondingly lower.
A89: Max interval — O₂ flush frequency | B89: spg_int_max | C89: min | D89: =target_DO_frac*O2_ceil_C*(V_charge/1000000)/O2_src_guard*60 -> 1.4644102 | E89: O₂-limited FALLBACK interval: zero-surface worst case (no surface credit; sizes on O2_src_guard D132). This is what D91 recommends until the surface path is demonstrated — i.e. until a surface kLa is measured (Calibrations) and the lag-source regime test (D134) passes.
A90: OPTIMAL pulse duration | B90: spg_dur_opt | C90: s | D90: =MAX(pulse_floor,flush_factor*headspace_V/(Q_CO2/60)) -> 0.78451305 | E90: ANSWER. Shortest reliable pulse → most frequent, smoothest DO, best OD-read windows.
A91: OPTIMAL sparge interval | B91: spg_int_opt | C91: min | D91: =IF(ISNUMBER(spg_int_DO),MIN(spg_int_carbon,spg_int_DO),MIN(spg_int_carbon,spg_int_max)) -> 13.911968 | E91: ANSWER. The shortest of the two upper bounds on the interval: carbon supply (D112) and headspace-oxygen dilution (spg_int_DO). If the DO target is unreachable at this surface kLa the sheet falls back to the lag-accumulation cap (D89) and D134 says so. No branch here depends on an unmeasured coefficient deciding which formula runs — kL_surf now moves the answer continuously instead of switching it.
A92: optimal interval (seconds) | B92: spg_int_opt_s | C92: s | D92: =spg_int_opt*60 -> 834.71806 | E92: Convenience: interval in seconds.
A93: resulting duty / binding constraint | B93: duty_actual | C93: - | D93: =spg_dur_opt/(spg_int_opt*60) -> 0.00093985393 | E93: Achieved duty at the optimum (= duty_opt unless the flush-frequency cap binds, raising it).
A94: binding constraint | B94: opt_binding | C94: - | D94: =IF(NOT(ISNUMBER(spg_int_DO)),"O2-INFEASIBLE (see D134)",IF(spg_int_DO<=spg_int_carbon,"O2-DILUTION (headspace O2 sets the interval)","CARBON (CO2 supply sets the interval)")) -> O2-DILUTION (headspace O2 sets the interval) | E94: Which constraint binds: headspace-oxygen dilution or carbon supply. The pH consequence of the winner is carried through the CO₂ limit cycle to the Chemistry sheet — a short oxygen-driven interval delivers far more CO₂ than the carbon demand and pushes pH down.
A95: OD-window check | B95: od_ok | C95: - | D95: =IF(spg_int*60-spg_dur>=5,"OK","TIGHT") -> OK | E95: ≥5 s gap between pulses for an OD read (uses the schedule IN USE, so it responds to your override). Can't measure OD while sparging.
A96: ACCURACY LIMIT — no validated kinetics | B96: kinetic_caveat | C96: - | D96: ="see note →" -> see note → | E96: Constraint-proxy optimiser, not a fitted growth model — no validated μ(O₂,pH,CO₂) or lag kinetics exist for this system. Gives the lag-minimising direction, not an exact optimum; bounded by etaF, surface kL and the unbuffered-pH simplification. Validate empirically.
A97: Measured surface kLa | B97: kLa_meas | C97: 1/h | D97: =IF(ISNUMBER(cal_kLa),cal_kLa,0) -> 0 | E97: Measured surface kLa (gassing-out). 0 = use the §11 estimate. kLa = slope of −LN(1−DO/DO_sat) vs time.
A98: Surface kLa used downstream | B98: kLa_surf_used | C98: 1/s | D98: =IF(AND(ISNUMBER(kLa_meas),kLa_meas>0),kLa_meas/3600,kLa_surf) -> 0.0072001037 | E98: What §11 actually uses: the measured surface kLa if one has been entered on the Calibrations tab (in 1/h), otherwise the penetration-theory estimate. The ISNUMBER test matters — an empty calibration returns a message, and in Excel text sorts above every number, so a bare ">0" test would have accepted it.
A99: Min reliable pulse (solenoid floor) | B99: pulse_floor | C99: s | D99: =min_sparge_cal -> 0.25 | E99: From Dosing.
A100: Average CO₂ supply rate | B100: CO2_supply | C100: mol/h | D100: =CO2_pulse*pulses_h -> 0.00046052659 | E100: From Dosing.
A101: Ideal gas constant | B101: R_gas | C101: J/mol/K | D101: 8.3144626 | E101: From Dosing.
A102: CO₂ volumetric flow rate | B102: Q_CO2 | C102: mL/min | D102: =IF(has_cal>0,flowrate_cal*60,NA()) -> 199.8 | E102: From Dosing.
...

Sheet CO2 flows
A1: CO₂ DOSING FLOWRATES
A2: Reactor | B2: date | C2: cylinder size | D2: observed volume* | E2: volume | F2: time | G2: flowrate | H2: average flowrate | I2: minimum sparge | J2: nominal flowrate | L2: KEY
C3: ml | D3: ml | E3: ml | F3: s | G3: ml/s | H3: ml/s | I3: s | J3: ml/s | L3: Flowrate set by inspection, as maximum to not give bubbles rising into vial neck
A4: ed04 | B4: 46190 | C4: 50 | D4: 0 | I4: 0.25 | J4: 3.33 | L4: First or last data point removed as suspect outlier
A5: ed04 | B5: 46190 | C5: 50 | D5: 50 | E5: =D5-D4 -> 50 | F5: 15 | G5: =E5/F5 -> 3.3333333 | H5: =AVERAGE(G5) -> 3.3333333
A6: ed04 | B6: 46190 | C6: 50 | D6: 0 | K6: Point | L6: Note
A7: ed04 | B7: 46190 | C7: 50 | D7: 12 | E7: =D7-D6 -> 12 | F7: 4 | G7: =E7/F7 -> 3 | H7: =AVERAGE(G7:G9) -> 3.3333333 | K7: * | L7: CO2 collected in measuring cyclinder over CO2-saturated water
A8: ed04 | B8: 46190 | C8: 50 | D8: 26 | E8: =D8-D7 -> 14 | F8: 4 | G8: =E8/F8 -> 3.5 | K8: 46190 | L8: Collected using inlet CO2 tube rather than outlet as MEP vialcap leaking
A9: ed04 | B9: 46190 | C9: 50 | D9: 40 | E9: =D9-D8 -> 14 | F9: 4 | G9: =E9/F9 -> 3.5 | K9: 46190 | L9: Collected over saturated NaHCO3 soln, as Martin innovated without thinking
A10: ed04 | B10: 46190 | C10: 50 | D10: 0
A11: ed04 | B11: 46190 | C11: 50 | D11: 6 | E11: =D11-D10 -> 6 | F11: 2 | G11: =E11/F11 -> 3 | H11: =AVERAGE(G11:G16) -> 3.75
A12: ed04 | B12: 46190 | C12: 50 | D12: 15 | E12: =D12-D11 -> 9 | F12: 2 | G12: =E12/F12 -> 4.5
A13: ed04 | B13: 46190 | C13: 50 | D13: 21 | E13: =D13-D12 -> 6 | F13: 2 | G13: =E13/F13 -> 3
A14: ed04 | B14: 46190 | C14: 50 | D14: 29 | E14: =D14-D13 -> 8 | F14: 2 | G14: =E14/F14 -> 4
A15: ed04 | B15: 46190 | C15: 50 | D15: 35 | E15: =D15-D14 -> 6 | F15: 2 | G15: =E15/F15 -> 3
A16: ed04 | B16: 46190 | C16: 50 | D16: 45 | E16: =D16-D15 -> 10 | F16: 2 | G16: =E16/F16 -> 5
A17: ed04 | B17: 46190 | C17: 50 | D17: 0
A18: ed04 | B18: 46190 | C18: 50 | D18: 4 | E18: =D18-D17 -> 4 | F18: 1 | G18: =E18/F18 -> 4 | H18: =AVERAGE(G18:G23) -> 3.8333333
A19: ed04 | B19: 46190 | C19: 50 | D19: 8 | E19: =D19-D18 -> 4 | F19: 1 | G19: =E19/F19 -> 4
A20: ed04 | B20: 46190 | C20: 50 | D20: 11 | E20: =D20-D19 -> 3 | F20: 1 | G20: =E20/F20 -> 3
A21: ed04 | B21: 46190 | C21: 50 | D21: 15 | E21: =D21-D20 -> 4 | F21: 1 | G21: =E21/F21 -> 4
A22: ed04 | B22: 46190 | C22: 50 | D22: 19 | E22: =D22-D21 -> 4 | F22: 1 | G22: =E22/F22 -> 4
A23: ed04 | B23: 46190 | C23: 50 | D23: 23 | E23: =D23-D22 -> 4 | F23: 1 | G23: =E23/F23 -> 4
A24: ed04 | B24: 46190 | C24: 50 | D24: 31
A25: ed04 | B25: 46190 | C25: 50 | D25: 33 | E25: =D25-D24 -> 2 | F25: 0.5 | G25: =E25/F25 -> 4 | H25: =AVERAGE(G25:G29) -> 4
A26: ed04 | B26: 46190 | C26: 50 | D26: 35 | E26: =D26-D25 -> 2 | F26: 0.5 | G26: =E26/F26 -> 4
A27: ed04 | B27: 46190 | C27: 50 | D27: 37 | E27: =D27-D26 -> 2 | F27: 0.5 | G27: =E27/F27 -> 4
A28: ed04 | B28: 46190 | C28: 50 | D28: 39 | E28: =D28-D27 -> 2 | F28: 0.5 | G28: =E28/F28 -> 4
A29: ed04 | B29: 46190 | C29: 50 | D29: 41 | E29: =D29-D28 -> 2 | F29: 0.5 | G29: =E29/F29 -> 4
A30: ed04 | B30: 46190 | C30: 50 | D30: 42 | E30: =D30-D29 -> 1 | F30: 0.25 | G30: =E30/F30 -> 4 | H30: =AVERAGE(G30:G34) -> 4
A31: ed04 | B31: 46190 | C31: 50 | D31: 43 | E31: =D31-D30 -> 1 | F31: 0.25 | G31: =E31/F31 -> 4
A32: ed04 | B32: 46190 | C32: 50 | D32: 44 | E32: =D32-D31 -> 1 | F32: 0.25 | G32: =E32/F32 -> 4
A33: ed04 | B33: 46190 | C33: 50 | D33: 45 | E33: =D33-D32 -> 1 | F33: 0.25 | G33: =E33/F33 -> 4
A34: ed04 | B34: 46190 | C34: 50 | D34: 46 | E34: =D34-D33 -> 1 | F34: 0.25 | G34: =E34/F34 -> 4
A35: ed04 | B35: 46190 | C35: 10 | D35: 0 | E35: =D35-D34 -> -46
A36: ed04 | B36: 46190 | C36: 10 | D36: 0.4 | E36: =D36-D35 -> 0.4 | F36: 0.2 | G36: =E36/F36 -> 2
A37: ed04 | B37: 46190 | C37: 10 | D37: 1.2 | E37: =D37-D36 -> 0.8 | F37: 0.2 | G37: =E37/F37 -> 4 | H37: =AVERAGE(G37:G39) -> 4.3333333
A38: ed04 | B38: 46190 | C38: 10 | D38: 2.2 | E38: =D38-D37 -> 1 | F38: 0.2 | G38: =E38/F38 -> 5
A39: ed04 | B39: 46190 | C39: 10 | D39: 3 | E39: =D39-D38 -> 0.8 | F39: 0.2 | G39: =E39/F39 -> 4
A40: ed04 | B40: 46190 | C40: 10 | D40: 0
A41: ed04 | B41: 46190 | C41: 10 | D41: 0.4 | E41: =D41-D40 -> 0.4 | F41: 0.1 | G41: =E41/F41 -> 4 | H41: =AVERAGE(G41:G45) -> 5.2
A42: ed04 | B42: 46190 | C42: 10 | D42: 0.8 | E42: =D42-D41 -> 0.4 | F42: 0.1 | G42: =E42/F42 -> 4
A43: ed04 | B43: 46190 | C43: 10 | D43: 1.4 | E43: =D43-D42 -> 0.6 | F43: 0.1 | G43: =E43/F43 -> 6
A44: ed04 | B44: 46190 | C44: 10 | D44: 2 | E44: =D44-D43 -> 0.6 | F44: 0.1 | G44: =E44/F44 -> 6
A45: ed04 | B45: 46190 | C45: 10 | D45: 2.6 | E45: =D45-D44 -> 0.6 | F45: 0.1 | G45: =E45/F45 -> 6
A46: ed04 | B46: 46190 | C46: 10 | D46: 2.8 | E46: =D46-D45 -> 0.2 | F46: 0.1 | G46: =E46/F46 -> 2

Sheet Calibrations
A1: CALIBRATIONS
A2: Fill the white cells only: Researcher, Date, the key (Reactor or Organism) and the raw measurements. Grey cells are computed automatically. Set Include to y for rows the model should use.
A3: The value in use for each calibration follows the rule stated under its heading. If no rows are included yet, the model falls back to its built-in default.
A5: =HYPERLINK("https://github.com/amy-bo/electroPioreactor/blob/CO2-modular/Media/protocols/gerrit-current.md","ELECTROLYSIS CURRENT") -> ELECTROLYSIS CURRENT
A6: Value in use: least-squares fit of current vs intensity, averaged across all included runs for the active reactor.
A7: Researcher | B7: Date | C7: Reactor | D7: Intensity | E7: Current | F7: Type (auto) | G7: Include? | H7: Notes
F8: =IFERROR(VLOOKUP(C8,Geometry!$A$59:$B$80,2,FALSE),"")
F9: =IFERROR(VLOOKUP(C9,Geometry!$A$59:$B$80,2,FALSE),"")
F10: =IFERROR(VLOOKUP(C10,Geometry!$A$59:$B$80,2,FALSE),"")
F11: =IFERROR(VLOOKUP(C11,Geometry!$A$59:$B$80,2,FALSE),"")
F12: =IFERROR(VLOOKUP(C12,Geometry!$A$59:$B$80,2,FALSE),"")
F13: =IFERROR(VLOOKUP(C13,Geometry!$A$59:$B$80,2,FALSE),"")
F14: =IFERROR(VLOOKUP(C14,Geometry!$A$59:$B$80,2,FALSE),"")
F15: =IFERROR(VLOOKUP(C15,Geometry!$A$59:$B$80,2,FALSE),"")
A16: Value in use - slope | C16: mA/% | D16: =IFERROR((COUNTIFS(C8:C15,Summary!$D$2,G8:G15,"y")*SUMPRODUCT((C8:C15=Summary!$D$2)*(G8:G15="y")*D8:D15*E8:E15)-SUMIFS(D8:D15,C8:C15,Summary!$D$2,G8:G15,"y")*SUMIFS(E8:E15,C8:C15,Summary!$D$2,G8:G15,"y"))/(COUNTIFS(C8:C15,Summary!$D$2,G8:G15,"y")*SUMPRODUCT((C8:C15=Summary!$D$2)*(G8:G15="y")*D8:D15*D8:D15)-SUMIFS(D8:D15,C8:C15,Summary!$D$2,G8:G15,"y")*SUMIFS(D8:D15,C8:C15,Summary!$D$2,G8:G15,"y")),"no included runs — model uses its default") -> no included runs — model uses its default
A17: Value in use - intercept | C17: mA | D17: =IFERROR((SUMIFS(E8:E15,C8:C15,Summary!$D$2,G8:G15,"y")-((COUNTIFS(C8:C15,Summary!$D$2,G8:G15,"y")*SUMPRODUCT((C8:C15=Summary!$D$2)*(G8:G15="y")*D8:D15*E8:E15)-SUMIFS(D8:D15,C8:C15,Summary!$D$2,G8:G15,"y")*SUMIFS(E8:E15,C8:C15,Summary!$D$2,G8:G15,"y"))/(COUNTIFS(C8:C15,Summary!$D$2,G8:G15,"y")*SUMPRODUCT((C8:C15=Summary!$D$2)*(G8:G15="y")*D8:D15*D8:D15)-SUMIFS(D8:D15,C8:C15,Summary!$D$2,G8:G15,"y")*SUMIFS(D8:D15,C8:C15,Summary!$D$2,G8:G15,"y")))*SUMIFS(D8:D15,C8:C15,Summary!$D$2,G8:G15,"y"))/COUNTIFS(C8:C15,Summary!$D$2,G8:G15,"y"),"no included runs — model uses its default") -> no included runs — model uses its default
A20: =HYPERLINK("https://github.com/amy-bo/electroPioreactor/blob/CO2-modular/Media/protocols/faradaic-efficiency.md","FARADAIC EFFICIENCY (cathodic etaF, anodic etaF_OER)") -> FARADAIC EFFICIENCY (cathodic etaF, anodic etaF_OER)
A21: Value in use: average of the included runs for the active reactor, taken separately for the H2 (cathode) and O2 (anode) electrodes. The gas volume is corrected for saturated water vapour at the temperature you record, per protocols/faradaic-efficiency.md.
A22: Researcher | B22: Date | C22: Reactor | D22: Charge Q | E22: Gas volume | F22: Temp | G22: Pressure | H22: Electrode | I22: etaF (computed) | J22: Type (auto) | K22: Include? | L22: Notes
I23: =IFERROR(((G23-'Mass Transfer'!$D$206)*(E23/1000000)/('Mass Transfer'!$D$101*(F23+273.15)))/(D23/(IF(H23="H2",2,4)*Electrochemistry!$D$15)),"") | J23: =IFERROR(VLOOKUP(C23,Geometry!$A$59:$B$80,2,FALSE),"")
I24: =IFERROR(((G24-'Mass Transfer'!$D$206)*(E24/1000000)/('Mass Transfer'!$D$101*(F24+273.15)))/(D24/(IF(H24="H2",2,4)*Electrochemistry!$D$15)),"") | J24: =IFERROR(VLOOKUP(C24,Geometry!$A$59:$B$80,2,FALSE),"")
I25: =IFERROR(((G25-'Mass Transfer'!$D$206)*(E25/1000000)/('Mass Transfer'!$D$101*(F25+273.15)))/(D25/(IF(H25="H2",2,4)*Electrochemistry!$D$15)),"") | J25: =IFERROR(VLOOKUP(C25,Geometry!$A$59:$B$80,2,FALSE),"")
I26: =IFERROR(((G26-'Mass Transfer'!$D$206)*(E26/1000000)/('Mass Transfer'!$D$101*(F26+273.15)))/(D26/(IF(H26="H2",2,4)*Electrochemistry!$D$15)),"") | J26: =IFERROR(VLOOKUP(C26,Geometry!$A$59:$B$80,2,FALSE),"")
I27: =IFERROR(((G27-'Mass Transfer'!$D$206)*(E27/1000000)/('Mass Transfer'!$D$101*(F27+273.15)))/(D27/(IF(H27="H2",2,4)*Electrochemistry!$D$15)),"") | J27: =IFERROR(VLOOKUP(C27,Geometry!$A$59:$B$80,2,FALSE),"")
I28: =IFERROR(((G28-'Mass Transfer'!$D$206)*(E28/1000000)/('Mass Transfer'!$D$101*(F28+273.15)))/(D28/(IF(H28="H2",2,4)*Electrochemistry!$D$15)),"") | J28: =IFERROR(VLOOKUP(C28,Geometry!$A$59:$B$80,2,FALSE),"")
I29: =IFERROR(((G29-'Mass Transfer'!$D$206)*(E29/1000000)/('Mass Transfer'!$D$101*(F29+273.15)))/(D29/(IF(H29="H2",2,4)*Electrochemistry!$D$15)),"") | J29: =IFERROR(VLOOKUP(C29,Geometry!$A$59:$B$80,2,FALSE),"")
I30: =IFERROR(((G30-'Mass Transfer'!$D$206)*(E30/1000000)/('Mass Transfer'!$D$101*(F30+273.15)))/(D30/(IF(H30="H2",2,4)*Electrochemistry!$D$15)),"") | J30: =IFERROR(VLOOKUP(C30,Geometry!$A$59:$B$80,2,FALSE),"")
A31: Value in use - cathode (H2) | C31: - | D31: =IFERROR(AVERAGEIFS(I23:I30,C23:C30,Summary!$D$2,K23:K30,"y",H23:H30,"H2"),"no included runs — model uses its default") -> no included runs — model uses its default
A32: Value in use - anode (O2) | C32: - | D32: =IFERROR(AVERAGEIFS(I23:I30,C23:C30,Summary!$D$2,K23:K30,"y",H23:H30,"O2"),"no included runs — model uses its default") -> no included runs — model uses its default
A35: =HYPERLINK("https://github.com/amy-bo/electroPioreactor/blob/CO2-modular/Media/protocols/surface-kla.md","SURFACE kLa (oxygen surface transfer)") -> SURFACE kLa (oxygen surface transfer)
A36: Value in use: average of the included kLa runs for the active reactor.
A37: Researcher | B37: Date | C37: Reactor | D37: kLa | E37: Type (auto) | F37: Include? | G37: Notes
E38: =IFERROR(VLOOKUP(C38,Geometry!$A$59:$B$80,2,FALSE),"")
E39: =IFERROR(VLOOKUP(C39,Geometry!$A$59:$B$80,2,FALSE),"")
E40: =IFERROR(VLOOKUP(C40,Geometry!$A$59:$B$80,2,FALSE),"")
E41: =IFERROR(VLOOKUP(C41,Geometry!$A$59:$B$80,2,FALSE),"")
E42: =IFERROR(VLOOKUP(C42,Geometry!$A$59:$B$80,2,FALSE),"")
E43: =IFERROR(VLOOKUP(C43,Geometry!$A$59:$B$80,2,FALSE),"")
E44: =IFERROR(VLOOKUP(C44,Geometry!$A$59:$B$80,2,FALSE),"")
E45: =IFERROR(VLOOKUP(C45,Geometry!$A$59:$B$80,2,FALSE),"")
A46: Value in use - kLa | C46: 1/h | D46: =IFERROR(AVERAGEIFS(D38:D45,C38:C45,Summary!$D$2,F38:F45,"y"),"no included runs — model uses its default") -> no included runs — model uses its default
A49: =HYPERLINK("https://github.com/amy-bo/electroPioreactor/blob/CO2-modular/Media/protocols/flow-calibration.md","CO2 FLOW (dosing flow rate)") -> CO2 FLOW (dosing flow rate)
A50: Value in use: the most recent included measurement for the active reactor (a flow rate is a valve/hardware setting, so the latest reading replaces older ones).
A51: Researcher | B51: Date | C51: Reactor | D51: CO2 volume | E51: Time | F51: Flow (computed) | G51: Type (auto) | H51: Include? | I51: Notes
F52: =IFERROR(D52/E52,"") | G52: =IFERROR(VLOOKUP(C52,Geometry!$A$59:$B$80,2,FALSE),"")
F53: =IFERROR(D53/E53,"") | G53: =IFERROR(VLOOKUP(C53,Geometry!$A$59:$B$80,2,FALSE),"")
F54: =IFERROR(D54/E54,"") | G54: =IFERROR(VLOOKUP(C54,Geometry!$A$59:$B$80,2,FALSE),"")
F55: =IFERROR(D55/E55,"") | G55: =IFERROR(VLOOKUP(C55,Geometry!$A$59:$B$80,2,FALSE),"")
F56: =IFERROR(D56/E56,"") | G56: =IFERROR(VLOOKUP(C56,Geometry!$A$59:$B$80,2,FALSE),"")
F57: =IFERROR(D57/E57,"") | G57: =IFERROR(VLOOKUP(C57,Geometry!$A$59:$B$80,2,FALSE),"")
F58: =IFERROR(D58/E58,"") | G58: =IFERROR(VLOOKUP(C58,Geometry!$A$59:$B$80,2,FALSE),"")
F59: =IFERROR(D59/E59,"") | G59: =IFERROR(VLOOKUP(C59,Geometry!$A$59:$B$80,2,FALSE),"")
A60: Value in use - flow rate | C60: mL/s | D60: =IFERROR(AVERAGEIFS(F52:F59,C52:C59,Summary!$D$2,H52:H59,"y",B52:B59,SUMPRODUCT(MAX((C52:C59=Summary!$D$2)*(H52:H59="y")*B52:B59))),"no included runs — model uses its default") -> no included runs — model uses its default
A63: =HYPERLINK("https://github.com/amy-bo/electroPioreactor/blob/CO2-modular/Media/protocols/vial-geometry.md","VIAL GEOMETRY (true volume & bore depth)") -> VIAL GEOMETRY (true volume & bore depth)
A64: Value in use: average across included vials of the active reactor type (all vials of a type are nominally identical, so averaging improves the estimate).
A65: Researcher | B65: Date | C65: Reactor | D65: Headspace mass | E65: Body mass | F65: Temp | G65: V total (computed) | H65: Bore depth (computed) | I65: Type (auto) | J65: Include? | K65: Notes
G66: =IFERROR(E66/(0.99705-0.00028*(F66-25)),"") -> 0 | H66: =IFERROR((E66/(0.99705-0.00028*(F66-25)))*1000/Geometry!$D$21,"") -> 0 | I66: =IFERROR(VLOOKUP(C66,Geometry!$A$59:$B$80,2,FALSE),"")
G67: =IFERROR(E67/(0.99705-0.00028*(F67-25)),"") -> 0 | H67: =IFERROR((E67/(0.99705-0.00028*(F67-25)))*1000/Geometry!$D$21,"") -> 0 | I67: =IFERROR(VLOOKUP(C67,Geometry!$A$59:$B$80,2,FALSE),"")
G68: =IFERROR(E68/(0.99705-0.00028*(F68-25)),"") -> 0 | H68: =IFERROR((E68/(0.99705-0.00028*(F68-25)))*1000/Geometry!$D$21,"") -> 0 | I68: =IFERROR(VLOOKUP(C68,Geometry!$A$59:$B$80,2,FALSE),"")
G69: =IFERROR(E69/(0.99705-0.00028*(F69-25)),"") -> 0 | H69: =IFERROR((E69/(0.99705-0.00028*(F69-25)))*1000/Geometry!$D$21,"") -> 0 | I69: =IFERROR(VLOOKUP(C69,Geometry!$A$59:$B$80,2,FALSE),"")
G70: =IFERROR(E70/(0.99705-0.00028*(F70-25)),"") -> 0 | H70: =IFERROR((E70/(0.99705-0.00028*(F70-25)))*1000/Geometry!$D$21,"") -> 0 | I70: =IFERROR(VLOOKUP(C70,Geometry!$A$59:$B$80,2,FALSE),"")
G71: =IFERROR(E71/(0.99705-0.00028*(F71-25)),"") -> 0 | H71: =IFERROR((E71/(0.99705-0.00028*(F71-25)))*1000/Geometry!$D$21,"") -> 0 | I71: =IFERROR(VLOOKUP(C71,Geometry!$A$59:$B$80,2,FALSE),"")
G72: =IFERROR(E72/(0.99705-0.00028*(F72-25)),"") -> 0 | H72: =IFERROR((E72/(0.99705-0.00028*(F72-25)))*1000/Geometry!$D$21,"") -> 0 | I72: =IFERROR(VLOOKUP(C72,Geometry!$A$59:$B$80,2,FALSE),"")
G73: =IFERROR(E73/(0.99705-0.00028*(F73-25)),"") -> 0 | H73: =IFERROR((E73/(0.99705-0.00028*(F73-25)))*1000/Geometry!$D$21,"") -> 0 | I73: =IFERROR(VLOOKUP(C73,Geometry!$A$59:$B$80,2,FALSE),"")
A74: Value in use - total vial volume | C74: mL | D74: =IFERROR(AVERAGEIFS(G66:G73,I66:I73,Geometry!$D$51,J66:J73,"y"),"no included runs — model uses its default") -> no included runs — model uses its default
A75: Value in use - usable depth | C75: mm | D75: =IFERROR(AVERAGEIFS(H66:H73,I66:I73,Geometry!$D$51,J66:J73,"y"),"no included runs — model uses its default") -> no included runs — model uses its default
A78: =HYPERLINK("https://github.com/amy-bo/electroPioreactor/blob/CO2-modular/Media/protocols/sinter-porosity.md","SINTER POROSITY (sparger frit grade)") -> SINTER POROSITY (sparger frit grade)
A79: Value in use: the most recent included measurement for the active reactor (the fitted frit is hardware, so the latest reading replaces older ones).
A80: Researcher | B80: Date | C80: Reactor | D80: Bubble-point | E80: Grade (computed) | F80: Type (auto) | G80: Include? | H80: Notes
E81: =IFERROR(IF((291.2/D81)>160,0,IF((291.2/D81)>100,1,IF((291.2/D81)>40,2,IF((291.2/D81)>16,3,IF((291.2/D81)>10,4,5))))),"") | F81: =IFERROR(VLOOKUP(C81,Geometry!$A$59:$B$80,2,FALSE),"")
E82: =IFERROR(IF((291.2/D82)>160,0,IF((291.2/D82)>100,1,IF((291.2/D82)>40,2,IF((291.2/D82)>16,3,IF((291.2/D82)>10,4,5))))),"") | F82: =IFERROR(VLOOKUP(C82,Geometry!$A$59:$B$80,2,FALSE),"")
E83: =IFERROR(IF((291.2/D83)>160,0,IF((291.2/D83)>100,1,IF((291.2/D83)>40,2,IF((291.2/D83)>16,3,IF((291.2/D83)>10,4,5))))),"") | F83: =IFERROR(VLOOKUP(C83,Geometry!$A$59:$B$80,2,FALSE),"")
E84: =IFERROR(IF((291.2/D84)>160,0,IF((291.2/D84)>100,1,IF((291.2/D84)>40,2,IF((291.2/D84)>16,3,IF((291.2/D84)>10,4,5))))),"") | F84: =IFERROR(VLOOKUP(C84,Geometry!$A$59:$B$80,2,FALSE),"")
E85: =IFERROR(IF((291.2/D85)>160,0,IF((291.2/D85)>100,1,IF((291.2/D85)>40,2,IF((291.2/D85)>16,3,IF((291.2/D85)>10,4,5))))),"") | F85: =IFERROR(VLOOKUP(C85,Geometry!$A$59:$B$80,2,FALSE),"")
E86: =IFERROR(IF((291.2/D86)>160,0,IF((291.2/D86)>100,1,IF((291.2/D86)>40,2,IF((291.2/D86)>16,3,IF((291.2/D86)>10,4,5))))),"") | F86: =IFERROR(VLOOKUP(C86,Geometry!$A$59:$B$80,2,FALSE),"")
E87: =IFERROR(IF((291.2/D87)>160,0,IF((291.2/D87)>100,1,IF((291.2/D87)>40,2,IF((291.2/D87)>16,3,IF((291.2/D87)>10,4,5))))),"") | F87: =IFERROR(VLOOKUP(C87,Geometry!$A$59:$B$80,2,FALSE),"")
E88: =IFERROR(IF((291.2/D88)>160,0,IF((291.2/D88)>100,1,IF((291.2/D88)>40,2,IF((291.2/D88)>16,3,IF((291.2/D88)>10,4,5))))),"") | F88: =IFERROR(VLOOKUP(C88,Geometry!$A$59:$B$80,2,FALSE),"")
A89: Value in use - porosity grade | C89: 0-5 | D89: =IFERROR(AVERAGEIFS(E81:E88,C81:C88,Summary!$D$2,G81:G88,"y",B81:B88,SUMPRODUCT(MAX((C81:C88=Summary!$D$2)*(G81:G88="y")*B81:B88))),"no included runs — model uses its default") -> no included runs — model uses its default
A92: =HYPERLINK("https://github.com/amy-bo/electroPioreactor/blob/CO2-modular/Media/protocols/dissolved-oxygen.md","DISSOLVED-OXYGEN THRESHOLDS (per organism)") -> DISSOLVED-OXYGEN THRESHOLDS (per organism)
A93: Value in use: average of the included values for the active organism.
A94: Researcher | B94: Date | C94: Organism | D94: Min DO | E94: Optimum DO | F94: Impairment DO | G94: Toxic DO | H94: Include? | I94: Notes
A103: Value in use - minimum DO | C103: mg/L | D103: =IFERROR(AVERAGEIFS(D95:D102,C95:C102,Summary!$D$4,H95:H102,"y"),"no included runs — model uses its default") -> no included runs — model uses its default
A104: Value in use - optimum DO | C104: mg/L | D104: =IFERROR(AVERAGEIFS(E95:E102,C95:C102,Summary!$D$4,H95:H102,"y"),"no included runs — model uses its default") -> no included runs — model uses its default
A105: Value in use - impairment DO | C105: mg/L | D105: =IFERROR(AVERAGEIFS(F95:F102,C95:C102,Summary!$D$4,H95:H102,"y"),"no included runs — model uses its default") -> no included runs — model uses its default
A106: Value in use - toxic DO | C106: mg/L | D106: =IFERROR(AVERAGEIFS(G95:G102,C95:C102,Summary!$D$4,H95:H102,"y"),"no included runs — model uses its default") -> no included runs — model uses its default
A109: =HYPERLINK("https://github.com/amy-bo/electroPioreactor/blob/CO2-modular/Media/protocols/knallgas-stoichiometry.md","KNALLGAS UPTAKE RATIO (per organism)") -> KNALLGAS UPTAKE RATIO (per organism)
A110: Value in use: average of the included ratios for the active organism.
A111: Researcher | B111: Date | C111: Organism | D111: H2 | E111: O2 | F111: CO2 | G111: Include? | H111: Notes
A120: Value in use - H2 | C120: parts | D120: =IFERROR(AVERAGEIFS(D112:D119,C112:C119,Summary!$D$4,G112:G119,"y"),"no included runs — model uses its default") -> no included runs — model uses its default
A121: Value in use - O2 | C121: parts | D121: =IFERROR(AVERAGEIFS(E112:E119,C112:C119,Summary!$D$4,G112:G119,"y"),"no included runs — model uses its default") -> no included runs — model uses its default
A122: Value in use - CO2 | C122: parts | D122: =IFERROR(AVERAGEIFS(F112:F119,C112:C119,Summary!$D$4,G112:G119,"y"),"no included runs — model uses its default") -> no included runs — model uses its default
A125: =HYPERLINK("https://github.com/amy-bo/electroPioreactor/blob/CO2-modular/Media/protocols/current-density-screen.md","CURRENT-DENSITY TOLERANCE (per organism)") -> CURRENT-DENSITY TOLERANCE (per organism)
A126: Value in use: average of the included screen results for the active organism.
A127: Researcher | B127: Date | C127: Organism | D127: j optimum | E127: j ceiling | F127: Include? | G127: Notes
A136: Value in use - optimum j | C136: mA/cm² | D136: =IFERROR(AVERAGEIFS(D128:D135,C128:C135,Summary!$D$4,F128:F135,"y"),"no included runs — model uses its default") -> no included runs — model uses its default
A137: Value in use - ceiling j | C137: mA/cm² | D137: =IFERROR(AVERAGEIFS(E128:E135,C128:C135,Summary!$D$4,F128:F135,"y"),"no included runs — model uses its default") -> no included runs — model uses its default
