Workbook
Name A_anode: Chemistry!$D$130
Name A_anode_wet: Electrochemistry!$D$46
Name A_cath_wet: Electrochemistry!$D$47
Name A_DH: Chemistry!$D$186
Name a_int: 'Mass Transfer'!$D$49
Name a_surf: 'Mass Transfer'!$D$71
Name A_x: Calibrations!$D$186
Name A_x: Geometry!$D$21
Name A_x: 'Mass Transfer'!$D$17
Name alk_NaHCO3_gL: Chemistry!$D$308
Name alk_needed: Chemistry!$D$306
Name alk_pH_target: Chemistry!$D$303
Name alk_pH_target_c: Chemistry!$D$304
Name alk_resid_t: Chemistry!$D$305
Name anode_dia: Electrochemistry!$D$42
Name anode_j_cont: Electrochemistry!$D$50
Name anode_j_max: Electrochemistry!$D$51
Name anode_material: Electrochemistry!$D$63
Name anode_shape: Electrochemistry!$D$41
Name b_anode: Electrochemistry!$D$107
Name b_cath: Electrochemistry!$D$109
Name beta_nonC: Chemistry!$D$295
Name bio_CO2: Biology!$D$12
Name bio_H2: Biology!$D$10
Name bio_O2: Biology!$D$11
Name bleach_flag: Chemistry!$D$109
Name bleach_rate: Chemistry!$D$107
Name bleach_t1ppm: Chemistry!$D$108
Name bp_const: Calibrations!$D$166
Name bubble_regime: 'Mass Transfer'!$D$64
Name buffer_caution_frac: Chemistry!$D$238
Name buffer_flag: Chemistry!$D$219
Name C_air_CO2: 'Mass Transfer'!$D$146
Name C_CO2_mf: 'Mass Transfer'!$D$382
Name C_cycle_peak: 'Mass Transfer'!$D$199
Name C_cycle_start: 'Mass Transfer'!$D$198
Name C_cycle_start_b: Biology!$D$97
Name C_eff: Chemistry!$D$145
Name C_eff_Cl2: Chemistry!$D$226
Name C_eff_hi: Chemistry!$D$157
Name C_eff_hi_Cl2: Chemistry!$D$260
Name C_eff_lo: Chemistry!$D$156
Name C_eff_lo_Cl2: Chemistry!$D$259
Name C_H2_sat: Biology!$D$41
Name C_sat_CO2: 'Mass Transfer'!$D$145
Name ca_rho_0: Calibrations!$D$181
Name ca_rho_k: Calibrations!$D$182
Name cal_Dint: Calibrations!$D$75
Name cal_DO_impair: Calibrations!$D$105
Name cal_DO_min: Calibrations!$D$103
Name cal_DO_opt: Calibrations!$D$104
Name cal_DO_toxic: Calibrations!$D$106
Name cal_etaF: Calibrations!$D$31
Name cal_etaF_OER: Calibrations!$D$32
Name cal_flow: Calibrations!$D$60
Name cal_gerrit_int: Calibrations!$D$17
Name cal_gerrit_slope: Calibrations!$D$16
Name cal_hs: Calibrations!$D$76
Name cal_hs_fill: Calibrations!$D$77
Name cal_j_ceiling: Calibrations!$D$137

Sheet Summary
A1: Parameter | B1: Name | C1: Unit | D1: Value | E1: Source | F1: Comment
A2: Reactor | B2: Reactor_sel | D2: ed04 | E2: select | F2: Active build. Choose from the values below. Dropdown.
A3: Electrode | B3: electrode_sel | D3: MMO tube | E3: select | F3: Anode material and sparger. Choose from the list (Electrochemistry A35:A38). Dropdown.
A4: HOB organism | B4: organism_sel | D4: Xanthobacter tagetidis | E4: select | F4: The HOB strain; sets the DO band the schedule targets.
A5: Media | B5: media_sel | D5: AMYBO03 | E5: select | F5: Growth medium.
A6: Electrolysis power | B6: led_intensity | C6: % | D6: 3 | E6: input | F6: LED channel D %, the AEP-Plugin 'electrolysis_power' setting (runtime-clamped 0–10 %); drives the electrolysis current via Gerrit's Law. The model needs 3–10 % (fit range ∩ plugin clamp), which the D6 validation enforces.
A7: Stirrer rate | B7: stir_rpm_set | C7: rpm | D7: 1000 | E7: input | F7: Stir rate; sets tip speed and surface O2 transfer.
A8: Temperature setpoint | B8: temp_C | C8: °C | D8: 30 | E8: input | F8: Temperature setpoint; sets Henry solubilities and rates.
A9: Media volume | B9: media_volume | C9: mL | E9: input/blank | F9: Liquid charged; leave blank to use the reactor's recommended max working volume.
A10: Ambient pressure | B10: P_atm_set | C10: Pa | E10: input/blank | F10: blank = default 101325 Pa
A11: Vent model | B11: vent_model_sel | C11: - | D11: Open vent | E11: select | F11: "Outflow only" = check valve or sealed cap that holds a vacuum (no air ever enters). "Open vent" = a plain needle or tube with no forced flow (air drawn back after each pulse; Q_backdraw, Mass Transfer D385, an estimate). "Air exchange" = measured bidirectional exchange at Q_vent (Mass Transfer D142). The MEP0.3 and AEP0.1.1 caps vent through 2 × 1/16" ID tubes to 0.2 µm PTFE filters, AEP0.2 through needles to the same filters, with no check valve: Open vent (owner, T5). Anything else → #N/A throughout.
A12: O₂ sizing phase | B12: O2_phase_sel | C12: - | D12: Growth | E12: select | F12: "Growth" sizes the headline schedule (rows 18–21) on the O₂ surplus after knallgas uptake; "Lag" on the whole net electrolytic O₂ plus H₂ (no uptake yet). Anything else → #N/A. Both phases are shown either way, and the start-up schedule (rows 31 and 33) is always the lag one. If the chosen phase’s DO target is unreachable (rows 65–66), the schedule falls back to the legacy O₂ flush guard (Mass Transfer D89).
A13: Added NaHCO₃ (on top of the recipe) | B13: NaHCO3_add_gL | C13: g/L | E13: input/blank | F13: NaHCO₃ added to the medium; blank = none. It feeds the charge balance, ionic strength, conductivity and CO₂ storage (Chemistry D44, D185, D180, D296), so pH, DO and the schedule respond. Row 80 then shows what is still needed. After a large addition (pH up by more than 0.1) re-enter the DIC reference pH, Chemistry D291 (D310 says when).
A14: N₂ dose (mean flow of timed pulses) | B14: N2_sweep_set | C14: mL/min | E14: input/blank | F14: Blank = none, the owner’s preference: fix the medium first (rows 80–81). If N₂ must be used it is pulsed apart from the CO₂ pulses (owner, T7); the balance takes its mean flow as an inert inflow with no O₂ or CO₂ (Mass Transfer D424–D425), exact for the mean-field fractions; the sawtooth of a separate N₂ flush is a model improvement (row 135).
A15: Solenoid command resolution | B15: pulse_res_set | C15: s | D15: 0.05 | E15: input | F15: Smallest step the AEP-Plugin solenoid timer is commanded in; the pulse is rounded to it (row 19). Same solenoid as ed04, whose logged pulses (0.2, 0.25, 0.4, 0.6 s) are all 0.05 s multiples (owner, T8).
A17: Results | B17: Name | C17: Unit | D17: Value | E17: Source | F17: Comment | G17: Override
A18: CO₂ sparge duration | B18: res_spg_dur | C18: s | D18: =IF('Mass Transfer'!has_cal=0,"calibrate this reactor first (CO₂ flow section of the Calibrations tab, or a CO2 flows row)",'Mass Transfer'!spg_dur_opt) -> 0.67407652 | E18: =HYPERLINK("#'Mass Transfer'!D90","→ Mass") -> → Mass | F18: How long to open the CO2 solenoid each dose.
A19: CO₂ sparge duration (as run) | B19: res_spg_dur_run | C19: s | D19: =IF(NOT(ISNUMBER(res_spg_dur)),res_spg_dur,'Mass Transfer'!spg_dur) -> 0.65 | F19: Pulse actually evaluated by every operating check below. Summary override wins, then Manual mode, otherwise the optimum rounded to the pulse resolution.
A20: ="CO₂ sparge interval ("&vent_model_sel&", sized on "&O2_phase_sel&")" -> CO₂ sparge interval (Open vent, sized on Growth) | B20: res_spg_int | C20: min | D20: =IF('Mass Transfer'!has_cal=0,"calibrate this reactor first (CO₂ flow section of the Calibrations tab, or a CO2 flows row)",'Mass Transfer'!spg_int_opt) -> 7.4219028 | E20: =HYPERLINK("#'Mass Transfer'!D91","→ Mass") -> → Mass | F20: Time between doses: the shortest of the carbon-limited, headspace-O₂-dilution and pH-ceiling intervals (rows 28–30), plus the H₂ flammability screen when the schedule is sized on Lag (row 12); row 22 says which binds. Sized for the vent model in row 11 and the pulse in row 19.
A21: CO₂ sparge interval (as run) | B21: res_spg_int_run | C21: min | D21: =IF(NOT(ISNUMBER(res_spg_int)),res_spg_int,'Mass Transfer'!spg_int) -> 7.19 | F21: Interval actually evaluated below, in decimal minutes. Default converts the commanded pulse to the ideal delivery duty and rounds down to 0.01 min; overrides and Manual mode are evaluated directly.
A22: Binding constraint on the interval | B22: res_binding | D22: ='Mass Transfer'!opt_binding -> O2-DILUTION (headspace O2 sets the interval) | E22: =HYPERLINK("#'Mass Transfer'!D94","→ Mass Transfer") -> → Mass Transfer | F22: Which upper bound sets row 20: carbon supply, headspace-O₂ dilution, the pH ceiling (rows 28–30) or, when sized on Lag, the H₂ flammability screen; an invalid selector or an unreachable target is named here instead.
A23: Cycle-average pH (activity scale, as a probe reads) | B23: res_pH | D23: =Chemistry!pH_meas -> 6.4877019 | E23: =HYPERLINK("#Chemistry!D220","→ Chemistry") -> → Chemistry | F23: pH at the cycle-average dissolved CO₂ of the schedule in use, on the activity scale a probe reads; the trough just after a pulse is lower. Colour: green inside the HOB band (Chemistry pH_band_lo–pH_band_hi), red outside pH_red_lo–pH_red_hi (Chemistry D299–D300), amber between; thresholds in rows 159–162.
A24: Cycle-mean DO (sawtooth, sizing phase) | B24: res_DO_ss | C24: mg/L | D24: ='Mass Transfer'!DO_ss -> 2.2745651 | E24: =HYPERLINK("#'Mass Transfer'!D108","→ Mass") -> → Mass | F24: Time-mean dissolved O₂ of the sawtooth model at the schedule in use, on the sizing phase; near the target by construction when O₂ dilution binds. Both phases, mean and peak: rows 59–62.
A25: Effective biocidal chlorine | B25: res_Cl2 | C25: mg/L | D25: =Chemistry!C_eff_Cl2 -> 0 | E25: =HYPERLINK("#Chemistry!D226","→ Chemistry") -> → Chemistry | F25: =IF(Chemistry!Cl_model_check<>"OK",Chemistry!Cl_model_check,"Effective chlorine on the as-Cl2 basis; zero for chloride-free medium. Lifetime and potency require measurement.") -> Effective chlorine on the as-Cl2 basis; zero for chloride-free medium. Lifetime and potency require measurement.
A27: SCHEDULE BOUNDS AND THE START-UP (LAG-PHASE) SCHEDULE
A28: Carbon-limited sparge interval | B28: res_spg_int_carbon | C28: min | D28: ='Mass Transfer'!spg_int_carbon -> 184.72314 | E28: =HYPERLINK("#'Mass Transfer'!D112","→ Mass") -> → Mass | F28: Interval set by CO₂ supply alone. The schedule uses it only when it is shorter than the O₂-dilution interval.
A29: DO-limited sparge interval | B29: res_spg_int_DO | C29: min | D29: ='Mass Transfer'!spg_int_DO -> 7.4219028 | E29: =HYPERLINK("#'Mass Transfer'!D185","→ Mass Transfer") -> → Mass Transfer | F29: Longest interval that still dilutes headspace O₂ enough to hold the DO target on the sizing phase (row 12). #N/A = the target is unreachable at this surface kLa.
A30: pH-ceiling interval (longest keeping pH at or under the band ceiling) | C30: min | D30: ='Mass Transfer'!spg_int_pH -> 212.48606 | E30: =HYPERLINK("#'Mass Transfer'!D432","→ Mass Transfer") -> → Mass Transfer | F30: Longest interval keeping pH at or under the band ceiling, for the pulse in use. Far above the other bounds, or "no pH bound", unless N₂ dilutes the headspace; then it stops pH overshooting the band once CO₂ no longer has to dilute O₂. Row 55 warns if a long interval lets the carbon pool run dry.
A31: Start-up (lag-phase) interval, same pulse | B31: res_spg_int_su | C31: min | D31: ='Mass Transfer'!spg_int_su_run -> 1.21 | E31: =HYPERLINK("#'Mass Transfer'!D547","→ Mass Transfer") -> → Mass Transfer | F31: Owner asked for both schedules (T4). Until uptake starts: the shortest of the lag O₂ bound (the legacy guard when the lag DO target is unreachable), the interval clearing the H₂ flammability screen (Biology D92), the lag pH ceiling and the carbon bound. Select Lag in row 12 to evaluate every output at exactly this schedule.
A32: As-run duty ÷ optimised duty | C32: × | D32: =IF(AND(ISNUMBER(res_spg_dur_run),ISNUMBER(res_spg_int_run),ISNUMBER('Mass Transfer'!duty_actual)),('Mass Transfer'!pulse_V0+'Mass Transfer'!Q_CO2_fit*res_spg_dur_run)/('Mass Transfer'!Q_CO2/60)/(60*res_spg_int_run)/'Mass Transfer'!duty_actual,"calibrate this reactor first (CO₂ flow section of the Calibrations tab, or a CO2 flows row)") -> 1.0006813 | E32: =HYPERLINK("#'Mass Transfer'!D93","→ Mass") -> → Mass | F32: Delivered CO₂ duty of the schedule as run (rows 19 and 21) against the sized duty; 1 = rounding the interval has not moved the CO₂ dose. The sizing already uses the commanded pulse (Mass Transfer D320), so a ratio near 1 also means the DO target holds.
A33: Start-up schedule: lag-phase DO and H₂ | B33: res_su_state | D33: =IF(ISNUMBER('Mass Transfer'!spg_int_su_run),"DO "&TEXT('Mass Transfer'!DO_avg_su_mgL,"0.0")&" mg/L mean, "&TEXT('Mass Transfer'!DO_peak_su_mgL,"0.0")&" peak; H₂ "&TEXT('Mass Transfer'!y_H2_end_su,"0%")&" before each pulse; set by "&'Mass Transfer'!su_binding,"no executable start-up schedule") -> DO 4.1 mg/L mean, 4.1 peak; H₂ 3% before each pulse; set by the legacy O₂ flush guard (lag DO target unreachable) | E33: =HYPERLINK("#'Mass Transfer'!D556","→ Mass Transfer") -> → Mass Transfer | F33: The lag sawtooth evaluated at the start-up interval (rows 61–62 show the lag phase at the headline schedule instead).
A34: Checks | D34: Value | E34: Source | F34: Comment
A35: Vial geometry consistent? | B35: chk_geom | D35: =Geometry!geom_check -> VIAL GEOMETRY INCONSISTENT - measure the true headspace (protocols/vial-geometry.md) | E35: =HYPERLINK("#Geometry!D90","→ Geometry") -> → Geometry | F35: Red until the vial headspace is measured (vial-geometry.md); while red, the pulse above is provisional (~4x uncertain). Once a headspace and its working fill are included on the Calibrations tab it reads OK, because the measured headspace replaces the cylinder approximation.
A36: Reactor calibrated? | B36: chk_cal | D36: ='Mass Transfer'!cal_warning -> calibrated: ed04 (flow from CO2 flows) | E36: =HYPERLINK("#'Mass Transfer'!D120","→ Mass") -> → Mass | F36: Red = no CO₂-flow calibration for this reactor (neither an included run in the Calibrations tab CO₂ flow section nor a CO2 flows row); results read 'calibrate first' (flow-calibration.md). Green names the source in use.
A37: O₂ within the organism band (mean vs optimum, peak vs impairment)? | B37: chk_DO_opt | D37: ='Mass Transfer'!DO_peak_band -> organism band unknown – peak 2.5 mg/L is under the inhibition ceiling | E37: =HYPERLINK("#'Mass Transfer'!D374","→ Mass Transfer") -> → Mass Transfer | F37: Rule (owner decision, option a): the cycle-MEAN dissolved O₂ is tested against the organism optimum — the schedule is sized on the mean, and the optimum is a time-averaged quantity — and the sawtooth PEAK (just before a pulse, sizing phase) against the impairment threshold. With the band unmeasured, the peak is tested against the inhibition ceiling. Not a tautology: the peak is not what the schedule is sized on.
A38: O₂ above organism minimum? | B38: chk_DO_min | D38: ='Mass Transfer'!DO_ss_vs_min -> minimum DO unknown - measure | E38: =HYPERLINK("#'Mass Transfer'!D110","→ Mass") -> → Mass | F38: Minimum DO is a data gap for most organisms (dissolved-oxygen.md).
A39: Can the interval relax to the carbon-limited one? | B39: chk_relax | D39: ='Mass Transfer'!sched_regime -> Do NOT relax: at the carbon-limited interval (185 min) the cycle-mean DO would be ≈13 mg/L, above the 10.1 mg/L inhibition ceiling (peaks higher) | E39: =HYPERLINK("#'Mass Transfer'!D113","→ Mass") -> → Mass | F39: Green only if CO₂ dosed for carbon alone would still hold dissolved O₂ at the target; otherwise it states the DO the longer interval would give.
A40: H₂ headspace flammable? | B40: chk_H2 | D40: =Biology!H2_safety -> POTENTIAL FLAMMABILITY (lag screen): H₂ 9% mean, 15% before each pulse; O₂ 5% mean, 8% before each pulse – until uptake starts, sparge every ≤2.3 min or sweep ≥1.0 mL/min N₂; vent to a hood; no ignition sources | E40: =HYPERLINK("#Biology!D44","→ Biology") -> → Biology | F40: Nominal lag-phase hazard screen, not safety certification. Predictions depend on unmeasured vent/transfer behaviour; validate mixture-specific limits, sampling and gas clearance before operation.
A41: Bubble model valid? | B41: chk_bubble | D41: ='Mass Transfer'!bubble_regime -> Dynamic | E41: =HYPERLINK("#'Mass Transfer'!D64","→ Mass") -> → Mass | F41: 'Sinter OOR' = sinter pore size out of the validated bubble range; sparge mass-transfer is approximate (expected for the porosity-0 disc).
A42: CO₂ supply meets demand? | B42: chk_CO2_supply | D42: =IFERROR("×"&TEXT('Mass Transfer'!CO2_sd_ratio,"0.0")&IF('Mass Transfer'!CO2_sd_ratio>=1," OK"," SHORTFALL (CO2 < demand)")&" delivered; ×"&TEXT('Mass Transfer'!CO2_uptake_ratio,"0.0")&" absorbed per pulse (row 77)","calibrate this reactor first") -> ×49.8 OK delivered; ×2.5 absorbed per pulse (row 77) | E42: =HYPERLINK("#'Mass Transfer'!D126","→ Mass") -> → Mass | F42: Ratio of CO₂ delivered to carbon demand (should be ≥ 1), with the absorbed ratio beside it (row 77): delivered counts gas the pulse expels unabsorbed, absorbed does not.
A43: Pulse ≥ solenoid floor? | B43: chk_pulse_floor | D43: =IFERROR('Mass Transfer'!dur_ok,"calibrate this reactor first (CO₂ flow section of the Calibrations tab, or a CO2 flows row)") -> OK | E43: =HYPERLINK("#'Mass Transfer'!D130","→ Mass") -> → Mass | F43: The optimal pulse must exceed the shortest reliable sparge (Calibrations tab CO₂-flow Min pulse, else CO2 flows column I, else the default on Mass Transfer D396).
A44: Dosing window OK? | B44: chk_od_window | D44: =IFERROR('Mass Transfer'!od_ok,"calibrate this reactor first (CO₂ flow section of the Calibrations tab, or a CO2 flows row)") -> OK | E44: =HYPERLINK("#'Mass Transfer'!D95","→ Mass") -> → Mass | F44: Enough gap between doses to read OD without sparging.
A45: Carryover risk? | B45: chk_carryover | D45: ='Mass Transfer'!carry_flag -> not measured – record the max flow without carryover for ed04 in CO2 flows column M | E45: =HYPERLINK("#'Mass Transfer'!D59","→ Mass") -> → Mass | F45: Pulse flow against the measured no-carryover maximum for this reactor (CO2 flows column M). Reads "not measured" (amber) until one is recorded; the superficial-velocity rule of thumb is row 51.
A46: Tip-speed shear OK? | B46: chk_tip | D46: ='Mass Transfer'!tip_warn -> OK | E46: =HYPERLINK("#'Mass Transfer'!D111","→ Mass") -> → Mass | F46: Stirrer tip speed under the conservative 1.5 m/s shear limit.
A47: Media volume fits vial? | B47: chk_media_vol | D47: =Geometry!media_vol_warn -> OK | E47: =HYPERLINK("#Geometry!D54","→ Geometry") -> → Geometry | F47: Media volume not exceeding the max working volume.
A48: Liquid level OK? | B48: chk_level | D48: =Geometry!depth_warn -> OK | E48: =HYPERLINK("#Geometry!D55","→ Geometry") -> → Geometry | F48: Liquid not above the usable vial depth.
A49: LED current-law in range? | B49: chk_led_law | D49: =Electrochemistry!I_valid -> OK | E49: =HYPERLINK("#Electrochemistry!D20","→ Electrochemistry") -> → Electrochemistry | F49: LED intensity within Gerrit's-Law validated band 3-25% (gerrit-current.md).
A50: Organism DO data present? | B50: chk_DO_data | D50: =IF(AND(ISNUMBER(Biology!DO_min),ISNUMBER(Biology!DO_opt),ISNUMBER(Biology!DO_impair),ISNUMBER(Biology!DO_toxic)),"inputs present","DATA GAP - organism DO thresholds unmeasured; results unreliable") -> DATA GAP - organism DO thresholds unmeasured; results unreliable | E50: =HYPERLINK("#Biology!D45","→ Biology") -> → Biology | F50: Red = the selected organism has no measured DO thresholds, so every DO/sparge verdict above is running on missing data.
A51: Carryover — superficial-velocity rule of thumb (secondary) | B51: chk_carry_usg | D51: ='Mass Transfer'!carry_flag_usg -> OK – 6.6 mm/s against the 50 mm/s rule of thumb | E51: =HYPERLINK("#'Mass Transfer'!D414","→ Mass Transfer") -> → Mass Transfer | F51: Secondary to row 45: gas velocity against the provisional 50 mm/s entrainment rule of thumb. It cannot fail at bench flows; row 45 tests the measured limit.
A52: DO target and pH band met together at the schedule in use? | D52: =IF(ISNA('Mass Transfer'!F_vent_ex+'Mass Transfer'!O2_src_sched),"#N/A – check the selectors in D2–D5, D11 and D12",IF(NOT(ISNUMBER('Mass Transfer'!spg_int_DO)),"DO target unreachable on the sizing phase; schedule is a legacy fallback",IF(OR(Chemistry!DIC_ref_check<>"OK",ABS(Electrochemistry!DO_lag_ref/Electrochemistry!ec_DO_lag-1)>Electrochemistry!DO_lag_tol),"watch – refresh the DIC or lag-DO reference before claiming either target",IF(AND(res_pH>=cf_pH_lo,res_pH<=cf_pH_hi,res_DO_ss<='Mass Transfer'!DO_target*'Mass Transfer'!M_O2),"yes – both targets met by the evaluated schedule","NO – evaluated schedule misses the pH band or mean DO target")))) -> NO – evaluated schedule misses the pH band or mean DO target | E52: =HYPERLINK("#Chemistry!D220","→ Chemistry") -> → Chemistry | F52: The vent model couples the two: when O₂ dilution binds, CO₂ is doing the O₂ dilution, so the DO-limited interval sets the pH (row 22 says which bound binds). Tests both band edges (rows 160–161) at the evaluated schedule, including any override in G18/G20. Red = the two targets conflict: fix the medium (rows 80–81) or measure the vent. Amber "watch" = the DIC or lag-DO reference needs re-entering first (Chemistry D310, Electrochemistry D134). #N/A = a selector (D2–D5, D11, D12) is not a listed value.
A53: Headspace sag per cycle if the vent held a vacuum | C53: - | D53: ='Mass Transfer'!hs_sag -> 0.050971246 | E53: =HYPERLINK("#'Mass Transfer'!D389","→ Mass Transfer") -> → Mass Transfer | F53: Upper bound on the per-cycle pressure deficit (fraction of 1 atm) that the "Outflow only" model implies at the schedule in use; 0.05 = 5 %.
A54: Outflow-only headspace physically plausible? | D54: ='Mass Transfer'!hs_sag_chk -> UNVERIFIED pressure closure: air ingress is assumed; measure vent make-up flow | E54: =HYPERLINK("#'Mass Transfer'!D391","→ Mass Transfer") -> → Mass Transfer | F54: "HEADSPACE SAGS" = the check-valve model needs more vacuum than a real cap holds: switch D11 to Open vent or Air exchange. With an open vent or air exchange it reads UNVERIFIED, because the air ingress is assumed until the vent back-draw is measured (row 121); OK when an N₂ dose covers the per-cycle deficit.
A55: Carbon pool stays above air equilibrium through the cycle? | B55: chk_pool | D55: ='Mass Transfer'!pool_start_chk -> OK | E55: =HYPERLINK("#'Mass Transfer'!D435","→ Mass Transfer") -> → Mass Transfer | F55: Pulse-start dissolved CO₂ against air equilibrium at the schedule in use; WATCH = fixation empties the pool within the cycle (only reachable with a long, N₂-relaxed interval).
A57: DISSOLVED O₂ AND HEADSPACE BY PHASE (both shown; row 12 picks which sizes the headline schedule)
A58: Vent air ingress in use | C58: mL/min | D58: ='Mass Transfer'!Q_vent_used -> 0.015 | E58: =HYPERLINK("#'Mass Transfer'!D386","→ Mass Transfer") -> → Mass Transfer | F58: 0 for "Outflow only"; Q_backdraw (Mass Transfer D385, an estimate) for "Open vent"; the measured Q_vent (Mass Transfer D142) for "Air exchange". The single number that reconciles the O₂, CO₂ and flammability blocks — measure it.
A59: Cycle-mean DO — growth phase | C59: mg/L | D59: ='Mass Transfer'!DO_avg_g_mgL -> 2.2745651 | E59: =HYPERLINK("#'Mass Transfer'!D343","→ Mass Transfer") -> → Mass Transfer | F59: Time-mean dissolved O₂ at the schedule in use with the growth-phase O₂ surplus (sawtooth model).
A60: Peak DO — growth phase | C60: mg/L | D60: ='Mass Transfer'!DO_peak_g_mgL -> 2.4528287 | E60: =HYPERLINK("#'Mass Transfer'!D344","→ Mass Transfer") -> → Mass Transfer | F60: Dissolved O₂ just before a pulse, growth phase. Compare with the organism band and the ceiling.
A61: Cycle-mean DO — lag phase | C61: mg/L | D61: ='Mass Transfer'!DO_avg_l_mgL -> 5.6407737 | E61: =HYPERLINK("#'Mass Transfer'!D364","→ Mass Transfer") -> → Mass Transfer | F61: Same schedule, no uptake yet: the whole net electrolytic O₂ crosses the surface. Expect this from inoculation until growth is established, and in every abiotic run.
A62: Peak DO — lag phase | C62: mg/L | D62: ='Mass Transfer'!DO_peak_l_mgL -> 6.0044228 | E62: =HYPERLINK("#'Mass Transfer'!D365","→ Mass Transfer") -> → Mass Transfer | F62: Lag-phase sawtooth peak; the discriminating prediction for an abiotic DO trace (R2 experiment 2).
A63: Peak DO under the inhibition ceiling? — growth | D63: ='Mass Transfer'!DO_peak_chk_g -> peak 2.5 mg/L under the 10.1 mg/L ceiling | E63: =HYPERLINK("#'Mass Transfer'!D348","→ Mass Transfer") -> → Mass Transfer | F63: Red = the growth-phase sawtooth peaks above the organism’s inhibition limit: its toxic DO when known, otherwise the 0.30 atm ceiling (Mass Transfer D565).
A64: Peak DO under the inhibition ceiling? — lag | D64: ='Mass Transfer'!DO_peak_chk_l -> peak 6.0 mg/L under the 10.1 mg/L ceiling | E64: =HYPERLINK("#'Mass Transfer'!D369","→ Mass Transfer") -> → Mass Transfer | F64: Red = the lag-phase peak breaches that limit at the schedule in use; the culture would then be inhibited before it can take up O₂ (Mass Transfer D565).
A65: DO target reachable? — growth | D65: ='Mass Transfer'!DO_feas_g -> reachable – kLa margin 1.74× | E65: =HYPERLINK("#'Mass Transfer'!D347","→ Mass Transfer") -> → Mass Transfer | F65: Surface kLa in use ÷ kLa required on the growth source. Below 1× no interval holds the target.
A66: DO target reachable? — lag | D66: ='Mass Transfer'!DO_feas_l -> UNREACHABLE at this surface kLa – margin 0.61× (raise kL_surf, lower the current, or accept a higher DO) | E66: =HYPERLINK("#'Mass Transfer'!D368","→ Mass Transfer") -> → Mass Transfer | F66: ="Same on the lag source. Currently "&TEXT('Mass Transfer'!kLa_margin_l,"0.00")&"×: "&IF('Mass Transfer'!kLa_margin_l<1,"the target cannot be held during lag at the kLa in use, whatever the schedule — an owner decision (target the ceiling with a margin during lag?).","the target can be held during lag at the kLa in use.") -> Same on the lag source. Currently 0.61×: the target cannot be held during lag at the kLa in use, whatever the schedule — an owner decision (target the ceiling with a margin during lag?).
A67: Surface kLa required — growth | C67: 1/h | D67: ='Mass Transfer'!kLa_surf_req_g*3600 -> 15.84859 | E67: =HYPERLINK("#'Mass Transfer'!D345","→ Mass Transfer") -> → Mass Transfer | F67: Per hour: compare with your measured kLa (Calibrations D46, 1/h); the estimate in use is Mass Transfer D98 (1/s × 3600).
A68: Surface kLa required — lag | C68: 1/h | D68: ='Mass Transfer'!kLa_surf_req_l*3600 -> 45.331425 | E68: =HYPERLINK("#'Mass Transfer'!D366","→ Mass Transfer") -> → Mass Transfer | F68: Per hour: compare with your measured kLa (Calibrations D46, 1/h); the estimate in use is Mass Transfer D98 (1/s × 3600).
A69: Headspace O₂ fraction (flux-mean; the headspace swings around it) — growth | C69: - | D69: ='Mass Transfer'!y_O2_mf_g -> 0.027660228 | E69: =HYPERLINK("#'Mass Transfer'!D329","→ Mass Transfer") -> → Mass Transfer | F69: Flux-mean O₂ in the vent gas at the schedule in use, growth phase.
A70: Headspace O₂ fraction (mean-field) — lag | C70: - | D70: ='Mass Transfer'!y_O2_mf_l -> 0.054287788 | E70: =HYPERLINK("#'Mass Transfer'!D351","→ Mass Transfer") -> → Mass Transfer | F70: Lag phase; with the H₂ fraction below it, the flammability basis of row 40.
A71: Headspace H₂ fraction (mean-field) — lag | C71: - | D71: ='Mass Transfer'!y_H2_mf_l -> 0.093870759 | E71: =HYPERLINK("#'Mass Transfer'!D352","→ Mass Transfer") -> → Mass Transfer | F71: Lag-phase H₂ in the headspace (LFL 4 %). Growth is zero only by the 100 % uptake assumption.
A72: Headspace CO₂ fraction (mean-field, sizing phase) | C72: - | D72: ='Mass Transfer'!y_CO2_mf -> 0.9400624 | E72: =HYPERLINK("#'Mass Transfer'!D381","→ Mass Transfer") -> → Mass Transfer | F72: What the vent model implies for the CO₂ the pH rests on: ~97 % for "Outflow only", lower when air enters ("Open vent", "Air exchange"). The pool model (Mass Transfer D200) should agree within the sawtooth.
A74: SUPPORTING FIGURES
A75: Stir-bar tip speed | B75: res_tip_speed | C75: m/s | D75: ='Mass Transfer'!tip_speed -> 0.62831853 | E75: =HYPERLINK("#'Mass Transfer'!D68","→ Mass") -> → Mass | F75: Checked against 1.5 m/s above.
A76: Carbon margin at the cycle trough | B76: res_carbon_margin | C76: × | D76: =Biology!CO2_margin_trough -> 508.69799 | E76: =HYPERLINK("#Biology!D98","→ Biology") -> → Biology | F76: Dissolved CO₂ at the lowest point of the dosing cycle vs RuBisCO Km (was the in-sparge saturation peak, which a sub-second pulse never reaches); large = ample carbon. Complements the supply:demand ratio (D42).
A77: CO₂ absorbed per pulse : carbon demand (dissolved, not delivered) | B77: res_CO2_uptake | C77: × | D77: ='Mass Transfer'!CO2_uptake_ratio -> 2.5014213 | E77: =HYPERLINK("#'Mass Transfer'!D417","→ Mass Transfer") -> → Mass Transfer | F77: Shown beside D42: CO₂ the liquid takes up after each pulse (incl. bicarbonate), per hour, over fixation. Informative, not pass/fail: below 1 the culture also draws on headspace CO₂ between pulses. Carbon sufficiency is row 76.
A79: MEDIA DESIGN — fix the medium first (owner, T7); N₂ only if it must, pulsed apart from CO₂
A80: NaHCO₃ still needed to lift pH to the target (first-order) | C80: g/L | D80: =Chemistry!alk_NaHCO3_gL -> 0.12312249 | E80: =HYPERLINK("#Chemistry!D306","→ Chemistry") -> → Chemistry | F80: Alkalinity still needed, on top of the recipe and any NaHCO₃ in D13, for a probe pH of Chemistry D303 (the 6.5 band floor by default) at today’s dissolved CO₂. Enter it in D13 to see the coupled result; re-read, as CO₂ storage moves with it.
A81: Same, as extra alkalinity | C81: mM | D81: =Chemistry!alk_needed*1000 -> 1.4656218 | E81: =HYPERLINK("#Chemistry!D306","→ Chemistry") -> → Chemistry | F81: Any strong base counts (NaHCO₃, KHCO₃, NaOH). Using nitrate or urea instead of NH₄⁺ also avoids the acid released as the culture takes up ammonium.
A82: N₂ (mean of timed pulses) that holds the DO target at the carbon-limited interval | C82: mL/min | D82: ='Mass Transfer'!N2_for_DO -> 0.33784664 | E82: =HYPERLINK("#'Mass Transfer'!D426","→ Mass Transfer") -> → Mass Transfer | F82: Sizing phase (row 12): the N₂ that removes the DO bound on the CO₂ schedule. With it in row 14 the pH ceiling (row 30) then usually sets the interval. #N/A = the DO target is unreachable at this surface kLa, which no N₂ fixes.
A83: N₂ (mean of timed pulses) that keeps lag-phase H₂ below the LFL | C83: mL/min | D83: =Biology!N2_sweep_H2safe -> 0.92785267 | E83: =HYPERLINK("#Biology!D88","→ Biology") -> → Biology | F83: Mean-field, with no CO₂ at all; the pre-pulse sawtooth peaks higher, so treat it as a lower bound and re-read row 40 with it entered. A screen, not a mixture safety certification.
A85: ELECTROLYSIS & CURRENT DENSITY
A86: Electrolysis current | B86: res_I_mA | C86: mA | D86: =Electrochemistry!I_app*1000 -> 5.69 | E86: =HYPERLINK("#Electrochemistry!D19","→ Electrochemistry") -> → Electrochemistry | F86: Cell current at the set Electrolysis power (Gerrit's Law).
A87: Anode current density | B87: res_j_anode | C87: mA/cm² | D87: =Electrochemistry!j_anode -> 3.2878104 | E87: =HYPERLINK("#Electrochemistry!D48","→ Electrochemistry") -> → Electrochemistry | F87: Current per unit submerged anode area (shape-aware).
A88: Current density status (now) | B88: res_j_status | D88: =Electrochemistry!j_flag -> watch - above optimum current density | E88: =HYPERLINK("#Electrochemistry!D62","→ Electrochemistry") -> → Electrochemistry | F88: Green = at/below the strain optimum; amber = above optimum; red = over the strain ceiling or the electrode's rating.
A89: Max Electrolysis power | B89: res_power_max | C89: % | D89: =Electrochemistry!power_max -> 10 | E89: =HYPERLINK("#Electrochemistry!D73","→ Electrochemistry") -> → Electrochemistry | F89: AEP-Plugin runtime clamp: electrolysis_power ≤ 10 %.
A90: Max electrolysis current | B90: res_I_max | C90: mA | D90: =Electrochemistry!I_max -> 12.9 | E90: =HYPERLINK("#Electrochemistry!D74","→ Electrochemistry") -> → Electrochemistry | F90: Highest cell current you can set (at max power).
A91: Max anode current density | B91: res_j_anode_max | C91: mA/cm² | D91: =Electrochemistry!j_anode_max -> 7.4539112 | E91: =HYPERLINK("#Electrochemistry!D75","→ Electrochemistry") -> → Electrochemistry | F91: Anode current density at max power.
A92: Current density status (at max power) | B92: res_j_status_max | D92: =Electrochemistry!j_flag_max -> EXCEED - max current over a limit | E92: =HYPERLINK("#Electrochemistry!D76","→ Electrochemistry") -> → Electrochemistry | F92: Whether the highest current you can set stays within the strain and electrode limits.
A94: ELECTROCHEMISTRY – CALCULATED (hand these to an electrochemist)
A95: Cathodic faradaic efficiency (calculated) | B95: res_etaF | C95: - | D95: =Electrochemistry!etaF_calc -> 0.96404431 | E95: =HYPERLINK("#Electrochemistry!D88","→ Electrochemistry") -> → Electrochemistry | F95: Fraction of cathode current making H₂ rather than reducing dissolved O₂.
A96: Estimated cell voltage | B96: res_V_cell | C96: V | D96: =Electrochemistry!V_cell_est -> 2.6494396 | E96: =HYPERLINK("#Electrochemistry!D119","→ Electrochemistry") -> → Electrochemistry | F96: Reversible voltage + both overpotentials + ohmic drop. Measure across the electrodes to test it.
A97: Cell-voltage verdict | B97: res_V_flag | C97: - | D97: =Electrochemistry!V_flag -> OK — 2.65 V estimated against a 5 V rail | E97: =HYPERLINK("#Electrochemistry!D122","→ Electrochemistry") -> → Electrochemistry | F97: Whether the 5 V drive rail can deliver the set current.
A98: Peroxide verdict | B98: res_H2O2_flag | C98: - | D98: =Electrochemistry!H2O2_flag -> watch — steady growth is clear (0.048 mg/L) but LAG PHASE is not: peroxide passes the threshold in 6 min (0.84 mg/L after 1 h) before biomass can scavenge it | E98: =HYPERLINK("#Electrochemistry!D99","→ Electrochemistry") -> → Electrochemistry | F98: H₂O₂ from the 2-electron branch of cathodic O₂ reduction, against the growth-inhibition threshold, in both the growing and the lag phase.
A99: Electrode-surface pH verdict | B99: res_buffer_flag | C99: - | D99: =Chemistry!buffer_flag -> OK — buffer holds the electrode surfaces at the bulk pH | E99: =HYPERLINK("#Chemistry!D219","→ Chemistry") -> → Chemistry | F99: Whether the phosphate buffer holds the electrode surfaces at the bulk pH at this current density.
A100: HOCl/Cl⁻ couple minus anode potential | B100: res_E_Cl_margin | C100: V | D100: =Chemistry!E_Cl_margin -> #N/A | E100: =HYPERLINK("#Chemistry!D209","→ Chemistry") -> → Chemistry | F100: Negative = the anode is above the chloride-oxidation couple: chlorine forms, limited by chloride transport (Chemistry D132).
A101: Copper dissolution headroom at the anode | B101: res_E_Cu_margin | C101: V | D101: =Chemistry!E_Cu_margin -> 1.2488841 | E101: =HYPERLINK("#Chemistry!D211","→ Chemistry") -> → Chemistry | F101: How far the operating anode sits above the Cu²⁺/Cu standard potential; positive = copper dissolution thermodynamically allowed.
A102: Measured (activity-scale) pH | B102: res_pH_probe | C102: - | D102: =Chemistry!pH_meas -> 6.4877019 | E102: =HYPERLINK("#Chemistry!D220","→ Chemistry") -> → Chemistry | F102: What a probe reads: the charge balance solves on concentrations, a glass electrode reads activity.
A103: Surface kLa required for the DO target | B103: res_kLa_req | C103: 1/h | D103: ='Mass Transfer'!kLa_surf_req*3600 -> 15.84859 | E103: =HYPERLINK("#'Mass Transfer'!D186","→ Mass Transfer") -> → Mass Transfer | F103: Below this, no sparge interval holds the target dissolved O₂ on the sizing phase. Per hour, the unit you measure in and the Calibrations tab takes (Calibrations D46). Both phases and their margins: rows 65–68.
A105: EXPERIMENTS TO IMPROVE ACCURACY (bench measurements; each replaces an estimate or a data gap) | B105: Impact | C105: Effort | D105: Protocol | F105: Why it matters
A106: Measure surface kLa (kL_surf) | B106: HIGH | C106: med | D106: =HYPERLINK("https://github.com/amy-bo/electroPioreactor/blob/AEP02/Media/protocols/surface-kla.md","surface-kla.md →") -> surface-kla.md → | F106: Sets how far dissolved O₂ must sit above the headspace to shed the surplus, and the feasibility margin behind the whole DO strategy (kLa in use ÷ kLa required). It moves the answer continuously.
A107: Measure / confirm vial total volume | B107: HIGH | C107: low | D107: =HYPERLINK("https://github.com/amy-bo/electroPioreactor/blob/AEP02/Media/protocols/vial-geometry.md","vial-geometry.md →") -> vial-geometry.md → | F107: Sets the headspace volume: the pulse moves slightly more than 1:1 with it (one headspace volume per pulse, less the fixed V₀; Mass Transfer D90) and the interval through the flush; also the liquid charge. Water-fill.
A108: Measure cathodic Faradaic efficiency (etaF) | B108: HIGH | C108: med | D108: =HYPERLINK("https://github.com/amy-bo/electroPioreactor/blob/AEP02/Media/protocols/faradaic-efficiency.md","faradaic-efficiency.md →") -> faradaic-efficiency.md → | F108: Calculated from the cathodic O₂ flux, but the calculation rests on an estimated electrode mass-transfer coefficient. Measuring it settles the H₂/O₂ split and the peroxide source at once.
...

Sheet Geometry
A1: GEOMETRY
A2: Parameter | B2: Name | C2: Unit | D2: Value | E2: Source / assumption
A4: IMPORTS (from other tabs)
A5: (import) Reactor selection | B5: reactor_sel | C5: - | D5: =Summary!Reactor_sel -> ed04 | E5: =HYPERLINK("#Summary!D2","→ Summary") -> → Summary
A6: (import) Media volume (set) | B6: media_volume | C6: mL | D6: =Summary!media_volume -> 0 | E6: =HYPERLINK("#Summary!D9","→ Summary") -> → Summary
A18: Vial outer diameter | B18: vial_OD | C18: mm | D18: =VLOOKUP(rx_ver,tbl_rxtype,MATCH("vial OD (mm)",tbl_rxtype_hdr,0),FALSE) -> 27.48 | E18: Selected by rx_ver; invalid version returns an error.
A19: Vial wall thickness | B19: vial_wall | C19: mm | D19: 1.1 | E19: Borosilicate vial; Pioreactor publish neither wall nor internal diameter, so wall estimated ~1.1 mm (typical for this glass-vial class).
A20: Vial internal diameter | B20: vial_ID | C20: mm | D20: =vial_OD-2*vial_wall -> 25.28 | E20: OD minus two wall thicknesses.
A21: Internal cross-sectional area | B21: A_x | C21: mm² | D21: =PI()/4*vial_ID^2 -> 501.931 | E21: Uniform-cylinder body approximation (neck excluded - see headspace).
A22: Internal usable depth | B22: D_int | C22: mm | D22: =VLOOKUP(rx_ver,tbl_rxtype,MATCH("usable depth (mm)",tbl_rxtype_hdr,0),FALSE) -> 55 | E22: Physical cap-to-base depth from the reactor-type table, selected by rx_ver. The Calibrations volume-equivalent depth (D75) is not a physical length and does not replace it.
A23: Recommended max working volume (datum) | B23: V_max | C23: mL | D23: =VLOOKUP(rx_ver,tbl_rxtype,MATCH("max working (mL)",tbl_rxtype_hdr,0),FALSE) -> 16 | E23: Selected by rx_ver.
A24: Total internal vial volume | B24: V_vial_total | C24: mL | D24: =IF(ISNUMBER(cal_Vtot),cal_Vtot,VLOOKUP(rx_ver,tbl_rxtype,MATCH("total vial (mL)",tbl_rxtype_hdr,0),FALSE)) -> 20 | E24: Selected by rx_ver.
A25: Bare liquid level (datum height) | B25: h_datum | C25: mm | D25: =V_max*1000/A_x -> 31.876891 | E25: Height the bare max volume reaches with no inserts.
A26: Electrode rod diameter | B26: rod_d | C26: mm | D26: 6 | E26: 6 mm rod electrodes.
A27: Number of electrodes | B27: rod_n | C27: - | D27: 2 | E27: Anode + cathode.
A28: Electrode tip clearance above base | B28: elec_clear | C28: mm | D28: 22 | E28: Held constant across builds (OD clear zone). 22 mm ↔ 33 mm insertion in AEP0.1.1. Input.
A29: Electrode insertion depth (derived) | B29: elec_ins | C29: mm | D29: =D_int-elec_clear -> 33 | E29: Cap underside -> tip. Increases for the taller AEP0.2 to keep clearance constant.
A30: Sparge tube OD | B30: spg_OD | C30: mm | D30: 3.175 | E30: 1/8" OD Flexelene 135C.
A31: Sparge tube ID | B31: spg_ID | C31: mm | D31: 1.5875 | E31: 1/16" ID.
A32: Sparge release height (= anode tip) | B32: spg_tip_h | C32: mm | D32: =elec_clear -> 22 | E32: CO₂ released near anode tip.
A33: Efflux tube OD | B33: eff_OD | C33: mm | D33: 3.175 | E33: 1/8" OD Flexelene 135C.
A34: Efflux tube ID | B34: eff_ID | C34: mm | D34: 1.5875 | E34: 1/16" ID.
A35: Electrode submerged length (@datum) | B35: elec_sub_L | C35: mm | D35: =MAX(0,h_datum-elec_clear) -> 9.8768913 | E35: For displacement bookkeeping.
A36: Electrode displaced volume | B36: elec_disp | C36: mL | D36: =rod_n*(PI()/4*rod_d^2)*elec_sub_L/1000 -> 0.55852505 | E36: Submerged rod volume.
A37: Sparge tube displaced volume | B37: spg_disp | C37: mL | D37: =(PI()/4*spg_OD^2)*MAX(0,h_datum-spg_tip_h)/1000 -> 0.078198355 | E37: Submerged sparge-tube volume.
A38: Efflux tube submerged length | B38: eff_sub_L | C38: mm | D38: =(eff_OD+eff_ID)/2 -> 2.38125 | E38: 45 deg cut; level held at top of the ID opening, so wall is wetted from tip up to (OD+ID)/2.
A39: Efflux tube displaced volume | B39: eff_disp | C39: mL | D39: =(PI()/4*(eff_OD^2-eff_ID^2))*eff_sub_L/1000 -> 0.014139811 | E39: Annular wall only (bore is open to withdrawal). 45 deg approximation.
A40: Total displaced volume | B40: disp_tot | C40: mL | D40: =elec_disp+spg_disp+eff_disp -> 0.65086321 | E40: Sum of submerged inserts.
A41: LIQUID VOLUME TO CHARGE | B41: V_charge | C41: mL | D41: =IF(media_volume>0,media_volume,ROUND(V_max-disp_tot,0)) -> 15 | E41: Integer mL to charge so the level matches the bare datum despite inserts.
A42: Resulting liquid level | B42: h_actual | C42: mm | D42: =(V_charge+disp_tot)*1000/A_x -> 31.181304 | E42: Level achieved by the integer charge (displacement taken at datum; sub-mm error).
A43: Sparge depth / bubble path length | B43: sparge_depth | C43: mm | D43: =MAX(0,h_actual-spg_tip_h) -> 9.1813041 | E43: Release point to surface.
A44: Gas-liquid interfacial area | B44: interface_A | C44: mm² | D44: =A_x-(rod_n*(PI()/4*rod_d^2)+(PI()/4*spg_OD^2)+(PI()/4*eff_OD^2)) -> 429.54773 | E44: Free surface = cross-section minus inserts piercing it.
A45: Extra headspace tube OD | B45: xtube_OD | C45: mm | D45: =eff_OD -> 3.175 | E45: 3 further 1/8" tubes (gas-out, etc.) through the cap.
A46: Number of extra headspace tubes | B46: xtube_n | C46: - | D46: 3 | E46: Protrude through the cap into headspace. 1x media in, 2x gas out
A47: Extra tube protrusion | B47: xtube_pro | C47: mm | D47: 5 | E47: Each protrudes ~5 mm below cap (45 deg cut). Input.
A48: Total in-vial insert volume | B48: V_inserts | C48: mL | D48: =(rod_n*(PI()/4*rod_d^2)*elec_ins+(PI()/4*spg_OD^2)*spg_len+(PI()/4*(eff_OD^2-eff_ID^2))*(D_int-h_actual)+xtube_n*(PI()/4*xtube_OD^2)*xtube_pro)/1000 -> 2.3875715 | E48: In-vial inserts: electrodes & sparge solid; efflux annular (open bore); extra tubes solid.
A49: Headspace gas volume | B49: headspace_V | C49: mL | D49: =IF(AND(ISNUMBER(cal_hs),ISNUMBER(cal_hs_fill)),cal_hs-(V_charge-cal_hs_fill),V_vial_total-V_charge-V_inserts) -> 2.6124285 | E49: Measured when the Calibrations vial-geometry runs exist for this reactor type (headspace at the measured working fill, shifted by any difference between that fill and V_charge); otherwise total vial volume − liquid charged − inserts.
A50: Sparge tube in-vial length | B50: spg_len | C50: mm | D50: =D_int-spg_tip_h -> 33 | E50: Cap underside to release point; tracks spg_tip_h.
A51: Reactor type (resolved from reactor) | B51: rx_ver | D51: =VLOOKUP(reactor_sel,tbl_reactor,MATCH("Type",tbl_reactor_hdr,0),FALSE) -> MEP0.3 | E51: Looked up from the reactor table (tbl_reactor, rows 58–80) by the Summary reactor (D2).
A52: Stir-bar length (from reactor type) | B52: stir_bar_L | D52: =VLOOKUP(rx_ver,tbl_rxtype,MATCH("stir bar L (mm)",tbl_rxtype_hdr,0),FALSE) -> 12 | E52: Looked up from the reactor-type table (tbl_rxtype, rows 83–87) by the resolved type (D51).
A53: 40 mL OD = 20 mL diameter (Pioreactor source); depths/volumes confirm by measurement.
A54: Media vs max working volume | B54: media_vol_warn | D54: =IF(V_charge>V_max,"MEDIA > MAX WORKING VOLUME","OK") -> OK | E54: Charge against the reactor-type maximum working volume (Geometry D23).
A55: Liquid level vs usable depth | B55: depth_warn | D55: =IF(h_actual>D_int,"LIQUID OVER USABLE DEPTH","OK") -> OK | E55: Achieved liquid level against the usable depth (D22).
A57: REACTOR LOOKUP (reactor ID → type)
A58: Reactor | B58: Type
A59: imp01 | B59: AEP0.1.1
A60: imp02 | B60: AEP0.1.1
A61: imp03 | B61: AEP0.1.1
A62: imp04 | B62: AEP0.1.1
A63: imp05 | B63: AEP0.1.1
A64: imp06 | B64: AEP0.1.1
A65: ed01 | B65: AEP0.1.1
A66: ed02 | B66: AEP0.1.1
A67: ed03 | B67: AEP0.1.1
A68: ed04 | B68: MEP0.3
A69: ed05 | B69: MEP0.3
... A80: nm02 | B80: AEP0.2
A82: REACTOR-TYPE LOOKUP (geometry & stir bar; pulled by type)
A83: Type | B83: Pioreactor | C83: vial (mL) | D83: usable depth (mm) | E83: max working (mL) | F83: total vial (mL) | G83: vial OD (mm) | H83: stir bar L (mm) | I83: stir bar dia (mm)
A84: AEP0.1.1 | B84: 1.1 | C84: 20 | D84: 55 | E84: 16 | F84: 20 | G84: 27.48 | H84: 12 | I84: 3
A85: MEP0.3 | B85: 1.1 | C85: 20 | D85: 55 | E85: 16 | F85: 20 | G85: 27.48 | H85: 12 | I85: 3
A86: AEP0.2 | B86: 1.5 | C86: 40 | D86: 95 | E86: 30 | F86: 42 | G86: 27.48 | H86: 15 | I86: 6
A87: AEP0.2a | B87: 1.5 | C87: 40 | D87: 95 | E87: 30 | F87: 42 | G87: 27.48 | H87: 15 | I87: 6
A89: VIAL GEOMETRY CONSISTENCY CHECK
A90: Vial geometry consistency check | B90: geom_check | D90: =IF(ABS(A_x*D_int/1000-V_vial_total)<=geom_tol_mL,"OK",IF(AND(ISNUMBER(cal_hs),ISNUMBER(cal_hs_fill)),"OK – headspace measured (the tapered vial differs from the cylinder, which no longer sets the headspace)","VIAL GEOMETRY INCONSISTENT - measure the true headspace (protocols/vial-geometry.md)")) -> VIAL GEOMETRY INCONSISTENT - measure the true headspace (protocols/vial-geometry.md) | E90: Compares the cylinder A_x × D_int with the total vial volume within geom_tol_mL; flags the vial-geometry experiment (Summary row 107) until the true headspace is measured. | F90: Fires INCONSISTENT while the headspace comes from the cylinder approximation: the bare cylinder (A_x × usable depth, ~28 mL) overstates the tapered 20 mL vial. Measuring the true headspace (Calibrations rows 63–77) makes it OK, because the measured headspace then replaces the approximation; the cylinder itself still differs from the vial.
A91: ELECTRODE GEOMETRY FOR THE OHMIC DROP
A92: Electrode centre-to-centre gap | B92: elec_gap | C92: mm | D92: 14 | E92: DATA GAP — measure across the cap ports with calipers. 14 mm is the mid-range for two 6 mm rods in a 25.3 mm bore. The solution resistance goes as acosh(gap/rod_d), so this sets the ohmic term in the cell-voltage budget (Electrochemistry).
A93: Electrode submerged length (at the achieved level) | B93: elec_sub_L_act | C93: mm | D93: =MAX(0,h_actual-elec_clear) -> 9.1813041 | E93: Submerged length at the ACHIEVED liquid level (D42), not the bare datum (D35, which exists for displacement bookkeeping). This is what sets the wetted area and hence current density.
A95: CONSISTENCY-CHECK TOLERANCE
A96: Vial volume consistency tolerance | B96: geom_tol_mL | C96: mL | D96: 3 | E96: Design assumption: allowed gap between the bare-cylinder volume (A_x × D_int) and the total vial volume.

Sheet Electrochemistry
A1: ELECTROCHEMISTRY
A2: Parameter | B2: Name | C2: Unit | D2: Value | E2: Source / assumption
A4: IMPORTS (from other tabs)
A5: (import) Temperature (absolute) | B5: T_K | C5: K | D5: =Biology!T_K -> 303.15 | E5: =HYPERLINK("#Biology!D18","→ Biology") -> → Biology
A6: (import) Surface pressure | B6: P_atm | C6: Pa | D6: =Biology!P_atm -> 101325 | E6: =HYPERLINK("#Biology!D19","→ Biology") -> → Biology
A7: (import) Ideal gas constant | B7: R_gas | C7: J/mol/K | D7: ='Mass Transfer'!R_gas -> 8.3144626 | E7: =HYPERLINK("#'Mass Transfer'!D101","→ Mass Transfer") -> → Mass Transfer
A8: (import) Electrode selection | B8: electrode_sel | D8: =Summary!electrode_sel -> MMO tube | E8: =HYPERLINK("#Summary!D3","→ Summary") -> → Summary
A10: LED intensity setpoint (Pioreactor LED_D) | B10: intensity | C10: % | D10: =Summary!led_intensity -> 3 | E10: Electrode drive via LED_D channel. Input.
A11: Gerrit's Law - slope | B11: gerrit_slope | C11: mA/% | D11: =IF(ISNUMBER(cal_gerrit_slope),cal_gerrit_slope,gerrit_slope_default) -> 1.03 | E11: Gerrit's Law fit (slope) - from LED-current calibration; see protocol gerrit-current.md
A12: Gerrit's Law - intercept | B12: gerrit_int | C12: mA | D12: =IF(ISNUMBER(cal_gerrit_int),cal_gerrit_int,gerrit_int_default) -> 2.6 | E12: Gerrit's Law fit (intercept); calibration-derived constant
A13: Gerrit's Law - min valid intensity | B13: gerrit_min | C13: % | D13: 3 | E13: Fit validated from 3%.
A14: Gerrit's Law - max valid intensity | B14: gerrit_max | C14: % | D14: 25 | E14: Fit validated to 25%; above this constant-current may fail as cell V nears the 5 V rail.
A15: Faraday constant | B15: F_const | C15: C/mol | D15: 96485.332 | E15: NIST CODATA (exact, SI 2019).
A16: Electrons per H₂ | B16: z_e_H2 | C16: - | D16: 2 | E16: 2H⁺ + 2e⁻ -> H₂.
A17: Electrons per O₂ | B17: z_e_O2 | C17: - | D17: 4 | E17: 2H₂O -> O₂ + 4H⁺ + 4e⁻.
A18: Faradaic efficiency – H₂ at cathode (HER share) | B18: etaF | C18: - | D18: =IF(ISNUMBER(cal_etaF),cal_etaF,etaF_calc) -> 0.96404431 | E18: Cathodic H₂ faradaic efficiency: a measured value from the Calibrations tab if there is one, otherwise CALCULATED (D88, etaF_calc) from the cathodic O₂ reduction competing for the current. Neutral-pH HER on stainless peaks near 97% before that competition is counted, so the calculated value remains an upper bound.
A19: Electrolysis current (Gerrit's Law) | B19: I_app | C19: A | D19: =IF(AND(intensity>=gerrit_min,intensity<=MIN(gerrit_max,power_max)),(gerrit_slope*intensity+gerrit_int)/1000,NA()) -> 0.00569 | E19: Empirical current fit only over the intersection of its validated range and the plugin runtime limit. Off and below-range commands return #N/A rather than inventing current from the fit intercept. Above-limit requests also return #N/A; the plugin clamps them.
A20: Gerrit's Law validity flag | B20: I_valid | C20: - | D20: =IF(AND(intensity>=gerrit_min,intensity<=MIN(gerrit_max,power_max)),"OK","OUT – no schedule: power outside validated fit/runtime range") -> OK | E20: Model domain: gerrit_min through MIN(gerrit_max,power_max), currently 3–10%. Lower-power/start-up behaviour needs measurement; no extrapolated schedule is issued.
A21: H₂ generation rate | B21: rH2_gen | C21: mol/h | D21: =I_app*etaF/(z_e_H2*F_const)*3600 -> 0.00010233412 | E21: Faraday: I x etaF /(z F).
A22: O₂ generation rate (anodic, gross) | B22: rO2_gen | C22: mol/h | D22: =I_app*etaF_OER/(z_e_O2*F_const)*3600 -> 5.305977e-05 | E22: Anodic OER, gross. Uses etaF_OER (anodic), not the cathodic etaF. H₂:O₂(anodic) = 2:1.
A23: H₂ generation rate (volumetric) | B23: V_H2_gen | C23: mL/min | D23: =rH2_gen/60*R_gas*T_K/P_atm*1000000 -> 0.0424272 | E23: Ideal gas at surface T,P. Collect gas over water to check against this.
A24: O₂ generation rate (volumetric) | B24: V_O2_gen | C24: mL/min | D24: =rO2_gen/60*R_gas*T_K/P_atm*1000000 -> 0.021998307 | E24: Anodic gross O₂.
A25: Total gas generation rate | B25: V_gas_total | C25: mL/min | D25: =V_H2_gen+V_O2_gen -> 0.064425507 | E25: Total electrolytic gas (H₂+O₂) — abiotic check: collect over water, no cells, to verify Gerrit/etaF. Less if etaF<1.
A26: Anodic O₂ faradaic efficiency | B26: etaF_OER | C26: - | D26: =IF(ISNUMBER(cal_etaF_OER),cal_etaF_OER,etaF_OER_calc) -> 0.99970505 | E26: Anodic O₂ faradaic efficiency: measured if available, otherwise CALCULATED (etaF_OER_calc) as 1 − the chlorine share − the metal-dissolution share − the anodic H₂-oxidation share. UdG contains chloride, so the chlorine current is modelled explicitly (D101). The faradaic-efficiency screen measures the sum of cathodic ORR and anodic HOR losses.
A27: Electrons per O₂ on the peroxide branch (cathode) | B27: z_e_ORR | C27: - | D27: =VLOOKUP(electrode_sel,tbl_electrode,MATCH("z_e_ORR",tbl_electrode_hdr,0),FALSE) -> 2 | E27: Electrode lookup: 2 e⁻ per O₂ on the peroxide branch (SS cathode, neutral pH) for every current electrode. The current drawn per O₂ is the weighted n_ORR_eff (D141), not this value.
A28: O₂ consumed at cathode (ORR) | B28: O2_cathode_ORR | C28: mol/h | D28: =I_app*(1-etaF)/(n_ORR_eff*F_const)*3600 -> 2.0630956e-06 | E28: Moles of O₂ reduced: the non-H₂ cathodic current (1−etaF) divided by n_ORR_eff·F. Equals the transport-limited O₂ flux when etaF is calculated; stays consistent if a measured etaF is in use. 0 at etaF = 1.
A29: Net O₂ to dissolved pool | B29: O2_net_gen | C29: mol/h | D29: =rO2_gen-O2_cathode_ORR+O2_H2O2_ret_g -> 5.1027984e-05 | E29: Anodic O₂ minus cathodic consumption at the design DO (D85), plus the O₂ returned by peroxide oxidation at the anode (D171) — the O₂ the dissolved pool receives in growth. The lag phase uses O2_net_lag (D132).
A30: z_e_ORR = 2 is the peroxide branch only; the current per O₂ is n_ORR_eff (D141, 2 and 4 e⁻ weighted by f_HOOH). etaF unmeasured — both live here per electrode.
A31: Sparger (from electrode) | B31: sparger_e | D31: =VLOOKUP(electrode_sel,tbl_electrode,MATCH("sparger",tbl_electrode_hdr,0),FALSE) -> Sintered | E31: Sparger type of the selected electrode assembly, looked up in the electrode table (tbl_electrode).
A32: Sinter porosity grade (from electrode) | B32: por_grade_e | D32: =IF(ISNUMBER(cal_sinter),cal_sinter,IF(ISNUMBER(VLOOKUP(electrode_sel,tbl_electrode,MATCH("sinter porosity",tbl_electrode_hdr,0),FALSE)),VLOOKUP(electrode_sel,tbl_electrode,MATCH("sinter porosity",tbl_electrode_hdr,0),FALSE),0)) -> 0 | E32: Porosity 0 = Gerrit's sourced sintered disc (SD8/0/P 8mm, fallback SD10/0/P 10mm; Scientific Glass Labs, 2026-05)
A33: ELECTRODE LOOKUP (selecting the electrode sets sparger, porosity, cathode)
A34: Electrode | B34: anode material | C34: anode dia (mm) | D34: sparger | E34: sinter porosity | F34: cathode | G34: cathode dia (mm) | H34: etaF | I34: z_e_ORR | J34: anode shape | K34: anode j cont (mA/cm²) | L34: anode j max (mA/cm²) | M34: cathode shape | N34: material note
A35: Pt/Ti rod | B35: Pt/Ti | C35: 6 | D35: Tube | E35: n/a | F35: SS rod | G35: 6 | H35: ? | I35: 2 | J35: rod | K35: 100 | L35: 500 | M35: rod | N35: Pt/Ti O₂-evolution; cells bind before the coating.
A36: MMO rod | B36: MMO | C36: 6 | D36: Tube | E36: n/a | F36: SS rod | G36: 6 | H36: ? | I36: 2 | J36: rod | K36: 50 | L36: 500 | M36: rod | N36: IrO₂-Ta₂O₅ O₂-selective; derates vs chloride.
A37: MMO tube | B37: MMO | C37: 6 | D37: Sintered | E37: 0 | F37: SS rod | G37: 6 | H37: ? | I37: 2 | J37: tube | K37: 10 | L37: 60 | M37: rod | N37: Tubular MMO CP rating ~100 A/m²; binds near the cell limit.
A38: Graphite rod | B38: Graphite | C38: 6 | D38: Tube | E38: n/a | F38: SS rod | G38: 6 | H38: ? | I38: 2 | J38: rod | K38: 35 | L38: 50 | M38: rod | N38: Consumable; ~35 mA/cm² erosion, unsuitable for sustained neutral O₂; testing only.
A40: CURRENT DENSITY, WETTED AREA & LIMITS
A41: Anode shape (from electrode) | B41: anode_shape | C41: - | D41: =VLOOKUP(electrode_sel,tbl_electrode,MATCH("anode shape",tbl_electrode_hdr,0),FALSE) -> tube | E41: Rod counts its end face; a tube does not.
A42: Anode diameter (from electrode) | B42: anode_dia | C42: mm | D42: =VLOOKUP(electrode_sel,tbl_electrode,MATCH("anode dia (mm)",tbl_electrode_hdr,0),FALSE) -> 6 | E42: Electrode table.
A43: Cathode shape (from electrode) | B43: cathode_shape | C43: - | D43: =VLOOKUP(electrode_sel,tbl_electrode,MATCH("cathode shape",tbl_electrode_hdr,0),FALSE) -> rod | E43: Rod/tube; sets the end-face term.
A44: Cathode diameter (from electrode) | B44: cathode_dia | C44: mm | D44: =VLOOKUP(electrode_sel,tbl_electrode,MATCH("cathode dia (mm)",tbl_electrode_hdr,0),FALSE) -> 6 | E44: Electrode table.
A45: (import) Submerged electrode length | B45: L_sub | C45: mm | D45: =Geometry!elec_sub_L_act -> 9.1813041 | E45: Submerged length at the achieved liquid level (Geometry D93), not the bare datum (Geometry D35), which would overstate the wetted area by about 6.5% and understate every current density by the same factor.
A46: Anode wetted area | B46: A_anode_wet | C46: cm² | D46: =(PI()*anode_dia*L_sub+IF(anode_shape="rod",PI()/4*anode_dia^2,0))/100 -> 1.7306351 | E46: Lateral π·d·L (+ end face for a rod). mm²→cm².
A47: Cathode wetted area | B47: A_cath_wet | C47: cm² | D47: =(PI()*cathode_dia*L_sub+IF(cathode_shape="rod",PI()/4*cathode_dia^2,0))/100 -> 2.0133784 | E47: Same, cathode.
A48: Anode current density | B48: j_anode | C48: mA/cm² | D48: =I_app*1000/A_anode_wet -> 3.2878104 | E48: I / anode wetted area.
A49: Cathode current density | B49: j_cathode | C49: mA/cm² | D49: =I_app*1000/A_cath_wet -> 2.8260957 | E49: I / cathode wetted area.
A50: Anode plating limit — continuous | B50: anode_j_cont | C50: mA/cm² | D50: =VLOOKUP(electrode_sel,tbl_electrode,MATCH("anode j cont (mA/cm²)",tbl_electrode_hdr,0),FALSE) -> 10 | E50: Coating continuous rating (electrode table).
A51: Anode plating limit — maximum | B51: anode_j_max | C51: mA/cm² | D51: =VLOOKUP(electrode_sel,tbl_electrode,MATCH("anode j max (mA/cm²)",tbl_electrode_hdr,0),FALSE) -> 60 | E51: Coating maximum (electrode table).
A52: Cathode (SS) HER limit — continuous | B52: cath_j_cont | C52: mA/cm² | D52: 80 | E52: Stainless-steel HER ~25–80 mA/cm² continuous.
A53: Cathode (SS) HER limit — maximum | B53: cath_j_max | C53: mA/cm² | D53: 250 | E53: Stainless-steel HER ~250 mA/cm² lab max.
A54: Fallback optimum j (unlisted strain) | B54: j_opt_default | C54: mA/cm² | D54: 1 | E54: Conservative fallback for an unlisted organism.
A55: Fallback ceiling j (unlisted strain) | B55: j_ceiling_default | C55: mA/cm² | D55: 2 | E55: Conservative fallback ceiling.
A56: Strain optimum current density | B56: j_opt_strain | C56: mA/cm² | D56: =IF(ISNA(MATCH(organism_sel,OrganismList,0)),NA(),IF(ISNUMBER(cal_j_opt),cal_j_opt,IFERROR(VLOOKUP(organism_sel,tbl_strain,MATCH("j_opt",tbl_strain_hdr,0),FALSE),j_opt_default))) -> 2 | E56: Strain table below; fallback if unlisted.
A57: Strain tolerated ceiling | B57: j_ceiling_strain | C57: mA/cm² | D57: =IF(ISNA(MATCH(organism_sel,OrganismList,0)),NA(),IF(ISNUMBER(cal_j_ceiling),cal_j_ceiling,IFERROR(VLOOKUP(organism_sel,tbl_strain,MATCH("j_ceiling",tbl_strain_hdr,0),FALSE),j_ceiling_default))) -> 4 | E57: Inhibition above this.
A58: Strain data confidence | B58: j_strain_conf | C58: - | D58: =IFERROR(VLOOKUP(organism_sel,tbl_strain,MATCH("confidence",tbl_strain_hdr,0),FALSE),"unknown") -> low | E58: low/unknown → provisional; run the screen.
A59: Current density vs strain | B59: j_bio_flag | C59: - | D59: =IF(j_anode<=j_opt_strain,"OK - at/below optimum",IF(j_anode<=j_ceiling_strain,"watch - above optimum","EXCEED - over strain ceiling")) -> watch - above optimum | E59: Green ≤ optimum, amber ≤ ceiling, red above.
A60: Current density vs anode plating | B60: j_mat_flag | C60: - | D60: =IF(j_anode>anode_j_max,"EXCEED - over plating maximum",IF(OR(j_anode>anode_j_cont,anode_material="Graphite"),IF(anode_material="Graphite","watch - graphite consumable in neutral O₂ (testing only)","watch - above continuous plating rating"),"OK - within plating rating")) -> OK - within plating rating | E60: Anode coating limit; graphite always ≥ amber.
A61: Cathode current density vs SS norm | B61: j_cath_flag | C61: - | D61: =IF(j_cathode<=cath_j_cont,"OK - cathode within HER norm",IF(j_cathode<=cath_j_max,"watch - high cathodic j","EXCEED - over SS HER norm")) -> OK - cathode within HER norm | E61: SS cathode HER check.
A62: CURRENT DENSITY STATUS (worst of above) | B62: j_flag | C62: - | D62: =IF(OR(ISNUMBER(SEARCH("EXCEED",j_bio_flag)),ISNUMBER(SEARCH("EXCEED",j_mat_flag)),ISNUMBER(SEARCH("EXCEED",j_cath_flag))),"EXCEED - current density over a limit",IF(OR(ISNUMBER(SEARCH("watch",j_bio_flag)),ISNUMBER(SEARCH("watch",j_mat_flag)),ISNUMBER(SEARCH("watch",j_cath_flag))),"watch - above optimum current density","OK - current density in range")) -> watch - above optimum current density | E62: Worst of strain, plating and cathode.
A63: Anode material (from electrode) | B63: anode_material | C63: - | D63: =VLOOKUP(electrode_sel,tbl_electrode,MATCH("anode material",tbl_electrode_hdr,0),FALSE) -> MMO | E63: Electrode table; drives the graphite warning.
A64: STRAIN CURRENT-DENSITY TOLERANCE (mA/cm²) — keyed on organism; see current-density-screen.md
A65: Strain / organism | B65: j_opt | C65: j_ceiling | D65: confidence | E65: source
A66: Cupriavidus necator | B66: 2 | C66: 4 | D66: low | E66: Inferred analogue (Zhang 2020; Bause 2018 biofilm 0.5). Run screen.
A67: Xanthobacter autotrophicus | B67: 2 | C67: 4 | D67: low | E67: No strain-specific j; mixed-HOB analogue. Run screen.
A68: Xanthobacter flavus | B68: 2 | C68: 4 | D68: low | E68: No strain-specific j; mixed-HOB analogue. Run screen.
A69: Xanthobacter tagetidis | B69: 2 | C69: 4 | D69: low | E69: No strain-specific j; mixed-HOB analogue. Run screen.
A70: Cupriavidus metallidurans | B70: 2 | C70: 4 | D70: low | E70: No strain-specific j; genus-mate of necator. Run screen.
A71: UdG (mixed) | B71: 2.14 | C71: 4.29 | D71: med | E71: Zhang 2020 (JCP 263:121596) + Pous 2022 (BiTE 18:101010); undivided cell.
A72: MAXIMUM-POWER CURRENT (AEP-Plugin clamp)
A73: Max electrolysis power | B73: power_max | C73: % | D73: 10 | E73: AEP-Plugin runtime clamp: electrolysis_power ≤ 10 % (MAX_ELECTROLYSIS_POWER).
A74: Max electrolysis current | B74: I_max | C74: mA | D74: =gerrit_slope*power_max+gerrit_int -> 12.9 | E74: Gerrit's Law at the power clamp.
A75: Max anode current density | B75: j_anode_max | C75: mA/cm² | D75: =I_max/A_anode_wet -> 7.4539112 | E75: Anode current density at max power.
A76: Status at max power | B76: j_flag_max | C76: - | D76: =IF(OR(j_anode_max>j_ceiling_strain,j_anode_max>anode_j_max),"EXCEED - max current over a limit",IF(OR(j_anode_max>j_opt_strain,j_anode_max>anode_j_cont),"watch - max current above optimum","OK - max current in range")) -> EXCEED - max current over a limit | E76: Worst of strain ceiling and plating at max power.
A78: CALCULATED FARADAIC SPLIT – the cathode competes with dissolved O₂
A80: (import) dissolved-O₂ ceiling | B80: ec_O2_ceil | C80: mol/m³ | D80: =Biology!O2_ceil_C -> 0.3147429 | E80: → Biology (O2_ceil_C)
A81: (import) O₂ diffusivity at reactor T | B81: ec_D_O2 | C81: m²/s | D81: ='Mass Transfer'!D_O2 -> 2.2495444e-09 | E81: → Mass Transfer (D_O2)
A82: Reactor liquid volume (V_charge in litres) | B82: ec_V_L | C82: L | D82: =V_charge/1000 -> 0.015 | E82: V_charge (D153, mL) / 1000 → L
A83: Electrode mass-transfer coefficient — O₂ | B83: km_O2 | C83: cm/s | D83: =IF(ISNUMBER(cal_km_O2),cal_km_O2,km_O2_default) -> 0.004 | E83: The measured value from the Calibrations tab (electrode mass-transfer section: ferricyanide limiting current scaled to O₂) when a run for this reactor at the Summary rpm and temperature is included; otherwise the swirl-velocity estimate km_O2_default (D165).
A84: Diffusivity exponent for k_m scaling | B84: km_exp | C84: - | D84: 0.644 | E84: k_m ∝ D^(1−0.356) from the Eisenberg correlation. (A rotating disc would give D^(2/3); a stagnant film D^1.)
A85: (import) Design DO for the cathodic O₂ flux (= the DO target) | B85: ec_DO_design | C85: mol/m³ | D85: ='Mass Transfer'!DO_target -> 0.071159265 | E85: → Mass Transfer (DO_target, D179): the dissolved O₂ the schedule is designed to hold — the organism optimum once one is entered, otherwise the target fraction of the inhibition ceiling. The growth-phase cathodic O₂ reduction is evaluated here rather than at the modelled steady DO, which would make the sheet circular (DO depends on the net O₂, which depends on this loss). The lag phase uses DO_lag_ref (D129).
A86: Cathodic O₂ current at the design DO | B86: i_ORR_design | C86: A | D86: =n_ORR_eff*F_const*(km_O2/100)*ec_DO_design*(A_cath_wet/10000) -> 0.00020458787 | E86: i = n_ORR_eff·F·k_m·C·A, the O₂ mass-transport limit at the cathode charged at the effective electron count (D141). Current that does NOT make hydrogen, and it consumes dissolved O₂. Le Bozec 2001 (Corros Sci 43:765) show ORR on 316L in neutral solution running mixed 2e⁻/4e⁻ and limited by the passive film as much as by transport, so this is an upper bound on the loss.
A87: Cathodic O₂ current at the ceiling DO | B87: i_ORR_ceiling | C87: A | D87: =n_ORR_eff*F_const*(km_O2/100)*ec_O2_ceil*(A_cath_wet/10000) -> 0.00090490786 | E87: The same flux if dissolved O₂ ever reached the inhibition ceiling — the worst case for the faradaic split.
A88: Cathodic faradaic efficiency (calculated) | B88: etaF_calc | C88: - | D88: =MAX(0,1-i_ORR_design/I_app) -> 0.96404431 | E88: 1 − (cathodic O₂ current)/(applied current). Neutral-pH HER on stainless also has its own kinetic losses; this accounts only for the O₂ that competes for the current.
A89: same, at the ceiling DO (worst case) | B89: etaF_calc_min | C89: - | D89: =MAX(0,1-i_ORR_ceiling/I_app) -> 0.84096523 | E89: Lower bound on the cathodic efficiency if DO ran up to the inhibition ceiling.
A90: HYDROGEN PEROXIDE — the 2-electron branch of that O₂ reduction
A91: Peroxide selectivity of the O₂ reduction | B91: f_HOOH | C91: - | D91: 0.15 | E91: 10–20% of the O₂ reduced on stainless in neutral solution leaves as H₂O₂ rather than water (Le Bozec et al. 2001, RRDE on 316L/904L; prereduced surfaces favour the 4e⁻ route, polished ones run mixed). 0.15 is the midpoint. Nobody has published a defensible j₀/Tafel pair for ORR on steel — the surface is a potential-history-dependent Cr/Fe oxide — so this is bounded by transport above and by selectivity here.
A92: Peroxide molar mass | B92: M_H2O2 | C92: g/mol | D92: 34.0147 | E92: H₂O₂, IUPAC atomic weights.
A93: Peroxide production rate | B93: r_H2O2 | C93: mg/L/h | D93: =f_HOOH*I_app*(1-etaF)/(n_ORR_eff*F_const)*M_H2O2*1000*3600/ec_V_L -> 0.70175578 | E93: Peroxide-branch share of the moles of O₂ reduced (f_HOOH × D28 flux), so it follows a measured etaF too. One H₂O₂ per O₂ on that branch. This source runs whenever there is current and dissolved O₂.
A94: Catalase clearance rate (growing culture) | B94: k_cat_cells | C94: 1/s | D94: 0.0041 | E94: First-order whole-culture peroxide clearance at ~1e8 cells/mL, from the measured half-lives (21 s at OD 1.0, 3.5 min at OD 0.1; Uhl & Dukan 2016, PLoS ONE 11:e0159706) — t½ ≈ 3 min here. Catalase is far below saturation at µM peroxide (Km is tens of mM), so first order is the right form. Scales with cell density: at inoculation it is effectively zero.
A95: Steady peroxide, growing culture | B95: H2O2_ss | C95: mg/L | D95: =r_H2O2/(k_cat_cells*3600) -> 0.047544429 | E95: Production ÷ catalase clearance. The bulk Fenton route is not modelled: the medium's 0.18 mM Fe(II) would consume peroxide within a second, but it is a one-shot 6 mg/L capacity that is itself oxidised away in 5–20 min, and bulk hydroxyl radicals are scavenged by bicarbonate within ~0.2 µm, far short of a cell. The damage route that matters is intracellular.
A96: Peroxide after 1 h with no biomass (lag) | B96: H2O2_lag_1h | C96: mg/L | D96: =r_H2O2_lag/(k_H2O2_anode*3600)*(1-EXP(-k_H2O2_anode*3600)) -> 0.84080932 | E96: No catalase pool at inoculation: peroxide accumulates at the lag-phase rate (D152) against the anodic sink (D151), approaching the plateau r/k. This is the exposed window.
A97: Peroxide growth-inhibition threshold | B97: H2O2_thresh | C97: mg/L | D97: 0.17 | E97: 5 µM sustained extracellular H₂O₂ measurably slows growth (doubling time 63 → 94 min); E. coli K-12 in glucose minimal medium, chemostatted rather than bolus exposure — the same shape as an electrode source. Li & Imlay 2018, Free Radic Biol Med 120:217. Killing is a different regime entirely, 1–2 mM. No H₂O₂ dose-response exists for C. necator, Hydrogenophaga or Xanthobacter; this is the E. coli number, used as the closest available.
A98: Time to that threshold during lag | B98: t_H2O2_thresh | C98: min | D98: =IF(r_H2O2_lag>0,IF(1-H2O2_thresh*k_H2O2_anode*3600/r_H2O2_lag>0,-LN(1-H2O2_thresh*k_H2O2_anode*3600/r_H2O2_lag)/k_H2O2_anode/60,NA()),NA()) -> 6.4601891 | E98: Time for an un-inoculated or just-inoculated vessel to pass the growth-inhibition threshold, with the anodic sink. #N/A = the plateau r/k never reaches the threshold.
A99: Peroxide verdict | B99: H2O2_flag | C99: - | D99: =IF(H2O2_ss>H2O2_thresh,"PEROXIDE ABOVE THE GROWTH-INHIBITION THRESHOLD even with a full catalase pool ("&TEXT(H2O2_ss,"0.00")&" mg/L)",IF(ISNUMBER(t_H2O2_thresh),"watch — steady growth is clear ("&TEXT(H2O2_ss,"0.000")&" mg/L) but LAG PHASE is not: peroxide passes the threshold in "&TEXT(t_H2O2_thresh,"0")&" min ("&TEXT(H2O2_lag_1h,"0.00")&" mg/L after 1 h) before biomass can scavenge it","OK — peroxide stays below the growth-inhibition threshold in both phases, including the lag plateau")) -> watch — steady growth is clear (0.048 mg/L) but LAG PHASE is not: peroxide passes the threshold in 6 min (0.84 mg/L after 1 h) before biomass can scavenge it | E99: Steady growth against the threshold first; then lag, judged on whether the lag plateau ever reaches the threshold (D98 is finite), not on the 1-hour level alone, which is quoted beside the crossing time.
A100: ANODIC CHARGE BUDGET
A101: (import) chlorine current | B101: ec_I_Cl | C101: A | D101: =Chemistry!I_Cl -> 0 | E101: → Chemistry (I_Cl, chloride-mass-transport limited)
A102: (import) metal-dissolution charge fraction | B102: ec_corr_I | C102: - | D102: =Chemistry!corr_I_frac -> 0 | E102: → Chemistry (corr_I_frac; a DATA GAP until measured)
A103: Chlorine share of the anodic current | B103: f_Cl_anode | C103: - | D103: =ec_I_Cl/I_app -> 0 | E103: Chlorine evolution as a fraction of the applied current, at the chloride mass-transport limit (2 e⁻ per net chloride, Chemistry D132). The anode sits above the HOCl/Cl⁻ couple (Chemistry D209), so chlorine is accessible and transport-limited; the share is small only because UdG chloride is trace.
A104: Anodic faradaic efficiency (calculated) | B104: etaF_OER_calc | C104: - | D104: =MAX(0,1-f_Cl_anode-IF(ISNUMBER(ec_corr_I),ec_corr_I,0)-IF(ISNUMBER(f_HOR_anode),f_HOR_anode,0)-f_H2O2_anode) -> 0.99970505 | E104: 1 − chlorine share − metal-dissolution share − anodic H₂-oxidation share (f_HOR_anode, D145) − peroxide-oxidation share (D170). It remains an UPPER BOUND while the metal and H₂ charges are unmeasured: a corroding anode, or one oxidising crossed-over H₂ (ceiling D148), takes current that this cell still credits to oxygen.
A105: CELL VOLTAGE BUDGET — is the drive capable, and what is the anode doing?
...

Sheet Chemistry
A1: CHEMISTRY — buffered pH & anodic bleaching (open-system carbonate+phosphate charge balance, van't Hoff to reactor T)
A2: Parameter | B2: Name | C2: Unit | D2: Value | E2: Source / assumption
A3: IMPORTS (from other tabs)
A4: (import) Reactor temperature | B4: TKc | C4: K | D4: =Biology!T_K -> 303.15 | E4: → Biology
A5: (import) Dissolved CO₂ (cycle average) | B5: CO2aqc | C5: mol/L | D5: ='Mass Transfer'!CO2aqc_ss -> 0.025556025 | E5: Schedule-dependent cycle-average dissolved CO₂ (mass-conserving limit cycle, bounded by air equilibrium and pure-CO₂ saturation).
A6: (import) Electrolysis current (Gerrit's Law) | B6: Iappc | C6: A | D6: =Electrochemistry!I_app -> 0.00569 | E6: → Electrochemistry (I_app)
A7: (import) Faraday constant | B7: Fcc | C7: C/mol | D7: =Electrochemistry!F_const -> 96485.332 | E7: → Electrochemistry (F_const)
A8: Reactor liquid volume (V_charge in litres) | B8: VLc | C8: L | D8: =V_charge/1000 -> 0.015 | E8: V_charge (D279, mL) / 1000 → L
A9: Molar gas constant | B9: R_gas | C9: J/mol/K | D9: ='Mass Transfer'!R_gas -> 8.3144626 | E9: → Mass Transfer (R_gas).
A11: EQUILIBRIUM CONSTANTS (van't Hoff to reactor T) | F11: K(T)=K₂₅·exp(−ΔH/R·(1/T−1/298.15)). ΔH = standard enthalpy of dissociation; well documented. Same van't Hoff treatment your sheet already uses for the Henry constants.
A12: constant | B12: K₂₅ | C12: ΔH kJ/mol | D12: K at reactor T | E12: source
A13: Carbonate Ka1 (pKa 6.35) | B13: 4.45e-07 | C13: 9.15 | D13: =B13*EXP(-C13*1000/R_gas*(1/TKc-1/T_ref)) -> 4.7293259e-07 | E13: Handbook: K₂₅ (CRC/IUPAC); ΔH dissociation (CRC)
A14: Carbonate Ka2 (pKa 10.33) | B14: 4.69e-11 | C14: 14.9 | D14: =B14*EXP(-C14*1000/R_gas*(1/TKc-1/T_ref)) -> 5.1787732e-11 | E14: Handbook: K₂₅ (CRC/IUPAC); ΔH dissociation (CRC)
A15: Phosphate Ka1 (pKa 2.15) | B15: 0.0071 | C15: -8 | D15: =B15*EXP(-C15*1000/R_gas*(1/TKc-1/T_ref)) -> 0.0067319686 | E15: Handbook: K₂₅ (CRC/IUPAC); ΔH dissociation (CRC)
A16: Phosphate Ka2 (pKa 7.20) | B16: 6.31e-08 | C16: 3.6 | D16: =B16*EXP(-C16*1000/R_gas*(1/TKc-1/T_ref)) -> 6.4629632e-08 | E16: Handbook: K₂₅ (CRC/IUPAC); ΔH dissociation (CRC)
A17: Phosphate Ka3 (pKa 12.38) | B17: 4.2e-13 | C17: 16 | D17: =B17*EXP(-C17*1000/R_gas*(1/TKc-1/T_ref)) -> 4.671774e-13 | E17: Handbook: K₂₅ (CRC/IUPAC); ΔH dissociation (CRC)
A18: Ammonium Ka (pKa 9.25) | B18: 5.6e-10 | C18: 52.2 | D18: =B18*EXP(-C18*1000/R_gas*(1/TKc-1/T_ref)) -> 7.9254089e-10 | E18: Handbook: K₂₅ (CRC/IUPAC); ΔH dissociation (CRC)
A19: Water Kw | B19: 1e-14 | C19: 55.8 | D19: =B19*EXP(-C19*1000/R_gas*(1/TKc-1/T_ref)) -> 1.4495593e-14 | E19: Handbook: K₂₅ (CRC/IUPAC); ΔH dissociation (CRC)
A20: Hypochlorous Ka (pKa 7.54) | B20: 2.8840315e-08 | C20: 13.8 | D20: =B20*EXP(-C20*1000/R_gas*(1/TKc-1/T_ref)) -> 3.1613717e-08 | E20: Handbook: K₂₅ (CRC/IUPAC); ΔH dissociation (CRC)
A21: HOCl pKa at reactor T | B21: pKa_HOCl | C21: - | D21: =-LOG10(Ka_HOCl) -> 7.5001244 | E21: = −log₁₀(Ka_HOCl at T)
A23: MEDIA IONIC COMPOSITION (per litre, as published; Excel derives the charge balance) | F23: Trace-metal salts omitted from SID (<0.2 mM charge, negligible vs ~50–60 mM); their chloride is carried in the chloride row.
A24: salt | B24: MW g/mol | C24: MC02 g/L | D24: UdG g/L | E24: source
A25: KH₂PO₄ | B25: 136.086 | C25: 0 | D25: 2.3 | E25: Pous 2022 (BiTE 101010) / Pous 2023 (JECE 111550), UdG recipe
A26: Na₂HPO₄ | B26: 141.96 | C26: 2.895 | D26: 2.9 | E26: Media/README.md (MC02); per Sydow 2017 SI Table S1
A27: NaH₂PO₄·2H₂O | B27: 156.01 | C27: 3.06 | D27: 0 | E27: Media/README.md (MC02); per Sydow 2017 SI Table S1
A28: NaHCO₃ | B28: 84.007 | C28: 0 | D28: 1.05 | E28: Pous 2022 (BiTE 101010) / Pous 2023 (JECE 111550), UdG recipe
A29: K₂SO₄ | B29: 174.26 | C29: 0.17 | D29: 0 | E29: Media/README.md (MC02); per Sydow 2017 SI Table S1
A30: CaSO₄·2H₂O | B30: 172.17 | C30: 0.097 | D30: 0 | E30: Media/README.md (MC02); per Sydow 2017 SI Table S1
A31: MgSO₄·7H₂O | B31: 246.48 | C31: 0.8 | D31: 0.5 | E31: Media/README.md (MC02); per Sydow 2017 SI Table S1
A32: (NH₄)₂SO₄ | B32: 132.14 | C32: 0.943 | D32: 0.47 | E32: Media/README.md (MC02); per Sydow 2017 SI Table S1
A33: CaCl₂ | B33: 110.98 | C33: 0 | D33: 0.01 | E33: Pous 2022 (BiTE 101010) / Pous 2023 (JECE 111550), UdG recipe = 0.01 g/L.
A35: MC02 — total phosphate | B35: PT_mc02 | C35: mol/L | D35: =mc_Na2HPO4/MW_Na2HPO4+mc_NaH2PO4_2H2O/MW_NaH2PO4_2H2O -> 0.040007196 | E35: Σ phosphate salts
A36: MC02 — strong-ion difference | B36: SID_mc02 | C36: mol/L | D36: =(2*mc_Na2HPO4/MW_Na2HPO4+mc_NaH2PO4_2H2O/MW_NaH2PO4_2H2O+2*mc_K2SO4/MW_K2SO4+2*mc_MgSO4_7H2O/MW_MgSO4_7H2O+2*mc_CaSO4_2H2O/MW_CaSO4_2H2O)-2*(mc_NH42SO4/MW_NH42SO4+mc_MgSO4_7H2O/MW_MgSO4_7H2O+mc_K2SO4/MW_K2SO4+mc_CaSO4_2H2O/MW_CaSO4_2H2O) -> 0.046127523 | E36: Σ strong cations − strong anions
A37: MC02 — total ammonium | B37: NT_mc02 | C37: mol/L | D37: =2*mc_NH42SO4/MW_NH42SO4 -> 0.014272741 | E37: Σ ammonium in the recipe: 2 × (NH₄)₂SO₄ per litre (MC02).
A38: MC02 — chloride | B38: Cl_mc02 | C38: mol/L | D38: =0 -> 0 | E38: no chloride salts
A39: UdG — total phosphate | B39: PT_udg | C39: mol/L | D39: =udg_KH2PO4/MW_KH2PO4+udg_Na2HPO4/MW_Na2HPO4 -> 0.037329367 | E39: Σ phosphate salts
A40: UdG — strong-ion difference | B40: SID_udg | C40: mol/L | D40: =(udg_NaHCO3/MW_NaHCO3+2*udg_Na2HPO4/MW_Na2HPO4+udg_KH2PO4/MW_KH2PO4+2*udg_MgSO4_7H2O/MW_MgSO4_7H2O+2*udg_CaCl2/MW_CaCl2)-(2*(udg_NH42SO4/MW_NH42SO4+udg_MgSO4_7H2O/MW_MgSO4_7H2O)+2*udg_CaCl2/MW_CaCl2) -> 0.063142948 | E40: Σ strong cations − strong anions
A41: UdG — total ammonium | B41: NT_udg | C41: mol/L | D41: =2*udg_NH42SO4/MW_NH42SO4 -> 0.0071136673 | E41: Σ ammonium in the recipe: 2 × (NH₄)₂SO₄ per litre (UdG).
A42: UdG — chloride | B42: Cl_udg | C42: mol/L | D42: =2*udg_CaCl2/MW_CaCl2 -> 0.00018021265 | E42: trace-metal Cl excluded (negligible)
A44: (sel) strong-ion difference | B44: pH_SID | C44: mol/L | D44: =IF(media_sel=INDEX(MediaList,1),SID_mc02,IF(media_sel=INDEX(MediaList,2),SID_udg,IF(media_sel=INDEX(MediaList,3),AMYBO03!SID_AMYBO03,NA())))+alk_add_M -> 0.11544691 | E44: by media_sel, plus any NaHCO₃ added on Summary D13 (alk_add_M, D318)
A45: (sel) total phosphate | B45: pH_PT | C45: mol/L | D45: =IF(media_sel=INDEX(MediaList,1),PT_mc02,IF(media_sel=INDEX(MediaList,2),PT_udg,IF(media_sel=INDEX(MediaList,3),AMYBO03!PT_AMYBO03,NA()))) -> 0.06000653 | E45: by media_sel
A46: (sel) total ammonium | B46: pH_NT | C46: mol/L | D46: =IF(media_sel=INDEX(MediaList,1),NT_mc02,IF(media_sel=INDEX(MediaList,2),NT_udg,IF(media_sel=INDEX(MediaList,3),AMYBO03!NT_AMYBO03,NA()))) -> 0.014272741 | E46: by media_sel
A47: (sel) chloride | B47: pH_Cl | C47: mol/L | D47: =IF(media_sel=INDEX(MediaList,1),Cl_mc02,IF(media_sel=INDEX(MediaList,2),Cl_udg,IF(media_sel=INDEX(MediaList,3),AMYBO03!Cl_AMYBO03,NA()))) -> 0 | E47: by media_sel
A49: pH SOLVE GRID (charge residual vs trial pH; root = operating pH). Constants are on the CONCENTRATION scale (activity-corrected, rows 186-194) because the balance is written in concentrations. | B49: residual mol/L | C49: interp pH at root
A50: 4 | B50: =pH_SID + pH_NT*(10^-A50)/((10^-A50)+KaN_c) + (10^-A50) - (pH_PT*Ka1p_c*(10^-A50)^2 + 2*pH_PT*Ka1p_c*Ka2p_c*(10^-A50) + 3*pH_PT*Ka1p_c*Ka2p_c*Ka3p_c)/((10^-A50)^3 + Ka1p_c*(10^-A50)^2 + Ka1p_c*Ka2p_c*(10^-A50) + Ka1p_c*Ka2p_c*Ka3p_c) - Ka1c_c*CO2aqc/(10^-A50) - 2*Ka1c_c*Ka2c_c*CO2aqc/(10^-A50)^2 - Kw_c/(10^-A50) -> 0.06996109 | C50: =IF(AND(B50>=0,B51<0),A50+pH_step*B50/(B50-B51),0) -> 0
A51: 4.1 | B51: =pH_SID + pH_NT*(10^-A51)/((10^-A51)+KaN_c) + (10^-A51) - (pH_PT*Ka1p_c*(10^-A51)^2 + 2*pH_PT*Ka1p_c*Ka2p_c*(10^-A51) + 3*pH_PT*Ka1p_c*Ka2p_c*Ka3p_c)/((10^-A51)^3 + Ka1p_c*(10^-A51)^2 + Ka1p_c*Ka2p_c*(10^-A51) + Ka1p_c*Ka2p_c*Ka3p_c) - Ka1c_c*CO2aqc/(10^-A51) - 2*Ka1c_c*Ka2c_c*CO2aqc/(10^-A51)^2 - Kw_c/(10^-A51) -> 0.069751418 | C51: =IF(AND(B51>=0,B52<0),A51+pH_step*B51/(B51-B52),0) -> 0
A52: 4.2 | B52: =pH_SID + pH_NT*(10^-A52)/((10^-A52)+KaN_c) + (10^-A52) - (pH_PT*Ka1p_c*(10^-A52)^2 + 2*pH_PT*Ka1p_c*Ka2p_c*(10^-A52) + 3*pH_PT*Ka1p_c*Ka2p_c*Ka3p_c)/((10^-A52)^3 + Ka1p_c*(10^-A52)^2 + Ka1p_c*Ka2p_c*(10^-A52) + Ka1p_c*Ka2p_c*Ka3p_c) - Ka1c_c*CO2aqc/(10^-A52) - 2*Ka1c_c*Ka2c_c*CO2aqc/(10^-A52)^2 - Kw_c/(10^-A52) -> 0.069543441 | C52: =IF(AND(B52>=0,B53<0),A52+pH_step*B52/(B52-B53),0) -> 0
A53: 4.3 | B53: =pH_SID + pH_NT*(10^-A53)/((10^-A53)+KaN_c) + (10^-A53) - (pH_PT*Ka1p_c*(10^-A53)^2 + 2*pH_PT*Ka1p_c*Ka2p_c*(10^-A53) + 3*pH_PT*Ka1p_c*Ka2p_c*Ka3p_c)/((10^-A53)^3 + Ka1p_c*(10^-A53)^2 + Ka1p_c*Ka2p_c*(10^-A53) + Ka1p_c*Ka2p_c*Ka3p_c) - Ka1c_c*CO2aqc/(10^-A53) - 2*Ka1c_c*Ka2c_c*CO2aqc/(10^-A53)^2 - Kw_c/(10^-A53) -> 0.069326274 | C53: =IF(AND(B53>=0,B54<0),A53+pH_step*B53/(B53-B54),0) -> 0
A54: 4.4 | B54: =pH_SID + pH_NT*(10^-A54)/((10^-A54)+KaN_c) + (10^-A54) - (pH_PT*Ka1p_c*(10^-A54)^2 + 2*pH_PT*Ka1p_c*Ka2p_c*(10^-A54) + 3*pH_PT*Ka1p_c*Ka2p_c*Ka3p_c)/((10^-A54)^3 + Ka1p_c*(10^-A54)^2 + Ka1p_c*Ka2p_c*(10^-A54) + Ka1p_c*Ka2p_c*Ka3p_c) - Ka1c_c*CO2aqc/(10^-A54) - 2*Ka1c_c*Ka2c_c*CO2aqc/(10^-A54)^2 - Kw_c/(10^-A54) -> 0.069088509 | C54: =IF(AND(B54>=0,B55<0),A54+pH_step*B54/(B54-B55),0) -> 0
A55: 4.5 | B55: =pH_SID + pH_NT*(10^-A55)/((10^-A55)+KaN_c) + (10^-A55) - (pH_PT*Ka1p_c*(10^-A55)^2 + 2*pH_PT*Ka1p_c*Ka2p_c*(10^-A55) + 3*pH_PT*Ka1p_c*Ka2p_c*Ka3p_c)/((10^-A55)^3 + Ka1p_c*(10^-A55)^2 + Ka1p_c*Ka2p_c*(10^-A55) + Ka1p_c*Ka2p_c*Ka3p_c) - Ka1c_c*CO2aqc/(10^-A55) - 2*Ka1c_c*Ka2c_c*CO2aqc/(10^-A55)^2 - Kw_c/(10^-A55) -> 0.068817642 | C55: =IF(AND(B55>=0,B56<0),A55+pH_step*B55/(B55-B56),0) -> 0
A56: 4.6 | B56: =pH_SID + pH_NT*(10^-A56)/((10^-A56)+KaN_c) + (10^-A56) - (pH_PT*Ka1p_c*(10^-A56)^2 + 2*pH_PT*Ka1p_c*Ka2p_c*(10^-A56) + 3*pH_PT*Ka1p_c*Ka2p_c*Ka3p_c)/((10^-A56)^3 + Ka1p_c*(10^-A56)^2 + Ka1p_c*Ka2p_c*(10^-A56) + Ka1p_c*Ka2p_c*Ka3p_c) - Ka1c_c*CO2aqc/(10^-A56) - 2*Ka1c_c*Ka2c_c*CO2aqc/(10^-A56)^2 - Kw_c/(10^-A56) -> 0.06849944 | C56: =IF(AND(B56>=0,B57<0),A56+pH_step*B56/(B56-B57),0) -> 0
A57: 4.7 | B57: =pH_SID + pH_NT*(10^-A57)/((10^-A57)+KaN_c) + (10^-A57) - (pH_PT*Ka1p_c*(10^-A57)^2 + 2*pH_PT*Ka1p_c*Ka2p_c*(10^-A57) + 3*pH_PT*Ka1p_c*Ka2p_c*Ka3p_c)/((10^-A57)^3 + Ka1p_c*(10^-A57)^2 + Ka1p_c*Ka2p_c*(10^-A57) + Ka1p_c*Ka2p_c*Ka3p_c) - Ka1c_c*CO2aqc/(10^-A57) - 2*Ka1c_c*Ka2c_c*CO2aqc/(10^-A57)^2 - Kw_c/(10^-A57) -> 0.068117226 | C57: =IF(AND(B57>=0,B58<0),A57+pH_step*B57/(B57-B58),0) -> 0
A58: 4.8 | B58: =pH_SID + pH_NT*(10^-A58)/((10^-A58)+KaN_c) + (10^-A58) - (pH_PT*Ka1p_c*(10^-A58)^2 + 2*pH_PT*Ka1p_c*Ka2p_c*(10^-A58) + 3*pH_PT*Ka1p_c*Ka2p_c*Ka3p_c)/((10^-A58)^3 + Ka1p_c*(10^-A58)^2 + Ka1p_c*Ka2p_c*(10^-A58) + Ka1p_c*Ka2p_c*Ka3p_c) - Ka1c_c*CO2aqc/(10^-A58) - 2*Ka1c_c*Ka2c_c*CO2aqc/(10^-A58)^2 - Kw_c/(10^-A58) -> 0.06765104 | C58: =IF(AND(B58>=0,B59<0),A58+pH_step*B58/(B58-B59),0) -> 0
A59: 4.9 | B59: =pH_SID + pH_NT*(10^-A59)/((10^-A59)+KaN_c) + (10^-A59) - (pH_PT*Ka1p_c*(10^-A59)^2 + 2*pH_PT*Ka1p_c*Ka2p_c*(10^-A59) + 3*pH_PT*Ka1p_c*Ka2p_c*Ka3p_c)/((10^-A59)^3 + Ka1p_c*(10^-A59)^2 + Ka1p_c*Ka2p_c*(10^-A59) + Ka1p_c*Ka2p_c*Ka3p_c) - Ka1c_c*CO2aqc/(10^-A59) - 2*Ka1c_c*Ka2c_c*CO2aqc/(10^-A59)^2 - Kw_c/(10^-A59) -> 0.067076664 | C59: =IF(AND(B59>=0,B60<0),A59+pH_step*B59/(B59-B60),0) -> 0
A60: 5 | B60: =pH_SID + pH_NT*(10^-A60)/((10^-A60)+KaN_c) + (10^-A60) - (pH_PT*Ka1p_c*(10^-A60)^2 + 2*pH_PT*Ka1p_c*Ka2p_c*(10^-A60) + 3*pH_PT*Ka1p_c*Ka2p_c*Ka3p_c)/((10^-A60)^3 + Ka1p_c*(10^-A60)^2 + Ka1p_c*Ka2p_c*(10^-A60) + Ka1p_c*Ka2p_c*Ka3p_c) - Ka1c_c*CO2aqc/(10^-A60) - 2*Ka1c_c*Ka2c_c*CO2aqc/(10^-A60)^2 - Kw_c/(10^-A60) -> 0.066364452 | C60: =IF(AND(B60>=0,B61<0),A60+pH_step*B60/(B60-B61),0) -> 0
A61: 5.1 | B61: =pH_SID + pH_NT*(10^-A61)/((10^-A61)+KaN_c) + (10^-A61) - (pH_PT*Ka1p_c*(10^-A61)^2 + 2*pH_PT*Ka1p_c*Ka2p_c*(10^-A61) + 3*pH_PT*Ka1p_c*Ka2p_c*Ka3p_c)/((10^-A61)^3 + Ka1p_c*(10^-A61)^2 + Ka1p_c*Ka2p_c*(10^-A61) + Ka1p_c*Ka2p_c*Ka3p_c) - Ka1c_c*CO2aqc/(10^-A61) - 2*Ka1c_c*Ka2c_c*CO2aqc/(10^-A61)^2 - Kw_c/(10^-A61) -> 0.065477937 | C61: =IF(AND(B61>=0,B62<0),A61+pH_step*B61/(B61-B62),0) -> 0
... A99: 8.9 | B99: =pH_SID + pH_NT*(10^-A99)/((10^-A99)+KaN_c) + (10^-A99) - (pH_PT*Ka1p_c*(10^-A99)^2 + 2*pH_PT*Ka1p_c*Ka2p_c*(10^-A99) + 3*pH_PT*Ka1p_c*Ka2p_c*Ka3p_c)/((10^-A99)^3 + Ka1p_c*(10^-A99)^2 + Ka1p_c*Ka2p_c*(10^-A99) + Ka1p_c*Ka2p_c*Ka3p_c) - Ka1c_c*CO2aqc/(10^-A99) - 2*Ka1c_c*Ka2c_c*CO2aqc/(10^-A99)^2 - Kw_c/(10^-A99) -> -21.887104 | C99: =IF(AND(B99>=0,B100<0),A99+pH_step*B99/(B99-B100),0) -> 0
A100: 9 | B100: =pH_SID + pH_NT*(10^-A100)/((10^-A100)+KaN_c) + (10^-A100) - (pH_PT*Ka1p_c*(10^-A100)^2 + 2*pH_PT*Ka1p_c*Ka2p_c*(10^-A100) + 3*pH_PT*Ka1p_c*Ka2p_c*Ka3p_c)/((10^-A100)^3 + Ka1p_c*(10^-A100)^2 + Ka1p_c*Ka2p_c*(10^-A100) + Ka1p_c*Ka2p_c*Ka3p_c) - Ka1c_c*CO2aqc/(10^-A100) - 2*Ka1c_c*Ka2c_c*CO2aqc/(10^-A100)^2 - Kw_c/(10^-A100) -> -29.058445 | C100: =0 -> 0
A102: Parameter | B102: Name | C102: Unit | D102: Value | E102: Source / assumption
A103: OPERATING pH (buffered, cycle average) | B103: pH_op | C103: - | D103: =IF(n_cross=1,SUM(C50:C100),NA()) -> 6.3600363 | E103: Root of the charge-balance grid, on the concentration scale. A pH probe reads hydrogen-ion ACTIVITY, so the comparable number is pH_meas (D220) — about 0.11 higher at this ionic strength. Every downstream pH comparison uses pH_meas. | F103: pH at the cycle-average dissolved CO₂ of the schedule in use. The trough just after a CO₂ pulse is lower; a probe with response lag reads near this value, not the trough.
A104: HOCl fraction at operating pH | B104: pH_fHOCl | C104: - | D104: =1/(1+KaHOCl_c/10^-pH_op) -> 0.88465073 | E104: Concentration-scale constant (KaHOCl_c) with the concentration-scale root pH_op, the consistent pair (R1-10); pH_meas (D220) is only for comparison with a probe.
A105: pH-grid crossings (must be exactly 1) | B105: n_cross | C105: - | D105: =SUMPRODUCT((B50:B99>=0)*(B51:B100<0)) -> 1 | E105: Count of +→− sign crossings of the charge residual on the pH grid. Exactly 1 = a single bracketed root inside [4,9]. 0 (root outside the grid) or >1 (non-monotone) must NOT be read as pH 0.
A106: ANODIC BLEACHING (free-chlorine evolution; conservative FE=1) | G106: HOCl-tolerance evidence (Comments)
A107: Naïve FE=1 production ceiling (NOT operative) | B107: bleach_rate | C107: mg/L/h | D107: =Iappc/(2*Fcc)*M_HOCl*3600/VLc -> 371.24491 | E107: =IF(P_HOCl>0,"Naive FE=1 ceiling; overstates operative production by "&TEXT(bleach_rate/(P_HOCl*M_HOCl*3600),"0")&" times","No chlorine production at the selected chloride inventory") -> No chlorine production at the selected chloride inventory | G107: Threshold seed 0.2 mg/L free chlorine = conservative FIRST-IMPAIRMENT floor for suspended gram-negative environmental bacteria; deliberately below water-industry disinfection doses. Tiers: 0.02-0.1 no inhibition; 0.2 first-impairment (pick); 0.3-0.6 measurable die-off; 0.75-1.75 complete regrowth inhibition.
A108: Time to ~1 ppm HOCl (FE=1) | B108: bleach_t1ppm | C108: min | D108: =1/(bleach_rate)*60 -> 0.16161838 | E108: ~1 mg/L HOCl ≈ bactericidal threshold | G108: C. necator: no direct HOCl MIC; genus-mate C. metallidurans is documented chlorine/chloramine-TOLERANT (Gomez-Alvarez/Wang 2018, STOTEN). 0.2 mg/L is a safety UNDERestimate, not its breaking point — do not assume necator is chlorine-fragile.
A109: Bleaching / hypochlorite flag | B109: bleach_flag | C109: - | D109: =IF(C_eff_Cl2<Cl_onset,"negligible free chlorine ("&TEXT(C_eff_Cl2,"0.00")&" mg/L as Cl₂ < onset); does NOT account for the Exp-2 death - see metal_flag",IF(C_eff_Cl2<Cl_kill,"sub-lethal "&TEXT(C_eff_Cl2,"0.00")&" mg/L as Cl₂ (band "&TEXT(C_eff_lo_Cl2,"0.00")&"-"&TEXT(C_eff_hi_Cl2,"0.00")&"); chloride-pool-bounded, cannot reach the kill threshold in this medium; does NOT explain the death - see metal_flag","SEVERE free chlorine: "&TEXT(C_eff_Cl2,"0.0")&" mg/L as Cl₂ - biofilm/electrode damage (Baek 2021)")) -> negligible free chlorine (0.00 mg/L as Cl₂ < onset); does NOT account for the Exp-2 death - see metal_flag | E109: Operative flag: effective biocidal chlorine (C_eff, D145) vs the sub-lethal onset (D146) and kill (D147). Graded — MILD for trace-chloride UdG, SEVERE only at high chloride/current. | G109: Hydrogenophaga: dominant chlorine/chloramine-RESISTANT genus in chloraminated distribution systems; survives >0.5 mg/L. Treat as resistant; 0.2 mg/L is a floor, not an observed inhibition point.
A110: pH band flag (HOB optimum 6.5–7.5) | B110: pH_band_flag | C110: - | D110: =IF(pH_meas<pH_band_lo,"pH BELOW HOB optimum (<"&TEXT(pH_band_lo,"0.0")&") — reduce the CO₂ dose or lengthen the interval",IF(pH_meas>pH_band_hi,"pH above optimum (>"&TEXT(pH_band_hi,"0.0")&")","pH in HOB band "&TEXT(pH_band_lo,"0.0")&"–"&TEXT(pH_band_hi,"0.0"))) -> pH BELOW HOB optimum (<6.5) — reduce the CO₂ dose or lengthen the interval | E110: HOB optimum 6.5–7.5 (Pous / Rovira-Alsina), compared against the activity-scale pH a probe would read. A short oxygen-driven sparge interval delivers far more CO₂ than the carbon demand, so this flag is the counterweight to the DO-limited interval on Mass Transfer. | G110: Xanthobacter: no species value found in literature (genuine gap — not invented); use the 0.2 mg/L gram-negative fallback. CONSERVATIVE-FLOOR CAVEAT: the 0.2 seed is a safety floor; real impairment for these resistant genera is likely higher (mid-tenths to >1 mg/L). necator/Xanthobacter rows are inferred, not measured.
A112: MEDIA LOOKUP (selector source)
A113: Media | B113: buffer | C113: buffer conc mM | D113: notes | E113: source
A114: MC02 | B114: phosphate | C114: =PT_mc02*1000 -> 40.007196 | D114: low-chloride, organic-free | E114: Media/README.md (MC02); per Sydow 2017 SI
A115: UdG phosphate | B115: phosphate | C115: =PT_udg*1000 -> 37.329367 | D115: low-chloride (trace Cl⁻); N varies urea/(NH₄)₂SO₄/NH₄Cl | E115: Pous 2022 & 2023; Rovira-Alsina 2025
A116: AMYBO03 | B116: phosphate | C116: =AMYBO03!PT_AMYBO03*1000 -> 60.00653 | D116: Teo final, carbon-free; full recipe on AMYBO03 | E116: Teo Reid MRes thesis, Table 2, PDF p.10
A125: Naïve FE=1 ceiling: all chloride → free chlorine (NOT operative) | B125: HOCl_max | C125: mg/L | D125: =pH_Cl*pH_fHOCl*M_HOCl -> 0 | E125: Naïve FE=1 ceiling: the whole chloride inventory converted to free chlorine, times the HOCl fraction at the operating pH. Superseded by the steady free chlorine HOCl_ss (D139); it ignores both the chloride mass-transport cap and the ammonium demand.
A127: FREE-CHLORINE PENALTY MODEL (graded, kinetic — operative; supersedes the naïve FE=1 ceiling above)
A128: Max active-Cl evolution efficiency (high-Cl plateau) | B128: FE_CER | C128: - | D128: 0.5 | E128: Active-chlorine current efficiency on the high-chloride plateau (approaches ~1 above ~50 mM Cl⁻; Vos & Koper, JACS 140:10270 / JEAC 819:260). 0.5 is a mid-plateau value and is NOT the operative limit here — at trace Cl⁻ the chloride mass-transport limit (D132) binds.
A129: Cl⁻ mass-transfer coefficient | B129: km_Cl | C129: cm/s | D129: =km_O2_c*(D_Cl/D_O2_c)^km_exp_c -> 0.0037463983 | E129: Scaled from the electrode O₂ mass-transfer coefficient by (D_Cl/D_O2)^0.644, the same correlation as km_HPO4/km_HCO3 (rows 275–276), so it follows a measured km_O2.
A130: Anode wetted area | B130: A_anode | C130: cm² | D130: =Electrochemistry!A_anode_wet -> 1.7306351 | E130: Computed from the shape-aware wetted area (Electrochemistry A_anode_wet); tracks reactor & electrode.
A131: Cl₂ current — efficiency-limited | B131: I_Cl_FE | C131: A | D131: =Iappc*FE_CER -> 0.002845 | E131: Applied anode current × plateau efficiency.
A132: Cl₂ current — chloride mass-transport limit | B132: I_Cl_mt | C132: A | D132: =n_e_Cl*Fcc*km_Cl*(pH_Cl*Cl_free_frac/1000)*A_anode -> 0 | E132: i_lim = n_e_Cl·F·k_m·[Cl⁻]·A with n_e_Cl = 2 per NET chloride consumed: Cl₂ hydrolysis (k ≈ 11–22 s⁻¹) is faster than diffusion across the layer (δ²/D ≈ 0.8 s), so the chloride it regenerates is re-oxidised at the surface (the direct route Cl⁻ + H₂O → HOCl + H⁺ + 2e⁻ gives the same). [Cl⁻] in mol/cm³ = pH_Cl/1000. At the anode potential (D256, above the HOCl/Cl⁻ couple) this transport limit is the central estimate, not a cap; the factor 2 rests on where hydrolysis happens.
A133: Realistic chlorine current (binding limit) | B133: I_Cl | C133: A | D133: =MIN(I_Cl_FE,I_Cl_mt) -> 0 | E133: Smaller of efficiency- and mass-transport-limited.
A134: Volumetric free-chlorine production | B134: P_HOCl | C134: mol/L/s | D134: =I_Cl/(n_e_Cl*Fcc*VLc) -> 0 | E134: P_HOCl = I_Cl/(n_e_Cl·F·V), n_e_Cl = 2 on every route (D148); at the transport limit this is k_m·[Cl⁻]·A/V, one HOCl per arriving chloride.
A135: Medium ammonium (as N) | B135: NH3_N | C135: mg/L | D135: =pH_NT*MW_N -> 199.91828 | E135: Active-medium total ammonium × 14.007 g/mol N.
A136: Monochloramine formation rate constant | B136: k1_NH2Cl | C136: M⁻¹s⁻¹ | D136: 4200000 | E136: HOCl + NH₃ → NH₂Cl, k₁ = 4.2e6 M⁻¹s⁻¹ (Morris & Isaac 1983; Jafvert & Valentine 1992, ES&T 26:577, DOI 10.1021/es00027a022). Fast but NOT instantaneous.
A137: Ammonium pKa (NH₄⁺/NH₃) | B137: pKa_NH4 | C137: - | D137: =-LOG10(Ka_NH4) -> 9.1009783 | E137: From the van ʼt Hoff-corrected Ka_NH4 (D18) so the sheet cannot hold two different ammonium pKa values at once. Only free NH₃ reacts with HOCl; at pH 7 about 0.6% of the ammonium pool is free NH₃, so the sink is finite and a steady residual coexists.
A138: Free ammonia | B138: NH3_free | C138: mol/L | D138: =pH_NT/(1+10^(pKa_NH4-pH_op)) -> 2.5868872e-05 | E138: NH₃ = NH₄_tot/(1+10^(pKa_NH4−pH)). The reactive fraction that scavenges HOCl.
A139: Steady bulk free HOCl | B139: HOCl_ss | C139: mol/L | D139: =P_HOCl/(k1_NH2Cl*NH3_free) -> 0 | E139: [HOCl]_ss = production/(k₁·NH₃_free). Non-zero by construction; rises with current, falls with ammonium/pH.
A140: Steady bulk free HOCl (mass) | B140: HOCl_ss_mgL | C140: mg/L | D140: =HOCl_ss*M_HOCl -> 0 | E140: Bulk free chlorine, mg/L. Small for UdG — below the impairment onset, so no bulk sterilisation (UdG runs for days).
A141: Anode boundary-layer enrichment | B141: f_local | C141: - | D141: 10 | E141: Local HOCl at the anode is higher than bulk before it diffuses out and meets ammonia (boundary-layer time ~0.1–10 s ≫ ms bulk scavenging). f_local ≥ 1; sub-mM value unmeasured — SENSITIVITY parameter.
A142: Monochloramine effective residence | B142: tau_NH2Cl | C142: h | D142: =IF(ISNUMBER(cal_tau_NH2Cl),cal_tau_NH2Cl,tau_NH2Cl_default) -> 1 | E142: The measured lifetime from the Calibrations tab (monochloramine section: DPD combined chlorine at plateau ÷ production rate) when one is included for this reactor and medium; otherwise tau_NH2Cl_default (D314). SENSITIVITY parameter: the fixed τ band (D150–D155, 1 min to 5 h) is shown beside it.
A143: Steady combined chlorine (monochloramine) | B143: NH2Cl_mgL | C143: mg/L | D143: =Cl_bound*M_HOCl -> 0 | E143: Steady combined chlorine from D311, on HOCl-equivalent mass basis; both the chloride transport/recycling limit and the actual current limit apply.
A144: Monochloramine potency divisor | B144: R_chloramine | C144: - | D144: 25 | E144: Monochloramine is ~18–70× less biocidal than free chlorine (EPA SWTR ~18×, Giardia; IWA 2008 ~70×, E. coli). 25 = conservative (kinder-to-chloramine).
A145: EFFECTIVE biocidal chlorine load | B145: C_eff | C145: mg/L | D145: =f_local*HOCl_ss_mgL+NH2Cl_mgL/R_chloramine -> 0 | E145: OPERATIVE bleaching value (HOCl basis): local-weighted free HOCl + combined chlorine ÷ potency. Combined chlorine is the recycling steady state (D143), so it rises with current and residence until it approaches the chloride pool (D149); Summary reports it as Cl₂ (D226).
A146: Free-chlorine impairment onset (sub-lethal) | B146: Cl_onset | C146: mg/L | D146: 0.1 | E146: Growth measurably slowed above ~0.1 mg/L free-Cl-equiv (graded, gram-negative proxy; Murray 2017 Ecotox 26:1115; HOCl oxidative-stress onset). Distinct from kill.
A147: Free-chlorine kill threshold | B147: Cl_kill | C147: mg/L | D147: 2 | E147: ~1–5 mg/L for tolerant gram-negatives; 2 used. Above C_eff this → biofilm/electrode damage (Baek 2021, CEJ 405:126742).
A148: electrons per produced HOCl | B148: n_e_Cl | C148: e-/HOCl | D148: =2 -> 2 | E148: Electrons per HOCl formed and per net chloride consumed — 2 on every route. 2Cl⁻ → Cl₂ + 2e⁻ then Cl₂ + H₂O → HOCl + H⁺ + Cl⁻ is 2 e⁻ per HOCl and 1 net chloride, because the regenerated chloride is re-oxidised inside the diffusion layer; the direct route Cl⁻ + H₂O → HOCl + H⁺ + 2e⁻ is also 2. Used both in the transport-limited current (D132) and in the production rate (D134).
A149: chloride-pool ceiling on chlorine | B149: Cl_pool_mgL | C149: mg/L | D149: =pH_Cl*M_HOCl -> 0 | E149: Total chloride pool as HOCl-equivalent; free + combined chlorine cannot exceed it at any instant, and the steady combined share is kτ/(1+kτ) of it (D143). UdG chloride is CaCl₂-derived (a closed batch also depletes it).
A150: monochloramine residence (low) | B150: tau_NH2Cl_lo | C150: h | D150: 0.016666667 | E150: Low bound of monochloramine residence (~1 min); weak estimate, swept for the C_eff band
A151: monochloramine residence (high) | B151: tau_NH2Cl_hi | C151: h | D151: 5 | E151: High bound of monochloramine residence (5 h); weak estimate, swept for the C_eff band
A152: chloramine potency divisor (low) | B152: R_chloramine_lo | C152: x | D152: 18 | E152: Most-potent end of the monochloramine potency-divisor band (defensible)
A153: chloramine potency divisor (high) | B153: R_chloramine_hi | C153: x | D153: 70 | E153: Least-potent end of the monochloramine potency-divisor band
...

Sheet Biology
A1: BIOLOGY
A2: Parameter | B2: Name | C2: Unit | D2: Value | E2: Source / assumption
A3: IMPORTS (from other tabs)
A4: (import) H₂ generation rate | B4: rH2_gen | C4: mol/h | D4: =Electrochemistry!rH2_gen -> 0.00010233412 | E4: =HYPERLINK("#Electrochemistry!D21","→ Electrochemistry") -> → Electrochemistry
A5: (import) Net O₂ to dissolved pool | B5: O2_net_gen | C5: mol/h | D5: =Electrochemistry!O2_net_gen -> 5.1027984e-05 | E5: =HYPERLINK("#Electrochemistry!D29","→ Electrochemistry") -> → Electrochemistry
A6: (import) LIQUID VOLUME TO CHARGE | B6: V_charge | C6: mL | D6: =Geometry!V_charge -> 15 | E6: =HYPERLINK("#Geometry!D41","→ Geometry") -> → Geometry
A7: (import) HOB organism | B7: organism_sel | D7: =Summary!organism_sel -> Xanthobacter tagetidis | E7: =HYPERLINK("#Summary!D4","→ Summary") -> → Summary
A10: Gas requirement ratio - H₂ | B10: bio_H2 | C10: - | D10: =IF(ISNUMBER(cal_knall_H2),cal_knall_H2,knall_H2_default) -> 6 | E10: H₂:O₂:CO₂ UPTAKE ratio (not feed; phase-dependent, Lu & Yu 2019). Knallgas caps O₂:H₂≤0.5; growth gives O₂:H₂≈0.29–0.35, CO₂:H₂≈0.15–0.19. 6:2:1 = mid-range central. Feed optimum 7:2:1 (Ishizaki 2001). Can't measure pre-growth.
A11: Gas requirement ratio - O₂ | B11: bio_O2 | C11: - | D11: =IF(ISNUMBER(cal_knall_O2),cal_knall_O2,knall_O2_default) -> 2 | E11: O₂:H₂ uptake, range 0.29–0.35 (×6 → 1.75–2.1). 2 = central; 1.8 (lean) is growth-protective.
A12: Gas requirement ratio - CO₂ | B12: bio_CO2 | C12: - | D12: =IF(ISNUMBER(cal_knall_CO2),cal_knall_CO2,knall_CO2_default) -> 1 | E12: CO₂:H₂ uptake, range 0.15–0.19 (×6 → 0.9–1.15). 1 = central. Supply ≫ demand → non-limiting.
A13: H₂ consumed | B13: H2_cons | C13: mol/h | D13: =MAX(0,rH2_gen-H2_HOR_b) -> 0.00010233412 | E13: Evolved H₂ minus any crossed-over H₂ the Pt anode oxidises (D96; 0 until measured), assumed fully consumed — steady growth only; ~0 during lag (see §13).
A14: O₂ consumed | B14: O2_cons | C14: mol/h | D14: =H2_cons*bio_O2/bio_H2 -> 3.4111374e-05 | E14: Assumes 100% H₂ uptake (upper bound); true limit is gas-liquid H₂ transfer — see H2_turnover
A15: CO₂ consumed (carbon fixation) | B15: CO2_cons | C15: mol/h | D15: =H2_cons*bio_CO2/bio_H2 -> 1.7055687e-05 | E15: H₂ consumed x (CO₂/H₂ ratio).
A16: EXCESS O₂ to remove | B16: O2_excess | C16: mol/h | D16: =MAX(0,O2_net_gen-O2_cons) -> 1.691661e-05 | E16: =IFERROR(("Net electrolytic O₂ minus biological uptake, floored at zero. The floor matters: at the knallgas cap (O₂:H₂ = 0.5, i.e. bio_O2 = 3) uptake exactly consumes the electrolytic surplus and everything "&"downstream that divides by this would blow up. A LOWER bound on the surplus: full H₂ uptake maximises respiration, so any H₂ that bubbles off uncaught raises the surplus (half uptake → ×")&TEXT((O2_net_gen-O2_cons/2)/O2_excess,"0.0")&"). Sensitive: each 1 % on bio_O2 moves it "&TEXT(O2_cons/O2_excess,"0.0")&" % the other way (linear, so symmetric).","Net electrolytic O₂ minus biological uptake, floored at zero: uptake consumes the whole surplus at these ratios.") -> Net electrolytic O₂ minus biological uptake, floored at zero. The floor matters: at the knallgas cap (O₂:H₂ = 0.5, i.e. bio_O2 = 3) uptake exactly consumes the electrolytic surplus and everything downstream that divides by this would blow up. A LOWER bound on the surplus: full H₂ uptake maximises respiration, so any H₂ that bubbles off uncaught raises the surplus (half uptake → ×2.0). Sensitive: each 1 % on bio_O2 moves it 2.0 % the other way (linear, so symmetric).
A17: Temperature | B17: T_C | C17: °C | D17: =Summary!temp_C -> 30 | E17: C. necator optimum ~30 °C. Input.
A18: Temperature (absolute) | B18: T_K | C18: K | D18: =T_C+T_zero_C -> 303.15 | E18: °C + 273.15.
A19: Surface pressure | B19: P_atm | C19: Pa | D19: =IF(P_atm_set>0,P_atm_set,Pa_per_atm) -> 101325 | E19: Atmospheric at the liquid surface (assumed).
A20: Standard atmosphere (atm->Pa) | B20: Pa_per_atm | C20: Pa/atm | D20: 101325 | E20: Defined: 1 atm = 101 325 Pa exactly.
A21: Henry solubility O₂ (ref, 298.15 K) | B21: H_O2ref | C21: mol/m³/Pa | D21: 1.2e-05 | E21: Sander (2023) recommended H^cp O2; reproduces ~7.5 mg/L air-saturation at 30 degC
A22: Henry T-dependence O₂ | B22: H_O2T | C22: K | D22: 1500 | E22: Sander (2023): d ln(Hcp)/d(1/T).
A23: Reference temperature | B23: T_ref | C23: K | D23: 298.15 | E23: Standard reference for Henry constants.
A24: Henry solubility O₂ at T | B24: H_O2_T | C24: mol/m³/Pa | D24: =H_O2ref*EXP(H_O2T*(1/T_K-1/T_ref))*f_salt_O2 -> 1.0354236e-05 | E24: van 't Hoff correction to reactor T, then salted out for the medium's ionic strength (f_salt_O2, D123). Moves the dissolved-O₂ ceiling (D27) and every Henry O₂ term.
A25: O₂ growth-inhibition ceiling (gas) | B25: O2_ceil_atm | C25: atm | D25: 0.3 | E25: Whole-cell growth inhibited above ~0.30 atm O₂ (Amer & Kim 2023); the [NiFe] hydrogenase itself is O₂-tolerant.
A26: O₂ ceiling (partial pressure) | B26: O2_ceil_Pa | C26: Pa | D26: =O2_ceil_atm*Pa_per_atm -> 30397.5 | E26: Ceiling in Pa.
A27: Dissolved-O₂ ceiling | B27: O2_ceil_C | C27: mol/m³ | D27: =H_O2_T*O2_ceil_Pa -> 0.3147429 | E27: Henry's law at the gas ceiling.
A28: Dissolved-O₂ ceiling | B28: O2_ceil_uM | C28: µM | D28: =O2_ceil_C*1000 -> 314.7429 | E28: mol/m³ = mM; ×1000 = µM. Aim: minimise dissolved O₂; floor set by O₂-removal capacity (§11).
A29: Henry solubility CO₂ (ref, 298.15 K) | B29: H_CO2ref | C29: mol/m³/Pa | D29: 0.00033 | E29: Sander (2023) compilation; CO₂ ~28× more soluble than O₂ (vs the 1.2e-5 O₂ Hcp).
A30: Henry T-dependence CO₂ | B30: H_CO2T | C30: K | D30: 2400 | E30: Sander (2023): d ln(Hcp)/d(1/T) for CO₂.
A31: Henry solubility CO₂ at T | B31: H_CO2_T | C31: mol/m³/Pa | D31: =H_CO2ref*EXP(H_CO2T*(1/T_K-1/T_ref)) -> 0.00028897092 | E31: van 't Hoff to reactor T.
A32: (import) CO₂ partial pressure at sparge (dry-gas basis) | B32: p_CO2_sparge | C32: Pa | D32: ='Mass Transfer'!P_dry -> 97088.35 | E32: Import from Mass Transfer!D418 (P_dry): a pure-CO₂ pulse in a water-saturated headspace carries p_CO₂ = P_atm − p_sat_w, the basis of Mass Transfer D145.
A33: Dissolved CO₂ (during sparge) | B33: CO2_diss | C33: mol/m³ | D33: =H_CO2_T*p_CO2_sparge -> 28.055709 | E33: Equilibrium dissolved CO₂ under a pure-CO₂ headspace on the dry-gas basis (= Mass Transfer C_sat_CO2, D145; mol/m³ = mM). Legacy upper bound: a sub-second pulse never reaches it.
A34: RuBisCO Km for CO₂ | B34: Km_CO2 | C34: µM | D34: 50 | E34: RuBisCO Km(CO₂) ~ order 50 µM. Coarse — confirm.
A35: Carbon margin (dissolved CO₂ : Km) | B35: CO2_carbon_margin | C35: × | D35: =CO2_diss*1000/Km_CO2 -> 561.11419 | E35: Dissolved CO₂ at full dry-basis saturation : RuBisCO Km. Legacy upper bound, superseded by the cycle-trough margin D98 (Summary D76).
A36: Carbonic-acid Ka1 (apparent) | B36: Ka1_carb | C36: mol/L | D36: 4.45e-07 | E36: CO₂(aq)+H₂O ⇌ H⁺+HCO₃⁻, pKa1 6.35 (25 °C).
A37: pH — UNBUFFERED worst case | B37: pH_CO2_unbuf | C37: - | D37: =-LOG10(SQRT(Ka1_carb*(CO2_diss/1000))) -> 3.9518094 | E37: Unbuffered worst case (pure water + CO₂) — lower bound only; the Sydow phosphate medium holds pH near setpoint.
A38: Henry solubility H₂ (ref, 298.15 K) | B38: H_H2ref | C38: mol/m³/Pa | D38: 7.8e-06 | E38: Sander (2023). H₂ ~1.5× less soluble than O₂ (vs the 1.2e-5 O₂ Hcp).
A39: Henry T-dependence H₂ | B39: H_H2T | C39: K | D39: 500 | E39: Sander (2023): d ln(Hcp)/d(1/T) for H₂ (weak T-dependence).
A40: Henry solubility H₂ at T | B40: H_H2_T | C40: mol/m³/Pa | D40: =H_H2ref*EXP(H_H2T*(1/T_K-1/T_ref)) -> 7.5872107e-06 | E40: van 't Hoff to reactor T.
A41: Dissolved-H₂ saturation (1 atm) | B41: C_H2_sat | C41: mol/m³ | D41: =H_H2_T*P_atm -> 0.76877412 | E41: Max dissolved H₂ at 1 atm — the cells' H₂ ceiling.
A42: Time to saturate dissolved H₂ (LAG) | B42: t_H2_sat | C42: min | D42: =C_H2_sat*(V_charge/1000000)/rH2_gen*60 -> 6.7611535 | E42: Lag: dissolved H₂ saturates this fast unconsumed, then bubbles off (lost + explosive headspace). Mirrors the O₂ lag timescale.
A43: H₂ pool turnovers per hour | B43: H2_turnover | C43: 1/h | D43: =rH2_gen/(V_charge/1000000)/C_H2_sat -> 8.8742254 | E43: H₂ evolved ÷ saturable pool. ≫1 → cells must consume in near-real-time or it escapes.
A44: H₂ headspace flammability verdict | B44: H2_safety | C44: - | D44: =IF(AND(y_H2_end_b>=H2_LFL,y_O2_end_b>=O2_LOC_H2*LOC_margin),"POTENTIAL FLAMMABILITY (lag screen): H₂ "&TEXT(y_H2_hs_lag,"0%")&" mean, "&TEXT(y_H2_end_b,"0%")&" before each pulse; O₂ "&TEXT(y_O2_hs_lag,"0%")&" mean, "&TEXT(y_O2_end_b,"0%")&" before each pulse – until uptake starts, "&IF(MAX(0,CEILING(spg_int_H2safe_saw,remedy_res)-remedy_res)*60>spg_dur_opt_b,"sparge every ≤"&TEXT(MAX(0,CEILING(spg_int_H2safe_saw,remedy_res)-remedy_res),"0.0")&" min or ","interval remedy unavailable; ")&"sweep ≥"&TEXT(FLOOR(N2_sweep_H2safe,remedy_res)+remedy_res,"0.0")&" mL/min N₂; vent to a hood; no ignition sources","Below nominal H₂/O₂ screening thresholds (lag; not safety certification): H₂ "&TEXT(y_H2_end_b,"0%")&", O₂ "&TEXT(y_O2_end_b,"0%")&" before each pulse ("&TEXT(y_H2_hs_lag,"0%")&" / "&TEXT(y_O2_hs_lag,"0%")&" mean)") -> POTENTIAL FLAMMABILITY (lag screen): H₂ 9% mean, 15% before each pulse; O₂ 5% mean, 8% before each pulse – until uptake starts, sparge every ≤2.3 min or sweep ≥1.0 mL/min N₂; vent to a hood; no ignition sources | E44: Conservative screen using nominal air LFL and diluted-mixture LOC with an assumed margin, not a validated H2/O2/CO2/N2 flammability envelope. Below threshold is not safety certification. Validate mixture limits and the actual vent/sweep before unattended use. | F44: Hazard verdict (lag-phase headspace flammability), not a data gap.
A45: Minimum DO (organism) | B45: DO_min | C45: mg/L | D45: =IF(ISNUMBER(cal_DO_min),cal_DO_min,IF(ISNUMBER(VLOOKUP(organism_sel,tbl_organism,MATCH("minimum DO",tbl_organism_hdr,0),FALSE)),VLOOKUP(organism_sel,tbl_organism,MATCH("minimum DO",tbl_organism_hdr,0),FALSE),NA())) -> #N/A | E45: The Calibrations DO section if a value is included for this organism, otherwise the HOB lookup (row 52 on, column "minimum DO"); #N/A = a data gap, to be measured (Summary row 113).
A46: Optimum DO (organism) | B46: DO_opt | C46: mg/L | D46: =IF(ISNUMBER(cal_DO_opt),cal_DO_opt,IF(ISNUMBER(VLOOKUP(organism_sel,tbl_organism,MATCH("optimum DO",tbl_organism_hdr,0),FALSE)),VLOOKUP(organism_sel,tbl_organism,MATCH("optimum DO",tbl_organism_hdr,0),FALSE),NA())) -> #N/A | E46: The Calibrations DO section if a value is included for this organism, otherwise the HOB lookup (row 52 on, column "optimum DO"); #N/A = a data gap, to be measured (Summary row 113).
A47: Impairment DO (organism) | B47: DO_impair | C47: mg/L | D47: =IF(ISNUMBER(cal_DO_impair),cal_DO_impair,IF(ISNUMBER(VLOOKUP(organism_sel,tbl_organism,MATCH("impairment DO",tbl_organism_hdr,0),FALSE)),VLOOKUP(organism_sel,tbl_organism,MATCH("impairment DO",tbl_organism_hdr,0),FALSE),NA())) -> #N/A | E47: The Calibrations DO section if a value is included for this organism, otherwise the HOB lookup (row 52 on, column "impairment DO"); #N/A = a data gap, to be measured (Summary row 113).
A48: Toxic/inhibition DO (organism) | B48: DO_toxic | C48: mg/L | D48: =IF(ISNUMBER(cal_DO_toxic),cal_DO_toxic,IF(ISNUMBER(VLOOKUP(organism_sel,tbl_organism,MATCH("toxic DO",tbl_organism_hdr,0),FALSE)),VLOOKUP(organism_sel,tbl_organism,MATCH("toxic DO",tbl_organism_hdr,0),FALSE),NA())) -> #N/A | E48: The Calibrations DO section if a value is included for this organism, otherwise the HOB lookup (row 52 on, column "toxic DO"); #N/A = a data gap, to be measured (Summary row 113).
A50: HOB LOOKUP (dissolved O₂ thresholds, mg/L)
A51: Organism | B51: minimum DO | C51: optimum DO | D51: impairment DO | E51: toxic DO | F51: source
A52: Cupriavidus necator | B52: ? | C52: 2.6 | D52: 3 | E52: 11.5 | F52: 11.5 = Wilde & Schlegel 1982 inhibition datum (the model computes its ceiling via Henry, ~10.7 mg/L at 30 °C). Optimum 2.6 and impairment 3.0 are provisional working values, not sourced measurements (protocols/dissolved-oxygen.md: optimum low, impairment not established).
A53: Xanthobacter autotrophicus | B53: ? | C53: ? | D53: ? | E53: 11.5 | F53: Wilde & Schlegel 1982 (~0.30 atm)
A54: Xanthobacter flavus | B54: ? | C54: ? | D54: ? | E54: ? | F54: no species data — assume genus ~11.5
A55: Xanthobacter tagetidis | B55: ? | C55: ? | D55: ? | E55: ? | F55: no species data — assume genus ~11.5
A56: Cupriavidus metallidurans | B56: ? | C56: ? | D56: ? | E56: ? | F56: no species data — assume genus ~11.5
A57: UdG (mixed) | B57: ? | C57: ? | D57: ? | E57: ? | F57: Rovira-Alsina 2025; Pous 2022/23
A59: TARGET DISSOLVED-OXYGEN FRACTION (one definition, used by every guard)
A60: Target DO fraction (optimum ÷ inhibition ceiling) | B60: DO_frac_target | C60: - | D60: =IF(ISNA(MATCH(organism_sel,OrganismList,0)),NA(),IF(AND(ISNUMBER(DO_opt),ISNUMBER(DO_toxic)),DO_opt/DO_toxic,DO_frac_fallback)) -> 0.22608696 | E60: Hold dissolved O₂ at or below this fraction of the inhibition ceiling. Taken from the selected organism's own measured band when there is one; otherwise the fallback below.
A61: fallback when the organism band is unmeasured | B61: DO_frac_fallback | C61: - | D61: 0.22608696 | E61: Provisional: C. necator optimum 2.6 ÷ inhibition 11.5 mg/L (row 52); the optimum is a working value, not a sourced measurement, so this stand-in for every unmeasured organism is a weak estimate until the DO-band experiment (Summary row 113).
A62: NAMED DEFAULTS, CONSTANTS AND IMPORTS
A63: Default H₂ uptake ratio (no calibration) | B63: knall_H2_default | C63: - | D63: 6 | E63: Used when no Calibrations knallgas run is included. 6:2:1 = mid-range central uptake ratio (Lu & Yu 2019; feed optimum 7:2:1, Ishizaki 2001).
A64: Default O₂ uptake ratio (no calibration) | B64: knall_O2_default | C64: - | D64: 2 | E64: As above: O₂:H₂ uptake 0.29–0.35 (×6 → 1.75–2.1), 2 = central.
A65: Default CO₂ uptake ratio (no calibration) | B65: knall_CO2_default | C65: - | D65: 1 | E65: As above: CO₂:H₂ uptake 0.15–0.19 (×6 → 0.9–1.15), 1 = central.
A66: Celsius-to-kelvin offset | B66: T_zero_C | C66: K | D66: 273.15 | E66: Defined (SI): 0 °C = 273.15 K exactly.
A67: (import) Ambient pressure setpoint | B67: P_atm_set | C67: Pa | D67: =Summary!P_atm_set -> 0 | E67: Import from Summary!D10 (blank reads as 0, so P_atm falls back to Pa_per_atm).
A75: HEADSPACE FLAMMABILITY (lag phase: electrolysis running, no H₂ uptake yet)
A76: (import) average CO₂ supply rate | B76: CO2_supply_b | C76: mol/h | D76: ='Mass Transfer'!CO2_supply -> 0.00084957368 | E76: Import from Mass Transfer!D100 (schedule in use).
A77: (import) CO₂ rate while the valve is open | B77: CO2_rate_full_b | C77: mol/h | D77: ='Mass Transfer'!CO2_rate_full -> 0.48191627 | E77: Import from Mass Transfer!D178.
A78: (import) optimal pulse, full-flow equivalent | B78: spg_dur_b | C78: s | D78: ='Mass Transfer'!spg_dur_eq_opt -> 0.78451305 | E78: Import from Mass Transfer!D409 (spg_dur_eq_opt): converts the H₂-safe duty to an interval on the same basis as the schedule.
A79: (import) ideal gas constant | B79: R_gas_b | C79: J/(mol·K) | D79: ='Mass Transfer'!R_gas -> 8.3144626 | E79: Import from Mass Transfer!D101.
A80: H₂ lower flammability limit | B80: H2_LFL | C80: - | D80: 0.04 | E80: 4.0 vol% in air or O₂ (Coward & Jones 1952; Zabetakis 1965, USBM Bulletin 627).
A81: Limiting O₂ concentration for H₂, CO₂ diluent | B81: O2_LOC_H2 | C81: - | D81: 0.052 | E81: About 5.2 vol% O₂ with CO₂ as diluent (5.0 % with N₂): Zabetakis 1965; NFPA 69 annex table.
A82: Design margin on the LOC | B82: LOC_margin | C82: - | D82: 0.6 | E82: NFPA 69: hold O₂ at or below 60 % of the LOC when it is not monitored continuously (check the edition in force).
A83: Gas evolved into the headspace (lag) | B83: n_flamm_src | C83: mol/h | D83: =H2_src_l_b+O2_src_l_b -> 0.00014515879 | E83: Lag phase: no uptake, so all electrolytic H₂ not oxidised at the anode (H2_src_l_b) and the net O₂ (O2_src_l_b, cathodic loss at the lag DO) reach the headspace.
A84: Headspace H₂ fraction (lag, mean-field) | B84: y_H2_hs_lag | C84: - | D84: =H2_src_l_b/(n_flamm_src+CO2_supply_b+F_dil_b) -> 0.093870759 | E84: Mean-field balance shared with Mass Transfer §300 (= y_H2_mf_l there): H₂ (net of anodic oxidation) over all gas leaving the headspace — evolved gas, CO₂ pulses and, in the "Open vent" and "Air exchange" vent models, the air drawn in. The pulse-to-pulse sawtooth peaks higher (y_H2_end_b, quoted in D44).
A85: Headspace O₂ fraction (lag, mean-field) | B85: y_O2_hs_lag | C85: - | D85: =(O2_src_l_b+y_O2_air_b*F_vent_ex_b)/(n_flamm_src+CO2_supply_b+F_dil_b) -> 0.054287788 | E85: As above for O₂ (= y_O2_mf_l on Mass Transfer), including the O₂ carried in by exchanged air. Air ingress lowers H₂ but raises O₂ toward 21 %, so it does not make the mixture safe.
A86: CO₂ duty that makes the lag headspace non-flammable | B86: duty_H2safe | C86: - | D86: =MAX(0,MIN(H2_src_l_b/H2_LFL-n_flamm_src-F_dil_b,(O2_src_l_b+y_O2_air_b*F_vent_ex_b)/(O2_LOC_H2*LOC_margin)-n_flamm_src-F_dil_b))/CO2_rate_full_b -> 0.0033458962 | E86: Least valve-open fraction that brings H₂ below the LFL or O₂ below the LOC margin, whichever needs less CO₂, from the same balance; exchanged air counts as diluent for H₂ and as an O₂ source for the LOC route.
A87: Interval that makes the lag headspace non-flammable | B87: spg_int_H2safe | C87: min | D87: =IF(duty_H2safe>0,spg_dur_b/(60*duty_H2safe),NA()) -> 3.9078371 | E87: Mean-field (flux-mean) interval, kept for comparison only: the verdict and remedy (D44) use the pre-pulse sawtooth tops (D92), which need a shorter interval.
A88: N₂ sweep that keeps lag H₂ below the LFL | B88: N2_sweep_H2safe | C88: mL/min | D88: =MAX(0,H2_src_l_b/H2_LFL-n_flamm_src-F_vent_ex_b)/3600*R_gas_b*T_K/P_atm*1000000*60 -> 0.92785267 | E88: Continuous inert headspace sweep that dilutes H₂ below the LFL with no CO₂ at all, net of any air exchange already diluting it.
A89: (import) optimal pulse duration | B89: spg_dur_opt_b | C89: s | D89: ='Mass Transfer'!spg_dur -> 0.65 | E89: Actual commanded pulse (Mass Transfer spg_dur), also the pulse required for the interval remedy.
A90: Longest gap keeping the lag pre-pulse H₂ below the LFL | B90: t_gap_H2_LFL | C90: min | D90: =IF(H2_src_l_b>H2_LFL*F_gap_l_b,n_hs_gas_b/F_gap_l_b*LN((1-H2_LFL*F_gap_l_b/(H2_src_l_b)*flush_ret_opt_b)/(1-H2_LFL*F_gap_l_b/(H2_src_l_b)))*60,"none needed") -> 1.674117 | E90: Exact on the Mass Transfer sawtooth (D388 form): the pre-pulse top y_end = (S/F)(1−e^−x)/(1−r·e^−x), x = F·t/n, r = flush_ret_opt, solved for y_end = LFL: x = ln((1−k·r)/(1−k)), k = LFL·F/S. Not circular: S, F, n and r do not depend on the interval. "none needed" = H₂ never reaches the LFL even with no pulses.
A91: Longest gap keeping the lag pre-pulse O₂ under the LOC margin | B91: t_gap_O2_LOC | C91: min | D91: =IF(O2_src_l_b+y_O2_air_b*F_vent_ex_b>O2_LOC_H2*LOC_margin*F_gap_l_b,n_hs_gas_b/F_gap_l_b*LN((1-O2_LOC_H2*LOC_margin*F_gap_l_b/(O2_src_l_b+y_O2_air_b*F_vent_ex_b)*flush_ret_opt_b)/(1-O2_LOC_H2*LOC_margin*F_gap_l_b/(O2_src_l_b+y_O2_air_b*F_vent_ex_b)))*60,"none needed") -> 2.301569 | E91: As above for O₂ (source incl. the O₂ in admitted air, Mass Transfer S_O2_l), against LOC × margin.
A92: Interval clearing the nominal lag hazard screen | B92: spg_int_H2safe_saw | C92: min | D92: =IF(OR(ISTEXT(t_gap_H2_LFL),ISTEXT(t_gap_O2_LOC)),"any interval",MAX(t_gap_H2_LFL,t_gap_O2_LOC)+spg_dur_opt_b/60) -> 2.3124023 | E92: Either route suffices (H₂ below the LFL or O₂ under the LOC margin, as D86 encodes), so the longer of the two gaps, plus the pulse. Quoted as the remedy in D44 (replaces the "mean-field ÷ 2" heuristic).
A95: ANODIC H₂ LOSS AND CARBON AT THE CYCLE TROUGH
A96: (import) H₂ oxidised at the anode | B96: H2_HOR_b | C96: mol/h | D96: =Electrochemistry!r_H2_HOR -> 0 | E96: → Electrochemistry (r_H2_HOR; 0 while f_HOR_anode is a data gap)
A97: (import) dissolved CO₂ at the start of a pulse (cycle trough) | B97: C_cycle_start_b | C97: mol/m³ | D97: ='Mass Transfer'!C_cycle_start -> 25.4349 | E97: → Mass Transfer (C_cycle_start, mass-conserving limit cycle)
A98: Carbon margin at the cycle trough (dissolved CO₂ : Km) | B98: CO2_margin_trough | C98: × | D98: =C_cycle_start_b*1000/Km_CO2 -> 508.69799 | E98: Lowest dissolved CO₂ of the dosing cycle (mol/m³ = mM, ×1000 → µM) against RuBisCO Km. A sub-second pulse never approaches the full-sparge saturation D33 uses, so this, not D35, is the carbon-availability test; schedule-dependent.
A110: IMPORTS FOR THE SHARED HEADSPACE BALANCE (Mass Transfer §300)
A111: (import) vent air-exchange flow | B111: F_vent_ex_b | C111: mol/h | D111: ='Mass Transfer'!F_vent_ex -> 3.61799e-05 | E111: Import from Mass Transfer!D308: zero for "Outflow only", Q_vent as mol/h for "Air exchange".
A112: (import) dry-air O₂ mole fraction | B112: y_O2_air_b | C112: - | D112: ='Mass Transfer'!y_O2_air -> 0.2095 | E112: Import from Mass Transfer!D307.
A113: (import) H₂ to headspace — lag (net of anodic oxidation) | B113: H2_src_l_b | C113: mol/h | D113: ='Mass Transfer'!H2_src_l -> 9.6772526e-05 | E113: Import from Mass Transfer!D314: evolved H₂ less the anodic H₂ oxidation (r_H2_HOR).
A114: (import) headspace H₂ just before a pulse (lag) | B114: y_H2_end_b | C114: - | D114: ='Mass Transfer'!y_H2_end_l -> 0.14641945 | E114: Import from Mass Transfer!D388 (sawtooth top).
A115: (import) O₂ to the headspace — lag (cathodic loss at the lag DO) | B115: O2_src_l_b | C115: mol/h | D115: ='Mass Transfer'!O2_src_l -> 4.8386263e-05 | E115: Import from Mass Transfer!D310 (O2_src_l = Electrochemistry O2_net_lag).
A116: (import) gas leaving the headspace between pulses — lag | B116: F_gap_l_b | C116: mol/h | D116: ='Mass Transfer'!F_gap_l -> 0.00018133869 | E116: Import from Mass Transfer!D353 (F_gap_l).
A117: (import) headspace gas inventory | B117: n_hs_gas_b | C117: mol | D117: ='Mass Transfer'!n_hs_gas -> 0.00010062821 | E117: Import from Mass Transfer!D150 (n_hs_gas).
A118: (import) headspace retained through the optimal pulse | B118: flush_ret_opt_b | C118: - | D118: ='Mass Transfer'!flush_ret -> 0.36359426 | E118: Retention of the actual commanded pulse, not the ideal design pulse.
A119: (import) headspace O₂ just before a pulse (lag) | B119: y_O2_end_b | C119: - | D119: ='Mass Transfer'!y_O2_end_l -> 0.084678003 | E119: Import from Mass Transfer!D358 (y_O2_end_l, sawtooth top).
A120: Remedy display resolution | B120: remedy_res | C120: - | D120: 0.1 | E120: Display increment: min for interval, mL/min for sweep. Bounds are rounded strictly in the protective direction.
A121: (import) ionic strength of the medium | B121: I_ionic_b | C121: mol/L | D121: =Chemistry!I_ionic -> 0.2001842 | E121: Import from Chemistry!D185 (I_ionic, by media_sel).
A122: Setschenow coefficient for O₂ (per unit ionic strength) | B122: ks_O2 | C122: L/mol | D122: 0.14 | E122: Weisenberger & Schumpe (1996) AIChE J 42:298, ion-specific h_i summed over the UdG recipe at 25 °C (Na⁺ 0.1143, K⁺ 0.0922, NH₄⁺ 0.0556, Mg²⁺ 0.1694, SO₄²⁻ 0.1117, H₂PO₄⁻ 0.0906, HPO₄²⁻ 0.1499, HCO₃⁻ 0.0967 L/mol; h_G(O₂) = 0) gives Σh·c = 0.0154 = 0.14 × I. Lumped per unit I, so approximate for other media.
A123: O₂ salting-out factor | B123: f_salt_O2 | C123: - | D123: =10^(-ks_O2*I_ionic_b) -> 0.93750634 | E123: Setschenow: log₁₀(H₀/H) = k_s·I. 0.965 for UdG (−3.5 %).
A125: (import) non-pulse inflow to the headspace (air + N₂) | B125: F_dil_b | C125: mol/h | D125: ='Mass Transfer'!F_dil -> 3.61799e-05 | E125: Import from Mass Transfer!D425 (F_dil): air ingress plus any N₂ sweep (Summary D14).

Sheet Mass Transfer
A1: MASS TRANSFER
A2: Parameter | B2: Name | C2: Unit | D2: Value | E2: Source / assumption
A4: IMPORTS (from other tabs)
A5: (import) Stir-bar length (from reactor type) | B5: stir_len | C5: mm | D5: =Geometry!stir_bar_L -> 12 | E5: =HYPERLINK("#Geometry!D52","→ Geometry") -> → Geometry | F5: Magnetic stir bar. Pioreactor max 20 mm; confirm the supplied bar's length.
A6: (import) Dissolved-O₂ ceiling | B6: O2_ceil_C | C6: mol/m³ | D6: =Biology!O2_ceil_C -> 0.3147429 | E6: =HYPERLINK("#Biology!D27","→ Biology") -> → Biology
A7: (import) O₂ ceiling (partial pressure) | B7: O2_ceil_Pa | C7: Pa | D7: =Biology!O2_ceil_Pa -> 30397.5 | E7: =HYPERLINK("#Biology!D26","→ Biology") -> → Biology
A8: (import) Temperature (absolute) | B8: T_K | C8: K | D8: =Biology!T_K -> 303.15 | E8: =HYPERLINK("#Biology!D18","→ Biology") -> → Biology
A9: (import) Surface pressure | B9: P_atm | C9: Pa | D9: =Biology!P_atm -> 101325 | E9: =HYPERLINK("#Biology!D19","→ Biology") -> → Biology
A10: (import) CO₂ consumed (carbon fixation) | B10: CO2_cons | C10: mol/h | D10: =Biology!CO2_cons -> 1.7055687e-05 | E10: =HYPERLINK("#Biology!D15","→ Biology") -> → Biology
A11: (import) EXCESS O₂ to remove | B11: O2_excess | C11: mol/h | D11: =Biology!O2_excess -> 1.691661e-05 | E11: =HYPERLINK("#Biology!D16","→ Biology") -> → Biology
A12: (import) Henry solubility O₂ at T | B12: H_O2_T | C12: mol/m³/Pa | D12: =Biology!H_O2_T -> 1.0354236e-05 | E12: =HYPERLINK("#Biology!D24","→ Biology") -> → Biology
A13: (import) Net O₂ to dissolved pool | B13: O2_net_gen | C13: mol/h | D13: =Electrochemistry!O2_net_gen -> 5.1027984e-05 | E13: =HYPERLINK("#Electrochemistry!D29","→ Electrochemistry") -> → Electrochemistry
A14: (import) Gas-liquid interfacial area | B14: interface_A | C14: mm² | D14: =Geometry!interface_A -> 429.54773 | E14: =HYPERLINK("#Geometry!D44","→ Geometry") -> → Geometry
A15: (import) Vial internal diameter | B15: vial_ID | C15: mm | D15: =Geometry!vial_ID -> 25.28 | E15: =HYPERLINK("#Geometry!D20","→ Geometry") -> → Geometry
A16: (import) LIQUID VOLUME TO CHARGE | B16: V_charge | C16: mL | D16: =Geometry!V_charge -> 15 | E16: =HYPERLINK("#Geometry!D41","→ Geometry") -> → Geometry
A17: (import) Internal cross-sectional area | B17: A_x | C17: mm² | D17: =Geometry!A_x -> 501.931 | E17: =HYPERLINK("#Geometry!D21","→ Geometry") -> → Geometry
A18: (import) Sparge tube ID | B18: spg_ID | C18: mm | D18: =Geometry!spg_ID -> 1.5875 | E18: =HYPERLINK("#Geometry!D31","→ Geometry") -> → Geometry
A19: (import) Headspace gas volume | B19: headspace_V | C19: mL | D19: =Geometry!headspace_V -> 2.6124285 | E19: =HYPERLINK("#Geometry!D49","→ Geometry") -> → Geometry
A20: (import) Sinter porosity grade (from electrode) | B20: por_grade | C20: 0-5 | D20: =Electrochemistry!por_grade_e -> 0 | E20: =HYPERLINK("#Electrochemistry!D32","→ Electrochemistry") -> → Electrochemistry
A21: (import) Sparger type (from electrode) | B21: sparger | C21: - | D21: =Electrochemistry!sparger_e -> Sintered | E21: =HYPERLINK("#Electrochemistry!D31","→ Electrochemistry") -> → Electrochemistry
A22: (import) Optimum DO (organism) | B22: DO_opt | D22: =Biology!DO_opt -> #N/A | E22: =HYPERLINK("#Biology!D46","→ Biology") -> → Biology
A23: (import) Impairment DO (organism) | B23: DO_impair | D23: =Biology!DO_impair -> #N/A | E23: =HYPERLINK("#Biology!D47","→ Biology") -> → Biology
A24: (import) Toxic/inhibition DO (organism) | B24: DO_toxic | D24: =Biology!DO_toxic -> #N/A | E24: =HYPERLINK("#Biology!D48","→ Biology") -> → Biology
A25: (import) Minimum DO (organism) | B25: DO_min | D25: =Biology!DO_min -> #N/A | E25: =HYPERLINK("#Biology!D45","→ Biology") -> → Biology
A27: valid sparger 1 | B27: spg_name_1 | C27: - | D27: Tube | E27: Bare 1/8" OD x 1/16" ID Flexelene 135C tube orifice.
A28: valid sparger 2 | B28: spg_name_2 | C28: - | D28: Sintered | E28: 10 mm sintered-glass disc annulus on a tubular anode.
A29: Surface tension (water, T) | B29: sigma | C29: N/m | D29: =sigma_0+sigma_k*(T_K-T_zero_C) -> 0.07118 | E29: IAPWS R1-76(2014), evaluated at the reactor temperature (T_C). Feeds the bubble-detachment diameter.
A30: Liquid density (water, T) | B30: rho_L | C30: kg/m³ | D30: =rho_0+rho_k*(T_K-T_zero_C) -> 995.662 | E30: IAPWS-95, evaluated at the reactor temperature.
A31: Gravitational acceleration | B31: g_const | C31: m/s² | D31: 9.80665 | E31: Standard gravity (defined).
A32: O₂ diffusivity in water (T) | B32: D_O2 | C32: m²/s | D32: =10^(HB_a+HB_b/T_K-(HB_c/T_K)^2)/10000 -> 2.2495444e-09 | E32: Han & Bartels (1996) evaluated at the reactor temperature. At 25 °C this is 2.00e-9 m²/s.
A33: Pore size - grade 0 | B33: por0_um | C33: µm | D33: 205 | E33: DURAN P0 160-250 µm, midpoint. ISO 4793 (paywalled) underlies; DURAN table is free.
A34: Pore size - grade 1 | B34: por1_um | C34: µm | D34: 130 | E34: DURAN P1 100-160 µm, midpoint.
A35: Pore size - grade 2 | B35: por2_um | C35: µm | D35: 70 | E35: DURAN P2 40-100 µm, midpoint.
A36: Pore size - grade 3 | B36: por3_um | C36: µm | D36: 28 | E36: DURAN P3 16-40 µm, midpoint.
A37: Pore size - grade 4 | B37: por4_um | C37: µm | D37: 13 | E37: DURAN P4 10-16 µm, midpoint.
A38: Pore size - grade 5 | B38: por5_um | C38: µm | D38: 1.3 | E38: DURAN P5 1.0-1.6 µm, midpoint.
A39: Selected sinter pore diameter | B39: por_pore | C39: m | D39: =CHOOSE(por_grade+1,por0_um,por1_um,por2_um,por3_um,por4_um,por5_um)/1000000 -> 0.000205 | E39: Picked by por_grade.
A40: Tube orifice diameter | B40: tube_d_m | C40: m | D40: =spg_ID/1000 -> 0.0015875 | E40: Tube ID in metres.
A41: Effective orifice/pore diameter | B41: d_orifice | C41: m | D41: =IF(sparger=spg_name_1,tube_d_m,IF(sparger=spg_name_2,por_pore,NA())) -> 0.000205 | E41: Tube ID or sinter pore; invalid sparger returns an error.
A42: Bubble detachment diameter | B42: d_bubble | C42: m | D42: =(6*d_orifice*sigma/(rho_L*g_const))^(1/3) -> 0.0020775118 | E42: Static low-flow force balance (buoyancy vs surface tension); valid in the quasi-static regime — see bubble_regime (§10).
A43: Bubble diameter (display) | B43: d_bubble_mm | C43: mm | D43: =d_bubble*1000 -> 2.0775118 | E43: Display of the Tate’s-law bubble diameter in mm for the sparger in use.
A44: Mendelson coefficient a | B44: mend_a | C44: - | D44: 2.14 | E44: Mendelson (1967) wave-theory bubble rise correlation (AIChE J, paywalled).
A45: Mendelson coefficient b | B45: mend_b | C45: - | D45: 0.505 | E45: Mendelson (1967), as above.
A46: Bubble rise velocity | B46: u_rise | C46: m/s | D46: =SQRT(mend_a*sigma/(rho_L*d_bubble)+mend_b*g_const*d_bubble) -> 0.28970505 | E46: Mendelson rise velocity, valid ~1–10 mm. Sub-mm bubbles (fine sinters) are out of range → bubble strip excluded and flagged (bubble_regime); §11 surface path and §14 optimiser unaffected. Tube = 4.1 mm.
A47: Superficial gas velocity (sparge on) | B47: u_sg | C47: m/s | D47: =(Q_CO2/1000000/60)/(A_x/1000000) -> 0.006634378 | E47: Gas flow / liquid cross-section.
A48: Gas holdup (sparge on) | B48: holdup | C48: - | D48: =u_sg/u_rise -> 0.022900457 | E48: ε ≈ superficial gas velocity / rise velocity.
A49: Interfacial area for transfer | B49: a_int | C49: 1/m | D49: =6*holdup/d_bubble -> 66.138129 | E49: a = 6ε/d_b (spheres).
A50: Bubble-liquid contact time | B50: t_contact | C50: s | D50: =d_bubble/u_rise -> 0.0071711273 | E50: d_b / rise velocity.
A51: Liquid-film coefficient kL | B51: kL | C51: m/s | D51: =2*SQRT(D_O2/(PI()*t_contact)) -> 0.00063198771 | E51: Higbie penetration theory.
A52: kLa during sparge | B52: kLa_sparge | C52: 1/s | D52: =kL*a_int -> 0.041798485 | E52: kL x a.
A53: kLa time-averaged | B53: kLa_avg | C53: 1/s | D53: =kLa_sparge*duty -> 6.2978709e-05 | E53: Sparge-on regime only; not meaningful in the surface-strip-dominated default
A54: O₂ strip rate at ceiling (sparge on) | B54: strip_sparge | C54: mol/h | D54: =IF(d_bubble<d_bubble_min_m,0,kLa_sparge*(V_charge/1000000)*O2_ceil_C*3600) -> 0.00071041193 | E54: Bubble O₂ strip at the ceiling driving force (best case). 0 for sub-mm bubbles (fine sinter, bubble model out of range — see bubble_regime). Evaluated at the generic 0.30 atm ceiling (D6), as a transfer capacity, not at the organism limit.
A55: O₂ strip rate time-averaged | B55: strip_avg | C55: mol/h | D55: =strip_sparge*duty -> 1.0703935e-06 | E55: x duty cycle.
A56: Strip capacity : excess-O₂ | B56: strip_ratio | C56: × | D56: =IF(O2_excess>0,strip_avg/O2_excess,NA()) -> 0.063274705 | E56: Bubble strip : surplus. ≪1 — the §11 surface path is the real route.
A57: Required time-avg kLa | B57: kLa_req | C57: 1/s | D57: =IF(O2_excess>0,O2_excess/3600/((V_charge/1000000)*O2_ceil_C),NA()) -> 0.00099532205 | E57: kLa that would exactly strip the excess at the ceiling. Evaluated at the generic 0.30 atm ceiling (D6), as a transfer capacity, not at the organism limit.
A58: Entrainment velocity ceiling (rule of thumb) | B58: u_g_max | C58: m/s | D58: 0.05 | E58: Provisional superficial-velocity ceiling above which droplet carryover to the hydrophilic vent filters becomes likely. Replace with measured value.
A59: Carryover flag | B59: carry_flag | C59: - | D59: =IF(carry_n=0,"not measured – record the max flow without carryover for "&Reactor&" in CO2 flows column M",IF(Q_CO2/60>Q_carry_max,"RISK – pulse flow "&TEXT(Q_CO2/60,"0.00")&" mL/s exceeds the measured "&TEXT(Q_carry_max,"0.00")&" mL/s no-carryover limit","OK – pulse flow "&TEXT(Q_CO2/60,"0.00")&" mL/s within the measured "&TEXT(Q_carry_max,"0.00")&" mL/s no-carryover limit")) -> not measured – record the max flow without carryover for ed04 in CO2 flows column M | E59: Pulse flow (Q_CO2) against the measured per-reactor no-carryover maximum (D413, CO2 flows column M). "not measured" until a value is entered, never a default OK. The superficial-velocity rule is the secondary line D414.
A60: CO₂ gas density (T,P) | B60: rho_CO2 | C60: kg/m³ | D60: =P_atm*(M_CO2/1000)/(R_gas*T_K) -> 1.769177 | E60: Ideal gas at surface conditions; for the orifice Weber number.
A61: Active sparge orifices | B61: n_pores_active | C61: - | D61: 1 | E61: Tube = 1. Sinter pore count unknown; 1 = worst case. DATA GAP.
A62: Gas velocity at orifice | B62: v_orifice | C62: m/s | D62: =(Q_CO2/1000000/60)/(n_pores_active*(PI()/4*d_orifice^2)) -> 100.88965 | E62: Sparge-on regime only; not meaningful in the surface-strip-dominated default
A63: Orifice Weber number | B63: We_orifice | C63: - | D63: =rho_CO2*v_orifice^2*d_orifice/sigma -> 51.863333 | E63: Sparge-on regime only; not meaningful in the surface-strip-dominated default
A64: Bubble-formation regime | B64: bubble_regime | C64: - | D64: =IF(d_bubble<d_bubble_min_m,"Sinter OOR – add fine-bubble model",IF(We_orifice<We_static_max,"Static","Dynamic")) -> Dynamic | E64: Tate's law assumes quasi-static detachment (We<~2). 'Sinter OOR' = sub-mm bubble; the fine-sinter model isn't built yet.
A65: O₂ time-to-ceiling (no removal) | B65: t_O2_ceiling | C65: min | D65: =IF(O2_excess>0,O2_ceil_org*(V_charge/1000000)/O2_excess*60,"never (source <= 0)") -> 16.744999 | E65: Minutes to reach the O₂ ceiling from ~0 with no removal (steady growth: the O₂ excess after biological uptake), the O₂ timescale.
A66: O₂ time-to-ceiling (with time-avg strip) | B66: t_O2_ceiling_strip | C66: min | D66: =IF(O2_excess-strip_avg>0,O2_ceil_org*(V_charge/1000000)/(O2_excess-strip_avg)*60,"never (strip ≥ source)") -> 17.876104 | E66: As above, crediting time-averaged bubble strip (≈unchanged → bubbles aren't the mechanism). "never" = cleared.
A67: (import) Stir-bar speed | B67: stir_rpm | C67: 1/min | D67: =Summary!stir_rpm_set -> 1000 | E67: → Summary (stir_rpm_set). Pioreactor stir setpoint. RPM floor ~125 (stalls below).
A68: Stir-bar tip speed | B68: tip_speed | C68: m/s | D68: =PI()*(stir_len/1000)*stir_rpm/60 -> 0.62831853 | E68: π·d·rpm/60.
A69: Surface renewal frequency | B69: s_renew | C69: 1/s | D69: =tip_speed/(vial_ID/1000) -> 24.854372 | E69: Surface renewal ≈ tip speed / vial ID. Coarse proxy.
A70: Surface liquid-film coeff kL | B70: kL_surf | C70: m/s | D70: =2*SQRT(D_O2*s_renew/PI()) -> 0.00026681101 | E70: Penetration-theory / surface-renewal proxy (Higbie form, t=1/s_renew) — coarse; measure by gassing-out (§15).
A71: Surface area per volume | B71: a_surf | C71: 1/m | D71: =interface_A/V_charge -> 28.636515 | E71: Free-surface area / liquid volume (mm²/mL = 1/m); uses interface_A (§1B).
A72: Surface O₂ transfer kLa | B72: kLa_surf | C72: 1/s | D72: =kL_surf*a_surf -> 0.0076405375 | E72: kL_surf × a_surf.
A73: O₂ strip via surface (ceiling) | B73: surf_strip | C73: mol/h | D73: =kLa_surf_used*(V_charge/1000000)*O2_ceil_C*3600 -> 0.00012985947 | E73: O₂ removable across the stirred surface at ceiling driving force — a FEASIBILITY CEILING for surf_ratio / O2_removal_ratio only. NEVER subtracted inside a safety guard (kL_surf is a ~375%-uncertain best-case proxy); the guards size on O2_src_guard (D132) with this credit withheld. Evaluated at the generic 0.30 atm ceiling (D6), as a transfer capacity, not at the organism limit.
A74: Surface strip : excess-O₂ | B74: surf_ratio | C74: × | D74: =IF(O2_excess>0,surf_strip/O2_excess,NA()) -> 7.6764476 | E74: Surface strip : surplus. Coarse (kL_surf). ≫ bubble path — the dominant O₂ route.
A77: Headspace flush time | B77: hs_flush_time | C77: min | D77: =headspace_V*spg_int/V_pulse -> 7.4168495 | E77: Mean time to deliver one headspace volume of CO₂: the interval × headspace ÷ pulse volume (D411).
A78: Combined O₂ removal : excess | B78: O2_removal_ratio | C78: × | D78: =IF(O2_excess>0,(strip_avg+surf_strip)/O2_excess,NA()) -> 7.7397223 | E78: Upper bound: surface + sparge O2 sinks are in series (liquid->headspace->vent), not strictly additive
A79: O₂ time-to-ceiling (LAG, no uptake) | B79: t_O2_ceiling_lag | C79: min | D79: =O2_ceil_org*(V_charge/1000000)/O2_net_gen*60 -> 5.5512405 | E79: Lag/establishment: no biological O₂ uptake yet, so the full net O₂ accumulates. Worst case.
A80: O₂ time-to-ceiling (with all removal) | B80: t_O2_ceiling_rem | C80: min | D80: =IF(O2_net_gen-strip_avg-surf_strip>0,O2_ceil_org*(V_charge/1000000)/(O2_net_gen-strip_avg-surf_strip)*60,"never (removal ≥ source)") -> never (removal ≥ source) | E80: Companion to t_O2_ceiling_lag crediting BOTH removal paths at their best-case ceiling driving force. Best-case diagnostic only: surf_strip is the ~375%-uncertain surface proxy, so this cell must never gate a schedule or a guard. "never" = removal exceeds the source at that best case.
A81: Schedule mode | B81: sched_mode | C81: - | D81: Optimal | E81: Set by the Summary 'Your setting' override (G18/G20) when filled; otherwise this Manual/Optimal selector + the manual cells below apply. Optimal = recommended schedule.
A82: Manual pulse duration | B82: spg_dur_man | C82: s | D82: 1 | E82: Your pulse length when sched_mode=Manual. Easiest: type into the Summary 'Your setting' column (G18) instead — it overrides everything.
A83: Manual sparge interval | B83: spg_int_man | C83: min | D83: 1 | E83: Your interval when sched_mode=Manual. Easiest: type into the Summary 'Your setting' column (G20) instead — it overrides everything.
A84: Target DO fraction (organism optimum / inhibition) | B84: target_DO_frac | C84: - | D84: =Biology!DO_frac_target -> 0.22608696 | E84: Imported from Biology D60: one definition of the target DO fraction, from the selected organism's measured band where there is one and from C. necator's 2.6/11.5 otherwise. Sizes the O₂ guards below.
A85: Min carbon supply margin | B85: carbon_margin_min | C85: - | D85: 2 | E85: Required CO₂ supply : fixation demand. Input.
A86: Duty floor — carbon | B86: duty_carbon | C86: - | D86: =carbon_margin_min*CO2_cons/(nCO2_rate*3600) -> 7.0782782e-05 | E86: Duty needed so CO₂ supply ≥ margin × fixation demand.
A87: Duty floor — O₂ venting (lag) | B87: duty_O2vent | C87: - | D87: =O2_src_guard/(target_DO_frac*(O2_ceil_Pa/P_atm))/(nCO2_rate*3600) -> 0.0015611336 | E87: Conservative O₂-vent duty: net O₂ with the surface-strip credit withheld (O2_src_guard). Sizes the O₂-limited fallback; the recommended schedule credits the surface estimate when DO is held.
A88: Optimal duty cycle | B88: duty_opt | C88: - | D88: =MAX(duty_carbon,duty_O2vent) -> 0.0015611336 | E88: Least feasible CO₂ duty (the larger of the two floors). Informative only: D91 takes the interval from the carbon (D112) and DO-dilution (D185) intervals, not from this duty.
A89: Max interval — legacy O₂ flush guard (fallback) | B89: spg_int_max | C89: min | D89: =target_DO_frac*O2_ceil_org*(V_charge/1000000)/O2_src_guard*60 -> 1.2550631 | E89: LEGACY O₂ flush guard, kept only as the fallback: fills target_DO_frac of the ceiling in the liquid from the zero-surface worst-case source (O2_src_guard, D132) with no venting. It predates the shared headspace balance (§300), so the vent model does not move it and the DO it gives is neither the target nor a ceiling margin. D91 uses it only when the DO target is unreachable (spg_int_DO, D185, is #N/A). A balance-derived replacement (size on the ceiling with a margin) is an owner decision.
A90: OPTIMAL pulse duration | B90: spg_dur_opt | C90: s | D90: =MAX(pulse_floor,(flush_factor*headspace_V-pulse_V0)/Q_CO2_fit) -> 0.67407652 | E90: ANSWER. Shortest reliable pulse: the time at which V₀ + Q_fit·t delivers flush_factor headspace volumes (R2-M3), never below the solenoid floor (pulse_floor).
A91: OPTIMAL sparge interval | B91: spg_int_opt | C91: min | D91: =IF(ISNA(F_vent_ex+O2_src_sched),NA(),IF(ph_unreach,NA(),MIN(spg_int_carbon,IF(ISNUMBER(spg_int_DO),spg_int_DO,spg_int_max),IF(ISNUMBER(spg_int_pH_opt),spg_int_pH_opt,spg_int_carbon),IF(O2_sizing_phase=phase_name_2,IF(ISNUMBER(spg_int_H2safe_opt),spg_int_H2safe_opt,spg_int_carbon),spg_int_carbon)))) -> 7.4219028 | E91: ANSWER. The shortest of the upper bounds on the interval: carbon supply (D112), headspace-O₂ dilution (spg_int_DO), the pH ceiling (D433) and, when the schedule is sized on Lag, the H₂ flammability screen (D563). #N/A for an invalid vent or phase selector or when no interval keeps pH under the band ceiling (D434). If the DO target is unreachable the legacy O₂ flush guard (D89) stands in for the O₂ bound and D134 says so.
A92: optimal interval (seconds) | B92: spg_int_opt_s | C92: s | D92: =spg_int_opt*60 -> 445.31417 | E92: Convenience: interval in seconds.
A93: resulting duty (full-flow equivalent) | B93: duty_actual | C93: - | D93: =spg_dur_eq_opt/(spg_int_opt*60) -> 0.0017617069 | E93: CO₂ actually delivered at the optimum as a fraction of continuous full flow: the full-flow-equivalent pulse (D409) over the interval. With a pulse intercept this exceeds the valve-open fraction (D105).
A94: binding constraint | B94: opt_binding | C94: - | D94: =IF(ISNA(F_vent_ex+O2_src_sched),"INVALID SELECTOR (check Summary D2–D5, D11, D12)",IF(ph_unreach,"pH CEILING UNREACHABLE – reduce the N₂ or the added alkalinity",IF(AND(O2_sizing_phase=phase_name_2,ISNUMBER(spg_int_H2safe_opt),spg_int_opt=spg_int_H2safe_opt),"H₂ FLAMMABILITY SCREEN (lag sizing; Biology D92 sets the interval)",IF(AND(ISNUMBER(spg_int_pH_opt),spg_int_opt=spg_int_pH_opt),"pH CEILING (keeping pH at or under the band ceiling sets the interval)",IF(NOT(ISNUMBER(spg_int_DO)),"O2-INFEASIBLE – the legacy O2 flush guard (D89) sets the interval (see D134)",IF(spg_int_DO<spg_int_carbon,"O2-DILUTION (headspace O2 sets the interval)","CARBON (CO2 supply sets the interval)")))))) -> O2-DILUTION (headspace O2 sets the interval) | E94: Which constraint binds: headspace-oxygen dilution or carbon supply. The pH consequence of the winner is carried through the CO₂ limit cycle to the Chemistry sheet — a short oxygen-driven interval delivers far more CO₂ than the carbon demand and pushes pH down.
A95: OD-window check | B95: od_ok | C95: - | D95: =IF(spg_int*60-spg_dur>=od_gap_min_s,"OK","TIGHT") -> OK | E95: ≥5 s gap between pulses for an OD read (uses the schedule IN USE, so it responds to your override). Can't measure OD while sparging.
A96: ACCURACY LIMIT — no validated kinetics | B96: kinetic_caveat | C96: - | D96: ="see note →" -> see note → | E96: Constraint-proxy optimiser, not a fitted growth model — no validated μ(O₂,pH,CO₂) or lag kinetics exist for this system. Gives the lag-minimising direction, not an exact optimum; bounded by etaF, surface kL and the unbuffered-pH simplification. Validate empirically.
A97: Measured surface kLa | B97: kLa_meas | C97: 1/h | D97: =IF(ISNUMBER(cal_kLa),cal_kLa,0) -> 0 | E97: Measured surface kLa (gassing-out). 0 = use the §11 estimate. kLa = slope of −LN(1−DO/DO_sat) vs time.
A98: Surface kLa used downstream | B98: kLa_surf_used | C98: 1/s | D98: =IF(AND(ISNUMBER(kLa_meas),kLa_meas>0),kLa_meas/3600,kLa_surf) -> 0.0076405375 | E98: What §11 actually uses: the measured surface kLa if one has been entered on the Calibrations tab (in 1/h), otherwise the penetration-theory estimate. The ISNUMBER test matters — an empty calibration returns a message, and in Excel text sorts above every number, so a bare ">0" test would have accepted it.
A99: Min reliable pulse (solenoid floor) | B99: pulse_floor | C99: s | D99: =min_sparge_cal -> 0.25 | E99: Solenoid floor in use = min_sparge_cal (D118): Calibrations tab Min pulse, else CO2 flows column I, else pulse_floor_default (D396).
A100: Average CO₂ supply rate | B100: CO2_supply | C100: mol/h | D100: =CO2_pulse*pulses_h -> 0.00084957368 | E100: From Dosing.
A101: Ideal gas constant | B101: R_gas | C101: J/mol/K | D101: 8.3144626 | E101: From Dosing.
A102: CO₂ volumetric flow rate | B102: Q_CO2 | C102: mL/min | D102: =IF(has_cal>0,flowrate_cal*60,NA()) -> 199.8 | E102: From Dosing.
A103: Molar mass CO₂ | B103: M_CO2 | C103: g/mol | D103: 44.0095 | E103: From Dosing.
A104: CO₂ molar flow during sparge | B104: nCO2_rate | C104: mol/s | D104: =P_atm*(Q_CO2/1000000/60)/(R_gas*T_K) -> 0.00013386563 | E104: Dry CO2-equivalent flow at P_atm and T_K. Calibration collection humidity/temperature remain unrecorded; verify before using absolute molar delivery. This convention is distinct from saturated headspace inventory.
...

Sheet CO2 flows
A1: CO₂ DOSING FLOWRATES
A2: Reactor | B2: date | C2: cylinder size | D2: observed volume* | E2: volume | F2: time | G2: flowrate | H2: average flowrate | I2: minimum sparge | J2: nominal flowrate | L2: KEY | M2: max flow without carryover | N2: excluded from pulse fit
C3: mL | D3: mL | E3: mL | F3: s | G3: mL/s | H3: mL/s | I3: s | J3: mL/s | L3: Flowrate set by inspection, as maximum to not give bubbles rising into vial neck | M3: mL/s | N3: 1 = yes
A4: ed04 | B4: 46190 | C4: 50 | D4: 0 | I4: 0.25 | J4: 3.33 | L4: First or last data point removed as suspect outlier
A5: ed04 | B5: 46190 | C5: 50 | D5: 50 | E5: =D5-D4 -> 50 | F5: 15 | G5: =E5/F5 -> 3.3333333 | H5: =AVERAGE(G5) -> 3.3333333
A6: ed04 | B6: 46190 | C6: 50 | D6: 0 | K6: Point | L6: Note
A7: ed04 | B7: 46190 | C7: 50 | D7: 12 | E7: =D7-D6 -> 12 | F7: 4 | G7: =E7/F7 -> 3 | H7: =AVERAGE(G7:G9) -> 3.3333333 | K7: * | L7: CO2 collected in measuring cylinder over CO2-saturated water
A8: ed04 | B8: 46190 | C8: 50 | D8: 26 | E8: =D8-D7 -> 14 | F8: 4 | G8: =E8/F8 -> 3.5 | K8: 46190 | L8: Collected using inlet CO2 tube rather than outlet as MEP vialcap leaking
A9: ed04 | B9: 46190 | C9: 50 | D9: 40 | E9: =D9-D8 -> 14 | F9: 4 | G9: =E9/F9 -> 3.5 | K9: 46190 | L9: Collected over saturated NaHCO3 solution
A10: ed04 | B10: 46190 | C10: 50 | D10: 0 | L10: Column M: highest steady flow at which no liquid is carried into the vial neck or vent for this reactor (measured; blank = not measured, and Mass Transfer carry_flag then reads "not measured"). If the lowest entry for the reactor is below the pulse flow, carry_flag reads RISK.
A11: ed04 | B11: 46190 | C11: 50 | D11: 6 | E11: =D11-D10 -> 6 | F11: 2 | G11: =E11/F11 -> 3 | H11: =AVERAGE(G11:G16) -> 3.75 | L11: Column N: 1 = point excluded from the pulse-volume fit V = V₀ + Q·t on Mass Transfer (rows 401–408); 1 is set on the two red outliers (G36, G46). Blank = used.
A12: ed04 | B12: 46190 | C12: 50 | D12: 15 | E12: =D12-D11 -> 9 | F12: 2 | G12: =E12/F12 -> 4.5
A13: ed04 | B13: 46190 | C13: 50 | D13: 21 | E13: =D13-D12 -> 6 | F13: 2 | G13: =E13/F13 -> 3
A14: ed04 | B14: 46190 | C14: 50 | D14: 29 | E14: =D14-D13 -> 8 | F14: 2 | G14: =E14/F14 -> 4
A15: ed04 | B15: 46190 | C15: 50 | D15: 35 | E15: =D15-D14 -> 6 | F15: 2 | G15: =E15/F15 -> 3
A16: ed04 | B16: 46190 | C16: 50 | D16: 45 | E16: =D16-D15 -> 10 | F16: 2 | G16: =E16/F16 -> 5
A17: ed04 | B17: 46190 | C17: 50 | D17: 0
A18: ed04 | B18: 46190 | C18: 50 | D18: 4 | E18: =D18-D17 -> 4 | F18: 1 | G18: =E18/F18 -> 4 | H18: =AVERAGE(G18:G23) -> 3.8333333
A19: ed04 | B19: 46190 | C19: 50 | D19: 8 | E19: =D19-D18 -> 4 | F19: 1 | G19: =E19/F19 -> 4
A20: ed04 | B20: 46190 | C20: 50 | D20: 11 | E20: =D20-D19 -> 3 | F20: 1 | G20: =E20/F20 -> 3
A21: ed04 | B21: 46190 | C21: 50 | D21: 15 | E21: =D21-D20 -> 4 | F21: 1 | G21: =E21/F21 -> 4
A22: ed04 | B22: 46190 | C22: 50 | D22: 19 | E22: =D22-D21 -> 4 | F22: 1 | G22: =E22/F22 -> 4
A23: ed04 | B23: 46190 | C23: 50 | D23: 23 | E23: =D23-D22 -> 4 | F23: 1 | G23: =E23/F23 -> 4
A24: ed04 | B24: 46190 | C24: 50 | D24: 31
A25: ed04 | B25: 46190 | C25: 50 | D25: 33 | E25: =D25-D24 -> 2 | F25: 0.5 | G25: =E25/F25 -> 4 | H25: =AVERAGE(G25:G29) -> 4
A26: ed04 | B26: 46190 | C26: 50 | D26: 35 | E26: =D26-D25 -> 2 | F26: 0.5 | G26: =E26/F26 -> 4
A27: ed04 | B27: 46190 | C27: 50 | D27: 37 | E27: =D27-D26 -> 2 | F27: 0.5 | G27: =E27/F27 -> 4
A28: ed04 | B28: 46190 | C28: 50 | D28: 39 | E28: =D28-D27 -> 2 | F28: 0.5 | G28: =E28/F28 -> 4
A29: ed04 | B29: 46190 | C29: 50 | D29: 41 | E29: =D29-D28 -> 2 | F29: 0.5 | G29: =E29/F29 -> 4
A30: ed04 | B30: 46190 | C30: 50 | D30: 42 | E30: =D30-D29 -> 1 | F30: 0.25 | G30: =E30/F30 -> 4 | H30: =AVERAGE(G30:G34) -> 4
A31: ed04 | B31: 46190 | C31: 50 | D31: 43 | E31: =D31-D30 -> 1 | F31: 0.25 | G31: =E31/F31 -> 4
A32: ed04 | B32: 46190 | C32: 50 | D32: 44 | E32: =D32-D31 -> 1 | F32: 0.25 | G32: =E32/F32 -> 4
A33: ed04 | B33: 46190 | C33: 50 | D33: 45 | E33: =D33-D32 -> 1 | F33: 0.25 | G33: =E33/F33 -> 4
A34: ed04 | B34: 46190 | C34: 50 | D34: 46 | E34: =D34-D33 -> 1 | F34: 0.25 | G34: =E34/F34 -> 4
A35: ed04 | B35: 46190 | C35: 10 | D35: 0 | E35: =D35-D34 -> -46
A36: ed04 | B36: 46190 | C36: 10 | D36: 0.4 | E36: =D36-D35 -> 0.4 | F36: 0.2 | G36: =E36/F36 -> 2 | N36: 1
A37: ed04 | B37: 46190 | C37: 10 | D37: 1.2 | E37: =D37-D36 -> 0.8 | F37: 0.2 | G37: =E37/F37 -> 4 | H37: =AVERAGE(G37:G39) -> 4.3333333
A38: ed04 | B38: 46190 | C38: 10 | D38: 2.2 | E38: =D38-D37 -> 1 | F38: 0.2 | G38: =E38/F38 -> 5
A39: ed04 | B39: 46190 | C39: 10 | D39: 3 | E39: =D39-D38 -> 0.8 | F39: 0.2 | G39: =E39/F39 -> 4
A40: ed04 | B40: 46190 | C40: 10 | D40: 0
A41: ed04 | B41: 46190 | C41: 10 | D41: 0.4 | E41: =D41-D40 -> 0.4 | F41: 0.1 | G41: =E41/F41 -> 4 | H41: =AVERAGE(G41:G45) -> 5.2
A42: ed04 | B42: 46190 | C42: 10 | D42: 0.8 | E42: =D42-D41 -> 0.4 | F42: 0.1 | G42: =E42/F42 -> 4
A43: ed04 | B43: 46190 | C43: 10 | D43: 1.4 | E43: =D43-D42 -> 0.6 | F43: 0.1 | G43: =E43/F43 -> 6
A44: ed04 | B44: 46190 | C44: 10 | D44: 2 | E44: =D44-D43 -> 0.6 | F44: 0.1 | G44: =E44/F44 -> 6
A45: ed04 | B45: 46190 | C45: 10 | D45: 2.6 | E45: =D45-D44 -> 0.6 | F45: 0.1 | G45: =E45/F45 -> 6
A46: ed04 | B46: 46190 | C46: 10 | D46: 2.8 | E46: =D46-D45 -> 0.2 | F46: 0.1 | G46: =E46/F46 -> 2 | N46: 1

Sheet Calibrations
A1: CALIBRATIONS
A2: Fill the white cells only: Researcher, Date, the key (Reactor or Organism) and the raw measurements. Grey cells are computed automatically. Set Include to y for rows the model should use.
A3: The value in use for each calibration follows the rule stated under its heading. If no rows are included yet, the model falls back to its built-in default.
A5: =HYPERLINK("https://github.com/amy-bo/electroPioreactor/blob/AEP02/Media/protocols/gerrit-current.md","ELECTROLYSIS CURRENT") -> ELECTROLYSIS CURRENT
A6: Value in use: one least-squares fit of current against intensity over every included point for the active reactor (pooled, so a run with more points weighs more).
A7: Researcher | B7: Date | C7: Reactor | D7: Intensity | E7: Current | F7: Type (auto) | G7: Include? | H7: Notes
F8: =IFERROR(INDEX(ReactorTypeList,MATCH(C8,ReactorList,0)),"")
F9: =IFERROR(INDEX(ReactorTypeList,MATCH(C9,ReactorList,0)),"")
F10: =IFERROR(INDEX(ReactorTypeList,MATCH(C10,ReactorList,0)),"")
F11: =IFERROR(INDEX(ReactorTypeList,MATCH(C11,ReactorList,0)),"")
F12: =IFERROR(INDEX(ReactorTypeList,MATCH(C12,ReactorList,0)),"")
F13: =IFERROR(INDEX(ReactorTypeList,MATCH(C13,ReactorList,0)),"")
F14: =IFERROR(INDEX(ReactorTypeList,MATCH(C14,ReactorList,0)),"")
F15: =IFERROR(INDEX(ReactorTypeList,MATCH(C15,ReactorList,0)),"")
A16: Value in use - slope | C16: mA/% | D16: =IFERROR((COUNTIFS(C8:C15,Reactor_sel,G8:G15,"y")*SUMPRODUCT((C8:C15=Reactor_sel)*(G8:G15="y")*D8:D15*E8:E15)-SUMIFS(D8:D15,C8:C15,Reactor_sel,G8:G15,"y")*SUMIFS(E8:E15,C8:C15,Reactor_sel,G8:G15,"y"))/(COUNTIFS(C8:C15,Reactor_sel,G8:G15,"y")*SUMPRODUCT((C8:C15=Reactor_sel)*(G8:G15="y")*D8:D15*D8:D15)-SUMIFS(D8:D15,C8:C15,Reactor_sel,G8:G15,"y")*SUMIFS(D8:D15,C8:C15,Reactor_sel,G8:G15,"y")),"no included runs — model uses its default") -> no included runs — model uses its default
A17: Value in use - intercept | C17: mA | D17: =IFERROR((SUMIFS(E8:E15,C8:C15,Reactor_sel,G8:G15,"y")-((COUNTIFS(C8:C15,Reactor_sel,G8:G15,"y")*SUMPRODUCT((C8:C15=Reactor_sel)*(G8:G15="y")*D8:D15*E8:E15)-SUMIFS(D8:D15,C8:C15,Reactor_sel,G8:G15,"y")*SUMIFS(E8:E15,C8:C15,Reactor_sel,G8:G15,"y"))/(COUNTIFS(C8:C15,Reactor_sel,G8:G15,"y")*SUMPRODUCT((C8:C15=Reactor_sel)*(G8:G15="y")*D8:D15*D8:D15)-SUMIFS(D8:D15,C8:C15,Reactor_sel,G8:G15,"y")*SUMIFS(D8:D15,C8:C15,Reactor_sel,G8:G15,"y")))*SUMIFS(D8:D15,C8:C15,Reactor_sel,G8:G15,"y"))/COUNTIFS(C8:C15,Reactor_sel,G8:G15,"y"),"no included runs — model uses its default") -> no included runs — model uses its default
A20: =HYPERLINK("https://github.com/amy-bo/electroPioreactor/blob/AEP02/Media/protocols/faradaic-efficiency.md","FARADAIC EFFICIENCY (cathodic etaF, anodic etaF_OER)") -> FARADAIC EFFICIENCY (cathodic etaF, anodic etaF_OER)
A21: Value in use: average of the included runs for the active reactor, taken separately for the H2 (cathode) and O2 (anode) electrodes. The gas volume is corrected for saturated water vapour at the temperature you record, per protocols/faradaic-efficiency.md.
A22: Researcher | B22: Date | C22: Reactor | D22: Charge Q | E22: Gas volume | F22: Temp | G22: Pressure | H22: Electrode | I22: etaF (computed) | J22: Type (auto) | K22: Include? | L22: Notes
I23: =IFERROR(((G23-pw_A*EXP(pw_B*F23/(F23+pw_C)))*(E23/1000000)/(R_gas*(F23+T_zero_C)))/(D23/(IF(H23="H2",z_e_H2,IF(H23="O2",z_e_O2,NA()))*F_const)),"") | J23: =IFERROR(INDEX(ReactorTypeList,MATCH(C23,ReactorList,0)),"")
I24: =IFERROR(((G24-pw_A*EXP(pw_B*F24/(F24+pw_C)))*(E24/1000000)/(R_gas*(F24+T_zero_C)))/(D24/(IF(H24="H2",z_e_H2,IF(H24="O2",z_e_O2,NA()))*F_const)),"") | J24: =IFERROR(INDEX(ReactorTypeList,MATCH(C24,ReactorList,0)),"")
I25: =IFERROR(((G25-pw_A*EXP(pw_B*F25/(F25+pw_C)))*(E25/1000000)/(R_gas*(F25+T_zero_C)))/(D25/(IF(H25="H2",z_e_H2,IF(H25="O2",z_e_O2,NA()))*F_const)),"") | J25: =IFERROR(INDEX(ReactorTypeList,MATCH(C25,ReactorList,0)),"")
I26: =IFERROR(((G26-pw_A*EXP(pw_B*F26/(F26+pw_C)))*(E26/1000000)/(R_gas*(F26+T_zero_C)))/(D26/(IF(H26="H2",z_e_H2,IF(H26="O2",z_e_O2,NA()))*F_const)),"") | J26: =IFERROR(INDEX(ReactorTypeList,MATCH(C26,ReactorList,0)),"")
I27: =IFERROR(((G27-pw_A*EXP(pw_B*F27/(F27+pw_C)))*(E27/1000000)/(R_gas*(F27+T_zero_C)))/(D27/(IF(H27="H2",z_e_H2,IF(H27="O2",z_e_O2,NA()))*F_const)),"") | J27: =IFERROR(INDEX(ReactorTypeList,MATCH(C27,ReactorList,0)),"")
I28: =IFERROR(((G28-pw_A*EXP(pw_B*F28/(F28+pw_C)))*(E28/1000000)/(R_gas*(F28+T_zero_C)))/(D28/(IF(H28="H2",z_e_H2,IF(H28="O2",z_e_O2,NA()))*F_const)),"") | J28: =IFERROR(INDEX(ReactorTypeList,MATCH(C28,ReactorList,0)),"")
I29: =IFERROR(((G29-pw_A*EXP(pw_B*F29/(F29+pw_C)))*(E29/1000000)/(R_gas*(F29+T_zero_C)))/(D29/(IF(H29="H2",z_e_H2,IF(H29="O2",z_e_O2,NA()))*F_const)),"") | J29: =IFERROR(INDEX(ReactorTypeList,MATCH(C29,ReactorList,0)),"")
I30: =IFERROR(((G30-pw_A*EXP(pw_B*F30/(F30+pw_C)))*(E30/1000000)/(R_gas*(F30+T_zero_C)))/(D30/(IF(H30="H2",z_e_H2,IF(H30="O2",z_e_O2,NA()))*F_const)),"") | J30: =IFERROR(INDEX(ReactorTypeList,MATCH(C30,ReactorList,0)),"")
A31: Value in use - cathode (H2) | C31: - | D31: =IFERROR(AVERAGEIFS(I23:I30,C23:C30,Reactor_sel,K23:K30,"y",H23:H30,"H2"),"no included runs — model uses its default") -> no included runs — model uses its default
A32: Value in use - anode (O2) | C32: - | D32: =IFERROR(AVERAGEIFS(I23:I30,C23:C30,Reactor_sel,K23:K30,"y",H23:H30,"O2"),"no included runs — model uses its default") -> no included runs — model uses its default
A35: =HYPERLINK("https://github.com/amy-bo/electroPioreactor/blob/AEP02/Media/protocols/surface-kla.md","SURFACE kLa (oxygen surface transfer)") -> SURFACE kLa (oxygen surface transfer)
A36: Value in use: average of the included kLa runs for the active reactor.
A37: Researcher | B37: Date | C37: Reactor | D37: kLa | E37: Type (auto) | F37: Include? | G37: Notes
E38: =IFERROR(INDEX(ReactorTypeList,MATCH(C38,ReactorList,0)),"")
E39: =IFERROR(INDEX(ReactorTypeList,MATCH(C39,ReactorList,0)),"")
E40: =IFERROR(INDEX(ReactorTypeList,MATCH(C40,ReactorList,0)),"")
E41: =IFERROR(INDEX(ReactorTypeList,MATCH(C41,ReactorList,0)),"")
E42: =IFERROR(INDEX(ReactorTypeList,MATCH(C42,ReactorList,0)),"")
E43: =IFERROR(INDEX(ReactorTypeList,MATCH(C43,ReactorList,0)),"")
E44: =IFERROR(INDEX(ReactorTypeList,MATCH(C44,ReactorList,0)),"")
E45: =IFERROR(INDEX(ReactorTypeList,MATCH(C45,ReactorList,0)),"")
A46: Value in use - kLa | C46: 1/h | D46: =IFERROR(AVERAGEIFS(D38:D45,C38:C45,Reactor_sel,F38:F45,"y"),"no included runs — model uses its default") -> no included runs — model uses its default
A49: =HYPERLINK("https://github.com/amy-bo/electroPioreactor/blob/AEP02/Media/protocols/flow-calibration.md","CO2 FLOW (dosing flow rate)") -> CO2 FLOW (dosing flow rate)
A50: Value in use: the most recent included measurement for the active reactor (a flow rate is a valve/hardware setting, so the latest reading replaces older ones). An included flow here calibrates the reactor on its own (no CO2 flows row needed). Min pulse (column J, optional): the shortest commanded pulse that still delivers a repeatable volume; the latest included entry sets the solenoid floor (row 61).
A51: Researcher | B51: Date | C51: Reactor | D51: CO2 volume | E51: Time | F51: Flow (computed) | G51: Type (auto) | H51: Include? | I51: Notes | J51: Min pulse (s)
F52: =IFERROR(D52/E52,"") | G52: =IFERROR(INDEX(ReactorTypeList,MATCH(C52,ReactorList,0)),"")
F53: =IFERROR(D53/E53,"") | G53: =IFERROR(INDEX(ReactorTypeList,MATCH(C53,ReactorList,0)),"")
F54: =IFERROR(D54/E54,"") | G54: =IFERROR(INDEX(ReactorTypeList,MATCH(C54,ReactorList,0)),"")
F55: =IFERROR(D55/E55,"") | G55: =IFERROR(INDEX(ReactorTypeList,MATCH(C55,ReactorList,0)),"")
F56: =IFERROR(D56/E56,"") | G56: =IFERROR(INDEX(ReactorTypeList,MATCH(C56,ReactorList,0)),"")
F57: =IFERROR(D57/E57,"") | G57: =IFERROR(INDEX(ReactorTypeList,MATCH(C57,ReactorList,0)),"")
F58: =IFERROR(D58/E58,"") | G58: =IFERROR(INDEX(ReactorTypeList,MATCH(C58,ReactorList,0)),"")
F59: =IFERROR(D59/E59,"") | G59: =IFERROR(INDEX(ReactorTypeList,MATCH(C59,ReactorList,0)),"")
A60: Value in use - flow rate | C60: mL/s | D60: =IFERROR(AVERAGEIFS(F52:F59,C52:C59,Reactor_sel,H52:H59,"y",B52:B59,SUMPRODUCT(MAX((C52:C59=Reactor_sel)*(H52:H59="y")*B52:B59))),"no included runs — model uses its default") -> no included runs — model uses its default
A61: Value in use - minimum reliable pulse | C61: s | D61: =IFERROR(AVERAGEIFS(J52:J59,C52:C59,Reactor_sel,H52:H59,"y",J52:J59,">0",B52:B59,SUMPRODUCT(MAX((C52:C59=Reactor_sel)*(H52:H59="y")*(J52:J59>0)*B52:B59))),"no included runs — model uses its default") -> no included runs — model uses its default
A63: =HYPERLINK("https://github.com/amy-bo/electroPioreactor/blob/AEP02/Media/protocols/vial-geometry.md","VIAL GEOMETRY (true volume & bore depth)") -> VIAL GEOMETRY (true volume & bore depth)
A64: Value in use: average across included vials of the active reactor type (all vials of a type are nominally identical). Headspace and total volume feed the model; the volume-equivalent depth (D75) is reported for the geometry check only, because a tapered vial’s equivalent depth is not its physical depth.
A65: Researcher | B65: Date | C65: Reactor | D65: Headspace mass | E65: Body mass | F65: Temp | G65: V total (computed) | H65: Volume-equivalent depth (computed) | I65: Type (auto) | J65: Include? | K65: Notes | L65: Headspace (computed) | M65: Working-fill mass | N65: Working fill (computed)
G66: =IF(E66="","",IFERROR(E66/((ca_rho_0+ca_rho_k*F66)/1000),"")) | H66: =IF(E66="","",IFERROR((E66/((ca_rho_0+ca_rho_k*F66)/1000))*1000/A_x,"")) | I66: =IFERROR(INDEX(ReactorTypeList,MATCH(C66,ReactorList,0)),"") | L66: =IF(D66="","",IFERROR(D66/((ca_rho_0+ca_rho_k*F66)/1000),"")) | N66: =IF(M66="","",IFERROR(M66/((ca_rho_0+ca_rho_k*F66)/1000),""))
G67: =IF(E67="","",IFERROR(E67/((ca_rho_0+ca_rho_k*F67)/1000),"")) | H67: =IF(E67="","",IFERROR((E67/((ca_rho_0+ca_rho_k*F67)/1000))*1000/A_x,"")) | I67: =IFERROR(INDEX(ReactorTypeList,MATCH(C67,ReactorList,0)),"") | L67: =IF(D67="","",IFERROR(D67/((ca_rho_0+ca_rho_k*F67)/1000),"")) | N67: =IF(M67="","",IFERROR(M67/((ca_rho_0+ca_rho_k*F67)/1000),""))
G68: =IF(E68="","",IFERROR(E68/((ca_rho_0+ca_rho_k*F68)/1000),"")) | H68: =IF(E68="","",IFERROR((E68/((ca_rho_0+ca_rho_k*F68)/1000))*1000/A_x,"")) | I68: =IFERROR(INDEX(ReactorTypeList,MATCH(C68,ReactorList,0)),"") | L68: =IF(D68="","",IFERROR(D68/((ca_rho_0+ca_rho_k*F68)/1000),"")) | N68: =IF(M68="","",IFERROR(M68/((ca_rho_0+ca_rho_k*F68)/1000),""))
G69: =IF(E69="","",IFERROR(E69/((ca_rho_0+ca_rho_k*F69)/1000),"")) | H69: =IF(E69="","",IFERROR((E69/((ca_rho_0+ca_rho_k*F69)/1000))*1000/A_x,"")) | I69: =IFERROR(INDEX(ReactorTypeList,MATCH(C69,ReactorList,0)),"") | L69: =IF(D69="","",IFERROR(D69/((ca_rho_0+ca_rho_k*F69)/1000),"")) | N69: =IF(M69="","",IFERROR(M69/((ca_rho_0+ca_rho_k*F69)/1000),""))
G70: =IF(E70="","",IFERROR(E70/((ca_rho_0+ca_rho_k*F70)/1000),"")) | H70: =IF(E70="","",IFERROR((E70/((ca_rho_0+ca_rho_k*F70)/1000))*1000/A_x,"")) | I70: =IFERROR(INDEX(ReactorTypeList,MATCH(C70,ReactorList,0)),"") | L70: =IF(D70="","",IFERROR(D70/((ca_rho_0+ca_rho_k*F70)/1000),"")) | N70: =IF(M70="","",IFERROR(M70/((ca_rho_0+ca_rho_k*F70)/1000),""))
G71: =IF(E71="","",IFERROR(E71/((ca_rho_0+ca_rho_k*F71)/1000),"")) | H71: =IF(E71="","",IFERROR((E71/((ca_rho_0+ca_rho_k*F71)/1000))*1000/A_x,"")) | I71: =IFERROR(INDEX(ReactorTypeList,MATCH(C71,ReactorList,0)),"") | L71: =IF(D71="","",IFERROR(D71/((ca_rho_0+ca_rho_k*F71)/1000),"")) | N71: =IF(M71="","",IFERROR(M71/((ca_rho_0+ca_rho_k*F71)/1000),""))
G72: =IF(E72="","",IFERROR(E72/((ca_rho_0+ca_rho_k*F72)/1000),"")) | H72: =IF(E72="","",IFERROR((E72/((ca_rho_0+ca_rho_k*F72)/1000))*1000/A_x,"")) | I72: =IFERROR(INDEX(ReactorTypeList,MATCH(C72,ReactorList,0)),"") | L72: =IF(D72="","",IFERROR(D72/((ca_rho_0+ca_rho_k*F72)/1000),"")) | N72: =IF(M72="","",IFERROR(M72/((ca_rho_0+ca_rho_k*F72)/1000),""))
G73: =IF(E73="","",IFERROR(E73/((ca_rho_0+ca_rho_k*F73)/1000),"")) | H73: =IF(E73="","",IFERROR((E73/((ca_rho_0+ca_rho_k*F73)/1000))*1000/A_x,"")) | I73: =IFERROR(INDEX(ReactorTypeList,MATCH(C73,ReactorList,0)),"") | L73: =IF(D73="","",IFERROR(D73/((ca_rho_0+ca_rho_k*F73)/1000),"")) | N73: =IF(M73="","",IFERROR(M73/((ca_rho_0+ca_rho_k*F73)/1000),""))
A74: Value in use - total vial volume | C74: mL | D74: =IFERROR(AVERAGEIFS(G66:G73,I66:I73,rx_ver,J66:J73,"y"),"no included runs — model uses its default") -> no included runs — model uses its default
A75: Value in use - volume-equivalent depth (body volume ÷ A_x; not the physical depth) | C75: mm | D75: =IFERROR(AVERAGEIFS(H66:H73,I66:I73,rx_ver,J66:J73,"y"),"no included runs — model uses its default") -> no included runs — model uses its default
A76: Value in use - headspace at working fill | C76: mL | D76: =IFERROR(AVERAGEIFS(L66:L73,I66:I73,rx_ver,J66:J73,"y"),"no included runs — model uses its default") -> no included runs — model uses its default
A77: Value in use - working fill behind that headspace | C77: mL | D77: =IFERROR(AVERAGEIFS(N66:N73,I66:I73,rx_ver,J66:J73,"y"),"no included runs — model uses its default") -> no included runs — model uses its default
A78: =HYPERLINK("https://github.com/amy-bo/electroPioreactor/blob/AEP02/Media/protocols/sinter-porosity.md","SINTER POROSITY (sparger frit grade)") -> SINTER POROSITY (sparger frit grade)
A79: Value in use: the bubble points of the most recent included runs for the active reactor are averaged first (D90) and then graded once (D89), so conflicting runs never average into a fractional grade; a pore size outside the listed DURAN classes is reported and the model keeps its default.
A80: Researcher | B80: Date | C80: Reactor | D80: Bubble-point | E80: Grade (computed) | F80: Type (auto) | G80: Include? | H80: Notes
E81: =IF(D81="","",IFERROR(IF((bp_const/D81)>por_p0_hi,"above P0 – not a listed grade",IF((bp_const/D81)>por_break_1,0,IF((bp_const/D81)>por_break_2,1,IF((bp_const/D81)>por_break_3,2,IF((bp_const/D81)>por_break_4,3,IF((bp_const/D81)>=por_break_5,4,IF(AND((bp_const/D81)>=por_p5_lo,(bp_const/D81)<=por_p5_hi),5,"between or below the listed grades – not used"))))))),"")) | F81: =IFERROR(INDEX(ReactorTypeList,MATCH(C81,ReactorList,0)),"")
E82: =IF(D82="","",IFERROR(IF((bp_const/D82)>por_p0_hi,"above P0 – not a listed grade",IF((bp_const/D82)>por_break_1,0,IF((bp_const/D82)>por_break_2,1,IF((bp_const/D82)>por_break_3,2,IF((bp_const/D82)>por_break_4,3,IF((bp_const/D82)>=por_break_5,4,IF(AND((bp_const/D82)>=por_p5_lo,(bp_const/D82)<=por_p5_hi),5,"between or below the listed grades – not used"))))))),"")) | F82: =IFERROR(INDEX(ReactorTypeList,MATCH(C82,ReactorList,0)),"")
E83: =IF(D83="","",IFERROR(IF((bp_const/D83)>por_p0_hi,"above P0 – not a listed grade",IF((bp_const/D83)>por_break_1,0,IF((bp_const/D83)>por_break_2,1,IF((bp_const/D83)>por_break_3,2,IF((bp_const/D83)>por_break_4,3,IF((bp_const/D83)>=por_break_5,4,IF(AND((bp_const/D83)>=por_p5_lo,(bp_const/D83)<=por_p5_hi),5,"between or below the listed grades – not used"))))))),"")) | F83: =IFERROR(INDEX(ReactorTypeList,MATCH(C83,ReactorList,0)),"")
E84: =IF(D84="","",IFERROR(IF((bp_const/D84)>por_p0_hi,"above P0 – not a listed grade",IF((bp_const/D84)>por_break_1,0,IF((bp_const/D84)>por_break_2,1,IF((bp_const/D84)>por_break_3,2,IF((bp_const/D84)>por_break_4,3,IF((bp_const/D84)>=por_break_5,4,IF(AND((bp_const/D84)>=por_p5_lo,(bp_const/D84)<=por_p5_hi),5,"between or below the listed grades – not used"))))))),"")) | F84: =IFERROR(INDEX(ReactorTypeList,MATCH(C84,ReactorList,0)),"")
E85: =IF(D85="","",IFERROR(IF((bp_const/D85)>por_p0_hi,"above P0 – not a listed grade",IF((bp_const/D85)>por_break_1,0,IF((bp_const/D85)>por_break_2,1,IF((bp_const/D85)>por_break_3,2,IF((bp_const/D85)>por_break_4,3,IF((bp_const/D85)>=por_break_5,4,IF(AND((bp_const/D85)>=por_p5_lo,(bp_const/D85)<=por_p5_hi),5,"between or below the listed grades – not used"))))))),"")) | F85: =IFERROR(INDEX(ReactorTypeList,MATCH(C85,ReactorList,0)),"")
E86: =IF(D86="","",IFERROR(IF((bp_const/D86)>por_p0_hi,"above P0 – not a listed grade",IF((bp_const/D86)>por_break_1,0,IF((bp_const/D86)>por_break_2,1,IF((bp_const/D86)>por_break_3,2,IF((bp_const/D86)>por_break_4,3,IF((bp_const/D86)>=por_break_5,4,IF(AND((bp_const/D86)>=por_p5_lo,(bp_const/D86)<=por_p5_hi),5,"between or below the listed grades – not used"))))))),"")) | F86: =IFERROR(INDEX(ReactorTypeList,MATCH(C86,ReactorList,0)),"")
E87: =IF(D87="","",IFERROR(IF((bp_const/D87)>por_p0_hi,"above P0 – not a listed grade",IF((bp_const/D87)>por_break_1,0,IF((bp_const/D87)>por_break_2,1,IF((bp_const/D87)>por_break_3,2,IF((bp_const/D87)>por_break_4,3,IF((bp_const/D87)>=por_break_5,4,IF(AND((bp_const/D87)>=por_p5_lo,(bp_const/D87)<=por_p5_hi),5,"between or below the listed grades – not used"))))))),"")) | F87: =IFERROR(INDEX(ReactorTypeList,MATCH(C87,ReactorList,0)),"")
E88: =IF(D88="","",IFERROR(IF((bp_const/D88)>por_p0_hi,"above P0 – not a listed grade",IF((bp_const/D88)>por_break_1,0,IF((bp_const/D88)>por_break_2,1,IF((bp_const/D88)>por_break_3,2,IF((bp_const/D88)>por_break_4,3,IF((bp_const/D88)>=por_break_5,4,IF(AND((bp_const/D88)>=por_p5_lo,(bp_const/D88)<=por_p5_hi),5,"between or below the listed grades – not used"))))))),"")) | F88: =IFERROR(INDEX(ReactorTypeList,MATCH(C88,ReactorList,0)),"")
A89: Value in use - porosity grade | C89: 0-5 | D89: =IF(NOT(ISNUMBER(cal_bp)),"no included runs — model uses its default",IF((bp_const/cal_bp)>por_p0_hi,"above P0 – not a listed grade; model uses its default",IF((bp_const/cal_bp)>por_break_1,0,IF((bp_const/cal_bp)>por_break_2,1,IF((bp_const/cal_bp)>por_break_3,2,IF((bp_const/cal_bp)>por_break_4,3,IF((bp_const/cal_bp)>=por_break_5,4,IF(AND((bp_const/cal_bp)>=por_p5_lo,(bp_const/cal_bp)<=por_p5_hi),5,"between or below the listed grades; model uses its default")))))))) -> no included runs — model uses its default
A90: Value in use - bubble point (mean of the latest included runs) | C90: kPa | D90: =IFERROR(AVERAGEIFS(D81:D88,C81:C88,Reactor_sel,G81:G88,"y",B81:B88,SUMPRODUCT(MAX((C81:C88=Reactor_sel)*(G81:G88="y")*B81:B88))),"no included runs — model uses its default") -> no included runs — model uses its default
A92: =HYPERLINK("https://github.com/amy-bo/electroPioreactor/blob/AEP02/Media/protocols/dissolved-oxygen.md","DISSOLVED-OXYGEN THRESHOLDS (per organism)") -> DISSOLVED-OXYGEN THRESHOLDS (per organism)
A93: Value in use: average of the included values for the active organism.
A94: Researcher | B94: Date | C94: Organism | D94: Min DO | E94: Optimum DO | F94: Impairment DO | G94: Toxic DO | H94: Include? | I94: Notes
A103: Value in use - minimum DO | C103: mg/L | D103: =IFERROR(AVERAGEIFS(D95:D102,C95:C102,organism_sel,H95:H102,"y"),"no included runs — model uses its default") -> no included runs — model uses its default
A104: Value in use - optimum DO | C104: mg/L | D104: =IFERROR(AVERAGEIFS(E95:E102,C95:C102,organism_sel,H95:H102,"y"),"no included runs — model uses its default") -> no included runs — model uses its default
A105: Value in use - impairment DO | C105: mg/L | D105: =IFERROR(AVERAGEIFS(F95:F102,C95:C102,organism_sel,H95:H102,"y"),"no included runs — model uses its default") -> no included runs — model uses its default
A106: Value in use - toxic DO | C106: mg/L | D106: =IFERROR(AVERAGEIFS(G95:G102,C95:C102,organism_sel,H95:H102,"y"),"no included runs — model uses its default") -> no included runs — model uses its default
A109: =HYPERLINK("https://github.com/amy-bo/electroPioreactor/blob/AEP02/Media/protocols/knallgas-stoichiometry.md","KNALLGAS UPTAKE RATIO (per organism)") -> KNALLGAS UPTAKE RATIO (per organism)
A110: Value in use: each included run is reduced to O₂ per H₂ and CO₂ per H₂ (columns I–J), the ratios are averaged over the included runs for the active organism, and the model takes them on an H₂ basis of knall_H2_basis (D199), so a run’s size does not weight the result.
A111: Researcher | B111: Date | C111: Organism | D111: H2 | E111: O2 | F111: CO2 | G111: Include? | H111: Notes | I111: O₂ per H₂ (computed) | J111: CO₂ per H₂ (computed)
I112: =IF(OR(D112="",E112=""),"",IFERROR(IF(D112>0,E112/D112,""),"")) | J112: =IF(OR(D112="",F112=""),"",IFERROR(IF(D112>0,F112/D112,""),""))
I113: =IF(OR(D113="",E113=""),"",IFERROR(IF(D113>0,E113/D113,""),"")) | J113: =IF(OR(D113="",F113=""),"",IFERROR(IF(D113>0,F113/D113,""),""))
I114: =IF(OR(D114="",E114=""),"",IFERROR(IF(D114>0,E114/D114,""),"")) | J114: =IF(OR(D114="",F114=""),"",IFERROR(IF(D114>0,F114/D114,""),""))
I115: =IF(OR(D115="",E115=""),"",IFERROR(IF(D115>0,E115/D115,""),"")) | J115: =IF(OR(D115="",F115=""),"",IFERROR(IF(D115>0,F115/D115,""),""))
I116: =IF(OR(D116="",E116=""),"",IFERROR(IF(D116>0,E116/D116,""),"")) | J116: =IF(OR(D116="",F116=""),"",IFERROR(IF(D116>0,F116/D116,""),""))
I117: =IF(OR(D117="",E117=""),"",IFERROR(IF(D117>0,E117/D117,""),"")) | J117: =IF(OR(D117="",F117=""),"",IFERROR(IF(D117>0,F117/D117,""),""))
I118: =IF(OR(D118="",E118=""),"",IFERROR(IF(D118>0,E118/D118,""),"")) | J118: =IF(OR(D118="",F118=""),"",IFERROR(IF(D118>0,F118/D118,""),""))
I119: =IF(OR(D119="",E119=""),"",IFERROR(IF(D119>0,E119/D119,""),"")) | J119: =IF(OR(D119="",F119=""),"",IFERROR(IF(D119>0,F119/D119,""),""))
...

Sheet AMYBO03
A2: AMYBO03 - Teo final minimal medium
A3: Source: Teo Reid, MRes Thesis Final, Table 2 and Medium section, PDF page 10.
A5: Base medium | B5: Formula | C5: g per L H2O | D5: MW g/mol | E5: Calculated mM | F5: Thesis mM
A6: Disodium hydrogen phosphate | B6: Na2HPO4 | C6: =amy_Na2HPO4_gL -> 4.26 | D6: =amy_Na2HPO4_MW -> 141.96 | E6: =amy_Na2HPO4_gL/amy_Na2HPO4_MW*1000 -> 30.008453 | F6: =amy_Na2HPO4_thesis_mM -> 30
A7: Sodium dihydrogen phosphate dihydrate | B7: NaH2PO4·2H2O | C7: =amy_NaH2PO4_gL -> 4.68 | D7: =amy_NaH2PO4_MW -> 156.01 | E7: =amy_NaH2PO4_gL/amy_NaH2PO4_MW*1000 -> 29.998077 | F7: =amy_NaH2PO4_thesis_mM -> 30
A8: Potassium sulfate | B8: K2SO4 | C8: =amy_K2SO4_gL -> 0.17 | D8: =amy_K2SO4_MW -> 174.26 | E8: =amy_K2SO4_gL/amy_K2SO4_MW*1000 -> 0.97555377 | F8: =amy_K2SO4_thesis_mM -> 0.98
A9: Calcium sulfate dihydrate | B9: CaSO4·2H2O | C9: =amy_CaSO4_gL -> 0.097 | D9: =amy_CaSO4_MW -> 172.17 | E9: =amy_CaSO4_gL/amy_CaSO4_MW*1000 -> 0.56339664 | F9: =amy_CaSO4_thesis_mM -> 0.56
A10: Magnesium sulfate heptahydrate | B10: MgSO4·7H2O | C10: =amy_MgSO4_gL -> 0.8 | D10: =amy_MgSO4_MW -> 246.48 | E10: =amy_MgSO4_gL/amy_MgSO4_MW*1000 -> 3.2456994 | F10: =amy_MgSO4_thesis_mM -> 3.25
A11: Ammonium sulfate | B11: (NH4)2SO4 | C11: =amy_NH4SO4_gL -> 0.943 | D11: =amy_NH4SO4_MW -> 132.14 | E11: =amy_NH4SO4_gL/amy_NH4SO4_MW*1000 -> 7.1363705 | F11: =amy_NH4SO4_thesis_mM -> 7.14
A12: Sodium bicarbonate | B12: NaHCO3 | C12: =amy_NaHCO3_gL -> 3.36 | D12: =amy_NaHCO3_MW -> 84.007 | E12: =amy_NaHCO3_gL/amy_NaHCO3_MW*1000 -> 39.996667 | F12: =amy_NaHCO3_thesis_mM -> 40
A14: Stock additions | B14: mL per L base | C14: Use
A15: Iron solution | B15: =amy_Fe_dose -> 0.68 | C15: Required
A16: Trace mineral solution | B16: =amy_TM_dose -> 0.05 | C16: Required
A17: Sodium gluconate solution | B17: =amy_gluconate_stock_dose -> 50 | C17: Optional, growth with carbon source
A18: Model basis | B18: =amy_organic_C_used -> 0 | C18: Carbon-free base plus required stocks; optional gluconate excluded
A20: Iron stock | B20: Formula | C20: g per L H2O | D20: MW g/mol | E20: Stock mM | F20: Dose mL/L | G20: Calculated final µM | H20: Thesis final µM | I20: Thesis stock mM
A21: Iron(II) sulfate heptahydrate | B21: FeSO4·7H2O | C21: =amy_FeSO4_gL -> 15 | D21: =amy_FeSO4_MW -> 278.01 | E21: =amy_FeSO4_gL/amy_FeSO4_MW*1000 -> 53.954894 | F21: =amy_Fe_dose -> 0.68 | G21: =amy_FeSO4_mM*amy_FeSO4_dose -> 36.689328 | H21: =amy_FeSO4_thesis_final -> 36.7 | I21: =amy_FeSO4_thesis_stock -> 54
A22: Sulfuric acid | B22: H2SO4 | D22: =amy_Fe_acid_MW -> 98.079 | E22: =amy_Fe_acid_mM -> 200 | F22: =amy_Fe_dose -> 0.68 | G22: =amy_Fe_acid_mM*amy_Fe_acid_dose -> 136 | H22: =amy_Fe_acid_thesis_final -> 140 | I22: =amy_Fe_acid_thesis_stock -> 200
A24: Trace mineral stock | B24: Formula | C24: g per L H2O | D24: MW g/mol | E24: Stock mM | F24: Dose mL/L | G24: Calculated final µM | H24: Thesis final µM | I24: Thesis stock mM
A25: Sodium molybdate dihydrate | B25: Na2MoO4·2H2O | C25: =amy_Na2MoO4_gL -> 1.8 | D25: =amy_Na2MoO4_MW -> 241.95 | E25: =amy_Na2MoO4_gL/amy_Na2MoO4_MW*1000 -> 7.4395536 | F25: =amy_TM_dose -> 0.05 | G25: =amy_Na2MoO4_mM*amy_Na2MoO4_dose -> 0.37197768 | H25: =amy_Na2MoO4_thesis_final -> 0.37 | I25: =amy_Na2MoO4_thesis_stock -> 7.44
A26: Zinc sulfate heptahydrate | B26: ZnSO4·7H2O | C26: =amy_ZnSO4_gL -> 2.4 | D26: =amy_ZnSO4_MW -> 287.54 | E26: =amy_ZnSO4_gL/amy_ZnSO4_MW*1000 -> 8.3466648 | F26: =amy_TM_dose -> 0.05 | G26: =amy_ZnSO4_mM*amy_ZnSO4_dose -> 0.41733324 | H26: =amy_ZnSO4_thesis_final -> 0.42 | I26: =amy_ZnSO4_thesis_stock -> 8.35
A27: Manganese(II) sulfate monohydrate | B27: MnSO4·H2O | C27: =amy_MnSO4_gL -> 2.4 | D27: =amy_MnSO4_MW -> 169.02 | E27: =amy_MnSO4_gL/amy_MnSO4_MW*1000 -> 14.199503 | F27: =amy_TM_dose -> 0.05 | G27: =amy_MnSO4_mM*amy_MnSO4_dose -> 0.70997515 | H27: =amy_MnSO4_thesis_final -> 0.71 | I27: =amy_MnSO4_thesis_stock -> 14.2
A28: Copper(II) sulfate pentahydrate | B28: CuSO4·5H2O | C28: =amy_CuSO4_gL -> 0.48 | D28: =amy_CuSO4_MW -> 249.68 | E28: =amy_CuSO4_gL/amy_CuSO4_MW*1000 -> 1.9224607 | F28: =amy_TM_dose -> 0.05 | G28: =amy_CuSO4_mM*amy_CuSO4_dose -> 0.096123037 | H28: =amy_CuSO4_thesis_final -> 0.096 | I28: =amy_CuSO4_thesis_stock -> 1.92
A29: Nickel(II) sulfate hexahydrate | B29: NiSO4·6H2O | C29: =amy_NiSO4_gL -> 1.5 | D29: =amy_NiSO4_MW -> 262.85 | E29: =amy_NiSO4_gL/amy_NiSO4_MW*1000 -> 5.7066768 | F29: =amy_TM_dose -> 0.05 | G29: =amy_NiSO4_mM*amy_NiSO4_dose -> 0.28533384 | H29: =amy_NiSO4_thesis_final -> 0.29 | I29: =amy_NiSO4_thesis_stock -> 5.71
A30: Cobalt(II) sulfate heptahydrate | B30: CoSO4·7H2O | C30: =amy_CoSO4_gL -> 0.0402 | D30: =amy_CoSO4_MW -> 281.1 | E30: =amy_CoSO4_gL/amy_CoSO4_MW*1000 -> 0.14300961 | F30: =amy_TM_dose -> 0.05 | G30: =amy_CoSO4_mM*amy_CoSO4_dose -> 0.0071504803 | H30: =amy_CoSO4_thesis_final -> 0.0072 | I30: =amy_CoSO4_thesis_stock -> 0.143
A31: Sulfuric acid | B31: H2SO4 | D31: =amy_TM_acid_MW -> 98.079 | E31: =amy_TM_acid_mM -> 200 | F31: =amy_TM_dose -> 0.05 | G31: =amy_TM_acid_mM*amy_TM_acid_dose -> 10 | H31: =amy_TM_acid_thesis_final -> 10 | I31: =amy_TM_acid_thesis_stock -> 200
A33: Optional carbon stock | B33: Formula | C33: g per L H2O | D33: MW g/mol | E33: Stock mM | F33: Dose mL/L | G33: Calculated final mM | H33: Thesis final mM | I33: Thesis stock mM
A34: Sodium gluconate | B34: C6H11NaO7 | C34: =amy_gluconate_gL -> 100 | D34: =amy_gluconate_MW -> 218.14 | E34: =amy_gluconate_gL/amy_gluconate_MW*1000 -> 458.4212 | F34: =amy_gluconate_stock_dose -> 50 | G34: =amy_gluconate_mM*amy_gluconate_dose/1000 -> 22.92106 | H34: =amy_gluconate_thesis_final -> 23 | I34: =amy_gluconate_thesis_stock -> 460
A36: Preparation and interpretation
A37: Make the base, iron, trace mineral and sodium gluconate solutions separately.
A38: Filter-sterilize each solution separately. Autoclaving changed the hue of some solutions.
A39: Add 0.68 mL iron stock and 0.05 mL trace mineral stock to 1 L base medium.
A40: For growth with a carbon source, add 50 mL sodium gluconate stock to 1 L base medium.
A41: Each acidified stock contains 11 mL concentrated sulfuric acid per L H2O; the thesis gives 0.2 M.
A42: Sulfuric acid aids iron and trace-mineral solubility. Iron was kept separate because it may reduce shelf life.
A43: Sodium gluconate stock: 10% w/v (0.46 M). Thesis nominal supplemented medium: 0.5% w/v (23 mM).
A44: Amounts and rounded thesis concentrations are both retained. Model calculations use weighed masses and stated doses.
A45: Basis: nominal amounts per L base medium. Stocks add 0.73 mL; with carbon stock they add 50.73 mL.
A46: If volumes are additive, divide nominal final concentrations by 1.00073 (carbon-free) or 1.05073 (with carbon).
A47: AMYBO03 selection uses carbon-free medium. Gluconate is documented here; organic-carbon growth is outside this gas model.
... A50: No vitamins are specified in Table 2. No extra ingredients or pH-adjustment reagents have been inferred.
A53: Model inputs | B53: Symbol | C53: mol/L unless stated | D53: Value
A54: Total phosphate | B54: PT_AMYBO03 | C54: mol/L | D54: =SUM(amy_Na2HPO4_mM,amy_NaH2PO4_mM)/1000 -> 0.06000653 | E54: Total analytical phosphate from the two weighed salts.
A55: Strong-ion difference | B55: SID_AMYBO03 | C55: mol/L | D55: =(2*amy_Na2HPO4_mM+amy_NaH2PO4_mM+amy_NaHCO3_mM+2*amy_K2SO4_mM+2*amy_CaSO4_mM+2*amy_MgSO4_mM)/1000-2*(amy_K2SO4_mM+amy_CaSO4_mM+amy_MgSO4_mM+amy_NH4SO4_mM)/1000-2*(amy_Fe_acid_final_uM+amy_TM_acid_final_uM)/1000000 -> 0.11544691 | E55: Strong cations minus sulfate; NH4 handled separately. Stock acid removes two equivalents per mole.
A56: Total ammonium | B56: NT_AMYBO03 | C56: mol/L | D56: =2*amy_NH4SO4_mM/1000 -> 0.014272741 | E56: Two ammonium ions per mole of ammonium sulfate.
A57: Chloride | B57: Cl_AMYBO03 | C57: mol/L | D57: 0 | E57: No chloride-bearing ingredient in the stated carbon-free recipe.
A58: Ideal conductivity (major ions) | B58: kappa0_AMYBO03 | C58: S/m | D58: =((2*amy_Na2HPO4_mM+amy_NaH2PO4_mM+amy_NaHCO3_mM)/1000*Chemistry!lam_Na+2*amy_K2SO4_mM/1000*Chemistry!lam_K+2*amy_NH4SO4_mM/1000*Chemistry!lam_NH4+amy_MgSO4_mM/1000*Chemistry!lam_Mg+amy_CaSO4_mM/1000*Chemistry!lam_Ca+amy_Na2HPO4_mM/1000*Chemistry!lam_HPO4+amy_NaH2PO4_mM/1000*Chemistry!lam_H2PO4+((SUM(amy_K2SO4_mM,amy_CaSO4_mM,amy_MgSO4_mM,amy_NH4SO4_mM)/1000)+(amy_FeSO4_final_uM+amy_Fe_acid_final_uM+SUM(amy_ZnSO4_final_uM,amy_MnSO4_final_uM,amy_CuSO4_final_uM,amy_NiSO4_final_uM,amy_CoSO4_final_uM,amy_TM_acid_final_uM))/1000000)*Chemistry!lam_SO4+amy_NaHCO3_mM/1000*Chemistry!lam_HCO3)/10 -> 1.6332034 | E58: Major-ion conductivity approximation; trace sulfate retained, trace cation mobilities/complexation omitted. Measure conductivity.
A59: Ionic strength (as-weighed salts) | B59: I_AMYBO03 | C59: mol/L | D59: =3*amy_Na2HPO4_mM/1000+amy_NaH2PO4_mM/1000+3*amy_K2SO4_mM/1000+4*(amy_CaSO4_mM+amy_MgSO4_mM)/1000+3*amy_NH4SO4_mM/1000+amy_NaHCO3_mM/1000+4*(amy_FeSO4_final_uM+SUM(amy_ZnSO4_final_uM,amy_MnSO4_final_uM,amy_CuSO4_final_uM,amy_NiSO4_final_uM,amy_CoSO4_final_uM))/1000000+3*amy_Na2MoO4_final_uM/1000000+3*(amy_Fe_acid_final_uM+amy_TM_acid_final_uM)/1000000 -> 0.2001842 | E59: As-weighed analytical ionic strength, not solved speciation. Includes complete trace salts and stock acid on this convention.
A61: SID = strong cations (Na⁺, K⁺, Mg²⁺, Ca²⁺) − strong anions (all sulfate), as MC02 (Chemistry D36); NH₄⁺ enters through NT. Sulfuric acid removes two equivalents per mole. Trace metal sulfates and molybdate cancel.
A62: Ionic strength follows the workbook as-weighed convention; acid contributes 2H+ + SO4²-. Speciation changes are not resolved here.
A64: Recipe tables above are calculated views. Edit the blue named inputs below; chemistry exports remain in rows 54–59.
A70: Parameter | B70: Defined name | C70: Unit | D70: Value | E70: Source / confidence
A71: Disodium hydrogen phosphate – weighed concentration | B71: amy_Na2HPO4_gL | C71: g/L | D71: 4.26 | E71: Teo Reid, MRes Thesis, Table 2 / Medium section (PDF p10); nominal per litre of base. Rounded thesis values retained for comparison.
A72: Disodium hydrogen phosphate – molar mass | B72: amy_Na2HPO4_MW | C72: g/mol | D72: 141.96 | E72: Formula molar mass, g/mol; hydrate state as stated in Teo Reid Table 2.
A73: Disodium hydrogen phosphate – thesis concentration | B73: amy_Na2HPO4_thesis_mM | C73: mmol/L | D73: 30 | E73: Teo Reid, MRes Thesis, Table 2 / Medium section (PDF p10); nominal per litre of base. Rounded thesis values retained for comparison.
A74: Sodium dihydrogen phosphate dihydrate – weighed concentration | B74: amy_NaH2PO4_gL | C74: g/L | D74: 4.68 | E74: Teo Reid, MRes Thesis, Table 2 / Medium section (PDF p10); nominal per litre of base. Rounded thesis values retained for comparison.
A75: Sodium dihydrogen phosphate dihydrate – molar mass | B75: amy_NaH2PO4_MW | C75: g/mol | D75: 156.01 | E75: Formula molar mass, g/mol; hydrate state as stated in Teo Reid Table 2.
A76: Sodium dihydrogen phosphate dihydrate – thesis concentration | B76: amy_NaH2PO4_thesis_mM | C76: mmol/L | D76: 30 | E76: Teo Reid, MRes Thesis, Table 2 / Medium section (PDF p10); nominal per litre of base. Rounded thesis values retained for comparison.
A77: Potassium sulfate – weighed concentration | B77: amy_K2SO4_gL | C77: g/L | D77: 0.17 | E77: Teo Reid, MRes Thesis, Table 2 / Medium section (PDF p10); nominal per litre of base. Rounded thesis values retained for comparison.
A78: Potassium sulfate – molar mass | B78: amy_K2SO4_MW | C78: g/mol | D78: 174.26 | E78: Formula molar mass, g/mol; hydrate state as stated in Teo Reid Table 2.
A79: Potassium sulfate – thesis concentration | B79: amy_K2SO4_thesis_mM | C79: mmol/L | D79: 0.98 | E79: Teo Reid, MRes Thesis, Table 2 / Medium section (PDF p10); nominal per litre of base. Rounded thesis values retained for comparison.
A80: Calcium sulfate dihydrate – weighed concentration | B80: amy_CaSO4_gL | C80: g/L | D80: 0.097 | E80: Teo Reid, MRes Thesis, Table 2 / Medium section (PDF p10); nominal per litre of base. Rounded thesis values retained for comparison.
A81: Calcium sulfate dihydrate – molar mass | B81: amy_CaSO4_MW | C81: g/mol | D81: 172.17 | E81: Formula molar mass, g/mol; hydrate state as stated in Teo Reid Table 2.
A82: Calcium sulfate dihydrate – thesis concentration | B82: amy_CaSO4_thesis_mM | C82: mmol/L | D82: 0.56 | E82: Teo Reid, MRes Thesis, Table 2 / Medium section (PDF p10); nominal per litre of base. Rounded thesis values retained for comparison.
... A135: Sodium gluconate – thesis stock concentration | B135: amy_gluconate_thesis_stock | C135: mmol/L | D135: 460 | E135: Teo Reid, MRes Thesis, Table 2 / Medium section (PDF p10); nominal per litre of base. Rounded thesis values retained for comparison.
